Workbook
Name lookup_beazley_lob: data_beazley_summary!$D$2:INDEX(data_beazley_summary!$D:$D, COUNTA(data_beazley_summary!$D:$D))
Name lookup_lloyds_lob: data_lloyds_summary!$D$2:INDEX(data_lloyds_summary!$D:$D, COUNTA(data_lloyds_summary!$D:$D))
Name lookup_own_detail_label: own_detail[Label]
Name lookup_own_lob: data_oe_summary!$BP$2:INDEX(data_oe_summary!$BP:$BP, COUNTA(data_oe_summary!$BP:$BP))
Name lookup_own_lob2: data_oe_summary!$BP$2:INDEX(data_oe_summary!$BP:$BP, COUNTA(data_oe_summary!$BP:$BP))
Name lookup_own_summary_label: own_summary[Label]
Name lst_own_detail__name: own_detail[Name]
Name summary_actuary: Summary!$C$28
Name summary_analysis: Summary!$C$31
Name summary_deal_status: Summary!$C$9
Name summary_ded_str_1: Summary!$C$19
Name summary_ded_str_2: Summary!$C$20
Name summary_ded_str_3: Summary!$C$21
Name summary_ded_str_4: Summary!$C$22
Name summary_ded_str_5: Summary!$C$23
Name summary_ded_str_6: Summary!$C$24
Name summary_ded_str_7: Summary!$C$25
Name summary_expiry_date: Summary!$C$15
Name summary_export_date: Summary!$C$29
Name summary_facility_type: Summary!$C$8
Name summary_final_bpi: Summary!$F$8
Name summary_final_gn_ulr: Summary!$F$7
Name summary_final_loadings: Summary!$F$5
Name summary_final_pc: Summary!$F$6
Name summary_final_roc: Summary!$F$10
Name summary_final_tpi: Summary!$F$9
Name summary_gn_prem: Summary!$C$18
Name summary_hx_model_ref: Summary!$C$30
Name summary_inception_date: Summary!$C$14
Name summary_insured_name: Summary!$C$5
Name summary_key_lob: Summary!$C$10
Name summary_key_uncertainty: Summary!$C$27
Name summary_line_size: Summary!$C$16
Name summary_max_avg_limit: Summary!$C$17
Name summary_pc: Summary!$C$26
Name summary_policy_reference: Summary!$C$6
Name summary_raw_bpi: Summary!$G$8
Name summary_raw_gn_ulr: Summary!$G$7
Name summary_raw_pc: Summary!$G$6
Name summary_raw_roc: Summary!$G$10
Name summary_raw_tpi: Summary!$G$9
Name summary_renewal: Summary!$C$13
Name summary_risk_codes: Summary!$C$12
Name summary_trifocus: Summary!$C$11
Name summary_underwriter: Summary!$C$7
Name table_beazley_detail: data_beazley_detail!$A$2
Name table_beazley_summary: data_beazley_summary!$A$2
Name table_deductions: SummaryTables!$B$240
Name table_deductions_basis_all: SummaryTables!$I$292
Name table_deductions_basis_consortium: SummaryTables!$D$292
Name table_deductions_basis_facility: SummaryTables!$E$292
Name table_deductions_basis_leader_fee: SummaryTables!$F$292
Name table_deductions_basis_market: SummaryTables!$C$292
Name table_deductions_basis_other: SummaryTables!$H$292
Name table_deductions_basis_service_fee: SummaryTables!$G$292
Name table_deductions_total_all: SummaryTables!$I$290
Name table_deductions_total_consortium: SummaryTables!$D$290
Name table_deductions_total_facility: SummaryTables!$E$290
Name table_deductions_total_leader_fee: SummaryTables!$F$290
Name table_deductions_total_market: SummaryTables!$C$290

Sheet Summary
A1: MAP Risks > Portfolio Underwriting > HX Model Output
B2: Pricing Note Tables
B4: Key Risk Details | C4: Comments | E4: Pricing Outputs | F4: Pricing Basis | G4: Excluding Loads
B5: Insured | E5: Anti-Selection / Uncertainty / Other Chg / UW Adj | G5: - / - / - / -
B6: Policy Reference | E6: PC impact on GN ULR
B7: Underwriter | E7: GN ULR % net of PC
B8: Facility Type | E8: BPI %
B9: Deal Status | E9: TPI %
B10: key LOB | E10: RoC %
B11: Trifocus
B12: Lloyd's Risk Codes (Top 5)
B13: Renewal?
B14: Inception
B15: Expiry
B16: % Line Size
B17: 100% Max / Average Limit
B18: 5623 GN Premium
B19: Total Deductions
B26: Profit Commission
B27: Key Uncertainties
B28: Pricing Actuary
... B31: Analysis File

Sheet SummaryTables
A1: MAP Risks > Portfolio Underwriting > HX Model Output
B5: Model GN ULR by Methodology
E7: GN ULR % by method | H7: Weightings
B8: Class of Business | C8: GN Premium (BST Share) | D8: % of Portfolio" | E8: Own Experience | F8: Lloyds Risk Code Projections | G8: Business Plan | H8: Own Experience | I8: Lloyds Risk Code Projections | J8: Business Plan | K8: Case Pricing | L8: Beazley Projection | M8: Model GN ULR%¹
B59: Total
B60: 1 Excl. NMP loadings, Anti-Selection Charge, Uncertainty Loading, UW Adjustments and impact of the profit commission
B63: Selected ULR % Final
C65: Pricing Output
B66: Class of Business | C66: Model GN ULR%1 | D66: NMP Loading | E66: Climate Change Load | F66: Selected GN ULR%² | G66: Anti-Selection | H66: Uncertainty | I66: Additional Charge | J66: PC Impact on GN ULR | K66: UW Adjustment | L66: Selected GN ULR%3
B117: Total | C117: 0.89504948 | D117: 0 | E117: 0 | F117: 0.89504948 | G117: 0 | H117: 0 | I117: 0 | J117: 0 | K117: 0 | L117: 0.89504948
B118: 1 Excl. Anti-Selection, Uncertainty and NMP/Climate loads
B119: 2 Excl. Anti-selection and Uncertainty load; and after NMP/Climate loads
B120: 3 Incl. Anti-selection, Uncertainty and NMP/Climate load, any UW Adjustments; and Impact of the profit commission
B123: Technical adequacy metrics
D125: Including Anti-Selection, Uncertainty Loading and UW Adjustment | H125: Excluding Anti-Selection & Uncertainty Load and UW Adjustment
B126: Class of Business | C126: GN Premium | D126: Selected GN ULR % | E126: BPI% | F126: TPI% | G126: RoC % | H126: GN ULR% | I126: BPI% | J126: TPI% | K126: RoC %
B177: Total
B180: Premium and Limit Profile
C182: Premium and Line Size | H182: Limit Profile
B183: Class of Business | C183: 100% GG Ultimate Premium | D183: Line Size | E183: =YEAR(summary_inception_date)&" GG Premium (BST Share)" -> 1900 GG Premium (BST Share) | F183: Total deductions % | G183: =YEAR(summary_inception_date)&" GN Premium (BST Share)" -> 1900 GN Premium (BST Share) | H183: Maximum @ 100% | I183: Average Limit @ 100% | J183: Maximum Limit @ BST Share
B234: Total
B237: Deductions
B239: Class of Business | C239: Market Deductions | D239: Consortium Managers fee / MGA fee | E239: Facility Brokerage | F239: Leaders Fee | G239: Service Fee | H239: Other | I239: Total Deductions
B290: Total deductions
B292: Premium Basis
B295: Rate change
B297: Class of Business | C297: =YEAR(summary_inception_date) -> 1900 | D297: =C297-1 -> 1899 | E297: =D297-1 -> 1898 | F297: =E297-1 -> 1897 | G297: =F297-1 -> 1896 | H297: =G297-1 -> 1895 | I297: =H297-1 -> 1894 | J297: =I297-1 -> 1893 | K297: =J297-1 -> 1892
B348: Total
B351: Own Experience Performance
B353: Class of Business | C353: CAT Basis | D353: Attritional | E353: Large | F353: CAT | G353: Total | H353: Total (Excl. CAT)
B404: Overal selected
B407: Profit Commission Structure
B409: Class of Business | C409: Interlocking? | D409: Deficit | E409: PC on underlying binders? | F409: PC Type | G409: UW Expense | H409: UW Expense Basis | I409: PC %

Sheet Own Experience Analysis
A1: delete
C2: Own Experience Summary | M2: Selected | S2: Model Default | Y2: Overrides Used?
D3: =INDEX(own_summary[Label],MATCH(D4,own_summary[Name],0)) -> Selected Line of Business | F3: =INDEX(own_summary[Label],MATCH(F4,own_summary[Name],0)) -> Claim Source | H3: =INDEX(own_summary[Label],MATCH(H4,own_summary[Name],0)) -> Claim Basis | I3: =INDEX(own_summary[Label],MATCH(I4,own_summary[Name],0)) -> Claim to Develop to Ultimate | J3: =INDEX(own_summary[Label],MATCH(J4,own_summary[Name],0)) -> Cat Basis | K3: =INDEX(own_summary[Label],MATCH(K4,own_summary[Name],0)) -> IELR Method & Weights | M3: =INDEX(own_summary[Label],MATCH(M4,own_summary[Name],0)) -> Attritional | N3: =INDEX(own_summary[Label],MATCH(N4,own_summary[Name],0)) -> Large | O3: =INDEX(own_summary[Label],MATCH(O4,own_summary[Name],0)) -> Cat (on Selected Basis) | P3: =INDEX(own_summary[Label],MATCH(P4,own_summary[Name],0)) -> Total | Q3: =INDEX(own_summary[Label],MATCH(Q4,own_summary[Name],0)) -> Total (Excl. CAT) | S3: =INDEX(own_summary[Label],MATCH(S4,own_summary[Name],0)) -> Attritional | T3: =INDEX(own_summary[Label],MATCH(T4,own_summary[Name],0)) -> Large | U3: =INDEX(own_summary[Label],MATCH(U4,own_summary[Name],0)) -> Cat (on Selected Basis) | V3: =INDEX(own_summary[Label],MATCH(V4,own_summary[Name],0)) -> Total | W3: =INDEX(own_summary[Label],MATCH(W4,own_summary[Name],0)) -> Total (Excl. CAT) | Y3: =INDEX(own_summary[Label],MATCH(Y4,own_summary[Name],0)) -> Devt | Z3: =INDEX(own_summary[Label],MATCH(Z4,own_summary[Name],0)) -> Indices | AA3: =INDEX(own_summary[Label],MATCH(AA4,own_summary[Name],0)) -> Premium | AB3: =INDEX(own_summary[Label],MATCH(AB4,own_summary[Name],0)) -> IELR Wgt | AC3: =INDEX(own_summary[Label],MATCH(AC4,own_summary[Name],0)) -> IELR | AD3: =INDEX(own_summary[Label],MATCH(AD4,own_summary[Name],0)) -> IBNR add | AF3: =INDEX(own_summary[Label],MATCH(AF4,own_summary[Name],0)) -> Ult Mtd | AG3: =INDEX(own_summary[Label],MATCH(AG4,own_summary[Name],0)) -> Ult | AH3: =INDEX(own_summary[Label],MATCH(AH4,own_summary[Name],0)) -> ULR Wgt
C4: =COUNTA(data_oe_summary!A:A)-1 -> 0 | D4: selected_lob | F4: claim_source | H4: claim_basis | I4: claim_to_develop_to_ultimate | J4: cat_basis | K4: ielr_approach | M4: selected_attr | N4: selected_large | O4: selected_cat | P4: selected_total | Q4: selected_total_excl_cat | S4: model_default_attr | T4: model_default_large | U4: model_default_cat | V4: model_default_total | W4: model_default_total_excl_cat | Y4: ovd_dev | Z4: ovd_index | AA4: ovd_premium | AB4: ovd_ielr_weights | AC4: ovd_ielr | AD4: ovd_ibnr | AF4: ovd_ultimate_method | AG4: ovd_ultimate | AH4: ovd_ulr_weights | AI4: ovd_ulr
D5: =MATCH(D4,data_oe_summary!$1:$1,0) -> 68 | F5: =MATCH(F4,data_oe_summary!$1:$1,0) -> 1 | H5: =MATCH(H4,data_oe_summary!$1:$1,0) -> 2 | I5: =MATCH(I4,data_oe_summary!$1:$1,0) -> 3 | J5: =MATCH(J4,data_oe_summary!$1:$1,0) -> 4 | K5: =MATCH(K4,data_oe_summary!$1:$1,0) -> 5 | M5: =MATCH(M4,data_oe_summary!$1:$1,0) -> 34 | N5: =MATCH(N4,data_oe_summary!$1:$1,0) -> 35 | O5: =MATCH(O4,data_oe_summary!$1:$1,0) -> 36 | P5: =MATCH(P4,data_oe_summary!$1:$1,0) -> 37 | Q5: =MATCH(Q4,data_oe_summary!$1:$1,0) -> 38 | S5: =MATCH(S4,data_oe_summary!$1:$1,0) -> 43 | T5: =MATCH(T4,data_oe_summary!$1:$1,0) -> 44 | U5: =MATCH(U4,data_oe_summary!$1:$1,0) -> 45 | V5: =MATCH(V4,data_oe_summary!$1:$1,0) -> 46 | W5: =MATCH(W4,data_oe_summary!$1:$1,0) -> 47 | Y5: =MATCH(Y4,data_oe_summary!$1:$1,0) -> 52 | Z5: =MATCH(Z4,data_oe_summary!$1:$1,0) -> 53 | AA5: =MATCH(AA4,data_oe_summary!$1:$1,0) -> 54 | AB5: =MATCH(AB4,data_oe_summary!$1:$1,0) -> 55 | AC5: =MATCH(AC4,data_oe_summary!$1:$1,0) -> 56 | AD5: =MATCH(AD4,data_oe_summary!$1:$1,0) -> 57 | AF5: =MATCH(AF4,data_oe_summary!$1:$1,0) -> 58 | AG5: =MATCH(AG4,data_oe_summary!$1:$1,0) -> 59 | AH5: =MATCH(AH4,data_oe_summary!$1:$1,0) -> 60
C6: =IF($C$4<=MAX($C$5:C5),"",SUM(C5,1)) | D6: =IF($C6="","",OFFSET(data_oe_summary!$A$1,$C6,D$5-1)) | F6: =IF($C6="","",OFFSET(data_oe_summary!$A$1,$C6,F$5-1)) | H6: =IF($C6="","",OFFSET(data_oe_summary!$A$1,$C6,H$5-1)) | I6: =IF($C6="","",OFFSET(data_oe_summary!$A$1,$C6,I$5-1)) | J6: =IF($C6="","",OFFSET(data_oe_summary!$A$1,$C6,J$5-1)) | K6: =IF($C6="","",OFFSET(data_oe_summary!$A$1,$C6,K$5-1)) | M6: =IF($C6="","",OFFSET(data_oe_summary!$A$1,$C6,M$5-1)) | N6: =IF($C6="","",OFFSET(data_oe_summary!$A$1,$C6,N$5-1)) | O6: =IF($C6="","",OFFSET(data_oe_summary!$A$1,$C6,O$5-1)) | P6: =IF($C6="","",OFFSET(data_oe_summary!$A$1,$C6,P$5-1)) | Q6: =IF($C6="","",OFFSET(data_oe_summary!$A$1,$C6,Q$5-1)) | S6: =IF($C6="","",OFFSET(data_oe_summary!$A$1,$C6,S$5-1)) | T6: =IF($C6="","",OFFSET(data_oe_summary!$A$1,$C6,T$5-1)) | U6: =IF($C6="","",OFFSET(data_oe_summary!$A$1,$C6,U$5-1)) | V6: =IF($C6="","",OFFSET(data_oe_summary!$A$1,$C6,V$5-1)) | W6: =IF($C6="","",OFFSET(data_oe_summary!$A$1,$C6,W$5-1)) | Y6: =IF($C6="","",OFFSET(data_oe_summary!$A$1,$C6,Y$5-1)) | Z6: =IF($C6="","",OFFSET(data_oe_summary!$A$1,$C6,Z$5-1)) | AA6: =IF($C6="","",OFFSET(data_oe_summary!$A$1,$C6,AA$5-1)) | AB6: =IF($C6="","",OFFSET(data_oe_summary!$A$1,$C6,AB$5-1)) | AC6: =IF($C6="","",OFFSET(data_oe_summary!$A$1,$C6,AC$5-1)) | AD6: =IF($C6="","",OFFSET(data_oe_summary!$A$1,$C6,AD$5-1)) | AF6: =IF($C6="","",OFFSET(data_oe_summary!$A$1,$C6,AF$5-1)) | AG6: =IF($C6="","",OFFSET(data_oe_summary!$A$1,$C6,AG$5-1)) | AH6: =IF($C6="","",OFFSET(data_oe_summary!$A$1,$C6,AH$5-1))
C7: =IF($C$4<=MAX($C$5:C6),"",SUM(C6,1)) | D7: =IF($C7="","",OFFSET(data_oe_summary!$A$1,$C7,D$5-1)) | F7: =IF($C7="","",OFFSET(data_oe_summary!$A$1,$C7,F$5-1)) | H7: =IF($C7="","",OFFSET(data_oe_summary!$A$1,$C7,H$5-1)) | I7: =IF($C7="","",OFFSET(data_oe_summary!$A$1,$C7,I$5-1)) | J7: =IF($C7="","",OFFSET(data_oe_summary!$A$1,$C7,J$5-1)) | K7: =IF($C7="","",OFFSET(data_oe_summary!$A$1,$C7,K$5-1)) | M7: =IF($C7="","",OFFSET(data_oe_summary!$A$1,$C7,M$5-1)) | N7: =IF($C7="","",OFFSET(data_oe_summary!$A$1,$C7,N$5-1)) | O7: =IF($C7="","",OFFSET(data_oe_summary!$A$1,$C7,O$5-1)) | P7: =IF($C7="","",OFFSET(data_oe_summary!$A$1,$C7,P$5-1)) | Q7: =IF($C7="","",OFFSET(data_oe_summary!$A$1,$C7,Q$5-1)) | S7: =IF($C7="","",OFFSET(data_oe_summary!$A$1,$C7,S$5-1)) | T7: =IF($C7="","",OFFSET(data_oe_summary!$A$1,$C7,T$5-1)) | U7: =IF($C7="","",OFFSET(data_oe_summary!$A$1,$C7,U$5-1)) | V7: =IF($C7="","",OFFSET(data_oe_summary!$A$1,$C7,V$5-1)) | W7: =IF($C7="","",OFFSET(data_oe_summary!$A$1,$C7,W$5-1)) | Y7: =IF($C7="","",OFFSET(data_oe_summary!$A$1,$C7,Y$5-1)) | Z7: =IF($C7="","",OFFSET(data_oe_summary!$A$1,$C7,Z$5-1)) | AA7: =IF($C7="","",OFFSET(data_oe_summary!$A$1,$C7,AA$5-1)) | AB7: =IF($C7="","",OFFSET(data_oe_summary!$A$1,$C7,AB$5-1)) | AC7: =IF($C7="","",OFFSET(data_oe_summary!$A$1,$C7,AC$5-1)) | AD7: =IF($C7="","",OFFSET(data_oe_summary!$A$1,$C7,AD$5-1)) | AF7: =IF($C7="","",OFFSET(data_oe_summary!$A$1,$C7,AF$5-1)) | AG7: =IF($C7="","",OFFSET(data_oe_summary!$A$1,$C7,AG$5-1)) | AH7: =IF($C7="","",OFFSET(data_oe_summary!$A$1,$C7,AH$5-1))
C8: =IF($C$4<=MAX($C$5:C7),"",SUM(C7,1)) | D8: =IF($C8="","",OFFSET(data_oe_summary!$A$1,$C8,D$5-1)) | F8: =IF($C8="","",OFFSET(data_oe_summary!$A$1,$C8,F$5-1)) | H8: =IF($C8="","",OFFSET(data_oe_summary!$A$1,$C8,H$5-1)) | I8: =IF($C8="","",OFFSET(data_oe_summary!$A$1,$C8,I$5-1)) | J8: =IF($C8="","",OFFSET(data_oe_summary!$A$1,$C8,J$5-1)) | K8: =IF($C8="","",OFFSET(data_oe_summary!$A$1,$C8,K$5-1)) | M8: =IF($C8="","",OFFSET(data_oe_summary!$A$1,$C8,M$5-1)) | N8: =IF($C8="","",OFFSET(data_oe_summary!$A$1,$C8,N$5-1)) | O8: =IF($C8="","",OFFSET(data_oe_summary!$A$1,$C8,O$5-1)) | P8: =IF($C8="","",OFFSET(data_oe_summary!$A$1,$C8,P$5-1)) | Q8: =IF($C8="","",OFFSET(data_oe_summary!$A$1,$C8,Q$5-1)) | S8: =IF($C8="","",OFFSET(data_oe_summary!$A$1,$C8,S$5-1)) | T8: =IF($C8="","",OFFSET(data_oe_summary!$A$1,$C8,T$5-1)) | U8: =IF($C8="","",OFFSET(data_oe_summary!$A$1,$C8,U$5-1)) | V8: =IF($C8="","",OFFSET(data_oe_summary!$A$1,$C8,V$5-1)) | W8: =IF($C8="","",OFFSET(data_oe_summary!$A$1,$C8,W$5-1)) | Y8: =IF($C8="","",OFFSET(data_oe_summary!$A$1,$C8,Y$5-1)) | Z8: =IF($C8="","",OFFSET(data_oe_summary!$A$1,$C8,Z$5-1)) | AA8: =IF($C8="","",OFFSET(data_oe_summary!$A$1,$C8,AA$5-1)) | AB8: =IF($C8="","",OFFSET(data_oe_summary!$A$1,$C8,AB$5-1)) | AC8: =IF($C8="","",OFFSET(data_oe_summary!$A$1,$C8,AC$5-1)) | AD8: =IF($C8="","",OFFSET(data_oe_summary!$A$1,$C8,AD$5-1)) | AF8: =IF($C8="","",OFFSET(data_oe_summary!$A$1,$C8,AF$5-1)) | AG8: =IF($C8="","",OFFSET(data_oe_summary!$A$1,$C8,AG$5-1)) | AH8: =IF($C8="","",OFFSET(data_oe_summary!$A$1,$C8,AH$5-1))
C9: =IF($C$4<=MAX($C$5:C8),"",SUM(C8,1)) | D9: =IF($C9="","",OFFSET(data_oe_summary!$A$1,$C9,D$5-1)) | F9: =IF($C9="","",OFFSET(data_oe_summary!$A$1,$C9,F$5-1)) | H9: =IF($C9="","",OFFSET(data_oe_summary!$A$1,$C9,H$5-1)) | I9: =IF($C9="","",OFFSET(data_oe_summary!$A$1,$C9,I$5-1)) | J9: =IF($C9="","",OFFSET(data_oe_summary!$A$1,$C9,J$5-1)) | K9: =IF($C9="","",OFFSET(data_oe_summary!$A$1,$C9,K$5-1)) | M9: =IF($C9="","",OFFSET(data_oe_summary!$A$1,$C9,M$5-1)) | N9: =IF($C9="","",OFFSET(data_oe_summary!$A$1,$C9,N$5-1)) | O9: =IF($C9="","",OFFSET(data_oe_summary!$A$1,$C9,O$5-1)) | P9: =IF($C9="","",OFFSET(data_oe_summary!$A$1,$C9,P$5-1)) | Q9: =IF($C9="","",OFFSET(data_oe_summary!$A$1,$C9,Q$5-1)) | S9: =IF($C9="","",OFFSET(data_oe_summary!$A$1,$C9,S$5-1)) | T9: =IF($C9="","",OFFSET(data_oe_summary!$A$1,$C9,T$5-1)) | U9: =IF($C9="","",OFFSET(data_oe_summary!$A$1,$C9,U$5-1)) | V9: =IF($C9="","",OFFSET(data_oe_summary!$A$1,$C9,V$5-1)) | W9: =IF($C9="","",OFFSET(data_oe_summary!$A$1,$C9,W$5-1)) | Y9: =IF($C9="","",OFFSET(data_oe_summary!$A$1,$C9,Y$5-1)) | Z9: =IF($C9="","",OFFSET(data_oe_summary!$A$1,$C9,Z$5-1)) | AA9: =IF($C9="","",OFFSET(data_oe_summary!$A$1,$C9,AA$5-1)) | AB9: =IF($C9="","",OFFSET(data_oe_summary!$A$1,$C9,AB$5-1)) | AC9: =IF($C9="","",OFFSET(data_oe_summary!$A$1,$C9,AC$5-1)) | AD9: =IF($C9="","",OFFSET(data_oe_summary!$A$1,$C9,AD$5-1)) | AF9: =IF($C9="","",OFFSET(data_oe_summary!$A$1,$C9,AF$5-1)) | AG9: =IF($C9="","",OFFSET(data_oe_summary!$A$1,$C9,AG$5-1)) | AH9: =IF($C9="","",OFFSET(data_oe_summary!$A$1,$C9,AH$5-1))
C10: =IF($C$4<=MAX($C$5:C9),"",SUM(C9,1)) | D10: =IF($C10="","",OFFSET(data_oe_summary!$A$1,$C10,D$5-1)) | F10: =IF($C10="","",OFFSET(data_oe_summary!$A$1,$C10,F$5-1)) | H10: =IF($C10="","",OFFSET(data_oe_summary!$A$1,$C10,H$5-1)) | I10: =IF($C10="","",OFFSET(data_oe_summary!$A$1,$C10,I$5-1)) | J10: =IF($C10="","",OFFSET(data_oe_summary!$A$1,$C10,J$5-1)) | K10: =IF($C10="","",OFFSET(data_oe_summary!$A$1,$C10,K$5-1)) | M10: =IF($C10="","",OFFSET(data_oe_summary!$A$1,$C10,M$5-1)) | N10: =IF($C10="","",OFFSET(data_oe_summary!$A$1,$C10,N$5-1)) | O10: =IF($C10="","",OFFSET(data_oe_summary!$A$1,$C10,O$5-1)) | P10: =IF($C10="","",OFFSET(data_oe_summary!$A$1,$C10,P$5-1)) | Q10: =IF($C10="","",OFFSET(data_oe_summary!$A$1,$C10,Q$5-1)) | S10: =IF($C10="","",OFFSET(data_oe_summary!$A$1,$C10,S$5-1)) | T10: =IF($C10="","",OFFSET(data_oe_summary!$A$1,$C10,T$5-1)) | U10: =IF($C10="","",OFFSET(data_oe_summary!$A$1,$C10,U$5-1)) | V10: =IF($C10="","",OFFSET(data_oe_summary!$A$1,$C10,V$5-1)) | W10: =IF($C10="","",OFFSET(data_oe_summary!$A$1,$C10,W$5-1)) | Y10: =IF($C10="","",OFFSET(data_oe_summary!$A$1,$C10,Y$5-1)) | Z10: =IF($C10="","",OFFSET(data_oe_summary!$A$1,$C10,Z$5-1)) | AA10: =IF($C10="","",OFFSET(data_oe_summary!$A$1,$C10,AA$5-1)) | AB10: =IF($C10="","",OFFSET(data_oe_summary!$A$1,$C10,AB$5-1)) | AC10: =IF($C10="","",OFFSET(data_oe_summary!$A$1,$C10,AC$5-1)) | AD10: =IF($C10="","",OFFSET(data_oe_summary!$A$1,$C10,AD$5-1)) | AE10: =IF($C10="","",OFFSET(data_oe_summary!$A$1,$C10,AE$5-1)) | AF10: =IF($C10="","",OFFSET(data_oe_summary!$A$1,$C10,AF$5-1)) | ... AH10: =IF($C10="","",OFFSET(data_oe_summary!$A$1,$C10,AH$5-1))
C11: =IF($C$4<=MAX($C$5:C10),"",SUM(C10,1)) | D11: =IF($C11="","",OFFSET(data_oe_summary!$A$1,$C11,D$5-1)) | F11: =IF($C11="","",OFFSET(data_oe_summary!$A$1,$C11,F$5-1)) | H11: =IF($C11="","",OFFSET(data_oe_summary!$A$1,$C11,H$5-1)) | I11: =IF($C11="","",OFFSET(data_oe_summary!$A$1,$C11,I$5-1)) | J11: =IF($C11="","",OFFSET(data_oe_summary!$A$1,$C11,J$5-1)) | K11: =IF($C11="","",OFFSET(data_oe_summary!$A$1,$C11,K$5-1)) | M11: =IF($C11="","",OFFSET(data_oe_summary!$A$1,$C11,M$5-1)) | N11: =IF($C11="","",OFFSET(data_oe_summary!$A$1,$C11,N$5-1)) | O11: =IF($C11="","",OFFSET(data_oe_summary!$A$1,$C11,O$5-1)) | P11: =IF($C11="","",OFFSET(data_oe_summary!$A$1,$C11,P$5-1)) | Q11: =IF($C11="","",OFFSET(data_oe_summary!$A$1,$C11,Q$5-1)) | S11: =IF($C11="","",OFFSET(data_oe_summary!$A$1,$C11,S$5-1)) | T11: =IF($C11="","",OFFSET(data_oe_summary!$A$1,$C11,T$5-1)) | U11: =IF($C11="","",OFFSET(data_oe_summary!$A$1,$C11,U$5-1)) | V11: =IF($C11="","",OFFSET(data_oe_summary!$A$1,$C11,V$5-1)) | W11: =IF($C11="","",OFFSET(data_oe_summary!$A$1,$C11,W$5-1)) | Y11: =IF($C11="","",OFFSET(data_oe_summary!$A$1,$C11,Y$5-1)) | Z11: =IF($C11="","",OFFSET(data_oe_summary!$A$1,$C11,Z$5-1)) | AA11: =IF($C11="","",OFFSET(data_oe_summary!$A$1,$C11,AA$5-1)) | AB11: =IF($C11="","",OFFSET(data_oe_summary!$A$1,$C11,AB$5-1)) | AC11: =IF($C11="","",OFFSET(data_oe_summary!$A$1,$C11,AC$5-1)) | AD11: =IF($C11="","",OFFSET(data_oe_summary!$A$1,$C11,AD$5-1)) | AE11: =IF($C11="","",OFFSET(data_oe_summary!$A$1,$C11,AE$5-1)) | AF11: =IF($C11="","",OFFSET(data_oe_summary!$A$1,$C11,AF$5-1)) | ... AH11: =IF($C11="","",OFFSET(data_oe_summary!$A$1,$C11,AH$5-1))
C12: =IF($C$4<=MAX($C$5:C11),"",SUM(C11,1)) | D12: =IF($C12="","",OFFSET(data_oe_summary!$A$1,$C12,D$5-1)) | F12: =IF($C12="","",OFFSET(data_oe_summary!$A$1,$C12,F$5-1)) | H12: =IF($C12="","",OFFSET(data_oe_summary!$A$1,$C12,H$5-1)) | I12: =IF($C12="","",OFFSET(data_oe_summary!$A$1,$C12,I$5-1)) | J12: =IF($C12="","",OFFSET(data_oe_summary!$A$1,$C12,J$5-1)) | K12: =IF($C12="","",OFFSET(data_oe_summary!$A$1,$C12,K$5-1)) | M12: =IF($C12="","",OFFSET(data_oe_summary!$A$1,$C12,M$5-1)) | N12: =IF($C12="","",OFFSET(data_oe_summary!$A$1,$C12,N$5-1)) | O12: =IF($C12="","",OFFSET(data_oe_summary!$A$1,$C12,O$5-1)) | P12: =IF($C12="","",OFFSET(data_oe_summary!$A$1,$C12,P$5-1)) | Q12: =IF($C12="","",OFFSET(data_oe_summary!$A$1,$C12,Q$5-1)) | S12: =IF($C12="","",OFFSET(data_oe_summary!$A$1,$C12,S$5-1)) | T12: =IF($C12="","",OFFSET(data_oe_summary!$A$1,$C12,T$5-1)) | U12: =IF($C12="","",OFFSET(data_oe_summary!$A$1,$C12,U$5-1)) | V12: =IF($C12="","",OFFSET(data_oe_summary!$A$1,$C12,V$5-1)) | W12: =IF($C12="","",OFFSET(data_oe_summary!$A$1,$C12,W$5-1)) | Y12: =IF($C12="","",OFFSET(data_oe_summary!$A$1,$C12,Y$5-1)) | Z12: =IF($C12="","",OFFSET(data_oe_summary!$A$1,$C12,Z$5-1)) | AA12: =IF($C12="","",OFFSET(data_oe_summary!$A$1,$C12,AA$5-1)) | AB12: =IF($C12="","",OFFSET(data_oe_summary!$A$1,$C12,AB$5-1)) | AC12: =IF($C12="","",OFFSET(data_oe_summary!$A$1,$C12,AC$5-1)) | AD12: =IF($C12="","",OFFSET(data_oe_summary!$A$1,$C12,AD$5-1)) | AE12: =IF($C12="","",OFFSET(data_oe_summary!$A$1,$C12,AE$5-1)) | AF12: =IF($C12="","",OFFSET(data_oe_summary!$A$1,$C12,AF$5-1)) | ... AH12: =IF($C12="","",OFFSET(data_oe_summary!$A$1,$C12,AH$5-1))
C13: =IF($C$4<=MAX($C$5:C12),"",SUM(C12,1)) | D13: =IF($C13="","",OFFSET(data_oe_summary!$A$1,$C13,D$5-1)) | F13: =IF($C13="","",OFFSET(data_oe_summary!$A$1,$C13,F$5-1)) | H13: =IF($C13="","",OFFSET(data_oe_summary!$A$1,$C13,H$5-1)) | I13: =IF($C13="","",OFFSET(data_oe_summary!$A$1,$C13,I$5-1)) | J13: =IF($C13="","",OFFSET(data_oe_summary!$A$1,$C13,J$5-1)) | K13: =IF($C13="","",OFFSET(data_oe_summary!$A$1,$C13,K$5-1)) | M13: =IF($C13="","",OFFSET(data_oe_summary!$A$1,$C13,M$5-1)) | N13: =IF($C13="","",OFFSET(data_oe_summary!$A$1,$C13,N$5-1)) | O13: =IF($C13="","",OFFSET(data_oe_summary!$A$1,$C13,O$5-1)) | P13: =IF($C13="","",OFFSET(data_oe_summary!$A$1,$C13,P$5-1)) | Q13: =IF($C13="","",OFFSET(data_oe_summary!$A$1,$C13,Q$5-1)) | S13: =IF($C13="","",OFFSET(data_oe_summary!$A$1,$C13,S$5-1)) | T13: =IF($C13="","",OFFSET(data_oe_summary!$A$1,$C13,T$5-1)) | U13: =IF($C13="","",OFFSET(data_oe_summary!$A$1,$C13,U$5-1)) | V13: =IF($C13="","",OFFSET(data_oe_summary!$A$1,$C13,V$5-1)) | W13: =IF($C13="","",OFFSET(data_oe_summary!$A$1,$C13,W$5-1)) | Y13: =IF($C13="","",OFFSET(data_oe_summary!$A$1,$C13,Y$5-1)) | Z13: =IF($C13="","",OFFSET(data_oe_summary!$A$1,$C13,Z$5-1)) | AA13: =IF($C13="","",OFFSET(data_oe_summary!$A$1,$C13,AA$5-1)) | AB13: =IF($C13="","",OFFSET(data_oe_summary!$A$1,$C13,AB$5-1)) | AC13: =IF($C13="","",OFFSET(data_oe_summary!$A$1,$C13,AC$5-1)) | AD13: =IF($C13="","",OFFSET(data_oe_summary!$A$1,$C13,AD$5-1)) | AE13: =IF($C13="","",OFFSET(data_oe_summary!$A$1,$C13,AE$5-1)) | AF13: =IF($C13="","",OFFSET(data_oe_summary!$A$1,$C13,AF$5-1)) | ... AH13: =IF($C13="","",OFFSET(data_oe_summary!$A$1,$C13,AH$5-1))
C14: =IF($C$4<=MAX($C$5:C13),"",SUM(C13,1)) | D14: =IF($C14="","",OFFSET(data_oe_summary!$A$1,$C14,D$5-1)) | F14: =IF($C14="","",OFFSET(data_oe_summary!$A$1,$C14,F$5-1)) | H14: =IF($C14="","",OFFSET(data_oe_summary!$A$1,$C14,H$5-1)) | I14: =IF($C14="","",OFFSET(data_oe_summary!$A$1,$C14,I$5-1)) | J14: =IF($C14="","",OFFSET(data_oe_summary!$A$1,$C14,J$5-1)) | K14: =IF($C14="","",OFFSET(data_oe_summary!$A$1,$C14,K$5-1)) | M14: =IF($C14="","",OFFSET(data_oe_summary!$A$1,$C14,M$5-1)) | N14: =IF($C14="","",OFFSET(data_oe_summary!$A$1,$C14,N$5-1)) | O14: =IF($C14="","",OFFSET(data_oe_summary!$A$1,$C14,O$5-1)) | P14: =IF($C14="","",OFFSET(data_oe_summary!$A$1,$C14,P$5-1)) | Q14: =IF($C14="","",OFFSET(data_oe_summary!$A$1,$C14,Q$5-1)) | S14: =IF($C14="","",OFFSET(data_oe_summary!$A$1,$C14,S$5-1)) | T14: =IF($C14="","",OFFSET(data_oe_summary!$A$1,$C14,T$5-1)) | U14: =IF($C14="","",OFFSET(data_oe_summary!$A$1,$C14,U$5-1)) | V14: =IF($C14="","",OFFSET(data_oe_summary!$A$1,$C14,V$5-1)) | W14: =IF($C14="","",OFFSET(data_oe_summary!$A$1,$C14,W$5-1)) | Y14: =IF($C14="","",OFFSET(data_oe_summary!$A$1,$C14,Y$5-1)) | Z14: =IF($C14="","",OFFSET(data_oe_summary!$A$1,$C14,Z$5-1)) | AA14: =IF($C14="","",OFFSET(data_oe_summary!$A$1,$C14,AA$5-1)) | AB14: =IF($C14="","",OFFSET(data_oe_summary!$A$1,$C14,AB$5-1)) | AC14: =IF($C14="","",OFFSET(data_oe_summary!$A$1,$C14,AC$5-1)) | AD14: =IF($C14="","",OFFSET(data_oe_summary!$A$1,$C14,AD$5-1)) | AE14: =IF($C14="","",OFFSET(data_oe_summary!$A$1,$C14,AE$5-1)) | AF14: =IF($C14="","",OFFSET(data_oe_summary!$A$1,$C14,AF$5-1)) | ... AH14: =IF($C14="","",OFFSET(data_oe_summary!$A$1,$C14,AH$5-1))
C15: =IF($C$4<=MAX($C$5:C14),"",SUM(C14,1)) | D15: =IF($C15="","",OFFSET(data_oe_summary!$A$1,$C15,D$5-1)) | F15: =IF($C15="","",OFFSET(data_oe_summary!$A$1,$C15,F$5-1)) | H15: =IF($C15="","",OFFSET(data_oe_summary!$A$1,$C15,H$5-1)) | I15: =IF($C15="","",OFFSET(data_oe_summary!$A$1,$C15,I$5-1)) | J15: =IF($C15="","",OFFSET(data_oe_summary!$A$1,$C15,J$5-1)) | K15: =IF($C15="","",OFFSET(data_oe_summary!$A$1,$C15,K$5-1)) | M15: =IF($C15="","",OFFSET(data_oe_summary!$A$1,$C15,M$5-1)) | N15: =IF($C15="","",OFFSET(data_oe_summary!$A$1,$C15,N$5-1)) | O15: =IF($C15="","",OFFSET(data_oe_summary!$A$1,$C15,O$5-1)) | P15: =IF($C15="","",OFFSET(data_oe_summary!$A$1,$C15,P$5-1)) | Q15: =IF($C15="","",OFFSET(data_oe_summary!$A$1,$C15,Q$5-1)) | S15: =IF($C15="","",OFFSET(data_oe_summary!$A$1,$C15,S$5-1)) | T15: =IF($C15="","",OFFSET(data_oe_summary!$A$1,$C15,T$5-1)) | U15: =IF($C15="","",OFFSET(data_oe_summary!$A$1,$C15,U$5-1)) | V15: =IF($C15="","",OFFSET(data_oe_summary!$A$1,$C15,V$5-1)) | W15: =IF($C15="","",OFFSET(data_oe_summary!$A$1,$C15,W$5-1)) | Y15: =IF($C15="","",OFFSET(data_oe_summary!$A$1,$C15,Y$5-1)) | Z15: =IF($C15="","",OFFSET(data_oe_summary!$A$1,$C15,Z$5-1)) | AA15: =IF($C15="","",OFFSET(data_oe_summary!$A$1,$C15,AA$5-1)) | AB15: =IF($C15="","",OFFSET(data_oe_summary!$A$1,$C15,AB$5-1)) | AC15: =IF($C15="","",OFFSET(data_oe_summary!$A$1,$C15,AC$5-1)) | AD15: =IF($C15="","",OFFSET(data_oe_summary!$A$1,$C15,AD$5-1)) | AE15: =IF($C15="","",OFFSET(data_oe_summary!$A$1,$C15,AE$5-1)) | AF15: =IF($C15="","",OFFSET(data_oe_summary!$A$1,$C15,AF$5-1)) | ... AH15: =IF($C15="","",OFFSET(data_oe_summary!$A$1,$C15,AH$5-1))
C20: Selected LOB | E20: =D6
C22: LOB Settings | J22: Selected IELRs | O22: Model Default - IELR Approach Analysis
A23: claim_source | B23: =MATCH(A23,$93:$93,0)-1 -> 2 | C23: =INDEX(own_summary[Label],MATCH(A23,own_summary[Name],0)) -> Claim Source | E23: =IF(ISNA(B23),"",OFFSET($B$95,0,B23-1)) -> #N/A | H23: ielr_attr | I23: =MATCH(H23,$93:$93,0)-1 -> 7 | J23: =INDEX(own_summary[Label],MATCH(H23,own_summary[Name],0)) -> Attritional IELR | L23: =IF(ISNA(I23),"",OFFSET($B$95,0,I23-1)) -> #N/A | Q23: Nominal | R23: On-level All Yr | S23: On-level CL Yr
A24: claim_basis | B24: =MATCH(A24,$93:$93,0)-1 -> 3 | C24: =INDEX(own_summary[Label],MATCH(A24,own_summary[Name],0)) -> Claim Basis | E24: =IF(ISNA(B24),"",OFFSET($B$95,0,B24-1)) -> #N/A | H24: ielr_large | I24: =MATCH(H24,$93:$93,0)-1 -> 8 | J24: =INDEX(own_summary[Label],MATCH(H24,own_summary[Name],0)) -> Large IELR | L24: =IF(ISNA(I24),"",OFFSET($B$95,0,I24-1)) -> #N/A | O24: =INDEX(own_summary[Label],MATCH(U24,own_summary[Name],0)) -> Attritional IELR | Q24: =IF(ISNA(Z24),"",OFFSET($B$95,0,Z24-1)) -> #N/A | R24: =IF(ISNA(AA24),"",OFFSET($B$95,0,AA24-1)) -> #N/A | S24: =IF(ISNA(AB24),"",OFFSET($B$95,0,AB24-1)) -> #N/A | U24: ielr_nominal_attr | V24: ielr_ol_all_yr_attr | W24: ielr_ol_cl_yr_attr | Z24: =MATCH(U24,$93:$93,0)-1 -> 20 | AA24: =MATCH(V24,$93:$93,0)-1 -> 25 | AB24: =MATCH(W24,$93:$93,0)-1 -> 30
A25: claim_to_develop_to_ultimate | B25: =MATCH(A25,$93:$93,0)-1 -> 4 | C25: =INDEX(own_summary[Label],MATCH(A25,own_summary[Name],0)) -> Claim to Develop to Ultimate | E25: =IF(ISNA(B25),"",OFFSET($B$95,0,B25-1)) -> #N/A | H25: ielr_cat | I25: =MATCH(H25,$93:$93,0)-1 -> 9 | J25: =INDEX(own_summary[Label],MATCH(H25,own_summary[Name],0)) -> CAT IELR | L25: =IF(ISNA(I25),"",OFFSET($B$95,0,I25-1)) -> #N/A | O25: =INDEX(own_summary[Label],MATCH(U25,own_summary[Name],0)) -> Large IELR | Q25: =IF(ISNA(Z25),"",OFFSET($B$95,0,Z25-1)) -> #N/A | R25: =IF(ISNA(AA25),"",OFFSET($B$95,0,AA25-1)) -> #N/A | S25: =IF(ISNA(AB25),"",OFFSET($B$95,0,AB25-1)) -> #N/A | U25: ielr_nominal_large | V25: ielr_ol_all_yr_large | W25: ielr_ol_cl_yr_large | Z25: =MATCH(U25,$93:$93,0)-1 -> 21 | AA25: =MATCH(V25,$93:$93,0)-1 -> 26 | AB25: =MATCH(W25,$93:$93,0)-1 -> 31
A26: cat_basis | B26: =MATCH(A26,$93:$93,0)-1 -> 5 | C26: =INDEX(own_summary[Label],MATCH(A26,own_summary[Name],0)) -> Cat Basis | E26: =IF(ISNA(B26),"",OFFSET($B$95,0,B26-1)) -> #N/A | H26: ielr_total | I26: =MATCH(H26,$93:$93,0)-1 -> 10 | J26: =INDEX(own_summary[Label],MATCH(H26,own_summary[Name],0)) -> Total IELR | L26: =IF(ISNA(I26),"",OFFSET($B$95,0,I26-1)) -> #N/A | O26: =INDEX(own_summary[Label],MATCH(U26,own_summary[Name],0)) -> CAT IELR | Q26: =IF(ISNA(Z26),"",OFFSET($B$95,0,Z26-1)) -> #N/A | R26: =IF(ISNA(AA26),"",OFFSET($B$95,0,AA26-1)) -> #N/A | S26: =IF(ISNA(AB26),"",OFFSET($B$95,0,AB26-1)) -> #N/A | U26: ielr_nominal_cat | V26: ielr_ol_all_yr_cat | W26: ielr_ol_cl_yr_cat | Z26: =MATCH(U26,$93:$93,0)-1 -> 22 | AA26: =MATCH(V26,$93:$93,0)-1 -> 27 | AB26: =MATCH(W26,$93:$93,0)-1 -> 32
A27: ielr_approach | B27: =MATCH(A27,$93:$93,0)-1 -> 6 | C27: =INDEX(own_summary[Label],MATCH(A27,own_summary[Name],0)) -> IELR Method & Weights | E27: =IF(ISNA(B27),"",OFFSET($B$95,0,B27-1)) -> #N/A | H27: ielr_total_excl_cat | I27: =MATCH(H27,$93:$93,0)-1 -> 11 | J27: =INDEX(own_summary[Label],MATCH(H27,own_summary[Name],0)) -> Total (Excl. CAT) IELR | L27: =IF(ISNA(I27),"",OFFSET($B$95,0,I27-1)) -> #N/A | O27: =INDEX(own_summary[Label],MATCH(U27,own_summary[Name],0)) -> Total IELR | Q27: =IF(ISNA(Z27),"",OFFSET($B$95,0,Z27-1)) -> #N/A | R27: =IF(ISNA(AA27),"",OFFSET($B$95,0,AA27-1)) -> #N/A | S27: =IF(ISNA(AB27),"",OFFSET($B$95,0,AB27-1)) -> #N/A | U27: ielr_nominal_total | V27: ielr_ol_all_yr_total | W27: ielr_ol_cl_yr_total | Z27: =MATCH(U27,$93:$93,0)-1 -> 23 | AA27: =MATCH(V27,$93:$93,0)-1 -> 28 | AB27: =MATCH(W27,$93:$93,0)-1 -> 33
H28: lloyds_selected_ielr | I28: =MATCH(H28,$93:$93,0)-1 -> 14 | J28: =INDEX(own_summary[Label],MATCH(H28,own_summary[Name],0)) -> Lloyds Selected IELR | L28: =IF(ISNA(I28),"",OFFSET($B$95,0,I28-1)) -> #N/A | O28: =INDEX(own_summary[Label],MATCH(U28,own_summary[Name],0)) -> Total (Excl. CAT) IELR | Q28: =IF(ISNA(Z28),"",OFFSET($B$95,0,Z28-1)) -> #N/A | R28: =IF(ISNA(AA28),"",OFFSET($B$95,0,AA28-1)) -> #N/A | S28: =IF(ISNA(AB28),"",OFFSET($B$95,0,AB28-1)) -> #N/A | U28: ielr_nominal_total_excl_cat | V28: ielr_ol_all_yr_total_excl_cat | W28: ielr_ol_cl_yr_total_excl_cat | Z28: =MATCH(U28,$93:$93,0)-1 -> 24 | AA28: =MATCH(V28,$93:$93,0)-1 -> 29 | AB28: =MATCH(W28,$93:$93,0)-1 -> 34
B31: hx name | C31: yoa | D31: latest_gpi | E31: latest_gnpi | F31: acquisition_costs | G31: latest_incurred_open_claims_attr | H31: latest_incurred_open_claims_large | I31: latest_incurred_open_claims_cat | J31: latest_incurred_open_claims_total | K31: latest_incurred_closed_claims_attr | L31: latest_incurred_closed_claims_large | M31: latest_incurred_closed_claims_cat | N31: latest_incurred_closed_claims_total | O31: latest_incurred_total_claims_attr | P31: latest_incurred_total_claims_large | Q31: latest_incurred_total_claims_cat | R31: latest_incurred_total_claims_total | S31: last_year_position_attr | T31: last_year_position_large | U31: last_year_position_cat | V31: last_year_position_total | W31: movement_attr | X31: movement_large | Y31: movement_cat | Z31: movement_total | AA31: gn_ilr_attr | AB31: gn_ilr_large | AC31: gn_ilr_cat | AD31: gn_ilr_total | AE31: null, | AF31: applied_rate_change | AG31: applied_inflation | AH31: applied_rate_change_cumulative | AI31: applied_inflation_cumulative | AJ31: onlevel_factor_cumulative | AK31: ul | AL31: development_pattern_premium_lloyds_unadjusted | AM31: development_pattern_paid_lloyds_unadjusted | AN31: development_pattern_incurred_lloyds_unadjusted | AO31: development_pattern_premium_lloyds | AP31: development_pattern_incurred_lloyds | AQ31: development_pattern_premium_override | AR31: development_pattern_incurred_override | AS31: development_pattern_premium_selected | AT31: development_pattern_incurred_selected | AU31: ul | AV31: ultimate_premium_selected_gnpi_cl | AW31: ultimate_premium_selected_gnpi_override | AX31: ultimate_premium_selected_gnpi_selected | AY31: ultimate_premium_selected_gnpi_selected_ol | AZ31: ultimate_incurred_cl_attr | BA31: ultimate_incurred_cl_large | BB31: ultimate_incurred_cl_cat | BC31: ultimate_incurred_cl_total | BD31: ultimate_incurred_cl_ielr | BE31: ultimate_incurred_ielr_attr | BF31: ultimate_incurred_ielr_large | BG31: ultimate_incurred_ielr_cat | BH31: ultimate_incurred_ielr_total | BI31: ultimate_incurred_bf_attr | BJ31: ultimate_incurred_bf_large | BK31: ultimate_incurred_bf_cat | BL31: ultimate_incurred_bf_total | BM31: ielr_weighting_cl_attr | BN31: ielr_weighting_cl_large | BO31: ielr_weighting_cl_cat | BP31: ielr_weighting_cl_total | BQ31: method_incurred | BR31: additional_ibnr_attr | BS31: additional_ibnr_large | BT31: additional_ibnr_cat | BU31: additional_ibnr_total | BV31: ultimate_incurred_selected_attr | BW31: ultimate_incurred_selected_large | BX31: ultimate_incurred_selected_cat | BY31: ultimate_incurred_selected_total | BZ31: ultimate_incurred_selected_total_x_cat | CA31: ultimate_ulr_selected_attr | CB31: ultimate_ulr_selected_large | CC31: ultimate_ulr_selected_cat | CD31: ultimate_ulr_selected_total | CE31: ultimate_ulr_selected_total_x_cat | CF31: ul | CG31: ultimate_ulr_on_levelled_attr | CH31: ultimate_ulr_on_levelled_large | CI31: ultimate_ulr_on_levelled_cat | CJ31: ultimate_ulr_on_levelled_total | CK31: ultimate_ulr_on_levelled_total_x_cat | CL31: ul | CM31: modelled_weighting | CN31: ielr_weighting_sel_attr | CO31: ielr_weighting_sel_large | CP31: ielr_weighting_sel_cat | CQ31: ielr_weighting_sel_total | CR31: ul | CS31: exposure_weighting_onlevel_1 | CT31: decay_ratio_weighting_2 | CU31: developed_weighting_3 | CV31: overall_weighting_onlevel | CW31: ul | CX31: exposure_weighting_nominal_1 | CY31: overall_weighting_nominal | CZ31: ul | DA31: adjustments_actual | DB31: adjustments_lower | DC31: adjustments_upper | DD31: adjustments_prem_lloyds_lower | DE31: adjustments_prem_lloyds_upper | DF31: adjustments_prem_lloyds_actual | DG31: adjustments_incurred_lloyds_lower | DH31: adjustments_incurred_lloyds_upper | DI31: adjustments_incurred_lloyds_actual | DJ31: adjustments_incurred_lloyds_actual
B32: Match Detail | C32: =MATCH(C31,99:99,0)-1 -> 4 | D32: =MATCH(D31,99:99,0)-1 -> 5 | E32: =MATCH(E31,99:99,0)-1 -> 6 | F32: =MATCH(F31,99:99,0)-1 -> 7 | G32: =MATCH(G31,99:99,0)-1 -> 21 | H32: =MATCH(H31,99:99,0)-1 -> 35 | I32: =MATCH(I31,99:99,0)-1 -> 49 | J32: =MATCH(J31,99:99,0)-1 -> 63 | ... DJ32: =MATCH(DJ31,99:99,0)-1 -> 111
B33: Match Summary | C33: =MATCH(C31,93:93,0)-1 -> 70 | D33: =MATCH(D31,93:93,0)-1 -> 71 | E33: =MATCH(E31,93:93,0)-1 -> 72 | F33: =MATCH(F31,93:93,0)-1 -> 73 | G33: =MATCH(G31,93:93,0)-1 -> 87 | H33: =MATCH(H31,93:93,0)-1 -> 99 | I33: =MATCH(I31,93:93,0)-1 -> 111 | J33: =MATCH(J31,93:93,0)-1 -> 123 | ... DJ33: =MATCH(DJ31,93:93,0)-1 -> #N/A
D35: Premium Current Position | G35: Open Incurred Claims (undeveloped) | K35: Closed Incurred Claims (undeveloped) | O35: Total Incurred Claims (undeveloped) | S35: Last Year's Position | W35: Movement | AA35: GN ILR % | AF35: Incremental Indices | AH35: Cumulative Indices | AL35: Development Pattern | AV35: Ultimate Premium - Selected | AZ35: CL - Ultimate Incurred | BE35: IELR - Ultimate Incurred | BI35: BF - Ultimate Incurred | BM35: IELR Weighting | BQ35: ="" | BR35: Additional IBNR (Additive to Ultimate Incurred - Selected) | BV35: Selected Ultimate | CA35: Selected ULR | CG35: On-Levelled | CN35: Selected Model Weighting | CS35: Weighting On-level | CX35: Weighting Nominal | DA35: Adjustments
C36: =IFERROR(INDEX(own_detail[Label],MATCH(C$31,own_detail[Name],0)),"") -> YoA | D36: =IFERROR(INDEX(own_detail[Label],MATCH(D$31,own_detail[Name],0)),"") -> Latest GPI | E36: =IFERROR(INDEX(own_detail[Label],MATCH(E$31,own_detail[Name],0)),"") -> Latest GNPI | F36: =IFERROR(INDEX(own_detail[Label],MATCH(F$31,own_detail[Name],0)),"") -> Acquisition Costs % | G36: =IFERROR(INDEX(own_detail[Label],MATCH(G$31,own_detail[Name],0)),"") -> Attritional | H36: =IFERROR(INDEX(own_detail[Label],MATCH(H$31,own_detail[Name],0)),"") -> Large | I36: =IFERROR(INDEX(own_detail[Label],MATCH(I$31,own_detail[Name],0)),"") -> Cat | J36: =IFERROR(INDEX(own_detail[Label],MATCH(J$31,own_detail[Name],0)),"") -> Total | ... DJ36: =IFERROR(INDEX(own_detail[Label],MATCH(DJ$31,own_detail[Name],0)),"") -> Incurred Lloyds Actual
B37: Detail row 1 | C37: =IF(ISNA(C$32),"",OFFSET($B101,0,C$32-1)) -> #N/A | D37: =IF(ISNA(D$32),"",OFFSET($B101,0,D$32-1)) -> #N/A | E37: =IF(ISNA(E$32),"",OFFSET($B101,0,E$32-1)) -> #N/A | F37: =IF(ISNA(F$32),"",OFFSET($B101,0,F$32-1)) -> #N/A | G37: =IF(ISNA(G$32),"",OFFSET($B101,0,G$32-1)) -> #N/A | H37: =IF(ISNA(H$32),"",OFFSET($B101,0,H$32-1)) -> #N/A | I37: =IF(ISNA(I$32),"",OFFSET($B101,0,I$32-1)) -> #N/A | J37: =IF(ISNA(J$32),"",OFFSET($B101,0,J$32-1)) -> #N/A | ... DJ37: =IF(ISNA(DJ$32),"",OFFSET($B101,0,DJ$32-1)) -> #N/A
B38: Detail row 2 | C38: =IF(ISNA(C$32),"",OFFSET($B102,0,C$32-1)) -> #N/A | D38: =IF(ISNA(D$32),"",OFFSET($B102,0,D$32-1)) -> #N/A | E38: =IF(ISNA(E$32),"",OFFSET($B102,0,E$32-1)) -> #N/A | F38: =IF(ISNA(F$32),"",OFFSET($B102,0,F$32-1)) -> #N/A | G38: =IF(ISNA(G$32),"",OFFSET($B102,0,G$32-1)) -> #N/A | H38: =IF(ISNA(H$32),"",OFFSET($B102,0,H$32-1)) -> #N/A | I38: =IF(ISNA(I$32),"",OFFSET($B102,0,I$32-1)) -> #N/A | J38: =IF(ISNA(J$32),"",OFFSET($B102,0,J$32-1)) -> #N/A | ... DJ38: =IF(ISNA(DJ$32),"",OFFSET($B102,0,DJ$32-1)) -> #N/A
B39: Detail row 3 | C39: =IF(ISNA(C$32),"",OFFSET($B103,0,C$32-1)) -> #N/A | D39: =IF(ISNA(D$32),"",OFFSET($B103,0,D$32-1)) -> #N/A | E39: =IF(ISNA(E$32),"",OFFSET($B103,0,E$32-1)) -> #N/A | F39: =IF(ISNA(F$32),"",OFFSET($B103,0,F$32-1)) -> #N/A | G39: =IF(ISNA(G$32),"",OFFSET($B103,0,G$32-1)) -> #N/A | H39: =IF(ISNA(H$32),"",OFFSET($B103,0,H$32-1)) -> #N/A | I39: =IF(ISNA(I$32),"",OFFSET($B103,0,I$32-1)) -> #N/A | J39: =IF(ISNA(J$32),"",OFFSET($B103,0,J$32-1)) -> #N/A | ... DJ39: =IF(ISNA(DJ$32),"",OFFSET($B103,0,DJ$32-1)) -> #N/A
B40: Detail row 4 | C40: =IF(ISNA(C$32),"",OFFSET($B104,0,C$32-1)) -> #N/A | D40: =IF(ISNA(D$32),"",OFFSET($B104,0,D$32-1)) -> #N/A | E40: =IF(ISNA(E$32),"",OFFSET($B104,0,E$32-1)) -> #N/A | F40: =IF(ISNA(F$32),"",OFFSET($B104,0,F$32-1)) -> #N/A | G40: =IF(ISNA(G$32),"",OFFSET($B104,0,G$32-1)) -> #N/A | H40: =IF(ISNA(H$32),"",OFFSET($B104,0,H$32-1)) -> #N/A | I40: =IF(ISNA(I$32),"",OFFSET($B104,0,I$32-1)) -> #N/A | J40: =IF(ISNA(J$32),"",OFFSET($B104,0,J$32-1)) -> #N/A | ... DJ40: =IF(ISNA(DJ$32),"",OFFSET($B104,0,DJ$32-1)) -> #N/A
B41: Detail row 5 | C41: =IF(ISNA(C$32),"",OFFSET($B105,0,C$32-1)) -> #N/A | D41: =IF(ISNA(D$32),"",OFFSET($B105,0,D$32-1)) -> #N/A | E41: =IF(ISNA(E$32),"",OFFSET($B105,0,E$32-1)) -> #N/A | F41: =IF(ISNA(F$32),"",OFFSET($B105,0,F$32-1)) -> #N/A | G41: =IF(ISNA(G$32),"",OFFSET($B105,0,G$32-1)) -> #N/A | H41: =IF(ISNA(H$32),"",OFFSET($B105,0,H$32-1)) -> #N/A | I41: =IF(ISNA(I$32),"",OFFSET($B105,0,I$32-1)) -> #N/A | J41: =IF(ISNA(J$32),"",OFFSET($B105,0,J$32-1)) -> #N/A | ... DJ41: =IF(ISNA(DJ$32),"",OFFSET($B105,0,DJ$32-1)) -> #N/A
B42: Detail row 6 | C42: =IF(ISNA(C$32),"",OFFSET($B106,0,C$32-1)) -> #N/A | D42: =IF(ISNA(D$32),"",OFFSET($B106,0,D$32-1)) -> #N/A | E42: =IF(ISNA(E$32),"",OFFSET($B106,0,E$32-1)) -> #N/A | F42: =IF(ISNA(F$32),"",OFFSET($B106,0,F$32-1)) -> #N/A | G42: =IF(ISNA(G$32),"",OFFSET($B106,0,G$32-1)) -> #N/A | H42: =IF(ISNA(H$32),"",OFFSET($B106,0,H$32-1)) -> #N/A | I42: =IF(ISNA(I$32),"",OFFSET($B106,0,I$32-1)) -> #N/A | J42: =IF(ISNA(J$32),"",OFFSET($B106,0,J$32-1)) -> #N/A | ... DJ42: =IF(ISNA(DJ$32),"",OFFSET($B106,0,DJ$32-1)) -> #N/A
B43: Detail row 7 | C43: =IF(ISNA(C$32),"",OFFSET($B107,0,C$32-1)) -> #N/A | D43: =IF(ISNA(D$32),"",OFFSET($B107,0,D$32-1)) -> #N/A | E43: =IF(ISNA(E$32),"",OFFSET($B107,0,E$32-1)) -> #N/A | F43: =IF(ISNA(F$32),"",OFFSET($B107,0,F$32-1)) -> #N/A | G43: =IF(ISNA(G$32),"",OFFSET($B107,0,G$32-1)) -> #N/A | H43: =IF(ISNA(H$32),"",OFFSET($B107,0,H$32-1)) -> #N/A | I43: =IF(ISNA(I$32),"",OFFSET($B107,0,I$32-1)) -> #N/A | J43: =IF(ISNA(J$32),"",OFFSET($B107,0,J$32-1)) -> #N/A | ... DJ43: =IF(ISNA(DJ$32),"",OFFSET($B107,0,DJ$32-1)) -> #N/A
B44: Detail row 8 | C44: =IF(ISNA(C$32),"",OFFSET($B108,0,C$32-1)) -> #N/A | D44: =IF(ISNA(D$32),"",OFFSET($B108,0,D$32-1)) -> #N/A | E44: =IF(ISNA(E$32),"",OFFSET($B108,0,E$32-1)) -> #N/A | F44: =IF(ISNA(F$32),"",OFFSET($B108,0,F$32-1)) -> #N/A | G44: =IF(ISNA(G$32),"",OFFSET($B108,0,G$32-1)) -> #N/A | H44: =IF(ISNA(H$32),"",OFFSET($B108,0,H$32-1)) -> #N/A | I44: =IF(ISNA(I$32),"",OFFSET($B108,0,I$32-1)) -> #N/A | J44: =IF(ISNA(J$32),"",OFFSET($B108,0,J$32-1)) -> #N/A | ... DJ44: =IF(ISNA(DJ$32),"",OFFSET($B108,0,DJ$32-1)) -> #N/A
B45: Detail row 9 | C45: =IF(ISNA(C$32),"",OFFSET($B109,0,C$32-1)) -> #N/A | D45: =IF(ISNA(D$32),"",OFFSET($B109,0,D$32-1)) -> #N/A | E45: =IF(ISNA(E$32),"",OFFSET($B109,0,E$32-1)) -> #N/A | F45: =IF(ISNA(F$32),"",OFFSET($B109,0,F$32-1)) -> #N/A | G45: =IF(ISNA(G$32),"",OFFSET($B109,0,G$32-1)) -> #N/A | H45: =IF(ISNA(H$32),"",OFFSET($B109,0,H$32-1)) -> #N/A | I45: =IF(ISNA(I$32),"",OFFSET($B109,0,I$32-1)) -> #N/A | J45: =IF(ISNA(J$32),"",OFFSET($B109,0,J$32-1)) -> #N/A | ... DJ45: =IF(ISNA(DJ$32),"",OFFSET($B109,0,DJ$32-1)) -> #N/A
B46: Detail row 10 | C46: =IF(ISNA(C$32),"",OFFSET($B110,0,C$32-1)) -> #N/A | D46: =IF(ISNA(D$32),"",OFFSET($B110,0,D$32-1)) -> #N/A | E46: =IF(ISNA(E$32),"",OFFSET($B110,0,E$32-1)) -> #N/A | F46: =IF(ISNA(F$32),"",OFFSET($B110,0,F$32-1)) -> #N/A | G46: =IF(ISNA(G$32),"",OFFSET($B110,0,G$32-1)) -> #N/A | H46: =IF(ISNA(H$32),"",OFFSET($B110,0,H$32-1)) -> #N/A | I46: =IF(ISNA(I$32),"",OFFSET($B110,0,I$32-1)) -> #N/A | J46: =IF(ISNA(J$32),"",OFFSET($B110,0,J$32-1)) -> #N/A | ... DJ46: =IF(ISNA(DJ$32),"",OFFSET($B110,0,DJ$32-1)) -> #N/A
B47: Detail row 11 | C47: =IF(ISNA(C$32),"",OFFSET($B111,0,C$32-1)) -> #N/A | D47: =IF(ISNA(D$32),"",OFFSET($B111,0,D$32-1)) -> #N/A | E47: =IF(ISNA(E$32),"",OFFSET($B111,0,E$32-1)) -> #N/A | F47: =IF(ISNA(F$32),"",OFFSET($B111,0,F$32-1)) -> #N/A | G47: =IF(ISNA(G$32),"",OFFSET($B111,0,G$32-1)) -> #N/A | H47: =IF(ISNA(H$32),"",OFFSET($B111,0,H$32-1)) -> #N/A | I47: =IF(ISNA(I$32),"",OFFSET($B111,0,I$32-1)) -> #N/A | J47: =IF(ISNA(J$32),"",OFFSET($B111,0,J$32-1)) -> #N/A | ... DJ47: =IF(ISNA(DJ$32),"",OFFSET($B111,0,DJ$32-1)) -> #N/A
B48: Detail row 12 | C48: =IF(ISNA(C$32),"",OFFSET($B112,0,C$32-1)) -> #N/A | D48: =IF(ISNA(D$32),"",OFFSET($B112,0,D$32-1)) -> #N/A | E48: =IF(ISNA(E$32),"",OFFSET($B112,0,E$32-1)) -> #N/A | F48: =IF(ISNA(F$32),"",OFFSET($B112,0,F$32-1)) -> #N/A | G48: =IF(ISNA(G$32),"",OFFSET($B112,0,G$32-1)) -> #N/A | H48: =IF(ISNA(H$32),"",OFFSET($B112,0,H$32-1)) -> #N/A | I48: =IF(ISNA(I$32),"",OFFSET($B112,0,I$32-1)) -> #N/A | J48: =IF(ISNA(J$32),"",OFFSET($B112,0,J$32-1)) -> #N/A | ... DJ48: =IF(ISNA(DJ$32),"",OFFSET($B112,0,DJ$32-1)) -> #N/A
... B52: Detail row 16 | C52: =IF(ISNA(C$32),"",OFFSET($B116,0,C$32-1)) -> #N/A | D52: =IF(ISNA(D$32),"",OFFSET($B116,0,D$32-1)) -> #N/A | E52: =IF(ISNA(E$32),"",OFFSET($B116,0,E$32-1)) -> #N/A | F52: =IF(ISNA(F$32),"",OFFSET($B116,0,F$32-1)) -> #N/A | G52: =IF(ISNA(G$32),"",OFFSET($B116,0,G$32-1)) -> #N/A | H52: =IF(ISNA(H$32),"",OFFSET($B116,0,H$32-1)) -> #N/A | I52: =IF(ISNA(I$32),"",OFFSET($B116,0,I$32-1)) -> #N/A | J52: =IF(ISNA(J$32),"",OFFSET($B116,0,J$32-1)) -> #N/A | ... DJ52: =IF(ISNA(DJ$32),"",OFFSET($B116,0,DJ$32-1)) -> #N/A
B53: Summary row 1 | C53: =IF(ISNA(C$33),"",OFFSET($B95,0,C$33-1)) -> #N/A | D53: =IF(ISNA(D$33),"",OFFSET($B95,0,D$33-1)) -> #N/A | E53: =IF(ISNA(E$33),"",OFFSET($B95,0,E$33-1)) -> #N/A | F53: =IF(ISNA(F$33),"",OFFSET($B95,0,F$33-1)) -> #N/A | G53: =IF(ISNA(G$33),"",OFFSET($B95,0,G$33-1)) -> #N/A | H53: =IF(ISNA(H$33),"",OFFSET($B95,0,H$33-1)) -> #N/A | I53: =IF(ISNA(I$33),"",OFFSET($B95,0,I$33-1)) -> #N/A | J53: =IF(ISNA(J$33),"",OFFSET($B95,0,J$33-1)) -> #N/A | ... DJ53: =IF(ISNA(DJ$33),"",OFFSET($B95,0,DJ$33-1))
C56: =C36 -> YoA | D56: Total GN ILR % | E56: Total GN ULR % | F56: On-levelled Total GN ULR % | G56: Pricing Basis % | L56: Model Default Loss Ratios | P56: Selected Loss Ratios
C57: =C37 -> #N/A | D57: =AD37 -> #N/A | E57: =CD37 -> #N/A | F57: =CJ37 -> #N/A | G57: =$R$65 -> #N/A | J57: model_default_attr | K57: =MATCH(J57,$93:$93,0)-1 -> 44 | L57: =INDEX(own_summary[Label],MATCH(J57,own_summary[Name],0)) -> Attritional | N57: =IF(ISNA(K57),"",OFFSET($B$95,0,K57-1)) -> #N/A | P57: =INDEX(own_summary[Label],MATCH(T57,own_summary[Name],0)) -> Attritional | R57: =IF(ISNA(S57),"",OFFSET($B$95,0,S57-1)) -> #N/A | S57: =MATCH(T57,$93:$93,0)-1 -> 35 | T57: selected_attr
C58: =C38 -> #N/A | D58: =AD38 -> #N/A | E58: =CD38 -> #N/A | F58: =CJ38 -> #N/A | G58: =$R$65 -> #N/A | J58: model_default_large | K58: =MATCH(J58,$93:$93,0)-1 -> 45 | L58: =INDEX(own_summary[Label],MATCH(J58,own_summary[Name],0)) -> Large | N58: =IF(ISNA(K58),"",OFFSET($B$95,0,K58-1)) -> #N/A | P58: =INDEX(own_summary[Label],MATCH(T58,own_summary[Name],0)) -> Large | R58: =IF(ISNA(S58),"",OFFSET($B$95,0,S58-1)) -> #N/A | S58: =MATCH(T58,$93:$93,0)-1 -> 36 | T58: selected_large
C59: =C39 -> #N/A | D59: =AD39 -> #N/A | E59: =CD39 -> #N/A | F59: =CJ39 -> #N/A | G59: =$R$65 -> #N/A | J59: model_default_cat_exp | K59: =MATCH(J59,$93:$93,0)-1 -> 49 | L59: =INDEX(own_summary[Label],MATCH(J59,own_summary[Name],0)) -> Cat (Experience) | N59: =IF(ISNA(K59),"",OFFSET($B$95,0,K59-1)) -> #N/A | P59: =INDEX(own_summary[Label],MATCH(T59,own_summary[Name],0)) -> Cat (Experience) | R59: =IF(ISNA(S59),"",OFFSET($B$95,0,S59-1)) -> #N/A | S59: =MATCH(T59,$93:$93,0)-1 -> 40 | T59: selected_cat_exp
C60: =C40 -> #N/A | D60: =AD40 -> #N/A | E60: =CD40 -> #N/A | F60: =CJ40 -> #N/A | G60: =$R$65 -> #N/A | J60: model_default_cat_bp | K60: =MATCH(J60,$93:$93,0)-1 -> 50 | L60: =INDEX(own_summary[Label],MATCH(J60,own_summary[Name],0)) -> Cat (BP) | N60: =IF(ISNA(K60),"",OFFSET($B$95,0,K60-1)) -> #N/A | P60: =INDEX(own_summary[Label],MATCH(T60,own_summary[Name],0)) -> Cat (BP) | R60: =IF(ISNA(S60),"",OFFSET($B$95,0,S60-1)) -> #N/A | S60: =MATCH(T60,$93:$93,0)-1 -> 41 | T60: selected_cat_bp
C61: =C41 -> #N/A | D61: =AD41 -> #N/A | E61: =CD41 -> #N/A | F61: =CJ41 -> #N/A | G61: =$R$65 -> #N/A | J61: model_default_cat_rms | K61: =MATCH(J61,$93:$93,0)-1 -> 51 | L61: =INDEX(own_summary[Label],MATCH(J61,own_summary[Name],0)) -> Cat (RMS) | N61: =IF(ISNA(K61),"",OFFSET($B$95,0,K61-1)) -> #N/A | P61: =INDEX(own_summary[Label],MATCH(T61,own_summary[Name],0)) -> Cat (RMS) | R61: =IF(ISNA(S61),"",OFFSET($B$95,0,S61-1)) -> #N/A | S61: =MATCH(T61,$93:$93,0)-1 -> 42 | T61: selected_cat_rms
C62: =C42 -> #N/A | D62: =AD42 -> #N/A | E62: =CD42 -> #N/A | F62: =CJ42 -> #N/A | G62: =$R$65 -> #N/A | J62: model_default_cat_basis | K62: =MATCH(J62,$93:$93,0)-1 -> 52 | L62: =INDEX(own_summary[Label],MATCH(J62,own_summary[Name],0)) -> Cat Basis | N62: =IF(ISNA(K62),"",OFFSET($B$95,0,K62-1)) -> #N/A | P62: =INDEX(own_summary[Label],MATCH(T62,own_summary[Name],0)) -> Cat Basis | R62: =IF(ISNA(S62),"",OFFSET($B$95,0,S62-1)) -> #N/A | S62: =MATCH(T62,$93:$93,0)-1 -> 43 | T62: selected_cat_basis
C63: =C43 -> #N/A | D63: =AD43 -> #N/A | E63: =CD43 -> #N/A | F63: =CJ43 -> #N/A | G63: =$R$65 -> #N/A | J63: model_default_cat | K63: =MATCH(J63,$93:$93,0)-1 -> 46 | L63: =INDEX(own_summary[Label],MATCH(J63,own_summary[Name],0)) -> Cat (on Selected Basis) | N63: =IF(ISNA(K63),"",OFFSET($B$95,0,K63-1)) -> #N/A | P63: =INDEX(own_summary[Label],MATCH(T63,own_summary[Name],0)) -> Cat (on Selected Basis) | R63: =IF(ISNA(S63),"",OFFSET($B$95,0,S63-1)) -> #N/A | S63: =MATCH(T63,$93:$93,0)-1 -> 37 | T63: selected_cat
C64: =C44 -> #N/A | D64: =AD44 -> #N/A | E64: =CD44 -> #N/A | F64: =CJ44 -> #N/A | G64: =$R$65 -> #N/A
C65: =C45 -> #N/A | D65: =AD45 -> #N/A | E65: =CD45 -> #N/A | F65: =CJ45 -> #N/A | G65: =$R$65 -> #N/A | J65: model_default_total | K65: =MATCH(J65,$93:$93,0)-1 -> 47 | L65: =INDEX(own_summary[Label],MATCH(J65,own_summary[Name],0)) -> Total | N65: =IF(ISNA(K65),"",OFFSET($B$95,0,K65-1)) -> #N/A | P65: =INDEX(own_summary[Label],MATCH(T65,own_summary[Name],0)) -> Total | R65: =IF(ISNA(S65),"",OFFSET($B$95,0,S65-1)) -> #N/A | S65: =MATCH(T65,$93:$93,0)-1 -> 38 | T65: selected_total
C66: =C46 -> #N/A | D66: =AD46 -> #N/A | E66: =CD46 -> #N/A | F66: =CJ46 -> #N/A | G66: =$R$65 -> #N/A | J66: model_default_total_excl_cat | K66: =MATCH(J66,$93:$93,0)-1 -> 48 | L66: =INDEX(own_summary[Label],MATCH(J66,own_summary[Name],0)) -> Total (Excl. CAT) | N66: =IF(ISNA(K66),"",OFFSET($B$95,0,K66-1)) -> #N/A | P66: =INDEX(own_summary[Label],MATCH(T66,own_summary[Name],0)) -> Total (Excl. CAT) | R66: =IF(ISNA(S66),"",OFFSET($B$95,0,S66-1)) -> #N/A | S66: =MATCH(T66,$93:$93,0)-1 -> 39 | T66: selected_total_excl_cat
C67: =C47 -> #N/A | D67: =AD47 -> #N/A | E67: =CD47 -> #N/A | F67: =CJ47 -> #N/A | G67: =$R$65 -> #N/A
C68: =C48 -> #N/A | D68: =AD48 -> #N/A | E68: =CD48 -> #N/A | F68: =CJ48 -> #N/A | G68: =$R$65 -> #N/A
C69: =C49 -> #N/A | D69: =AD49 -> #N/A | E69: =CD49 -> #N/A | F69: =CJ49 -> #N/A | G69: =$R$65 -> #N/A | L69: Please note any rationale for selection below, and any use of overrides:
C70: =C50 -> #N/A | D70: =AD50 -> #N/A | E70: =CD50 -> #N/A | F70: =CJ50 -> #N/A | G70: =$R$65 -> #N/A | J70: actuarial_notes | K70: =MATCH(J70,$93:$93,0)-1 -> 67 | L70: =IF(ISNA(K70),"",OFFSET($B$95,0,K70-1)) -> #N/A
C71: =C51 -> #N/A | D71: =AD51 -> #N/A | E71: =CD51 -> #N/A | F71: =CJ51 -> #N/A | G71: =$R$65 -> #N/A
C72: =C52 -> #N/A | D72: =AD52 -> #N/A | E72: =CD52 -> #N/A | F72: =CJ52 -> #N/A | G72: =$R$65 -> #N/A
B83: settings
B84: key | D84: selected_lob
B85: value | D85: =E20
B86: summary col | D86: =MATCH(D84,data_oe_summary!1:1,0) -> 68
B87: summary row | D87: =MATCH(D85,OFFSET(data_oe_summary!A:A,0,D86-1),0) -> #N/A
B88: detail col | D88: =MATCH(D84,data_oe_detail!1:1,0) -> 2
B89: detail row | D89: =MATCH(D85,OFFSET(data_oe_detail!A:A,0,D88-1),0) -> #N/A
B91: summary
B92: hx label | C92: =INDEX(own_summary[Label],MATCH(C$93,own_summary[Name],0)) -> Claim Source | D92: =INDEX(own_summary[Label],MATCH(D$93,own_summary[Name],0)) -> Claim Basis | E92: =INDEX(own_summary[Label],MATCH(E$93,own_summary[Name],0)) -> Claim to Develop to Ultimate | F92: =INDEX(own_summary[Label],MATCH(F$93,own_summary[Name],0)) -> Cat Basis | G92: =INDEX(own_summary[Label],MATCH(G$93,own_summary[Name],0)) -> IELR Method & Weights | H92: =INDEX(own_summary[Label],MATCH(H$93,own_summary[Name],0)) -> Attritional IELR | I92: =INDEX(own_summary[Label],MATCH(I$93,own_summary[Name],0)) -> Large IELR | J92: =INDEX(own_summary[Label],MATCH(J$93,own_summary[Name],0)) -> CAT IELR | ... EH92: =INDEX(own_summary[Label],MATCH(EH$93,own_summary[Name],0)) -> Total (excl. Cat)
B93: hx name | C93: =data_oe_summary!A1 -> claim_source | D93: =data_oe_summary!B1 -> claim_basis | E93: =data_oe_summary!C1 -> claim_to_develop_to_ultimate | F93: =data_oe_summary!D1 -> cat_basis | G93: =data_oe_summary!E1 -> ielr_approach | H93: =data_oe_summary!F1 -> ielr_attr | I93: =data_oe_summary!G1 -> ielr_large | J93: =data_oe_summary!H1 -> ielr_cat | ... EH93: =data_oe_summary!EF1 -> ultimate_ulr_on_levelled_total_x_cat
B94: excel col | C94: 1 | D94: =C94+1 -> 2 | E94: =D94+1 -> 3 | F94: =E94+1 -> 4 | G94: =F94+1 -> 5 | H94: =G94+1 -> 6 | I94: =H94+1 -> 7 | J94: =I94+1 -> 8 | K94: =J94+1 -> 9 | ... EH94: =EG94+1 -> 136
C95: =OFFSET(data_oe_summary!$A$1,$D$87+$B95-1,C$94-1) -> #N/A | D95: =OFFSET(data_oe_summary!$A$1,$D$87+$B95-1,D$94-1) -> #N/A | E95: =OFFSET(data_oe_summary!$A$1,$D$87+$B95-1,E$94-1) -> #N/A | F95: =OFFSET(data_oe_summary!$A$1,$D$87+$B95-1,F$94-1) -> #N/A | G95: =OFFSET(data_oe_summary!$A$1,$D$87+$B95-1,G$94-1) -> #N/A | H95: =OFFSET(data_oe_summary!$A$1,$D$87+$B95-1,H$94-1) -> #N/A | I95: =OFFSET(data_oe_summary!$A$1,$D$87+$B95-1,I$94-1) -> #N/A | J95: =OFFSET(data_oe_summary!$A$1,$D$87+$B95-1,J$94-1) -> #N/A | ... EH95: =OFFSET(data_oe_summary!$A$1,$D$87+$B95-1,EH$94-1) -> #N/A
B97: detail
B98: hx label | C98: =INDEX(own_detail[Label],MATCH(C$99,own_detail[Name],0)) -> Number of Line of Business | D98: =INDEX(own_detail[Label],MATCH(D$99,own_detail[Name],0)) -> Selected Line of Business | E98: =INDEX(own_detail[Label],MATCH(E$99,own_detail[Name],0)) -> YoA | F98: =INDEX(own_detail[Label],MATCH(F$99,own_detail[Name],0)) -> Latest GPI | G98: =INDEX(own_detail[Label],MATCH(G$99,own_detail[Name],0)) -> Latest GNPI | H98: =INDEX(own_detail[Label],MATCH(H$99,own_detail[Name],0)) -> Acquisition Costs % | I98: =INDEX(own_detail[Label],MATCH(I$99,own_detail[Name],0)) -> Ultimate GNPI - CL | J98: =INDEX(own_detail[Label],MATCH(J$99,own_detail[Name],0)) -> Ultimate GNPI - Override | ... DH98: =INDEX(own_detail[Label],MATCH(DH$99,own_detail[Name],0)) -> Incurred Lloyds Actual
B99: hx name | C99: =data_oe_detail!A1 -> lob_number | D99: =data_oe_detail!B1 -> selected_lob | E99: =data_oe_detail!C1 -> yoa | F99: =data_oe_detail!D1 -> latest_gpi | G99: =data_oe_detail!E1 -> latest_gnpi | H99: =data_oe_detail!F1 -> acquisition_costs | I99: =data_oe_detail!G1 -> ultimate_premium_selected_gnpi_cl | J99: =data_oe_detail!H1 -> ultimate_premium_selected_gnpi_override | ... DH99: =data_oe_detail!DF1 -> adjustments_incurred_lloyds_actual
B100: excel col | C100: 1 | D100: =C100+1 -> 2 | E100: =D100+1 -> 3 | F100: =E100+1 -> 4 | G100: =F100+1 -> 5 | H100: =G100+1 -> 6 | I100: =H100+1 -> 7 | J100: =I100+1 -> 8 | K100: =J100+1 -> 9 | ... DH100: =DG100+1 -> 110
B101: 0 | C101: =OFFSET(data_oe_detail!$A$1,$D$89+$B101-1,C$100-1) -> #N/A | D101: =OFFSET(data_oe_detail!$A$1,$D$89+$B101-1,D$100-1) -> #N/A | E101: =OFFSET(data_oe_detail!$A$1,$D$89+$B101-1,E$100-1) -> #N/A | F101: =OFFSET(data_oe_detail!$A$1,$D$89+$B101-1,F$100-1) -> #N/A | G101: =OFFSET(data_oe_detail!$A$1,$D$89+$B101-1,G$100-1) -> #N/A | H101: =OFFSET(data_oe_detail!$A$1,$D$89+$B101-1,H$100-1) -> #N/A | I101: =OFFSET(data_oe_detail!$A$1,$D$89+$B101-1,I$100-1) -> #N/A | J101: =OFFSET(data_oe_detail!$A$1,$D$89+$B101-1,J$100-1) -> #N/A | ... DH101: =OFFSET(data_oe_detail!$A$1,$D$89+$B101-1,DH$100-1) -> #N/A
B102: 1 | C102: =OFFSET(data_oe_detail!$A$1,$D$89+$B102-1,C$100-1) -> #N/A | D102: =OFFSET(data_oe_detail!$A$1,$D$89+$B102-1,D$100-1) -> #N/A | E102: =OFFSET(data_oe_detail!$A$1,$D$89+$B102-1,E$100-1) -> #N/A | F102: =OFFSET(data_oe_detail!$A$1,$D$89+$B102-1,F$100-1) -> #N/A | G102: =OFFSET(data_oe_detail!$A$1,$D$89+$B102-1,G$100-1) -> #N/A | H102: =OFFSET(data_oe_detail!$A$1,$D$89+$B102-1,H$100-1) -> #N/A | I102: =OFFSET(data_oe_detail!$A$1,$D$89+$B102-1,I$100-1) -> #N/A | J102: =OFFSET(data_oe_detail!$A$1,$D$89+$B102-1,J$100-1) -> #N/A | ... DH102: =OFFSET(data_oe_detail!$A$1,$D$89+$B102-1,DH$100-1) -> #N/A
B103: 2 | C103: =OFFSET(data_oe_detail!$A$1,$D$89+$B103-1,C$100-1) -> #N/A | D103: =OFFSET(data_oe_detail!$A$1,$D$89+$B103-1,D$100-1) -> #N/A | E103: =OFFSET(data_oe_detail!$A$1,$D$89+$B103-1,E$100-1) -> #N/A | F103: =OFFSET(data_oe_detail!$A$1,$D$89+$B103-1,F$100-1) -> #N/A | G103: =OFFSET(data_oe_detail!$A$1,$D$89+$B103-1,G$100-1) -> #N/A | H103: =OFFSET(data_oe_detail!$A$1,$D$89+$B103-1,H$100-1) -> #N/A | I103: =OFFSET(data_oe_detail!$A$1,$D$89+$B103-1,I$100-1) -> #N/A | J103: =OFFSET(data_oe_detail!$A$1,$D$89+$B103-1,J$100-1) -> #N/A | ... DH103: =OFFSET(data_oe_detail!$A$1,$D$89+$B103-1,DH$100-1) -> #N/A
B104: 3 | C104: =OFFSET(data_oe_detail!$A$1,$D$89+$B104-1,C$100-1) -> #N/A | D104: =OFFSET(data_oe_detail!$A$1,$D$89+$B104-1,D$100-1) -> #N/A | E104: =OFFSET(data_oe_detail!$A$1,$D$89+$B104-1,E$100-1) -> #N/A | F104: =OFFSET(data_oe_detail!$A$1,$D$89+$B104-1,F$100-1) -> #N/A | G104: =OFFSET(data_oe_detail!$A$1,$D$89+$B104-1,G$100-1) -> #N/A | H104: =OFFSET(data_oe_detail!$A$1,$D$89+$B104-1,H$100-1) -> #N/A | I104: =OFFSET(data_oe_detail!$A$1,$D$89+$B104-1,I$100-1) -> #N/A | J104: =OFFSET(data_oe_detail!$A$1,$D$89+$B104-1,J$100-1) -> #N/A | ... DH104: =OFFSET(data_oe_detail!$A$1,$D$89+$B104-1,DH$100-1) -> #N/A
B105: 4 | C105: =OFFSET(data_oe_detail!$A$1,$D$89+$B105-1,C$100-1) -> #N/A | D105: =OFFSET(data_oe_detail!$A$1,$D$89+$B105-1,D$100-1) -> #N/A | E105: =OFFSET(data_oe_detail!$A$1,$D$89+$B105-1,E$100-1) -> #N/A | F105: =OFFSET(data_oe_detail!$A$1,$D$89+$B105-1,F$100-1) -> #N/A | G105: =OFFSET(data_oe_detail!$A$1,$D$89+$B105-1,G$100-1) -> #N/A | H105: =OFFSET(data_oe_detail!$A$1,$D$89+$B105-1,H$100-1) -> #N/A | I105: =OFFSET(data_oe_detail!$A$1,$D$89+$B105-1,I$100-1) -> #N/A | J105: =OFFSET(data_oe_detail!$A$1,$D$89+$B105-1,J$100-1) -> #N/A | ... DH105: =OFFSET(data_oe_detail!$A$1,$D$89+$B105-1,DH$100-1) -> #N/A
B106: 5 | C106: =OFFSET(data_oe_detail!$A$1,$D$89+$B106-1,C$100-1) -> #N/A | D106: =OFFSET(data_oe_detail!$A$1,$D$89+$B106-1,D$100-1) -> #N/A | E106: =OFFSET(data_oe_detail!$A$1,$D$89+$B106-1,E$100-1) -> #N/A | F106: =OFFSET(data_oe_detail!$A$1,$D$89+$B106-1,F$100-1) -> #N/A | G106: =OFFSET(data_oe_detail!$A$1,$D$89+$B106-1,G$100-1) -> #N/A | H106: =OFFSET(data_oe_detail!$A$1,$D$89+$B106-1,H$100-1) -> #N/A | I106: =OFFSET(data_oe_detail!$A$1,$D$89+$B106-1,I$100-1) -> #N/A | J106: =OFFSET(data_oe_detail!$A$1,$D$89+$B106-1,J$100-1) -> #N/A | ... DH106: =OFFSET(data_oe_detail!$A$1,$D$89+$B106-1,DH$100-1) -> #N/A
B107: 6 | C107: =OFFSET(data_oe_detail!$A$1,$D$89+$B107-1,C$100-1) -> #N/A | D107: =OFFSET(data_oe_detail!$A$1,$D$89+$B107-1,D$100-1) -> #N/A | E107: =OFFSET(data_oe_detail!$A$1,$D$89+$B107-1,E$100-1) -> #N/A | F107: =OFFSET(data_oe_detail!$A$1,$D$89+$B107-1,F$100-1) -> #N/A | G107: =OFFSET(data_oe_detail!$A$1,$D$89+$B107-1,G$100-1) -> #N/A | H107: =OFFSET(data_oe_detail!$A$1,$D$89+$B107-1,H$100-1) -> #N/A | I107: =OFFSET(data_oe_detail!$A$1,$D$89+$B107-1,I$100-1) -> #N/A | J107: =OFFSET(data_oe_detail!$A$1,$D$89+$B107-1,J$100-1) -> #N/A | ... DH107: =OFFSET(data_oe_detail!$A$1,$D$89+$B107-1,DH$100-1) -> #N/A
B108: 7 | C108: =OFFSET(data_oe_detail!$A$1,$D$89+$B108-1,C$100-1) -> #N/A | D108: =OFFSET(data_oe_detail!$A$1,$D$89+$B108-1,D$100-1) -> #N/A | E108: =OFFSET(data_oe_detail!$A$1,$D$89+$B108-1,E$100-1) -> #N/A | F108: =OFFSET(data_oe_detail!$A$1,$D$89+$B108-1,F$100-1) -> #N/A | G108: =OFFSET(data_oe_detail!$A$1,$D$89+$B108-1,G$100-1) -> #N/A | H108: =OFFSET(data_oe_detail!$A$1,$D$89+$B108-1,H$100-1) -> #N/A | I108: =OFFSET(data_oe_detail!$A$1,$D$89+$B108-1,I$100-1) -> #N/A | J108: =OFFSET(data_oe_detail!$A$1,$D$89+$B108-1,J$100-1) -> #N/A | ... DH108: =OFFSET(data_oe_detail!$A$1,$D$89+$B108-1,DH$100-1) -> #N/A
B109: 8 | C109: =OFFSET(data_oe_detail!$A$1,$D$89+$B109-1,C$100-1) -> #N/A | D109: =OFFSET(data_oe_detail!$A$1,$D$89+$B109-1,D$100-1) -> #N/A | E109: =OFFSET(data_oe_detail!$A$1,$D$89+$B109-1,E$100-1) -> #N/A | F109: =OFFSET(data_oe_detail!$A$1,$D$89+$B109-1,F$100-1) -> #N/A | G109: =OFFSET(data_oe_detail!$A$1,$D$89+$B109-1,G$100-1) -> #N/A | H109: =OFFSET(data_oe_detail!$A$1,$D$89+$B109-1,H$100-1) -> #N/A | I109: =OFFSET(data_oe_detail!$A$1,$D$89+$B109-1,I$100-1) -> #N/A | J109: =OFFSET(data_oe_detail!$A$1,$D$89+$B109-1,J$100-1) -> #N/A | ... DH109: =OFFSET(data_oe_detail!$A$1,$D$89+$B109-1,DH$100-1) -> #N/A
B110: 9 | C110: =OFFSET(data_oe_detail!$A$1,$D$89+$B110-1,C$100-1) -> #N/A | D110: =OFFSET(data_oe_detail!$A$1,$D$89+$B110-1,D$100-1) -> #N/A | E110: =OFFSET(data_oe_detail!$A$1,$D$89+$B110-1,E$100-1) -> #N/A | F110: =OFFSET(data_oe_detail!$A$1,$D$89+$B110-1,F$100-1) -> #N/A | G110: =OFFSET(data_oe_detail!$A$1,$D$89+$B110-1,G$100-1) -> #N/A | H110: =OFFSET(data_oe_detail!$A$1,$D$89+$B110-1,H$100-1) -> #N/A | I110: =OFFSET(data_oe_detail!$A$1,$D$89+$B110-1,I$100-1) -> #N/A | J110: =OFFSET(data_oe_detail!$A$1,$D$89+$B110-1,J$100-1) -> #N/A | ... DH110: =OFFSET(data_oe_detail!$A$1,$D$89+$B110-1,DH$100-1) -> #N/A
B111: 10 | C111: =OFFSET(data_oe_detail!$A$1,$D$89+$B111-1,C$100-1) -> #N/A | D111: =OFFSET(data_oe_detail!$A$1,$D$89+$B111-1,D$100-1) -> #N/A | E111: =OFFSET(data_oe_detail!$A$1,$D$89+$B111-1,E$100-1) -> #N/A | F111: =OFFSET(data_oe_detail!$A$1,$D$89+$B111-1,F$100-1) -> #N/A | G111: =OFFSET(data_oe_detail!$A$1,$D$89+$B111-1,G$100-1) -> #N/A | H111: =OFFSET(data_oe_detail!$A$1,$D$89+$B111-1,H$100-1) -> #N/A | I111: =OFFSET(data_oe_detail!$A$1,$D$89+$B111-1,I$100-1) -> #N/A | J111: =OFFSET(data_oe_detail!$A$1,$D$89+$B111-1,J$100-1) -> #N/A | ... DH111: =OFFSET(data_oe_detail!$A$1,$D$89+$B111-1,DH$100-1) -> #N/A
B112: 11 | C112: =OFFSET(data_oe_detail!$A$1,$D$89+$B112-1,C$100-1) -> #N/A | D112: =OFFSET(data_oe_detail!$A$1,$D$89+$B112-1,D$100-1) -> #N/A | E112: =OFFSET(data_oe_detail!$A$1,$D$89+$B112-1,E$100-1) -> #N/A | F112: =OFFSET(data_oe_detail!$A$1,$D$89+$B112-1,F$100-1) -> #N/A | G112: =OFFSET(data_oe_detail!$A$1,$D$89+$B112-1,G$100-1) -> #N/A | H112: =OFFSET(data_oe_detail!$A$1,$D$89+$B112-1,H$100-1) -> #N/A | I112: =OFFSET(data_oe_detail!$A$1,$D$89+$B112-1,I$100-1) -> #N/A | J112: =OFFSET(data_oe_detail!$A$1,$D$89+$B112-1,J$100-1) -> #N/A | ... DH112: =OFFSET(data_oe_detail!$A$1,$D$89+$B112-1,DH$100-1) -> #N/A
... B116: 15 | C116: =OFFSET(data_oe_detail!$A$1,$D$89+$B116-1,C$100-1) -> #N/A | D116: =OFFSET(data_oe_detail!$A$1,$D$89+$B116-1,D$100-1) -> #N/A | E116: =OFFSET(data_oe_detail!$A$1,$D$89+$B116-1,E$100-1) -> #N/A | F116: =OFFSET(data_oe_detail!$A$1,$D$89+$B116-1,F$100-1) -> #N/A | G116: =OFFSET(data_oe_detail!$A$1,$D$89+$B116-1,G$100-1) -> #N/A | H116: =OFFSET(data_oe_detail!$A$1,$D$89+$B116-1,H$100-1) -> #N/A | I116: =OFFSET(data_oe_detail!$A$1,$D$89+$B116-1,I$100-1) -> #N/A | J116: =OFFSET(data_oe_detail!$A$1,$D$89+$B116-1,J$100-1) -> #N/A | ... DH116: =OFFSET(data_oe_detail!$A$1,$D$89+$B116-1,DH$100-1) -> #N/A

Sheet paths
A1: own_detail | B1: lst_own_detail__name | L1: own_summary | W1: lloyds_detail | AH1: lloyds_summary | AS1: beazley_detail | BD1: beazley_summary
A2: Path | B2: Name | C2: Type | D2: Mode | E2: Optionality | F2: Label | G2: Default Value | H2: Async Input | I2: Async Output | J2: for python | L2: Path | M2: Name | N2: Type | O2: Mode | P2: Optionality | Q2: Label | R2: Default Value | S2: Async Input | T2: Async Output | U2: for python | W2: Path | X2: Name | Y2: Type | Z2: Mode | AA2: Optionality | AB2: Label | AC2: Default Value | AD2: Async Input | AE2: Async Output | AF2: for python | AH2: Path | AI2: Name | AJ2: Type | AK2: Mode | AL2: Optionality | AM2: Label | AN2: Default Value | AO2: Async Input | AP2: Async Output | AQ2: for python | AS2: Path | AT2: Name | AU2: Type | AV2: Mode | AW2: Optionality | AX2: Label | AY2: Default Value | AZ2: Async Input | BA2: Async Output | BB2: for python | BD2: Path | BE2: Name | BF2: Type | BG2: Mode | BH2: Optionality | BI2: Label | BJ2: Default Value | BK2: Async Input | BL2: Async Output | BM2: for python
A3: cds/projections_own_experience/detail_table/lob_number | B3: lob_number | C3: int | D3: output | E3: n/a | F3: Number of Line of Business | G3: n/a | H3: ['calculate_profit_commission_task'] | I3: n/a | J3: =",'"&own_detail[[#This Row],[Name]]&"'" -> ,'lob_number' | L3: cds/projections_own_experience/summary_table/claim_source | M3: claim_source | N3: str | O3: input | P3: required | Q3: Claim Source | R3: <hx_data_schema.nodes.Undefined object at 0x7f415a6cbe00> | S3: ['calculate_profit_commission_task', 'sync_lob_lists_task'] | T3: n/a | U3: =",'"&own_summary[[#This Row],[Name]]&"'" -> ,'claim_source' | W3: cds/projections_lloyds/detail_table/yoa | X3: yoa | Y3: str | Z3: output | AA3: n/a | AB3: YoA | AC3: n/a | AD3: n/a | AE3: [] | AF3: =",'"&lloyds_detail[[#This Row],[Name]]&"'" -> ,'yoa' | AH3: cds/projections_lloyds/summary_table/lob_number | AI3: lob_number | AJ3: int | AK3: output | AL3: n/a | AM3: Number of Line of Business | AN3: n/a | AO3: n/a | AP3: [] | AQ3: =",'"&lloyds_summary[[#This Row],[Name]]&"'" -> ,'lob_number' | AS3: cds/projections_beazley/detail_table/yoa | AT3: yoa | AU3: str | AV3: output | AW3: n/a | AX3: YoA | AY3: n/a | AZ3: n/a | BA3: [] | BB3: =",'"&beazley_detail[[#This Row],[Name]]&"'" -> ,'yoa' | BD3: cds/projections_beazley/summary_table/lob_number | BE3: lob_number | BF3: int | BG3: output | BH3: n/a | BI3: Number of Line of Business | BJ3: n/a | BK3: n/a | BL3: [] | BM3: =",'"&beazley_summary[[#This Row],[Name]]&"'" -> ,'lob_number'
A4: cds/projections_own_experience/detail_table/selected_lob | B4: selected_lob | C4: str | D4: output | E4: n/a | F4: Selected Line of Business | G4: n/a | H4: ['calculate_profit_commission_task'] | I4: n/a | J4: =",'"&own_detail[[#This Row],[Name]]&"'" -> ,'selected_lob' | L4: cds/projections_own_experience/summary_table/claim_basis | M4: claim_basis | N4: str | O4: input | P4: required | Q4: Claim Basis | R4: <hx_data_schema.nodes.Undefined object at 0x7f415a6cbe00> | S4: ['calculate_profit_commission_task', 'sync_lob_lists_task'] | T4: n/a | U4: =",'"&own_summary[[#This Row],[Name]]&"'" -> ,'claim_basis' | W4: cds/projections_lloyds/detail_table/latest_gpi | X4: latest_gpi | Y4: float | Z4: output | AA4: n/a | AB4: Latest GPI | AC4: n/a | AD4: n/a | AE4: [] | AF4: =",'"&lloyds_detail[[#This Row],[Name]]&"'" -> ,'latest_gpi' | AH4: cds/projections_lloyds/summary_table/risk_code | AI4: risk_code | AJ4: str | AK4: output | AL4: n/a | AM4: Risk Code | AN4: n/a | AO4: n/a | AP4: [] | AQ4: =",'"&lloyds_summary[[#This Row],[Name]]&"'" -> ,'risk_code' | AS4: cds/projections_beazley/detail_table/latest_gpi | AT4: latest_gpi | AU4: float | AV4: output | AW4: n/a | AX4: Latest GPI | AY4: n/a | AZ4: n/a | BA4: [] | BB4: =",'"&beazley_detail[[#This Row],[Name]]&"'" -> ,'latest_gpi' | BD4: cds/projections_beazley/summary_table/risk_code | BE4: risk_code | BF4: str | BG4: output | BH4: n/a | BI4: Risk Code | BJ4: n/a | BK4: n/a | BL4: [] | BM4: =",'"&beazley_summary[[#This Row],[Name]]&"'" -> ,'risk_code'
A5: cds/projections_own_experience/detail_table/yoa | B5: yoa | C5: str | D5: output | E5: n/a | F5: YoA | G5: n/a | H5: ['calculate_profit_commission_task'] | I5: n/a | J5: =",'"&own_detail[[#This Row],[Name]]&"'" -> ,'yoa' | L5: cds/projections_own_experience/summary_table/claim_to_develop_to_ultimate | M5: claim_to_develop_to_ultimate | N5: str | O5: input | P5: required | Q5: Claim to Develop to Ultimate | R5: <hx_data_schema.nodes.Undefined object at 0x7f415a6cbe00> | S5: ['calculate_profit_commission_task', 'sync_lob_lists_task'] | T5: n/a | U5: =",'"&own_summary[[#This Row],[Name]]&"'" -> ,'claim_to_develop_to_ultimate' | W5: cds/projections_lloyds/detail_table/latest_gnpi | X5: latest_gnpi | Y5: float | Z5: output | AA5: n/a | AB5: Latest GNPI | AC5: n/a | AD5: n/a | AE5: [] | AF5: =",'"&lloyds_detail[[#This Row],[Name]]&"'" -> ,'latest_gnpi' | AH5: cds/projections_lloyds/summary_table/selected_lob | AI5: selected_lob | AJ5: str | AK5: output | AL5: n/a | AM5: Selected Line of Business | AN5: n/a | AO5: n/a | AP5: [] | AQ5: =",'"&lloyds_summary[[#This Row],[Name]]&"'" -> ,'selected_lob' | AS5: cds/projections_beazley/detail_table/latest_gnpi | AT5: latest_gnpi | AU5: float | AV5: output | AW5: n/a | AX5: Latest GNPI | AY5: n/a | AZ5: n/a | BA5: [] | BB5: =",'"&beazley_detail[[#This Row],[Name]]&"'" -> ,'latest_gnpi' | BD5: cds/projections_beazley/summary_table/selected_lob | BE5: selected_lob | BF5: str | BG5: output | BH5: n/a | BI5: Selected Line of Business | BJ5: n/a | BK5: n/a | BL5: [] | BM5: =",'"&beazley_summary[[#This Row],[Name]]&"'" -> ,'selected_lob'
A6: cds/projections_own_experience/detail_table/latest_gpi | B6: latest_gpi | C6: float | D6: output | E6: n/a | F6: Latest GPI | G6: n/a | H6: ['calculate_profit_commission_task'] | I6: n/a | J6: =",'"&own_detail[[#This Row],[Name]]&"'" -> ,'latest_gpi' | L6: cds/projections_own_experience/summary_table/cat_basis | M6: cat_basis | N6: str | O6: input | P6: required | Q6: Cat Basis | R6: <hx_data_schema.nodes.Undefined object at 0x7f415a6cbe00> | S6: ['calculate_profit_commission_task', 'sync_lob_lists_task'] | T6: n/a | U6: =",'"&own_summary[[#This Row],[Name]]&"'" -> ,'cat_basis' | W6: cds/projections_lloyds/detail_table/latest_paid | X6: latest_paid | Y6: float | Z6: output | AA6: n/a | AB6: Latest Paid | AC6: n/a | AD6: n/a | AE6: [] | AF6: =",'"&lloyds_detail[[#This Row],[Name]]&"'" -> ,'latest_paid' | AH6: cds/projections_lloyds/summary_table/lookup_lob | AI6: lookup_lob | AJ6: str | AK6: output | AL6: n/a | AM6: Lookup LOB | AN6: n/a | AO6: n/a | AP6: [] | AQ6: =",'"&lloyds_summary[[#This Row],[Name]]&"'" -> ,'lookup_lob' | AS6: cds/projections_beazley/detail_table/latest_paid | AT6: latest_paid | AU6: float | AV6: output | AW6: n/a | AX6: Latest Paid | AY6: n/a | AZ6: n/a | BA6: [] | BB6: =",'"&beazley_detail[[#This Row],[Name]]&"'" -> ,'latest_paid' | BD6: cds/projections_beazley/summary_table/lookup_lob | BE6: lookup_lob | BF6: str | BG6: output | BH6: n/a | BI6: Lookup LOB | BJ6: n/a | BK6: n/a | BL6: [] | BM6: =",'"&beazley_summary[[#This Row],[Name]]&"'" -> ,'lookup_lob'
A7: cds/projections_own_experience/detail_table/latest_gnpi | B7: latest_gnpi | C7: float | D7: output | E7: n/a | F7: Latest GNPI | G7: n/a | H7: ['calculate_profit_commission_task'] | I7: n/a | J7: =",'"&own_detail[[#This Row],[Name]]&"'" -> ,'latest_gnpi' | L7: cds/projections_own_experience/summary_table/ielr_approach | M7: ielr_approach | N7: str | O7: input | P7: required | Q7: IELR Method & Weights | R7: On-level | S7: ['calculate_profit_commission_task', 'sync_lob_lists_task'] | T7: n/a | U7: =",'"&own_summary[[#This Row],[Name]]&"'" -> ,'ielr_approach' | W7: cds/projections_lloyds/detail_table/latest_incurred | X7: latest_incurred | Y7: float | Z7: output | AA7: n/a | AB7: Latest Incurred | AC7: n/a | AD7: n/a | AE7: [] | AF7: =",'"&lloyds_detail[[#This Row],[Name]]&"'" -> ,'latest_incurred' | AH7: cds/projections_lloyds/summary_table/bp_class | AI7: bp_class | AJ7: str | AK7: output | AL7: n/a | AM7: Beazley Business Plan class | AN7: n/a | AO7: n/a | AP7: [] | AQ7: =",'"&lloyds_summary[[#This Row],[Name]]&"'" -> ,'bp_class' | AS7: cds/projections_beazley/detail_table/latest_incurred | AT7: latest_incurred | AU7: float | AV7: output | AW7: n/a | AX7: Latest Incurred | AY7: n/a | AZ7: n/a | BA7: [] | BB7: =",'"&beazley_detail[[#This Row],[Name]]&"'" -> ,'latest_incurred' | BD7: cds/projections_beazley/summary_table/bp_class | BE7: bp_class | BF7: str | BG7: output | BH7: n/a | BI7: Beazley Business Plan class | BJ7: n/a | BK7: n/a | BL7: [] | BM7: =",'"&beazley_summary[[#This Row],[Name]]&"'" -> ,'bp_class'
A8: cds/projections_own_experience/detail_table/acquisition_costs | B8: acquisition_costs | C8: float | D8: output | E8: n/a | F8: Acquisition Costs % | G8: n/a | H8: ['calculate_profit_commission_task'] | I8: n/a | J8: =",'"&own_detail[[#This Row],[Name]]&"'" -> ,'acquisition_costs' | L8: cds/projections_own_experience/summary_table/ielr_attr | M8: ielr_attr | N8: float | O8: override | P8: n/a | Q8: Attritional IELR | R8: n/a | S8: ['calculate_profit_commission_task', 'sync_lob_lists_task'] | T8: n/a | U8: =",'"&own_summary[[#This Row],[Name]]&"'" -> ,'ielr_attr' | W8: cds/projections_lloyds/detail_table/acquisition_ratio | X8: acquisition_ratio | Y8: float | Z8: output | AA8: n/a | AB8: Acquisition costs % | AC8: n/a | AD8: n/a | AE8: [] | AF8: =",'"&lloyds_detail[[#This Row],[Name]]&"'" -> ,'acquisition_ratio' | AH8: cds/projections_lloyds/summary_table/tracker_class | AI8: tracker_class | AJ8: str | AK8: output | AL8: n/a | AM8: Tracker Class | AN8: n/a | AO8: n/a | AP8: [] | AQ8: =",'"&lloyds_summary[[#This Row],[Name]]&"'" -> ,'tracker_class' | AS8: cds/projections_beazley/detail_table/acquisition_ratio | AT8: acquisition_ratio | AU8: float | AV8: output | AW8: n/a | AX8: Acquisition costs % | AY8: n/a | AZ8: n/a | BA8: [] | BB8: =",'"&beazley_detail[[#This Row],[Name]]&"'" -> ,'acquisition_ratio' | BD8: cds/projections_beazley/summary_table/tracker_class | BE8: tracker_class | BF8: str | BG8: output | BH8: n/a | BI8: Tracker Class | BJ8: n/a | BK8: n/a | BL8: [] | BM8: =",'"&beazley_summary[[#This Row],[Name]]&"'" -> ,'tracker_class'
A9: cds/projections_own_experience/detail_table/ultimate_premium_selected_gnpi_cl | B9: ultimate_premium_selected_gnpi_cl | C9: float | D9: output | E9: n/a | F9: Ultimate GNPI - CL | G9: n/a | H9: ['calculate_profit_commission_task'] | I9: n/a | J9: =",'"&own_detail[[#This Row],[Name]]&"'" -> ,'ultimate_premium_selected_gnpi_cl' | L9: cds/projections_own_experience/summary_table/ielr_large | M9: ielr_large | N9: float | O9: override | P9: n/a | Q9: Large IELR | R9: n/a | S9: ['calculate_profit_commission_task', 'sync_lob_lists_task'] | T9: n/a | U9: =",'"&own_summary[[#This Row],[Name]]&"'" -> ,'ielr_large' | W9: cds/projections_lloyds/detail_table/incurred_loss_ratio | X9: incurred_loss_ratio | Y9: float | Z9: output | AA9: n/a | AB9: Incurred Loss ratio | AC9: n/a | AD9: n/a | AE9: [] | AF9: =",'"&lloyds_detail[[#This Row],[Name]]&"'" -> ,'incurred_loss_ratio' | AH9: cds/projections_lloyds/summary_table/projection_type | AI9: projection_type | AJ9: str | AK9: input | AL9: required | AM9: Projection Type | AN9: <hx_data_schema.nodes.Undefined object at 0x7f415a6cbe00> | AO9: ['sync_lob_lists_task'] | AP9: [] | AQ9: =",'"&lloyds_summary[[#This Row],[Name]]&"'" -> ,'projection_type' | AS9: cds/projections_beazley/detail_table/incurred_loss_ratio | AT9: incurred_loss_ratio | AU9: float | AV9: output | AW9: n/a | AX9: Incurred Loss ratio | AY9: n/a | AZ9: n/a | BA9: [] | BB9: =",'"&beazley_detail[[#This Row],[Name]]&"'" -> ,'incurred_loss_ratio' | BD9: cds/projections_beazley/summary_table/projection_type | BE9: projection_type | BF9: str | BG9: input | BH9: required | BI9: Projection Type | BJ9: <hx_data_schema.nodes.Undefined object at 0x7f415a6cbe00> | BK9: ['sync_lob_lists_task'] | BL9: [] | BM9: =",'"&beazley_summary[[#This Row],[Name]]&"'" -> ,'projection_type'
A10: cds/projections_own_experience/detail_table/ultimate_premium_selected_gnpi_override | B10: ultimate_premium_selected_gnpi_override | C10: float | D10: input | E10: optional | F10: Ultimate GNPI - Override | G10: None | H10: ['calculate_profit_commission_task'] | I10: n/a | J10: =",'"&own_detail[[#This Row],[Name]]&"'" -> ,'ultimate_premium_selected_gnpi_override' | L10: cds/projections_own_experience/summary_table/ielr_cat | M10: ielr_cat | N10: float | O10: override | P10: n/a | Q10: CAT IELR | R10: n/a | S10: ['calculate_profit_commission_task', 'sync_lob_lists_task'] | T10: n/a | U10: =",'"&own_summary[[#This Row],[Name]]&"'" -> ,'ielr_cat' | W10: cds/projections_lloyds/detail_table/ultimate_gnpi | X10: ultimate_gnpi | Y10: float | Z10: output | AA10: n/a | AB10: Ultimate GNPI | AC10: n/a | AD10: n/a | AE10: [] | AF10: =",'"&lloyds_detail[[#This Row],[Name]]&"'" -> ,'ultimate_gnpi' | AH10: cds/projections_lloyds/summary_table/ielr_approach | AI10: ielr_approach | AJ10: str | AK10: input | AL10: required | AM10: IELR Method & Weights | AN10: <hx_data_schema.nodes.Undefined object at 0x7f415a6cbe00> | AO10: ['sync_lob_lists_task'] | AP10: [] | AQ10: =",'"&lloyds_summary[[#This Row],[Name]]&"'" -> ,'ielr_approach' | AS10: cds/projections_beazley/detail_table/ultimate_gnpi | AT10: ultimate_gnpi | AU10: float | AV10: output | AW10: n/a | AX10: Ultimate GNPI | AY10: n/a | AZ10: n/a | BA10: [] | BB10: =",'"&beazley_detail[[#This Row],[Name]]&"'" -> ,'ultimate_gnpi' | BD10: cds/projections_beazley/summary_table/ielr_approach | BE10: ielr_approach | BF10: str | BG10: input | BH10: required | BI10: IELR Method & Weights | BJ10: <hx_data_schema.nodes.Undefined object at 0x7f415a6cbe00> | BK10: ['sync_lob_lists_task'] | BL10: [] | BM10: =",'"&beazley_summary[[#This Row],[Name]]&"'" -> ,'ielr_approach'
A11: cds/projections_own_experience/detail_table/ultimate_premium_selected_gnpi_selected | B11: ultimate_premium_selected_gnpi_selected | C11: float | D11: output | E11: n/a | F11: Ultimate GNPI - Selected | G11: n/a | H11: ['calculate_profit_commission_task'] | I11: n/a | J11: =",'"&own_detail[[#This Row],[Name]]&"'" -> ,'ultimate_premium_selected_gnpi_selected' | L11: cds/projections_own_experience/summary_table/ielr_total | M11: ielr_total | N11: float | O11: override | P11: n/a | Q11: Total IELR | R11: n/a | S11: ['calculate_profit_commission_task', 'sync_lob_lists_task'] | T11: n/a | U11: =",'"&own_summary[[#This Row],[Name]]&"'" -> ,'ielr_total' | W11: cds/projections_lloyds/detail_table/ultimate_gnpi_ol_model | X11: ultimate_gnpi_ol_model | Y11: float | Z11: output | AA11: n/a | AB11: Ultimate GNPI On-level Default | AC11: n/a | AD11: n/a | AE11: [] | AF11: =",'"&lloyds_detail[[#This Row],[Name]]&"'" -> ,'ultimate_gnpi_ol_model' | AH11: cds/projections_lloyds/summary_table/ielr_source | AI11: ielr_source | AJ11: str | AK11: input | AL11: required | AM11: Selected IELR Source | AN11: <hx_data_schema.nodes.Undefined object at 0x7f415a6cbe00> | AO11: ['sync_lob_lists_task'] | AP11: [] | AQ11: =",'"&lloyds_summary[[#This Row],[Name]]&"'" -> ,'ielr_source' | AS11: cds/projections_beazley/detail_table/ultimate_gnpi_ol_model | AT11: ultimate_gnpi_ol_model | AU11: float | AV11: output | AW11: n/a | AX11: Ultimate GNPI On-level Default | AY11: n/a | AZ11: n/a | BA11: [] | BB11: =",'"&beazley_detail[[#This Row],[Name]]&"'" -> ,'ultimate_gnpi_ol_model' | BD11: cds/projections_beazley/summary_table/ielr_source | BE11: ielr_source | BF11: str | BG11: input | BH11: required | BI11: Selected IELR Source | BJ11: <hx_data_schema.nodes.Undefined object at 0x7f415a6cbe00> | BK11: ['sync_lob_lists_task'] | BL11: [] | BM11: =",'"&beazley_summary[[#This Row],[Name]]&"'" -> ,'ielr_source'
A12: cds/projections_own_experience/detail_table/ultimate_premium_selected_gnpi_selected_ol | B12: ultimate_premium_selected_gnpi_selected_ol | C12: float | D12: output | E12: n/a | F12: Ultimate GNPI On-level Selected | G12: n/a | H12: ['calculate_profit_commission_task'] | I12: n/a | J12: =",'"&own_detail[[#This Row],[Name]]&"'" -> ,'ultimate_premium_selected_gnpi_selected_ol' | L12: cds/projections_own_experience/summary_table/ielr_total_excl_cat | M12: ielr_total_excl_cat | N12: float | O12: output | P12: n/a | Q12: Total (Excl. CAT) IELR | R12: n/a | S12: ['calculate_profit_commission_task'] | T12: n/a | U12: =",'"&own_summary[[#This Row],[Name]]&"'" -> ,'ielr_total_excl_cat' | W12: cds/projections_lloyds/detail_table/ultimate_gnpi_ol_selected | X12: ultimate_gnpi_ol_selected | Y12: float | Z12: output | AA12: n/a | AB12: Ultimate GNPI On-level Selected | AC12: n/a | AD12: n/a | AE12: [] | AF12: =",'"&lloyds_detail[[#This Row],[Name]]&"'" -> ,'ultimate_gnpi_ol_selected' | AH12: cds/projections_lloyds/summary_table/cat_lr_source | AI12: cat_lr_source | AJ12: str | AK12: input | AL12: required | AM12: GN Cat ULR Source | AN12: <hx_data_schema.nodes.Undefined object at 0x7f415a6cbe00> | AO12: ['sync_lob_lists_task'] | AP12: [] | AQ12: =",'"&lloyds_summary[[#This Row],[Name]]&"'" -> ,'cat_lr_source' | AS12: cds/projections_beazley/detail_table/ultimate_gnpi_ol_selected | AT12: ultimate_gnpi_ol_selected | AU12: float | AV12: output | AW12: n/a | AX12: Ultimate GNPI On-level Selected | AY12: n/a | AZ12: n/a | BA12: [] | BB12: =",'"&beazley_detail[[#This Row],[Name]]&"'" -> ,'ultimate_gnpi_ol_selected' | BD12: cds/projections_beazley/summary_table/cat_lr_source | BE12: cat_lr_source | BF12: str | BG12: input | BH12: required | BI12: GN Cat ULR Source | BJ12: <hx_data_schema.nodes.Undefined object at 0x7f415a6cbe00> | BK12: ['sync_lob_lists_task'] | BL12: [] | BM12: =",'"&beazley_summary[[#This Row],[Name]]&"'" -> ,'cat_lr_source'
A13: cds/projections_own_experience/detail_table/ultimate_incurred_cl_ielr | B13: ultimate_incurred_cl_ielr | C13: float | D13: output | E13: n/a | F13: CL - IELR | G13: n/a | H13: ['calculate_profit_commission_task'] | I13: n/a | J13: =",'"&own_detail[[#This Row],[Name]]&"'" -> ,'ultimate_incurred_cl_ielr' | L13: cds/projections_own_experience/summary_table/lloyds_model_ielr | M13: lloyds_model_ielr | N13: float | O13: output | P13: n/a | Q13: Lloyds Model IELR | R13: n/a | S13: ['calculate_profit_commission_task'] | T13: n/a | U13: =",'"&own_summary[[#This Row],[Name]]&"'" -> ,'lloyds_model_ielr' | W13: cds/projections_lloyds/detail_table/ultimate_cl_paid | X13: ultimate_cl_paid | Y13: float | Z13: output | AA13: n/a | AB13: CL Ultimate Paid | AC13: n/a | AD13: n/a | AE13: [] | AF13: =",'"&lloyds_detail[[#This Row],[Name]]&"'" -> ,'ultimate_cl_paid' | AH13: cds/projections_lloyds/summary_table/lloyds_ielr | AI13: lloyds_ielr | AJ13: float | AK13: output | AL13: n/a | AM13: Lloyds IELR | AN13: n/a | AO13: n/a | AP13: [] | AQ13: =",'"&lloyds_summary[[#This Row],[Name]]&"'" -> ,'lloyds_ielr' | AS13: cds/projections_beazley/detail_table/ultimate_cl_paid | AT13: ultimate_cl_paid | AU13: float | AV13: output | AW13: n/a | AX13: CL Ultimate Paid | AY13: n/a | AZ13: n/a | BA13: [] | BB13: =",'"&beazley_detail[[#This Row],[Name]]&"'" -> ,'ultimate_cl_paid' | BD13: cds/projections_beazley/summary_table/lloyds_ielr | BE13: lloyds_ielr | BF13: float | BG13: output | BH13: n/a | BI13: Lloyds IELR | BJ13: n/a | BK13: n/a | BL13: [] | BM13: =",'"&beazley_summary[[#This Row],[Name]]&"'" -> ,'lloyds_ielr'
A14: cds/projections_own_experience/detail_table/additional_ibnr_attr | B14: additional_ibnr_attr | C14: float | D14: input | E14: optional | F14: Attritional | G14: 0 | H14: ['calculate_profit_commission_task'] | I14: n/a | J14: =",'"&own_detail[[#This Row],[Name]]&"'" -> ,'additional_ibnr_attr' | L14: cds/projections_own_experience/summary_table/lloyds_model_final_gn_ulr | M14: lloyds_model_final_gn_ulr | N14: float | O14: output | P14: n/a | Q14: Lloyds Model GNULR | R14: n/a | S14: ['calculate_profit_commission_task'] | T14: n/a | U14: =",'"&own_summary[[#This Row],[Name]]&"'" -> ,'lloyds_model_final_gn_ulr' | W14: cds/projections_lloyds/detail_table/ultimate_cl_paid_ulr | X14: ultimate_cl_paid_ulr | Y14: float | Z14: output | AA14: n/a | AB14: CL ULR Paid | AC14: n/a | AD14: n/a | AE14: [] | AF14: =",'"&lloyds_detail[[#This Row],[Name]]&"'" -> ,'ultimate_cl_paid_ulr' | AH14: cds/projections_lloyds/summary_table/composition | AI14: composition | AJ14: float | AK14: output | AL14: n/a | AM14: Composition | AN14: n/a | AO14: n/a | AP14: [] | AQ14: =",'"&lloyds_summary[[#This Row],[Name]]&"'" -> ,'composition' | AS14: cds/projections_beazley/detail_table/ultimate_cl_paid_ulr | AT14: ultimate_cl_paid_ulr | AU14: float | AV14: output | AW14: n/a | AX14: CL ULR Paid | AY14: n/a | AZ14: n/a | BA14: [] | BB14: =",'"&beazley_detail[[#This Row],[Name]]&"'" -> ,'ultimate_cl_paid_ulr' | BD14: cds/projections_beazley/summary_table/composition | BE14: composition | BF14: float | BG14: output | BH14: n/a | BI14: Composition | BJ14: n/a | BK14: n/a | BL14: [] | BM14: =",'"&beazley_summary[[#This Row],[Name]]&"'" -> ,'composition'
A15: cds/projections_own_experience/detail_table/additional_ibnr_large | B15: additional_ibnr_large | C15: float | D15: input | E15: optional | F15: Large | G15: 0 | H15: ['calculate_profit_commission_task'] | I15: n/a | J15: =",'"&own_detail[[#This Row],[Name]]&"'" -> ,'additional_ibnr_large' | L15: cds/projections_own_experience/summary_table/lloyds_selected_ielr | M15: lloyds_selected_ielr | N15: float | O15: output | P15: n/a | Q15: Lloyds Selected IELR | R15: n/a | S15: ['calculate_profit_commission_task'] | T15: n/a | U15: =",'"&own_summary[[#This Row],[Name]]&"'" -> ,'lloyds_selected_ielr' | W15: cds/projections_lloyds/detail_table/ultimate_cl_incurred | X15: ultimate_cl_incurred | Y15: float | Z15: output | AA15: n/a | AB15: CL Ultimate Incurred | AC15: n/a | AD15: n/a | AE15: [] | AF15: =",'"&lloyds_detail[[#This Row],[Name]]&"'" -> ,'ultimate_cl_incurred' | AH15: cds/projections_lloyds/summary_table/model_ielr_nominal | AI15: model_ielr_nominal | AJ15: float | AK15: output | AL15: n/a | AM15: Model Default IELR - Nominal | AN15: n/a | AO15: n/a | AP15: [] | AQ15: =",'"&lloyds_summary[[#This Row],[Name]]&"'" -> ,'model_ielr_nominal' | AS15: cds/projections_beazley/detail_table/ultimate_cl_incurred | AT15: ultimate_cl_incurred | AU15: float | AV15: output | AW15: n/a | AX15: CL Ultimate Incurred | AY15: n/a | AZ15: n/a | BA15: [] | BB15: =",'"&beazley_detail[[#This Row],[Name]]&"'" -> ,'ultimate_cl_incurred' | BD15: cds/projections_beazley/summary_table/model_ielr_nominal | BE15: model_ielr_nominal | BF15: float | BG15: output | BH15: n/a | BI15: Model Default IELR - Nominal | BJ15: n/a | BK15: n/a | BL15: [] | BM15: =",'"&beazley_summary[[#This Row],[Name]]&"'" -> ,'model_ielr_nominal'
A16: cds/projections_own_experience/detail_table/additional_ibnr_cat | B16: additional_ibnr_cat | C16: float | D16: input | E16: optional | F16: Cat | G16: 0 | H16: ['calculate_profit_commission_task'] | I16: n/a | J16: =",'"&own_detail[[#This Row],[Name]]&"'" -> ,'additional_ibnr_cat' | L16: cds/projections_own_experience/summary_table/lloyds_selected_final_gn_ulr | M16: lloyds_selected_final_gn_ulr | N16: float | O16: output | P16: n/a | Q16: Lloyds Selected GNULR | R16: n/a | S16: ['calculate_profit_commission_task'] | T16: n/a | U16: =",'"&own_summary[[#This Row],[Name]]&"'" -> ,'lloyds_selected_final_gn_ulr' | W16: cds/projections_lloyds/detail_table/ultimate_cl_incurred_ulr | X16: ultimate_cl_incurred_ulr | Y16: float | Z16: output | AA16: n/a | AB16: CL ULR Incurred | AC16: n/a | AD16: n/a | AE16: [] | AF16: =",'"&lloyds_detail[[#This Row],[Name]]&"'" -> ,'ultimate_cl_incurred_ulr' | AH16: cds/projections_lloyds/summary_table/model_ielr_onlevel | AI16: model_ielr_onlevel | AJ16: float | AK16: output | AL16: n/a | AM16: Model Default IELR - On-Level | AN16: n/a | AO16: n/a | AP16: [] | AQ16: =",'"&lloyds_summary[[#This Row],[Name]]&"'" -> ,'model_ielr_onlevel' | AS16: cds/projections_beazley/detail_table/ultimate_cl_incurred_ulr | AT16: ultimate_cl_incurred_ulr | AU16: float | AV16: output | AW16: n/a | AX16: CL ULR Incurred | AY16: n/a | AZ16: n/a | BA16: [] | BB16: =",'"&beazley_detail[[#This Row],[Name]]&"'" -> ,'ultimate_cl_incurred_ulr' | BD16: cds/projections_beazley/summary_table/model_ielr_onlevel | BE16: model_ielr_onlevel | BF16: float | BG16: output | BH16: n/a | BI16: Model Default IELR - On-Level | BJ16: n/a | BK16: n/a | BL16: [] | BM16: =",'"&beazley_summary[[#This Row],[Name]]&"'" -> ,'model_ielr_onlevel'
A17: cds/projections_own_experience/detail_table/additional_ibnr_total | B17: additional_ibnr_total | C17: float | D17: output | E17: n/a | F17: Total | G17: n/a | H17: ['calculate_profit_commission_task'] | I17: n/a | J17: =",'"&own_detail[[#This Row],[Name]]&"'" -> ,'additional_ibnr_total' | L17: cds/projections_own_experience/summary_table/beazley_model_ielr | M17: beazley_model_ielr | N17: float | O17: output | P17: n/a | Q17: Beazley Model IELR | R17: n/a | S17: ['calculate_profit_commission_task'] | T17: n/a | U17: =",'"&own_summary[[#This Row],[Name]]&"'" -> ,'beazley_model_ielr' | W17: cds/projections_lloyds/detail_table/ultimate_ielr_model | X17: ultimate_ielr_model | Y17: float | Z17: output | AA17: n/a | AB17: Model Incurred | AC17: n/a | AD17: n/a | AE17: [] | AF17: =",'"&lloyds_detail[[#This Row],[Name]]&"'" -> ,'ultimate_ielr_model' | AH17: cds/projections_lloyds/summary_table/model_ielr_ol_allyr | AI17: model_ielr_ol_allyr | AJ17: float | AK17: output | AL17: n/a | AM17: Model Default IELR - On-level All yr | AN17: n/a | AO17: n/a | AP17: [] | AQ17: =",'"&lloyds_summary[[#This Row],[Name]]&"'" -> ,'model_ielr_ol_allyr' | AS17: cds/projections_beazley/detail_table/ultimate_ielr_model | AT17: ultimate_ielr_model | AU17: float | AV17: output | AW17: n/a | AX17: Model Incurred | AY17: n/a | AZ17: n/a | BA17: [] | BB17: =",'"&beazley_detail[[#This Row],[Name]]&"'" -> ,'ultimate_ielr_model' | BD17: cds/projections_beazley/summary_table/model_ielr_ol_allyr | BE17: model_ielr_ol_allyr | BF17: float | BG17: output | BH17: n/a | BI17: Model Default IELR - On-level All yr | BJ17: n/a | BK17: n/a | BL17: [] | BM17: =",'"&beazley_summary[[#This Row],[Name]]&"'" -> ,'model_ielr_ol_allyr'
A18: cds/projections_own_experience/detail_table/is_row_visible | B18: is_row_visible | C18: bool | D18: output | E18: n/a | F18: is_row_visible | G18: n/a | H18: ['calculate_profit_commission_task'] | I18: n/a | J18: =",'"&own_detail[[#This Row],[Name]]&"'" -> ,'is_row_visible' | L18: cds/projections_own_experience/summary_table/beazley_model_final_gn_ulr | M18: beazley_model_final_gn_ulr | N18: float | O18: output | P18: n/a | Q18: Beazley Model GNULR | R18: n/a | S18: ['calculate_profit_commission_task'] | T18: n/a | U18: =",'"&own_summary[[#This Row],[Name]]&"'" -> ,'beazley_model_final_gn_ulr' | W18: cds/projections_lloyds/detail_table/ultimate_ielr_model_ulr | X18: ultimate_ielr_model_ulr | Y18: float | Z18: output | AA18: n/a | AB18: IELR Model | AC18: n/a | AD18: n/a | AE18: [] | AF18: =",'"&lloyds_detail[[#This Row],[Name]]&"'" -> ,'ultimate_ielr_model_ulr' | AH18: cds/projections_lloyds/summary_table/model_ielr | AI18: model_ielr | AJ18: float | AK18: output | AL18: n/a | AM18: Model Default IELR - Incurred | AN18: n/a | AO18: n/a | AP18: [] | AQ18: =",'"&lloyds_summary[[#This Row],[Name]]&"'" -> ,'model_ielr' | AS18: cds/projections_beazley/detail_table/ultimate_ielr_model_ulr | AT18: ultimate_ielr_model_ulr | AU18: float | AV18: output | AW18: n/a | AX18: IELR Model | AY18: n/a | AZ18: n/a | BA18: [] | BB18: =",'"&beazley_detail[[#This Row],[Name]]&"'" -> ,'ultimate_ielr_model_ulr' | BD18: cds/projections_beazley/summary_table/model_ielr | BE18: model_ielr | BF18: float | BG18: output | BH18: n/a | BI18: Model Default IELR - Incurred | BJ18: n/a | BK18: n/a | BL18: [] | BM18: =",'"&beazley_summary[[#This Row],[Name]]&"'" -> ,'model_ielr'
A19: cds/projections_own_experience/detail_table/lob_visible_1 | B19: lob_visible_1 | C19: bool | D19: output | E19: n/a | F19: lob_visible_1 | G19: n/a | H19: ['calculate_profit_commission_task'] | I19: n/a | J19: =",'"&own_detail[[#This Row],[Name]]&"'" -> ,'lob_visible_1' | L19: cds/projections_own_experience/summary_table/beazley_selected_ielr | M19: beazley_selected_ielr | N19: float | O19: output | P19: n/a | Q19: Beazley Selected IELR | R19: n/a | S19: ['calculate_profit_commission_task'] | T19: n/a | U19: =",'"&own_summary[[#This Row],[Name]]&"'" -> ,'beazley_selected_ielr' | W19: cds/projections_lloyds/detail_table/ultimate_ielr_selected | X19: ultimate_ielr_selected | Y19: float | Z19: output | AA19: n/a | AB19: Selected Incurred | AC19: n/a | AD19: n/a | AE19: [] | AF19: =",'"&lloyds_detail[[#This Row],[Name]]&"'" -> ,'ultimate_ielr_selected' | AH19: cds/projections_lloyds/summary_table/model_gn_ulr | AI19: model_gn_ulr | AJ19: float | AK19: output | AL19: n/a | AM19: GN ULR | AN19: n/a | AO19: n/a | AP19: [] | AQ19: =",'"&lloyds_summary[[#This Row],[Name]]&"'" -> ,'model_gn_ulr' | AS19: cds/projections_beazley/detail_table/ultimate_ielr_selected | AT19: ultimate_ielr_selected | AU19: float | AV19: output | AW19: n/a | AX19: Selected Incurred | AY19: n/a | AZ19: n/a | BA19: [] | BB19: =",'"&beazley_detail[[#This Row],[Name]]&"'" -> ,'ultimate_ielr_selected' | BD19: cds/projections_beazley/summary_table/model_gn_ulr | BE19: model_gn_ulr | BF19: float | BG19: output | BH19: n/a | BI19: GN ULR | BJ19: n/a | BK19: n/a | BL19: [] | BM19: =",'"&beazley_summary[[#This Row],[Name]]&"'" -> ,'model_gn_ulr'
A20: cds/projections_own_experience/detail_table/lob_visible_2 | B20: lob_visible_2 | C20: bool | D20: output | E20: n/a | F20: lob_visible_2 | G20: n/a | H20: ['calculate_profit_commission_task'] | I20: n/a | J20: =",'"&own_detail[[#This Row],[Name]]&"'" -> ,'lob_visible_2' | L20: cds/projections_own_experience/summary_table/beazley_selected_final_gn_ulr | M20: beazley_selected_final_gn_ulr | N20: float | O20: output | P20: n/a | Q20: Beazley Selected GNULR | R20: n/a | S20: ['calculate_profit_commission_task'] | T20: n/a | U20: =",'"&own_summary[[#This Row],[Name]]&"'" -> ,'beazley_selected_final_gn_ulr' | W20: cds/projections_lloyds/detail_table/ultimate_ielr_selected_ulr | X20: ultimate_ielr_selected_ulr | Y20: float | Z20: output | AA20: n/a | AB20: IELR Selected | AC20: n/a | AD20: n/a | AE20: [] | AF20: =",'"&lloyds_detail[[#This Row],[Name]]&"'" -> ,'ultimate_ielr_selected_ulr' | AH20: cds/projections_lloyds/summary_table/model_base_aqn | AI20: model_base_aqn | AJ20: float | AK20: output | AL20: n/a | AM20: Base Aqn | AN20: n/a | AO20: n/a | AP20: [] | AQ20: =",'"&lloyds_summary[[#This Row],[Name]]&"'" -> ,'model_base_aqn' | AS20: cds/projections_beazley/detail_table/ultimate_ielr_selected_ulr | AT20: ultimate_ielr_selected_ulr | AU20: float | AV20: output | AW20: n/a | AX20: IELR Selected | AY20: n/a | AZ20: n/a | BA20: [] | BB20: =",'"&beazley_detail[[#This Row],[Name]]&"'" -> ,'ultimate_ielr_selected_ulr' | BD20: cds/projections_beazley/summary_table/model_base_aqn | BE20: model_base_aqn | BF20: float | BG20: output | BH20: n/a | BI20: Base Aqn | BJ20: n/a | BK20: n/a | BL20: [] | BM20: =",'"&beazley_summary[[#This Row],[Name]]&"'" -> ,'model_base_aqn'
A21: cds/projections_own_experience/detail_table/lob_visible_3 | B21: lob_visible_3 | C21: bool | D21: output | E21: n/a | F21: lob_visible_3 | G21: n/a | H21: ['calculate_profit_commission_task'] | I21: n/a | J21: =",'"&own_detail[[#This Row],[Name]]&"'" -> ,'lob_visible_3' | L21: cds/projections_own_experience/summary_table/ielr_nominal_attr | M21: ielr_nominal_attr | N21: float | O21: output | P21: n/a | Q21: Attritional IELR | R21: n/a | S21: ['calculate_profit_commission_task'] | T21: n/a | U21: =",'"&own_summary[[#This Row],[Name]]&"'" -> ,'ielr_nominal_attr' | W21: cds/projections_lloyds/detail_table/ultimate_bf_model_paid | X21: ultimate_bf_model_paid | Y21: float | Z21: output | AA21: n/a | AB21: Model Paid | AC21: n/a | AD21: n/a | AE21: [] | AF21: =",'"&lloyds_detail[[#This Row],[Name]]&"'" -> ,'ultimate_bf_model_paid' | AH21: cds/projections_lloyds/summary_table/model_acc_aqn | AI21: model_acc_aqn | AJ21: float | AK21: output | AL21: n/a | AM21: Account Aqn | AN21: n/a | AO21: n/a | AP21: [] | AQ21: =",'"&lloyds_summary[[#This Row],[Name]]&"'" -> ,'model_acc_aqn' | AS21: cds/projections_beazley/detail_table/ultimate_bf_model_paid | AT21: ultimate_bf_model_paid | AU21: float | AV21: output | AW21: n/a | AX21: Model Paid | AY21: n/a | AZ21: n/a | BA21: [] | BB21: =",'"&beazley_detail[[#This Row],[Name]]&"'" -> ,'ultimate_bf_model_paid' | BD21: cds/projections_beazley/summary_table/model_acc_aqn | BE21: model_acc_aqn | BF21: float | BG21: output | BH21: n/a | BI21: Account Aqn | BJ21: n/a | BK21: n/a | BL21: [] | BM21: =",'"&beazley_summary[[#This Row],[Name]]&"'" -> ,'model_acc_aqn'
A22: cds/projections_own_experience/detail_table/latest_incurred_open_claims_attr | B22: latest_incurred_open_claims_attr | C22: float | D22: output | E22: n/a | F22: Attritional | G22: n/a | H22: ['calculate_profit_commission_task'] | I22: n/a | J22: =",'"&own_detail[[#This Row],[Name]]&"'" -> ,'latest_incurred_open_claims_attr' | L22: cds/projections_own_experience/summary_table/ielr_nominal_large | M22: ielr_nominal_large | N22: float | O22: output | P22: n/a | Q22: Large IELR | R22: n/a | S22: ['calculate_profit_commission_task'] | T22: n/a | U22: =",'"&own_summary[[#This Row],[Name]]&"'" -> ,'ielr_nominal_large' | W22: cds/projections_lloyds/detail_table/ultimate_bf_model_incurred | X22: ultimate_bf_model_incurred | Y22: float | Z22: output | AA22: n/a | AB22: Model Incurred | AC22: n/a | AD22: n/a | AE22: [] | AF22: =",'"&lloyds_detail[[#This Row],[Name]]&"'" -> ,'ultimate_bf_model_incurred' | AH22: cds/projections_lloyds/summary_table/model_adj_gn_ulr | AI22: model_adj_gn_ulr | AJ22: float | AK22: output | AL22: n/a | AM22: GN ULR Acc Aqn | AN22: n/a | AO22: n/a | AP22: [] | AQ22: =",'"&lloyds_summary[[#This Row],[Name]]&"'" -> ,'model_adj_gn_ulr' | AS22: cds/projections_beazley/detail_table/ultimate_bf_model_incurred | AT22: ultimate_bf_model_incurred | AU22: float | AV22: output | AW22: n/a | AX22: Model Incurred | AY22: n/a | AZ22: n/a | BA22: [] | BB22: =",'"&beazley_detail[[#This Row],[Name]]&"'" -> ,'ultimate_bf_model_incurred' | BD22: cds/projections_beazley/summary_table/model_adj_gn_ulr | BE22: model_adj_gn_ulr | BF22: float | BG22: output | BH22: n/a | BI22: GN ULR Acc Aqn | BJ22: n/a | BK22: n/a | BL22: [] | BM22: =",'"&beazley_summary[[#This Row],[Name]]&"'" -> ,'model_adj_gn_ulr'
A23: cds/projections_own_experience/detail_table/latest_incurred_closed_claims_attr | B23: latest_incurred_closed_claims_attr | C23: float | D23: output | E23: n/a | F23: Attritional | G23: n/a | H23: ['calculate_profit_commission_task'] | I23: n/a | J23: =",'"&own_detail[[#This Row],[Name]]&"'" -> ,'latest_incurred_closed_claims_attr' | L23: cds/projections_own_experience/summary_table/ielr_nominal_cat | M23: ielr_nominal_cat | N23: float | O23: output | P23: n/a | Q23: CAT IELR | R23: n/a | S23: ['calculate_profit_commission_task'] | T23: n/a | U23: =",'"&own_summary[[#This Row],[Name]]&"'" -> ,'ielr_nominal_cat' | W23: cds/projections_lloyds/detail_table/ultimate_bf_selected_paid | X23: ultimate_bf_selected_paid | Y23: float | Z23: output | AA23: n/a | AB23: Selected Paid | AC23: n/a | AD23: n/a | AE23: [] | AF23: =",'"&lloyds_detail[[#This Row],[Name]]&"'" -> ,'ultimate_bf_selected_paid' | AH23: cds/projections_lloyds/summary_table/model_final_gn_ulr | AI23: model_final_gn_ulr | AJ23: float | AK23: output | AL23: n/a | AM23: Final GN ULR | AN23: n/a | AO23: n/a | AP23: [] | AQ23: =",'"&lloyds_summary[[#This Row],[Name]]&"'" -> ,'model_final_gn_ulr' | AS23: cds/projections_beazley/detail_table/ultimate_bf_selected_paid | AT23: ultimate_bf_selected_paid | AU23: float | AV23: output | AW23: n/a | AX23: Selected Paid | AY23: n/a | AZ23: n/a | BA23: [] | BB23: =",'"&beazley_detail[[#This Row],[Name]]&"'" -> ,'ultimate_bf_selected_paid' | BD23: cds/projections_beazley/summary_table/model_final_gn_ulr | BE23: model_final_gn_ulr | BF23: float | BG23: output | BH23: n/a | BI23: Final GN ULR | BJ23: n/a | BK23: n/a | BL23: [] | BM23: =",'"&beazley_summary[[#This Row],[Name]]&"'" -> ,'model_final_gn_ulr'
A24: cds/projections_own_experience/detail_table/latest_incurred_total_claims_attr | B24: latest_incurred_total_claims_attr | C24: float | D24: output | E24: n/a | F24: Attritional | G24: n/a | H24: ['calculate_profit_commission_task'] | I24: n/a | J24: =",'"&own_detail[[#This Row],[Name]]&"'" -> ,'latest_incurred_total_claims_attr' | L24: cds/projections_own_experience/summary_table/ielr_nominal_total | M24: ielr_nominal_total | N24: float | O24: output | P24: n/a | Q24: Total IELR | R24: n/a | S24: ['calculate_profit_commission_task'] | T24: n/a | U24: =",'"&own_summary[[#This Row],[Name]]&"'" -> ,'ielr_nominal_total' | W24: cds/projections_lloyds/detail_table/ultimate_bf_selected_incurred | X24: ultimate_bf_selected_incurred | Y24: float | Z24: output | AA24: n/a | AB24: Selected Incurred | AC24: n/a | AD24: n/a | AE24: [] | AF24: =",'"&lloyds_detail[[#This Row],[Name]]&"'" -> ,'ultimate_bf_selected_incurred' | AH24: cds/projections_lloyds/summary_table/selected_ielr | AI24: selected_ielr | AJ24: float | AK24: override | AL24: n/a | AM24: Selected IELR - Incurred | AN24: n/a | AO24: ['sync_lob_lists_task'] | AP24: [] | AQ24: =",'"&lloyds_summary[[#This Row],[Name]]&"'" -> ,'selected_ielr' | AS24: cds/projections_beazley/detail_table/ultimate_bf_selected_incurred | AT24: ultimate_bf_selected_incurred | AU24: float | AV24: output | AW24: n/a | AX24: Selected Incurred | AY24: n/a | AZ24: n/a | BA24: [] | BB24: =",'"&beazley_detail[[#This Row],[Name]]&"'" -> ,'ultimate_bf_selected_incurred' | BD24: cds/projections_beazley/summary_table/selected_ielr | BE24: selected_ielr | BF24: float | BG24: override | BH24: n/a | BI24: Selected IELR - Incurred | BJ24: n/a | BK24: ['sync_lob_lists_task'] | BL24: [] | BM24: =",'"&beazley_summary[[#This Row],[Name]]&"'" -> ,'selected_ielr'
A25: cds/projections_own_experience/detail_table/last_year_position_attr | B25: last_year_position_attr | C25: float | D25: input | E25: optional | F25: Attritional | G25: 0 | H25: ['calculate_profit_commission_task'] | I25: n/a | J25: =",'"&own_detail[[#This Row],[Name]]&"'" -> ,'last_year_position_attr' | L25: cds/projections_own_experience/summary_table/ielr_nominal_total_excl_cat | M25: ielr_nominal_total_excl_cat | N25: float | O25: output | P25: n/a | Q25: Total (Excl. CAT) IELR | R25: n/a | S25: ['calculate_profit_commission_task'] | T25: n/a | U25: =",'"&own_summary[[#This Row],[Name]]&"'" -> ,'ielr_nominal_total_excl_cat' | W25: cds/projections_lloyds/detail_table/ultimate_model | X25: ultimate_model | Y25: float | Z25: output | AA25: n/a | AB25: Model Ult. Incurred | AC25: n/a | AD25: n/a | AE25: [] | AF25: =",'"&lloyds_detail[[#This Row],[Name]]&"'" -> ,'ultimate_model' | AH25: cds/projections_lloyds/summary_table/selected_gn_ulr | AI25: selected_gn_ulr | AJ25: float | AK25: output | AL25: n/a | AM25: GN ULR | AN25: n/a | AO25: n/a | AP25: [] | AQ25: =",'"&lloyds_summary[[#This Row],[Name]]&"'" -> ,'selected_gn_ulr' | AS25: cds/projections_beazley/detail_table/ultimate_model | AT25: ultimate_model | AU25: float | AV25: output | AW25: n/a | AX25: Model Ult. Incurred | AY25: n/a | AZ25: n/a | BA25: [] | BB25: =",'"&beazley_detail[[#This Row],[Name]]&"'" -> ,'ultimate_model' | BD25: cds/projections_beazley/summary_table/selected_gn_ulr | BE25: selected_gn_ulr | BF25: float | BG25: output | BH25: n/a | BI25: GN ULR | BJ25: n/a | BK25: n/a | BL25: [] | BM25: =",'"&beazley_summary[[#This Row],[Name]]&"'" -> ,'selected_gn_ulr'
A26: cds/projections_own_experience/detail_table/movement_attr | B26: movement_attr | C26: float | D26: output | E26: n/a | F26: Attritional | G26: n/a | H26: ['calculate_profit_commission_task'] | I26: n/a | J26: =",'"&own_detail[[#This Row],[Name]]&"'" -> ,'movement_attr' | L26: cds/projections_own_experience/summary_table/ielr_ol_all_yr_attr | M26: ielr_ol_all_yr_attr | N26: float | O26: output | P26: n/a | Q26: Attritional IELR | R26: n/a | S26: ['calculate_profit_commission_task'] | T26: n/a | U26: =",'"&own_summary[[#This Row],[Name]]&"'" -> ,'ielr_ol_all_yr_attr' | W26: cds/projections_lloyds/detail_table/ultimate_model_ulr | X26: ultimate_model_ulr | Y26: float | Z26: output | AA26: n/a | AB26: Model Ult. ULR | AC26: n/a | AD26: n/a | AE26: [] | AF26: =",'"&lloyds_detail[[#This Row],[Name]]&"'" -> ,'ultimate_model_ulr' | AH26: cds/projections_lloyds/summary_table/selected_base_aqn | AI26: selected_base_aqn | AJ26: float | AK26: output | AL26: n/a | AM26: Base Aqn | AN26: n/a | AO26: n/a | AP26: [] | AQ26: =",'"&lloyds_summary[[#This Row],[Name]]&"'" -> ,'selected_base_aqn' | AS26: cds/projections_beazley/detail_table/ultimate_model_ulr | AT26: ultimate_model_ulr | AU26: float | AV26: output | AW26: n/a | AX26: Model Ult. ULR | AY26: n/a | AZ26: n/a | BA26: [] | BB26: =",'"&beazley_detail[[#This Row],[Name]]&"'" -> ,'ultimate_model_ulr' | BD26: cds/projections_beazley/summary_table/selected_base_aqn | BE26: selected_base_aqn | BF26: float | BG26: output | BH26: n/a | BI26: Base Aqn | BJ26: n/a | BK26: n/a | BL26: [] | BM26: =",'"&beazley_summary[[#This Row],[Name]]&"'" -> ,'selected_base_aqn'
A27: cds/projections_own_experience/detail_table/gn_ilr_attr | B27: gn_ilr_attr | C27: float | D27: output | E27: n/a | F27: Attritional | G27: n/a | H27: ['calculate_profit_commission_task'] | I27: n/a | J27: =",'"&own_detail[[#This Row],[Name]]&"'" -> ,'gn_ilr_attr' | L27: cds/projections_own_experience/summary_table/ielr_ol_all_yr_large | M27: ielr_ol_all_yr_large | N27: float | O27: output | P27: n/a | Q27: Large IELR | R27: n/a | S27: ['calculate_profit_commission_task'] | T27: n/a | U27: =",'"&own_summary[[#This Row],[Name]]&"'" -> ,'ielr_ol_all_yr_large' | W27: cds/projections_lloyds/detail_table/ultimate_selected | X27: ultimate_selected | Y27: float | Z27: output | AA27: n/a | AB27: Selected Ult. Incurred | AC27: n/a | AD27: n/a | AE27: [] | AF27: =",'"&lloyds_detail[[#This Row],[Name]]&"'" -> ,'ultimate_selected' | AH27: cds/projections_lloyds/summary_table/selected_acc_aqn | AI27: selected_acc_aqn | AJ27: float | AK27: output | AL27: n/a | AM27: Account Aqn | AN27: n/a | AO27: n/a | AP27: [] | AQ27: =",'"&lloyds_summary[[#This Row],[Name]]&"'" -> ,'selected_acc_aqn' | AS27: cds/projections_beazley/detail_table/ultimate_selected | AT27: ultimate_selected | AU27: float | AV27: output | AW27: n/a | AX27: Selected Ult. Incurred | AY27: n/a | AZ27: n/a | BA27: [] | BB27: =",'"&beazley_detail[[#This Row],[Name]]&"'" -> ,'ultimate_selected' | BD27: cds/projections_beazley/summary_table/selected_acc_aqn | BE27: selected_acc_aqn | BF27: float | BG27: output | BH27: n/a | BI27: Account Aqn | BJ27: n/a | BK27: n/a | BL27: [] | BM27: =",'"&beazley_summary[[#This Row],[Name]]&"'" -> ,'selected_acc_aqn'
A28: cds/projections_own_experience/detail_table/ultimate_incurred_ielr_attr | B28: ultimate_incurred_ielr_attr | C28: float | D28: output | E28: n/a | F28: Attritional | G28: n/a | H28: ['calculate_profit_commission_task'] | I28: n/a | J28: =",'"&own_detail[[#This Row],[Name]]&"'" -> ,'ultimate_incurred_ielr_attr' | L28: cds/projections_own_experience/summary_table/ielr_ol_all_yr_cat | M28: ielr_ol_all_yr_cat | N28: float | O28: output | P28: n/a | Q28: CAT IELR | R28: n/a | S28: ['calculate_profit_commission_task'] | T28: n/a | U28: =",'"&own_summary[[#This Row],[Name]]&"'" -> ,'ielr_ol_all_yr_cat' | W28: cds/projections_lloyds/detail_table/ultimate_selected_ulr | X28: ultimate_selected_ulr | Y28: float | Z28: output | AA28: n/a | AB28: Selected Ult. ULR | AC28: n/a | AD28: n/a | AE28: [] | AF28: =",'"&lloyds_detail[[#This Row],[Name]]&"'" -> ,'ultimate_selected_ulr' | AH28: cds/projections_lloyds/summary_table/selected_adj_gn_ulr | AI28: selected_adj_gn_ulr | AJ28: float | AK28: output | AL28: n/a | AM28: GN ULR Acc Aqn | AN28: n/a | AO28: n/a | AP28: [] | AQ28: =",'"&lloyds_summary[[#This Row],[Name]]&"'" -> ,'selected_adj_gn_ulr' | AS28: cds/projections_beazley/detail_table/ultimate_selected_ulr | AT28: ultimate_selected_ulr | AU28: float | AV28: output | AW28: n/a | AX28: Selected Ult. ULR | AY28: n/a | AZ28: n/a | BA28: [] | BB28: =",'"&beazley_detail[[#This Row],[Name]]&"'" -> ,'ultimate_selected_ulr' | BD28: cds/projections_beazley/summary_table/selected_adj_gn_ulr | BE28: selected_adj_gn_ulr | BF28: float | BG28: output | BH28: n/a | BI28: GN ULR Acc Aqn | BJ28: n/a | BK28: n/a | BL28: [] | BM28: =",'"&beazley_summary[[#This Row],[Name]]&"'" -> ,'selected_adj_gn_ulr'
A29: cds/projections_own_experience/detail_table/ultimate_incurred_bf_attr | B29: ultimate_incurred_bf_attr | C29: float | D29: output | E29: n/a | F29: Attritional | G29: n/a | H29: ['calculate_profit_commission_task'] | I29: n/a | J29: =",'"&own_detail[[#This Row],[Name]]&"'" -> ,'ultimate_incurred_bf_attr' | L29: cds/projections_own_experience/summary_table/ielr_ol_all_yr_total | M29: ielr_ol_all_yr_total | N29: float | O29: output | P29: n/a | Q29: Total IELR | R29: n/a | S29: ['calculate_profit_commission_task'] | T29: n/a | U29: =",'"&own_summary[[#This Row],[Name]]&"'" -> ,'ielr_ol_all_yr_total' | W29: cds/projections_lloyds/detail_table/on_levelled_model_ulr | X29: on_levelled_model_ulr | Y29: float | Z29: output | AA29: n/a | AB29: Model ULR | AC29: n/a | AD29: n/a | AE29: [] | AF29: =",'"&lloyds_detail[[#This Row],[Name]]&"'" -> ,'on_levelled_model_ulr' | AH29: cds/projections_lloyds/summary_table/selected_final_gn_ulr | AI29: selected_final_gn_ulr | AJ29: float | AK29: output | AL29: n/a | AM29: Final GN ULR | AN29: n/a | AO29: n/a | AP29: [] | AQ29: =",'"&lloyds_summary[[#This Row],[Name]]&"'" -> ,'selected_final_gn_ulr' | AS29: cds/projections_beazley/detail_table/on_levelled_model_ulr | AT29: on_levelled_model_ulr | AU29: float | AV29: output | AW29: n/a | AX29: Model ULR | AY29: n/a | AZ29: n/a | BA29: [] | BB29: =",'"&beazley_detail[[#This Row],[Name]]&"'" -> ,'on_levelled_model_ulr' | BD29: cds/projections_beazley/summary_table/selected_final_gn_ulr | BE29: selected_final_gn_ulr | BF29: float | BG29: output | BH29: n/a | BI29: Final GN ULR | BJ29: n/a | BK29: n/a | BL29: [] | BM29: =",'"&beazley_summary[[#This Row],[Name]]&"'" -> ,'selected_final_gn_ulr'
A30: cds/projections_own_experience/detail_table/ultimate_incurred_cl_attr | B30: ultimate_incurred_cl_attr | C30: float | D30: output | E30: n/a | F30: Attritional | G30: n/a | H30: ['calculate_profit_commission_task'] | I30: n/a | J30: =",'"&own_detail[[#This Row],[Name]]&"'" -> ,'ultimate_incurred_cl_attr' | L30: cds/projections_own_experience/summary_table/ielr_ol_all_yr_total_excl_cat | M30: ielr_ol_all_yr_total_excl_cat | N30: float | O30: output | P30: n/a | Q30: Total (Excl. CAT) IELR | R30: n/a | S30: ['calculate_profit_commission_task'] | T30: n/a | U30: =",'"&own_summary[[#This Row],[Name]]&"'" -> ,'ielr_ol_all_yr_total_excl_cat' | W30: cds/projections_lloyds/detail_table/on_levelled_selected_ulr | X30: on_levelled_selected_ulr | Y30: float | Z30: output | AA30: n/a | AB30: Selected ULR | AC30: n/a | AD30: n/a | AE30: [] | AF30: =",'"&lloyds_detail[[#This Row],[Name]]&"'" -> ,'on_levelled_selected_ulr' | AH30: cds/projections_lloyds/summary_table/bp_cat | AI30: bp_cat | AJ30: bool | AK30: input | AL30: required | AM30: Apply BP Cat ULR? | AN30: FALSE | AO30: ['sync_lob_lists_task'] | AP30: [] | AQ30: =",'"&lloyds_summary[[#This Row],[Name]]&"'" -> ,'bp_cat' | AS30: cds/projections_beazley/detail_table/on_levelled_selected_ulr | AT30: on_levelled_selected_ulr | AU30: float | AV30: output | AW30: n/a | AX30: Selected ULR | AY30: n/a | AZ30: n/a | BA30: [] | BB30: =",'"&beazley_detail[[#This Row],[Name]]&"'" -> ,'on_levelled_selected_ulr' | BD30: cds/projections_beazley/summary_table/bp_cat | BE30: bp_cat | BF30: bool | BG30: input | BH30: required | BI30: Apply BP Cat ULR? | BJ30: FALSE | BK30: ['sync_lob_lists_task'] | BL30: [] | BM30: =",'"&beazley_summary[[#This Row],[Name]]&"'" -> ,'bp_cat'
A31: cds/projections_own_experience/detail_table/ielr_weighting_cl_attr | B31: ielr_weighting_cl_attr | C31: float | D31: override | E31: n/a | F31: Attritional | G31: n/a | H31: ['calculate_profit_commission_task'] | I31: n/a | J31: =",'"&own_detail[[#This Row],[Name]]&"'" -> ,'ielr_weighting_cl_attr' | L31: cds/projections_own_experience/summary_table/ielr_ol_cl_yr_attr | M31: ielr_ol_cl_yr_attr | N31: float | O31: output | P31: n/a | Q31: Attritional IELR | R31: n/a | S31: ['calculate_profit_commission_task'] | T31: n/a | U31: =",'"&own_summary[[#This Row],[Name]]&"'" -> ,'ielr_ol_cl_yr_attr' | W31: cds/projections_lloyds/detail_table/lob_number | X31: lob_number | Y31: int | Z31: output | AA31: n/a | AB31: Number of Line of Business | AC31: n/a | AD31: n/a | AE31: [] | AF31: =",'"&lloyds_detail[[#This Row],[Name]]&"'" -> ,'lob_number' | AH31: cds/projections_lloyds/summary_table/bp_cat_load | AI31: bp_cat_load | AJ31: float | AK31: override | AL31: n/a | AM31: BP Cat Load | AN31: n/a | AO31: ['sync_lob_lists_task'] | AP31: [] | AQ31: =",'"&lloyds_summary[[#This Row],[Name]]&"'" -> ,'bp_cat_load' | AS31: cds/projections_beazley/detail_table/lob_number | AT31: lob_number | AU31: int | AV31: output | AW31: n/a | AX31: Number of Line of Business | AY31: n/a | AZ31: n/a | BA31: [] | BB31: =",'"&beazley_detail[[#This Row],[Name]]&"'" -> ,'lob_number' | BD31: cds/projections_beazley/summary_table/bp_cat_load | BE31: bp_cat_load | BF31: float | BG31: override | BH31: n/a | BI31: BP Cat Load | BJ31: n/a | BK31: ['sync_lob_lists_task'] | BL31: [] | BM31: =",'"&beazley_summary[[#This Row],[Name]]&"'" -> ,'bp_cat_load'
A32: cds/projections_own_experience/detail_table/ultimate_incurred_selected_attr | B32: ultimate_incurred_selected_attr | C32: float | D32: override | E32: n/a | F32: Attritional | G32: n/a | H32: ['calculate_profit_commission_task'] | I32: n/a | J32: =",'"&own_detail[[#This Row],[Name]]&"'" -> ,'ultimate_incurred_selected_attr' | L32: cds/projections_own_experience/summary_table/ielr_ol_cl_yr_large | M32: ielr_ol_cl_yr_large | N32: float | O32: output | P32: n/a | Q32: Large IELR | R32: n/a | S32: ['calculate_profit_commission_task'] | T32: n/a | U32: =",'"&own_summary[[#This Row],[Name]]&"'" -> ,'ielr_ol_cl_yr_large' | W32: cds/projections_lloyds/detail_table/risk_code | X32: risk_code | Y32: str | Z32: output | AA32: n/a | AB32: Risk Code | AC32: n/a | AD32: n/a | AE32: [] | AF32: =",'"&lloyds_detail[[#This Row],[Name]]&"'" -> ,'risk_code' | AH32: cds/projections_lloyds/summary_table/actuarial_notes | AI32: actuarial_notes | AJ32: str | AK32: input | AL32: optional | AM32: Actuarial Notes | AN32: None | AO32: ['sync_lob_lists_task'] | AP32: [] | AQ32: =",'"&lloyds_summary[[#This Row],[Name]]&"'" -> ,'actuarial_notes' | AS32: cds/projections_beazley/detail_table/risk_code | AT32: risk_code | AU32: str | AV32: output | AW32: n/a | AX32: Risk Code | AY32: n/a | AZ32: n/a | BA32: [] | BB32: =",'"&beazley_detail[[#This Row],[Name]]&"'" -> ,'risk_code' | BD32: cds/projections_beazley/summary_table/actuarial_notes | BE32: actuarial_notes | BF32: str | BG32: input | BH32: optional | BI32: Actuarial Notes | BJ32: None | BK32: ['sync_lob_lists_task'] | BL32: [] | BM32: =",'"&beazley_summary[[#This Row],[Name]]&"'" -> ,'actuarial_notes'
A33: cds/projections_own_experience/detail_table/ultimate_ulr_selected_attr | B33: ultimate_ulr_selected_attr | C33: float | D33: output | E33: n/a | F33: Attritional | G33: n/a | H33: ['calculate_profit_commission_task'] | I33: n/a | J33: =",'"&own_detail[[#This Row],[Name]]&"'" -> ,'ultimate_ulr_selected_attr' | L33: cds/projections_own_experience/summary_table/ielr_ol_cl_yr_cat | M33: ielr_ol_cl_yr_cat | N33: float | O33: output | P33: n/a | Q33: CAT IELR | R33: n/a | S33: ['calculate_profit_commission_task'] | T33: n/a | U33: =",'"&own_summary[[#This Row],[Name]]&"'" -> ,'ielr_ol_cl_yr_cat' | W33: cds/projections_lloyds/detail_table/selected_lob | X33: selected_lob | Y33: str | Z33: output | AA33: n/a | AB33: Selected Line of Business | AC33: n/a | AD33: n/a | AE33: [] | AF33: =",'"&lloyds_detail[[#This Row],[Name]]&"'" -> ,'selected_lob' | AH33: cds/projections_lloyds/summary_table/is_row_visible | AI33: is_row_visible | AJ33: bool | AK33: output | AL33: n/a | AM33: is_row_visible | AN33: n/a | AO33: n/a | AP33: [] | AQ33: =",'"&lloyds_summary[[#This Row],[Name]]&"'" -> ,'is_row_visible' | AS33: cds/projections_beazley/detail_table/selected_lob | AT33: selected_lob | AU33: str | AV33: output | AW33: n/a | AX33: Selected Line of Business | AY33: n/a | AZ33: n/a | BA33: [] | BB33: =",'"&beazley_detail[[#This Row],[Name]]&"'" -> ,'selected_lob' | BD33: cds/projections_beazley/summary_table/is_row_visible | BE33: is_row_visible | BF33: bool | BG33: output | BH33: n/a | BI33: is_row_visible | BJ33: n/a | BK33: n/a | BL33: [] | BM33: =",'"&beazley_summary[[#This Row],[Name]]&"'" -> ,'is_row_visible'
A34: cds/projections_own_experience/detail_table/ultimate_ulr_on_levelled_attr | B34: ultimate_ulr_on_levelled_attr | C34: float | D34: output | E34: n/a | F34: Attritional | G34: n/a | H34: ['calculate_profit_commission_task'] | I34: n/a | J34: =",'"&own_detail[[#This Row],[Name]]&"'" -> ,'ultimate_ulr_on_levelled_attr' | L34: cds/projections_own_experience/summary_table/ielr_ol_cl_yr_total | M34: ielr_ol_cl_yr_total | N34: float | O34: output | P34: n/a | Q34: Total IELR | R34: n/a | S34: ['calculate_profit_commission_task'] | T34: n/a | U34: =",'"&own_summary[[#This Row],[Name]]&"'" -> ,'ielr_ol_cl_yr_total' | W34: cds/projections_lloyds/detail_table/lookup_lob | X34: lookup_lob | Y34: str | Z34: output | AA34: n/a | AB34: Lookup LOB | AC34: n/a | AD34: n/a | AE34: [] | AF34: =",'"&lloyds_detail[[#This Row],[Name]]&"'" -> ,'lookup_lob' | AH34: cds/projections_lloyds/summary_table/lob_visible_1 | AI34: lob_visible_1 | AJ34: bool | AK34: output | AL34: n/a | AM34: lob_visible_1 | AN34: n/a | AO34: n/a | AP34: [] | AQ34: =",'"&lloyds_summary[[#This Row],[Name]]&"'" -> ,'lob_visible_1' | AS34: cds/projections_beazley/detail_table/lookup_lob | AT34: lookup_lob | AU34: str | AV34: output | AW34: n/a | AX34: Lookup LOB | AY34: n/a | AZ34: n/a | BA34: [] | BB34: =",'"&beazley_detail[[#This Row],[Name]]&"'" -> ,'lookup_lob' | BD34: cds/projections_beazley/summary_table/lob_visible_1 | BE34: lob_visible_1 | BF34: bool | BG34: output | BH34: n/a | BI34: lob_visible_1 | BJ34: n/a | BK34: n/a | BL34: [] | BM34: =",'"&beazley_summary[[#This Row],[Name]]&"'" -> ,'lob_visible_1'
A35: cds/projections_own_experience/detail_table/ielr_weighting_sel_attr | B35: ielr_weighting_sel_attr | C35: float | D35: override | E35: n/a | F35: Attritional | G35: n/a | H35: ['calculate_profit_commission_task'] | I35: n/a | J35: =",'"&own_detail[[#This Row],[Name]]&"'" -> ,'ielr_weighting_sel_attr' | L35: cds/projections_own_experience/summary_table/ielr_ol_cl_yr_total_excl_cat | M35: ielr_ol_cl_yr_total_excl_cat | N35: float | O35: output | P35: n/a | Q35: Total (Excl. CAT) IELR | R35: n/a | S35: ['calculate_profit_commission_task'] | T35: n/a | U35: =",'"&own_summary[[#This Row],[Name]]&"'" -> ,'ielr_ol_cl_yr_total_excl_cat' | W35: cds/projections_lloyds/detail_table/dev_patterns_gnpi | X35: dev_patterns_gnpi | Y35: float | Z35: override | AA35: n/a | AB35: GNPI | AC35: n/a | AD35: n/a | AE35: [] | AF35: =",'"&lloyds_detail[[#This Row],[Name]]&"'" -> ,'dev_patterns_gnpi' | AH35: cds/projections_lloyds/summary_table/lob_visible_2 | AI35: lob_visible_2 | AJ35: bool | AK35: output | AL35: n/a | AM35: lob_visible_2 | AN35: n/a | AO35: n/a | AP35: [] | AQ35: =",'"&lloyds_summary[[#This Row],[Name]]&"'" -> ,'lob_visible_2' | AS35: cds/projections_beazley/detail_table/dev_patterns_gnpi | AT35: dev_patterns_gnpi | AU35: float | AV35: override | AW35: n/a | AX35: GNPI | AY35: n/a | AZ35: n/a | BA35: [] | BB35: =",'"&beazley_detail[[#This Row],[Name]]&"'" -> ,'dev_patterns_gnpi' | BD35: cds/projections_beazley/summary_table/lob_visible_2 | BE35: lob_visible_2 | BF35: bool | BG35: output | BH35: n/a | BI35: lob_visible_2 | BJ35: n/a | BK35: n/a | BL35: [] | BM35: =",'"&beazley_summary[[#This Row],[Name]]&"'" -> ,'lob_visible_2'
A36: cds/projections_own_experience/detail_table/latest_incurred_open_claims_large | B36: latest_incurred_open_claims_large | C36: float | D36: output | E36: n/a | F36: Large | G36: n/a | H36: ['calculate_profit_commission_task'] | I36: n/a | J36: =",'"&own_detail[[#This Row],[Name]]&"'" -> ,'latest_incurred_open_claims_large' | L36: cds/projections_own_experience/summary_table/selected_attr | M36: selected_attr | N36: float | O36: override | P36: n/a | Q36: Attritional | R36: n/a | S36: ['calculate_profit_commission_task', 'sync_lob_lists_task'] | T36: n/a | U36: =",'"&own_summary[[#This Row],[Name]]&"'" -> ,'selected_attr' | W36: cds/projections_lloyds/detail_table/dev_patterns_paid | X36: dev_patterns_paid | Y36: float | Z36: override | AA36: n/a | AB36: Paid | AC36: n/a | AD36: n/a | AE36: [] | AF36: =",'"&lloyds_detail[[#This Row],[Name]]&"'" -> ,'dev_patterns_paid' | AH36: cds/projections_lloyds/summary_table/lob_visible_3 | AI36: lob_visible_3 | AJ36: bool | AK36: output | AL36: n/a | AM36: lob_visible_3 | AN36: n/a | AO36: n/a | AP36: [] | AQ36: =",'"&lloyds_summary[[#This Row],[Name]]&"'" -> ,'lob_visible_3' | AS36: cds/projections_beazley/detail_table/dev_patterns_paid | AT36: dev_patterns_paid | AU36: float | AV36: override | AW36: n/a | AX36: Paid | AY36: n/a | AZ36: n/a | BA36: [] | BB36: =",'"&beazley_detail[[#This Row],[Name]]&"'" -> ,'dev_patterns_paid' | BD36: cds/projections_beazley/summary_table/lob_visible_3 | BE36: lob_visible_3 | BF36: bool | BG36: output | BH36: n/a | BI36: lob_visible_3 | BJ36: n/a | BK36: n/a | BL36: [] | BM36: =",'"&beazley_summary[[#This Row],[Name]]&"'" -> ,'lob_visible_3'
A37: cds/projections_own_experience/detail_table/latest_incurred_closed_claims_large | B37: latest_incurred_closed_claims_large | C37: float | D37: output | E37: n/a | F37: Large | G37: n/a | H37: ['calculate_profit_commission_task'] | I37: n/a | J37: =",'"&own_detail[[#This Row],[Name]]&"'" -> ,'latest_incurred_closed_claims_large' | L37: cds/projections_own_experience/summary_table/selected_large | M37: selected_large | N37: float | O37: override | P37: n/a | Q37: Large | R37: n/a | S37: ['calculate_profit_commission_task', 'sync_lob_lists_task'] | T37: n/a | U37: =",'"&own_summary[[#This Row],[Name]]&"'" -> ,'selected_large' | W37: cds/projections_lloyds/detail_table/dev_patterns_incurred | X37: dev_patterns_incurred | Y37: float | Z37: override | AA37: n/a | AB37: Incurred | AC37: n/a | AD37: n/a | AE37: [] | AF37: =",'"&lloyds_detail[[#This Row],[Name]]&"'" -> ,'dev_patterns_incurred' | AH37: cds/projections_lloyds/summary_table/comments | AI37: comments | AJ37: str | AK37: input | AL37: optional | AM37: Comments | AN37: None | AO37: n/a | AP37: [] | AQ37: =",'"&lloyds_summary[[#This Row],[Name]]&"'" -> ,'comments' | AS37: cds/projections_beazley/detail_table/dev_patterns_incurred | AT37: dev_patterns_incurred | AU37: float | AV37: override | AW37: n/a | AX37: Incurred | AY37: n/a | AZ37: n/a | BA37: [] | BB37: =",'"&beazley_detail[[#This Row],[Name]]&"'" -> ,'dev_patterns_incurred' | BD37: cds/projections_beazley/summary_table/comments | BE37: comments | BF37: str | BG37: input | BH37: optional | BI37: Comments | BJ37: None | BK37: n/a | BL37: [] | BM37: =",'"&beazley_summary[[#This Row],[Name]]&"'" -> ,'comments'
A38: cds/projections_own_experience/detail_table/latest_incurred_total_claims_large | B38: latest_incurred_total_claims_large | C38: float | D38: output | E38: n/a | F38: Large | G38: n/a | H38: ['calculate_profit_commission_task'] | I38: n/a | J38: =",'"&own_detail[[#This Row],[Name]]&"'" -> ,'latest_incurred_total_claims_large' | L38: cds/projections_own_experience/summary_table/selected_cat | M38: selected_cat | N38: float | O38: override | P38: n/a | Q38: Cat (on Selected Basis) | R38: n/a | S38: ['calculate_profit_commission_task', 'sync_lob_lists_task'] | T38: n/a | U38: =",'"&own_summary[[#This Row],[Name]]&"'" -> ,'selected_cat' | W38: cds/projections_lloyds/detail_table/weighting_ielr | X38: weighting_ielr | Y38: float | Z38: override | AA38: n/a | AB38: IELR Weighting | AC38: n/a | AD38: n/a | AE38: [] | AF38: =",'"&lloyds_detail[[#This Row],[Name]]&"'" -> ,'weighting_ielr' | AH38: cds/projections_lloyds/summary_table/checked | AI38: checked | AJ38: bool | AK38: input | AL38: required | AM38: Checked | AN38: FALSE | AO38: n/a | AP38: [] | AQ38: =",'"&lloyds_summary[[#This Row],[Name]]&"'" -> ,'checked' | AS38: cds/projections_beazley/detail_table/weighting_ielr | AT38: weighting_ielr | AU38: float | AV38: override | AW38: n/a | AX38: IELR Weighting | AY38: n/a | AZ38: n/a | BA38: [] | BB38: =",'"&beazley_detail[[#This Row],[Name]]&"'" -> ,'weighting_ielr' | BD38: cds/projections_beazley/summary_table/checked | BE38: checked | BF38: bool | BG38: input | BH38: required | BI38: Checked | BJ38: FALSE | BK38: n/a | BL38: [] | BM38: =",'"&beazley_summary[[#This Row],[Name]]&"'" -> ,'checked'
A39: cds/projections_own_experience/detail_table/last_year_position_large | B39: last_year_position_large | C39: float | D39: input | E39: optional | F39: Large | G39: 0 | H39: ['calculate_profit_commission_task'] | I39: n/a | J39: =",'"&own_detail[[#This Row],[Name]]&"'" -> ,'last_year_position_large' | L39: cds/projections_own_experience/summary_table/selected_total | M39: selected_total | N39: float | O39: output | P39: n/a | Q39: Total | R39: n/a | S39: ['calculate_profit_commission_task'] | T39: n/a | U39: =",'"&own_summary[[#This Row],[Name]]&"'" -> ,'selected_total' | W39: cds/projections_lloyds/detail_table/method_paid | X39: method_paid | Y39: str | Z39: override | AA39: n/a | AB39: Method Paid | AC39: n/a | AD39: n/a | AE39: [] | AF39: =",'"&lloyds_detail[[#This Row],[Name]]&"'" -> ,'method_paid' | AH39: cds/projections_lloyds/summary_table/yoa | AI39: yoa | AJ39: str | AK39: output | AL39: n/a | AM39: YoA | AN39: n/a | AO39: n/a | AP39: [] | AQ39: =",'"&lloyds_summary[[#This Row],[Name]]&"'" -> ,'yoa' | AS39: cds/projections_beazley/detail_table/method_paid | AT39: method_paid | AU39: str | AV39: override | AW39: n/a | AX39: Method Paid | AY39: n/a | AZ39: n/a | BA39: [] | BB39: =",'"&beazley_detail[[#This Row],[Name]]&"'" -> ,'method_paid' | BD39: cds/projections_beazley/summary_table/yoa | BE39: yoa | BF39: str | BG39: output | BH39: n/a | BI39: YoA | BJ39: n/a | BK39: n/a | BL39: [] | BM39: =",'"&beazley_summary[[#This Row],[Name]]&"'" -> ,'yoa'
A40: cds/projections_own_experience/detail_table/movement_large | B40: movement_large | C40: float | D40: output | E40: n/a | F40: Large | G40: n/a | H40: ['calculate_profit_commission_task'] | I40: n/a | J40: =",'"&own_detail[[#This Row],[Name]]&"'" -> ,'movement_large' | L40: cds/projections_own_experience/summary_table/selected_total_excl_cat | M40: selected_total_excl_cat | N40: float | O40: output | P40: n/a | Q40: Total (Excl. CAT) | R40: n/a | S40: ['calculate_profit_commission_task'] | T40: n/a | U40: =",'"&own_summary[[#This Row],[Name]]&"'" -> ,'selected_total_excl_cat' | W40: cds/projections_lloyds/detail_table/method_incurred | X40: method_incurred | Y40: str | Z40: override | AA40: n/a | AB40: Method Incurred | AC40: n/a | AD40: n/a | AE40: [] | AF40: =",'"&lloyds_detail[[#This Row],[Name]]&"'" -> ,'method_incurred' | AH40: cds/projections_lloyds/summary_table/latest_gpi | AI40: latest_gpi | AJ40: float | AK40: output | AL40: n/a | AM40: Latest GPI | AN40: n/a | AO40: n/a | AP40: [] | AQ40: =",'"&lloyds_summary[[#This Row],[Name]]&"'" -> ,'latest_gpi' | AS40: cds/projections_beazley/detail_table/method_incurred | AT40: method_incurred | AU40: str | AV40: override | AW40: n/a | AX40: Method Incurred | AY40: n/a | AZ40: n/a | BA40: [] | BB40: =",'"&beazley_detail[[#This Row],[Name]]&"'" -> ,'method_incurred' | BD40: cds/projections_beazley/summary_table/latest_gpi | BE40: latest_gpi | BF40: float | BG40: output | BH40: n/a | BI40: Latest GPI | BJ40: n/a | BK40: n/a | BL40: [] | BM40: =",'"&beazley_summary[[#This Row],[Name]]&"'" -> ,'latest_gpi'
A41: cds/projections_own_experience/detail_table/gn_ilr_large | B41: gn_ilr_large | C41: float | D41: output | E41: n/a | F41: Large | G41: n/a | H41: ['calculate_profit_commission_task'] | I41: n/a | J41: =",'"&own_detail[[#This Row],[Name]]&"'" -> ,'gn_ilr_large' | L41: cds/projections_own_experience/summary_table/selected_cat_exp | M41: selected_cat_exp | N41: float | O41: output | P41: n/a | Q41: Cat (Experience) | R41: n/a | S41: ['calculate_profit_commission_task'] | T41: n/a | U41: =",'"&own_summary[[#This Row],[Name]]&"'" -> ,'selected_cat_exp' | W41: cds/projections_lloyds/detail_table/inflation_model | X41: inflation_model | Y41: float | Z41: output | AA41: n/a | AB41: Model Inflation | AC41: n/a | AD41: n/a | AE41: [] | AF41: =",'"&lloyds_detail[[#This Row],[Name]]&"'" -> ,'inflation_model' | AH41: cds/projections_lloyds/summary_table/latest_gnpi | AI41: latest_gnpi | AJ41: float | AK41: output | AL41: n/a | AM41: Latest GNPI | AN41: n/a | AO41: n/a | AP41: [] | AQ41: =",'"&lloyds_summary[[#This Row],[Name]]&"'" -> ,'latest_gnpi' | AS41: cds/projections_beazley/detail_table/inflation_model | AT41: inflation_model | AU41: float | AV41: output | AW41: n/a | AX41: Model Inflation | AY41: n/a | AZ41: n/a | BA41: [] | BB41: =",'"&beazley_detail[[#This Row],[Name]]&"'" -> ,'inflation_model' | BD41: cds/projections_beazley/summary_table/latest_gnpi | BE41: latest_gnpi | BF41: float | BG41: output | BH41: n/a | BI41: Latest GNPI | BJ41: n/a | BK41: n/a | BL41: [] | BM41: =",'"&beazley_summary[[#This Row],[Name]]&"'" -> ,'latest_gnpi'
A42: cds/projections_own_experience/detail_table/ultimate_incurred_ielr_large | B42: ultimate_incurred_ielr_large | C42: float | D42: output | E42: n/a | F42: Large | G42: n/a | H42: ['calculate_profit_commission_task'] | I42: n/a | J42: =",'"&own_detail[[#This Row],[Name]]&"'" -> ,'ultimate_incurred_ielr_large' | L42: cds/projections_own_experience/summary_table/selected_cat_bp | M42: selected_cat_bp | N42: float | O42: output | P42: n/a | Q42: Cat (BP) | R42: n/a | S42: ['calculate_profit_commission_task'] | T42: n/a | U42: =",'"&own_summary[[#This Row],[Name]]&"'" -> ,'selected_cat_bp' | W42: cds/projections_lloyds/detail_table/rate_change_model | X42: rate_change_model | Y42: float | Z42: output | AA42: n/a | AB42: Model Rate Change | AC42: n/a | AD42: n/a | AE42: [] | AF42: =",'"&lloyds_detail[[#This Row],[Name]]&"'" -> ,'rate_change_model' | AH42: cds/projections_lloyds/summary_table/latest_paid | AI42: latest_paid | AJ42: float | AK42: output | AL42: n/a | AM42: Latest Paid | AN42: n/a | AO42: n/a | AP42: [] | AQ42: =",'"&lloyds_summary[[#This Row],[Name]]&"'" -> ,'latest_paid' | AS42: cds/projections_beazley/detail_table/rate_change_model | AT42: rate_change_model | AU42: float | AV42: output | AW42: n/a | AX42: Model Rate Change | AY42: n/a | AZ42: n/a | BA42: [] | BB42: =",'"&beazley_detail[[#This Row],[Name]]&"'" -> ,'rate_change_model' | BD42: cds/projections_beazley/summary_table/latest_paid | BE42: latest_paid | BF42: float | BG42: output | BH42: n/a | BI42: Latest Paid | BJ42: n/a | BK42: n/a | BL42: [] | BM42: =",'"&beazley_summary[[#This Row],[Name]]&"'" -> ,'latest_paid'
A43: cds/projections_own_experience/detail_table/ultimate_incurred_bf_large | B43: ultimate_incurred_bf_large | C43: float | D43: output | E43: n/a | F43: Large | G43: n/a | H43: ['calculate_profit_commission_task'] | I43: n/a | J43: =",'"&own_detail[[#This Row],[Name]]&"'" -> ,'ultimate_incurred_bf_large' | L43: cds/projections_own_experience/summary_table/selected_cat_rms | M43: selected_cat_rms | N43: float | O43: output | P43: n/a | Q43: Cat (RMS) | R43: n/a | S43: ['calculate_profit_commission_task'] | T43: n/a | U43: =",'"&own_summary[[#This Row],[Name]]&"'" -> ,'selected_cat_rms' | W43: cds/projections_lloyds/detail_table/rate_change_selected | X43: rate_change_selected | Y43: float | Z43: override | AA43: n/a | AB43: Selected Rate Change | AC43: n/a | AD43: n/a | AE43: [] | AF43: =",'"&lloyds_detail[[#This Row],[Name]]&"'" -> ,'rate_change_selected' | AH43: cds/projections_lloyds/summary_table/latest_incurred | AI43: latest_incurred | AJ43: float | AK43: output | AL43: n/a | AM43: Latest Incurred | AN43: n/a | AO43: n/a | AP43: [] | AQ43: =",'"&lloyds_summary[[#This Row],[Name]]&"'" -> ,'latest_incurred' | AS43: cds/projections_beazley/detail_table/rate_change_selected | AT43: rate_change_selected | AU43: float | AV43: override | AW43: n/a | AX43: Selected Rate Change | AY43: n/a | AZ43: n/a | BA43: [] | BB43: =",'"&beazley_detail[[#This Row],[Name]]&"'" -> ,'rate_change_selected' | BD43: cds/projections_beazley/summary_table/latest_incurred | BE43: latest_incurred | BF43: float | BG43: output | BH43: n/a | BI43: Latest Incurred | BJ43: n/a | BK43: n/a | BL43: [] | BM43: =",'"&beazley_summary[[#This Row],[Name]]&"'" -> ,'latest_incurred'
A44: cds/projections_own_experience/detail_table/ultimate_incurred_cl_large | B44: ultimate_incurred_cl_large | C44: float | D44: output | E44: n/a | F44: Large | G44: n/a | H44: ['calculate_profit_commission_task'] | I44: n/a | J44: =",'"&own_detail[[#This Row],[Name]]&"'" -> ,'ultimate_incurred_cl_large' | L44: cds/projections_own_experience/summary_table/selected_cat_basis | M44: selected_cat_basis | N44: str | O44: output | P44: n/a | Q44: Cat Basis | R44: n/a | S44: ['calculate_profit_commission_task'] | T44: n/a | U44: =",'"&own_summary[[#This Row],[Name]]&"'" -> ,'selected_cat_basis' | W44: cds/projections_lloyds/detail_table/inflation_model_index | X44: inflation_model_index | Y44: float | Z44: output | AA44: n/a | AB44: Model Inflation Index | AC44: n/a | AD44: n/a | AE44: [] | AF44: =",'"&lloyds_detail[[#This Row],[Name]]&"'" -> ,'inflation_model_index' | AH44: cds/projections_lloyds/summary_table/acquisition_ratio | AI44: acquisition_ratio | AJ44: float | AK44: output | AL44: n/a | AM44: Acquisition costs % | AN44: n/a | AO44: n/a | AP44: [] | AQ44: =",'"&lloyds_summary[[#This Row],[Name]]&"'" -> ,'acquisition_ratio' | AS44: cds/projections_beazley/detail_table/inflation_model_index | AT44: inflation_model_index | AU44: float | AV44: output | AW44: n/a | AX44: Model Inflation Index | AY44: n/a | AZ44: n/a | BA44: [] | BB44: =",'"&beazley_detail[[#This Row],[Name]]&"'" -> ,'inflation_model_index' | BD44: cds/projections_beazley/summary_table/acquisition_ratio | BE44: acquisition_ratio | BF44: float | BG44: output | BH44: n/a | BI44: Acquisition costs % | BJ44: n/a | BK44: n/a | BL44: [] | BM44: =",'"&beazley_summary[[#This Row],[Name]]&"'" -> ,'acquisition_ratio'
A45: cds/projections_own_experience/detail_table/ielr_weighting_cl_large | B45: ielr_weighting_cl_large | C45: float | D45: override | E45: n/a | F45: Large | G45: n/a | H45: ['calculate_profit_commission_task'] | I45: n/a | J45: =",'"&own_detail[[#This Row],[Name]]&"'" -> ,'ielr_weighting_cl_large' | L45: cds/projections_own_experience/summary_table/model_default_attr | M45: model_default_attr | N45: float | O45: override | P45: n/a | Q45: Attritional | R45: n/a | S45: ['calculate_profit_commission_task', 'sync_lob_lists_task'] | T45: n/a | U45: =",'"&own_summary[[#This Row],[Name]]&"'" -> ,'model_default_attr' | W45: cds/projections_lloyds/detail_table/rate_change_model_index | X45: rate_change_model_index | Y45: float | Z45: output | AA45: n/a | AB45: Model Rate Change Index | AC45: n/a | AD45: n/a | AE45: [] | AF45: =",'"&lloyds_detail[[#This Row],[Name]]&"'" -> ,'rate_change_model_index' | AH45: cds/projections_lloyds/summary_table/incurred_loss_ratio | AI45: incurred_loss_ratio | AJ45: float | AK45: output | AL45: n/a | AM45: Incurred Loss ratio | AN45: n/a | AO45: n/a | AP45: [] | AQ45: =",'"&lloyds_summary[[#This Row],[Name]]&"'" -> ,'incurred_loss_ratio' | AS45: cds/projections_beazley/detail_table/rate_change_model_index | AT45: rate_change_model_index | AU45: float | AV45: output | AW45: n/a | AX45: Model Rate Change Index | AY45: n/a | AZ45: n/a | BA45: [] | BB45: =",'"&beazley_detail[[#This Row],[Name]]&"'" -> ,'rate_change_model_index' | BD45: cds/projections_beazley/summary_table/incurred_loss_ratio | BE45: incurred_loss_ratio | BF45: float | BG45: output | BH45: n/a | BI45: Incurred Loss ratio | BJ45: n/a | BK45: n/a | BL45: [] | BM45: =",'"&beazley_summary[[#This Row],[Name]]&"'" -> ,'incurred_loss_ratio'
A46: cds/projections_own_experience/detail_table/ultimate_incurred_selected_large | B46: ultimate_incurred_selected_large | C46: float | D46: override | E46: n/a | F46: Large | G46: n/a | H46: ['calculate_profit_commission_task'] | I46: n/a | J46: =",'"&own_detail[[#This Row],[Name]]&"'" -> ,'ultimate_incurred_selected_large' | L46: cds/projections_own_experience/summary_table/model_default_large | M46: model_default_large | N46: float | O46: override | P46: n/a | Q46: Large | R46: n/a | S46: ['calculate_profit_commission_task', 'sync_lob_lists_task'] | T46: n/a | U46: =",'"&own_summary[[#This Row],[Name]]&"'" -> ,'model_default_large' | W46: cds/projections_lloyds/detail_table/rate_change_selected_index | X46: rate_change_selected_index | Y46: float | Z46: output | AA46: n/a | AB46: Selected Rate Change Index | AC46: n/a | AD46: n/a | AE46: [] | AF46: =",'"&lloyds_detail[[#This Row],[Name]]&"'" -> ,'rate_change_selected_index' | AH46: cds/projections_lloyds/summary_table/ultimate_gnpi | AI46: ultimate_gnpi | AJ46: float | AK46: output | AL46: n/a | AM46: Ultimate GNPI | AN46: n/a | AO46: n/a | AP46: [] | AQ46: =",'"&lloyds_summary[[#This Row],[Name]]&"'" -> ,'ultimate_gnpi' | AS46: cds/projections_beazley/detail_table/rate_change_selected_index | AT46: rate_change_selected_index | AU46: float | AV46: output | AW46: n/a | AX46: Selected Rate Change Index | AY46: n/a | AZ46: n/a | BA46: [] | BB46: =",'"&beazley_detail[[#This Row],[Name]]&"'" -> ,'rate_change_selected_index' | BD46: cds/projections_beazley/summary_table/ultimate_gnpi | BE46: ultimate_gnpi | BF46: float | BG46: output | BH46: n/a | BI46: Ultimate GNPI | BJ46: n/a | BK46: n/a | BL46: [] | BM46: =",'"&beazley_summary[[#This Row],[Name]]&"'" -> ,'ultimate_gnpi'
A47: cds/projections_own_experience/detail_table/ultimate_ulr_selected_large | B47: ultimate_ulr_selected_large | C47: float | D47: output | E47: n/a | F47: Large | G47: n/a | H47: ['calculate_profit_commission_task'] | I47: n/a | J47: =",'"&own_detail[[#This Row],[Name]]&"'" -> ,'ultimate_ulr_selected_large' | L47: cds/projections_own_experience/summary_table/model_default_cat | M47: model_default_cat | N47: float | O47: override | P47: n/a | Q47: Cat (on Selected Basis) | R47: n/a | S47: ['calculate_profit_commission_task', 'sync_lob_lists_task'] | T47: n/a | U47: =",'"&own_summary[[#This Row],[Name]]&"'" -> ,'model_default_cat' | W47: cds/projections_lloyds/detail_table/loss_ratio_model_index | X47: loss_ratio_model_index | Y47: float | Z47: output | AA47: n/a | AB47: Model Loss Ratio Index | AC47: n/a | AD47: n/a | AE47: [] | AF47: =",'"&lloyds_detail[[#This Row],[Name]]&"'" -> ,'loss_ratio_model_index' | AH47: cds/projections_lloyds/summary_table/ultimate_gnpi_ol_model | AI47: ultimate_gnpi_ol_model | AJ47: float | AK47: output | AL47: n/a | AM47: Ultimate GNPI On-level Default | AN47: n/a | AO47: n/a | AP47: [] | AQ47: =",'"&lloyds_summary[[#This Row],[Name]]&"'" -> ,'ultimate_gnpi_ol_model' | AS47: cds/projections_beazley/detail_table/loss_ratio_model_index | AT47: loss_ratio_model_index | AU47: float | AV47: output | AW47: n/a | AX47: Model Loss Ratio Index | AY47: n/a | AZ47: n/a | BA47: [] | BB47: =",'"&beazley_detail[[#This Row],[Name]]&"'" -> ,'loss_ratio_model_index' | BD47: cds/projections_beazley/summary_table/ultimate_gnpi_ol_model | BE47: ultimate_gnpi_ol_model | BF47: float | BG47: output | BH47: n/a | BI47: Ultimate GNPI On-level Default | BJ47: n/a | BK47: n/a | BL47: [] | BM47: =",'"&beazley_summary[[#This Row],[Name]]&"'" -> ,'ultimate_gnpi_ol_model'
A48: cds/projections_own_experience/detail_table/ultimate_ulr_on_levelled_large | B48: ultimate_ulr_on_levelled_large | C48: float | D48: output | E48: n/a | F48: Large | G48: n/a | H48: ['calculate_profit_commission_task'] | I48: n/a | J48: =",'"&own_detail[[#This Row],[Name]]&"'" -> ,'ultimate_ulr_on_levelled_large' | L48: cds/projections_own_experience/summary_table/model_default_total | M48: model_default_total | N48: float | O48: output | P48: n/a | Q48: Total | R48: n/a | S48: ['calculate_profit_commission_task'] | T48: n/a | U48: =",'"&own_summary[[#This Row],[Name]]&"'" -> ,'model_default_total' | W48: cds/projections_lloyds/detail_table/loss_ratio_selected_index | X48: loss_ratio_selected_index | Y48: float | Z48: output | AA48: n/a | AB48: Selected Loss Ratio Index | AC48: n/a | AD48: n/a | AE48: [] | AF48: =",'"&lloyds_detail[[#This Row],[Name]]&"'" -> ,'loss_ratio_selected_index' | AH48: cds/projections_lloyds/summary_table/ultimate_gnpi_ol_selected | AI48: ultimate_gnpi_ol_selected | AJ48: float | AK48: output | AL48: n/a | AM48: Ultimate GNPI On-level Selected | AN48: n/a | AO48: n/a | AP48: [] | AQ48: =",'"&lloyds_summary[[#This Row],[Name]]&"'" -> ,'ultimate_gnpi_ol_selected' | AS48: cds/projections_beazley/detail_table/loss_ratio_selected_index | AT48: loss_ratio_selected_index | AU48: float | AV48: output | AW48: n/a | AX48: Selected Loss Ratio Index | AY48: n/a | AZ48: n/a | BA48: [] | BB48: =",'"&beazley_detail[[#This Row],[Name]]&"'" -> ,'loss_ratio_selected_index' | BD48: cds/projections_beazley/summary_table/ultimate_gnpi_ol_selected | BE48: ultimate_gnpi_ol_selected | BF48: float | BG48: output | BH48: n/a | BI48: Ultimate GNPI On-level Selected | BJ48: n/a | BK48: n/a | BL48: [] | BM48: =",'"&beazley_summary[[#This Row],[Name]]&"'" -> ,'ultimate_gnpi_ol_selected'
A49: cds/projections_own_experience/detail_table/ielr_weighting_sel_large | B49: ielr_weighting_sel_large | C49: float | D49: override | E49: n/a | F49: Large | G49: n/a | H49: ['calculate_profit_commission_task'] | I49: n/a | J49: =",'"&own_detail[[#This Row],[Name]]&"'" -> ,'ielr_weighting_sel_large' | L49: cds/projections_own_experience/summary_table/model_default_total_excl_cat | M49: model_default_total_excl_cat | N49: float | O49: output | P49: n/a | Q49: Total (Excl. CAT) | R49: n/a | S49: ['calculate_profit_commission_task'] | T49: n/a | U49: =",'"&own_summary[[#This Row],[Name]]&"'" -> ,'model_default_total_excl_cat' | W49: cds/projections_lloyds/detail_table/weighting_model | X49: weighting_model | Y49: float | Z49: output | AA49: n/a | AB49: Model Weighting | AC49: n/a | AD49: n/a | AE49: [] | AF49: =",'"&lloyds_detail[[#This Row],[Name]]&"'" -> ,'weighting_model' | AH49: cds/projections_lloyds/summary_table/ultimate_cl_paid | AI49: ultimate_cl_paid | AJ49: float | AK49: output | AL49: n/a | AM49: CL Ultimate Paid | AN49: n/a | AO49: n/a | AP49: [] | AQ49: =",'"&lloyds_summary[[#This Row],[Name]]&"'" -> ,'ultimate_cl_paid' | AS49: cds/projections_beazley/detail_table/weighting_model | AT49: weighting_model | AU49: float | AV49: output | AW49: n/a | AX49: Model Weighting | AY49: n/a | AZ49: n/a | BA49: [] | BB49: =",'"&beazley_detail[[#This Row],[Name]]&"'" -> ,'weighting_model' | BD49: cds/projections_beazley/summary_table/ultimate_cl_paid | BE49: ultimate_cl_paid | BF49: float | BG49: output | BH49: n/a | BI49: CL Ultimate Paid | BJ49: n/a | BK49: n/a | BL49: [] | BM49: =",'"&beazley_summary[[#This Row],[Name]]&"'" -> ,'ultimate_cl_paid'
A50: cds/projections_own_experience/detail_table/latest_incurred_open_claims_cat | B50: latest_incurred_open_claims_cat | C50: float | D50: output | E50: n/a | F50: Cat | G50: n/a | H50: ['calculate_profit_commission_task'] | I50: n/a | J50: =",'"&own_detail[[#This Row],[Name]]&"'" -> ,'latest_incurred_open_claims_cat' | L50: cds/projections_own_experience/summary_table/model_default_cat_exp | M50: model_default_cat_exp | N50: float | O50: output | P50: n/a | Q50: Cat (Experience) | R50: n/a | S50: ['calculate_profit_commission_task'] | T50: n/a | U50: =",'"&own_summary[[#This Row],[Name]]&"'" -> ,'model_default_cat_exp' | W50: cds/projections_lloyds/detail_table/weighting_selected | X50: weighting_selected | Y50: float | Z50: override | AA50: n/a | AB50: Selected Weighting | AC50: n/a | AD50: n/a | AE50: [] | AF50: =",'"&lloyds_detail[[#This Row],[Name]]&"'" -> ,'weighting_selected' | AH50: cds/projections_lloyds/summary_table/ultimate_cl_paid_ulr | AI50: ultimate_cl_paid_ulr | AJ50: float | AK50: output | AL50: n/a | AM50: CL ULR Paid | AN50: n/a | AO50: n/a | AP50: [] | AQ50: =",'"&lloyds_summary[[#This Row],[Name]]&"'" -> ,'ultimate_cl_paid_ulr' | AS50: cds/projections_beazley/detail_table/weighting_selected | AT50: weighting_selected | AU50: float | AV50: override | AW50: n/a | AX50: Selected Weighting | AY50: n/a | AZ50: n/a | BA50: [] | BB50: =",'"&beazley_detail[[#This Row],[Name]]&"'" -> ,'weighting_selected' | BD50: cds/projections_beazley/summary_table/ultimate_cl_paid_ulr | BE50: ultimate_cl_paid_ulr | BF50: float | BG50: output | BH50: n/a | BI50: CL ULR Paid | BJ50: n/a | BK50: n/a | BL50: [] | BM50: =",'"&beazley_summary[[#This Row],[Name]]&"'" -> ,'ultimate_cl_paid_ulr'
A51: cds/projections_own_experience/detail_table/latest_incurred_closed_claims_cat | B51: latest_incurred_closed_claims_cat | C51: float | D51: output | E51: n/a | F51: Cat | G51: n/a | H51: ['calculate_profit_commission_task'] | I51: n/a | J51: =",'"&own_detail[[#This Row],[Name]]&"'" -> ,'latest_incurred_closed_claims_cat' | L51: cds/projections_own_experience/summary_table/model_default_cat_bp | M51: model_default_cat_bp | N51: float | O51: output | P51: n/a | Q51: Cat (BP) | R51: n/a | S51: ['calculate_profit_commission_task'] | T51: n/a | U51: =",'"&own_summary[[#This Row],[Name]]&"'" -> ,'model_default_cat_bp' | W51: cds/projections_lloyds/detail_table/weighting_1_exposure_onlevel | X51: weighting_1_exposure_onlevel | Y51: float | Z51: output | AA51: n/a | AB51: Exposure - weighting 1 | AC51: n/a | AD51: n/a | AE51: [] | AF51: =",'"&lloyds_detail[[#This Row],[Name]]&"'" -> ,'weighting_1_exposure_onlevel' | AH51: cds/projections_lloyds/summary_table/ultimate_cl_incurred | AI51: ultimate_cl_incurred | AJ51: float | AK51: output | AL51: n/a | AM51: CL Ultimate Incurred | AN51: n/a | AO51: n/a | AP51: [] | AQ51: =",'"&lloyds_summary[[#This Row],[Name]]&"'" -> ,'ultimate_cl_incurred' | AS51: cds/projections_beazley/detail_table/weighting_1_exposure_onlevel | AT51: weighting_1_exposure_onlevel | AU51: float | AV51: output | AW51: n/a | AX51: Exposure - weighting 1 | AY51: n/a | AZ51: n/a | BA51: [] | BB51: =",'"&beazley_detail[[#This Row],[Name]]&"'" -> ,'weighting_1_exposure_onlevel' | BD51: cds/projections_beazley/summary_table/ultimate_cl_incurred | BE51: ultimate_cl_incurred | BF51: float | BG51: output | BH51: n/a | BI51: CL Ultimate Incurred | BJ51: n/a | BK51: n/a | BL51: [] | BM51: =",'"&beazley_summary[[#This Row],[Name]]&"'" -> ,'ultimate_cl_incurred'
A52: cds/projections_own_experience/detail_table/latest_incurred_total_claims_cat | B52: latest_incurred_total_claims_cat | C52: float | D52: output | E52: n/a | F52: Cat | G52: n/a | H52: ['calculate_profit_commission_task'] | I52: n/a | J52: =",'"&own_detail[[#This Row],[Name]]&"'" -> ,'latest_incurred_total_claims_cat' | L52: cds/projections_own_experience/summary_table/model_default_cat_rms | M52: model_default_cat_rms | N52: float | O52: output | P52: n/a | Q52: Cat (RMS) | R52: n/a | S52: ['calculate_profit_commission_task'] | T52: n/a | U52: =",'"&own_summary[[#This Row],[Name]]&"'" -> ,'model_default_cat_rms' | W52: cds/projections_lloyds/detail_table/weighting_2_decay_ratio | X52: weighting_2_decay_ratio | Y52: float | Z52: output | AA52: n/a | AB52: Decay Ratio - weighting 2 | AC52: n/a | AD52: n/a | AE52: [] | AF52: =",'"&lloyds_detail[[#This Row],[Name]]&"'" -> ,'weighting_2_decay_ratio' | AH52: cds/projections_lloyds/summary_table/ultimate_cl_incurred_ulr | AI52: ultimate_cl_incurred_ulr | AJ52: float | AK52: output | AL52: n/a | AM52: CL ULR Incurred | AN52: n/a | AO52: n/a | AP52: [] | AQ52: =",'"&lloyds_summary[[#This Row],[Name]]&"'" -> ,'ultimate_cl_incurred_ulr' | AS52: cds/projections_beazley/detail_table/weighting_2_decay_ratio | AT52: weighting_2_decay_ratio | AU52: float | AV52: output | AW52: n/a | AX52: Decay Ratio - weighting 2 | AY52: n/a | AZ52: n/a | BA52: [] | BB52: =",'"&beazley_detail[[#This Row],[Name]]&"'" -> ,'weighting_2_decay_ratio' | BD52: cds/projections_beazley/summary_table/ultimate_cl_incurred_ulr | BE52: ultimate_cl_incurred_ulr | BF52: float | BG52: output | BH52: n/a | BI52: CL ULR Incurred | BJ52: n/a | BK52: n/a | BL52: [] | BM52: =",'"&beazley_summary[[#This Row],[Name]]&"'" -> ,'ultimate_cl_incurred_ulr'
A53: cds/projections_own_experience/detail_table/last_year_position_cat | B53: last_year_position_cat | C53: float | D53: input | E53: optional | F53: Cat | G53: 0 | H53: ['calculate_profit_commission_task'] | I53: n/a | J53: =",'"&own_detail[[#This Row],[Name]]&"'" -> ,'last_year_position_cat' | L53: cds/projections_own_experience/summary_table/model_default_cat_basis | M53: model_default_cat_basis | N53: str | O53: output | P53: n/a | Q53: Cat Basis | R53: n/a | S53: ['calculate_profit_commission_task'] | T53: n/a | U53: =",'"&own_summary[[#This Row],[Name]]&"'" -> ,'model_default_cat_basis' | W53: cds/projections_lloyds/detail_table/weighting_3_developed | X53: weighting_3_developed | Y53: float | Z53: output | AA53: n/a | AB53: % Develop - Weighting 3 | AC53: n/a | AD53: n/a | AE53: [] | AF53: =",'"&lloyds_detail[[#This Row],[Name]]&"'" -> ,'weighting_3_developed' | AH53: cds/projections_lloyds/summary_table/ultimate_ielr_model | AI53: ultimate_ielr_model | AJ53: float | AK53: output | AL53: n/a | AM53: Model Incurred | AN53: n/a | AO53: n/a | AP53: [] | AQ53: =",'"&lloyds_summary[[#This Row],[Name]]&"'" -> ,'ultimate_ielr_model' | AS53: cds/projections_beazley/detail_table/weighting_3_developed | AT53: weighting_3_developed | AU53: float | AV53: output | AW53: n/a | AX53: % Develop - Weighting 3 | AY53: n/a | AZ53: n/a | BA53: [] | BB53: =",'"&beazley_detail[[#This Row],[Name]]&"'" -> ,'weighting_3_developed' | BD53: cds/projections_beazley/summary_table/ultimate_ielr_model | BE53: ultimate_ielr_model | BF53: float | BG53: output | BH53: n/a | BI53: Model Incurred | BJ53: n/a | BK53: n/a | BL53: [] | BM53: =",'"&beazley_summary[[#This Row],[Name]]&"'" -> ,'ultimate_ielr_model'
A54: cds/projections_own_experience/detail_table/movement_cat | B54: movement_cat | C54: float | D54: output | E54: n/a | F54: Cat | G54: n/a | H54: ['calculate_profit_commission_task'] | I54: n/a | J54: =",'"&own_detail[[#This Row],[Name]]&"'" -> ,'movement_cat' | L54: cds/projections_own_experience/summary_table/ovd_dev | M54: ovd_dev | N54: str | O54: output | P54: n/a | Q54: Devt | R54: n/a | S54: ['calculate_profit_commission_task'] | T54: n/a | U54: =",'"&own_summary[[#This Row],[Name]]&"'" -> ,'ovd_dev' | W54: cds/projections_lloyds/detail_table/weighting_onlevel | X54: weighting_onlevel | Y54: float | Z54: output | AA54: n/a | AB54: Onlevel Weighting | AC54: n/a | AD54: n/a | AE54: [] | AF54: =",'"&lloyds_detail[[#This Row],[Name]]&"'" -> ,'weighting_onlevel' | AH54: cds/projections_lloyds/summary_table/ultimate_ielr_model_ulr | AI54: ultimate_ielr_model_ulr | AJ54: float | AK54: output | AL54: n/a | AM54: IELR Model | AN54: n/a | AO54: n/a | AP54: [] | AQ54: =",'"&lloyds_summary[[#This Row],[Name]]&"'" -> ,'ultimate_ielr_model_ulr' | AS54: cds/projections_beazley/detail_table/weighting_onlevel | AT54: weighting_onlevel | AU54: float | AV54: output | AW54: n/a | AX54: Onlevel Weighting | AY54: n/a | AZ54: n/a | BA54: [] | BB54: =",'"&beazley_detail[[#This Row],[Name]]&"'" -> ,'weighting_onlevel' | BD54: cds/projections_beazley/summary_table/ultimate_ielr_model_ulr | BE54: ultimate_ielr_model_ulr | BF54: float | BG54: output | BH54: n/a | BI54: IELR Model | BJ54: n/a | BK54: n/a | BL54: [] | BM54: =",'"&beazley_summary[[#This Row],[Name]]&"'" -> ,'ultimate_ielr_model_ulr'
A55: cds/projections_own_experience/detail_table/gn_ilr_cat | B55: gn_ilr_cat | C55: float | D55: output | E55: n/a | F55: Cat | G55: n/a | H55: ['calculate_profit_commission_task'] | I55: n/a | J55: =",'"&own_detail[[#This Row],[Name]]&"'" -> ,'gn_ilr_cat' | L55: cds/projections_own_experience/summary_table/ovd_index | M55: ovd_index | N55: str | O55: output | P55: n/a | Q55: Indices | R55: n/a | S55: ['calculate_profit_commission_task'] | T55: n/a | U55: =",'"&own_summary[[#This Row],[Name]]&"'" -> ,'ovd_index' | W55: cds/projections_lloyds/detail_table/weighting_1_exposure_nominal | X55: weighting_1_exposure_nominal | Y55: float | Z55: output | AA55: n/a | AB55: Exposure - weighting 1 | AC55: n/a | AD55: n/a | AE55: [] | AF55: =",'"&lloyds_detail[[#This Row],[Name]]&"'" -> ,'weighting_1_exposure_nominal' | AH55: cds/projections_lloyds/summary_table/ultimate_ielr_selected | AI55: ultimate_ielr_selected | AJ55: float | AK55: output | AL55: n/a | AM55: Selected Incurred | AN55: n/a | AO55: n/a | AP55: [] | AQ55: =",'"&lloyds_summary[[#This Row],[Name]]&"'" -> ,'ultimate_ielr_selected' | AS55: cds/projections_beazley/detail_table/weighting_1_exposure_nominal | AT55: weighting_1_exposure_nominal | AU55: float | AV55: output | AW55: n/a | AX55: Exposure - weighting 1 | AY55: n/a | AZ55: n/a | BA55: [] | BB55: =",'"&beazley_detail[[#This Row],[Name]]&"'" -> ,'weighting_1_exposure_nominal' | BD55: cds/projections_beazley/summary_table/ultimate_ielr_selected | BE55: ultimate_ielr_selected | BF55: float | BG55: output | BH55: n/a | BI55: Selected Incurred | BJ55: n/a | BK55: n/a | BL55: [] | BM55: =",'"&beazley_summary[[#This Row],[Name]]&"'" -> ,'ultimate_ielr_selected'
A56: cds/projections_own_experience/detail_table/ultimate_incurred_ielr_cat | B56: ultimate_incurred_ielr_cat | C56: float | D56: output | E56: n/a | F56: Cat | G56: n/a | H56: ['calculate_profit_commission_task'] | I56: n/a | J56: =",'"&own_detail[[#This Row],[Name]]&"'" -> ,'ultimate_incurred_ielr_cat' | L56: cds/projections_own_experience/summary_table/ovd_premium | M56: ovd_premium | N56: str | O56: output | P56: n/a | Q56: Premium | R56: n/a | S56: ['calculate_profit_commission_task'] | T56: n/a | U56: =",'"&own_summary[[#This Row],[Name]]&"'" -> ,'ovd_premium' | W56: cds/projections_lloyds/detail_table/weighting_nominal | X56: weighting_nominal | Y56: float | Z56: output | AA56: n/a | AB56: Nominal Weighting | AC56: n/a | AD56: n/a | AE56: [] | AF56: =",'"&lloyds_detail[[#This Row],[Name]]&"'" -> ,'weighting_nominal' | AH56: cds/projections_lloyds/summary_table/ultimate_ielr_selected_ulr | AI56: ultimate_ielr_selected_ulr | AJ56: float | AK56: output | AL56: n/a | AM56: IELR Selected | AN56: n/a | AO56: n/a | AP56: [] | AQ56: =",'"&lloyds_summary[[#This Row],[Name]]&"'" -> ,'ultimate_ielr_selected_ulr' | AS56: cds/projections_beazley/detail_table/weighting_nominal | AT56: weighting_nominal | AU56: float | AV56: output | AW56: n/a | AX56: Nominal Weighting | AY56: n/a | AZ56: n/a | BA56: [] | BB56: =",'"&beazley_detail[[#This Row],[Name]]&"'" -> ,'weighting_nominal' | BD56: cds/projections_beazley/summary_table/ultimate_ielr_selected_ulr | BE56: ultimate_ielr_selected_ulr | BF56: float | BG56: output | BH56: n/a | BI56: IELR Selected | BJ56: n/a | BK56: n/a | BL56: [] | BM56: =",'"&beazley_summary[[#This Row],[Name]]&"'" -> ,'ultimate_ielr_selected_ulr'
A57: cds/projections_own_experience/detail_table/ultimate_incurred_bf_cat | B57: ultimate_incurred_bf_cat | C57: float | D57: output | E57: n/a | F57: Cat | G57: n/a | H57: ['calculate_profit_commission_task'] | I57: n/a | J57: =",'"&own_detail[[#This Row],[Name]]&"'" -> ,'ultimate_incurred_bf_cat' | L57: cds/projections_own_experience/summary_table/ovd_ielr_weights | M57: ovd_ielr_weights | N57: str | O57: output | P57: n/a | Q57: IELR Wgt | R57: n/a | S57: ['calculate_profit_commission_task'] | T57: n/a | U57: =",'"&own_summary[[#This Row],[Name]]&"'" -> ,'ovd_ielr_weights' | W57: cds/projections_lloyds/detail_table/is_row_visible | X57: is_row_visible | Y57: bool | Z57: output | AA57: n/a | AB57: is_row_visible | AC57: n/a | AD57: n/a | AE57: [] | AF57: =",'"&lloyds_detail[[#This Row],[Name]]&"'" -> ,'is_row_visible' | AH57: cds/projections_lloyds/summary_table/ultimate_bf_model_paid | AI57: ultimate_bf_model_paid | AJ57: float | AK57: output | AL57: n/a | AM57: Model Paid | AN57: n/a | AO57: n/a | AP57: [] | AQ57: =",'"&lloyds_summary[[#This Row],[Name]]&"'" -> ,'ultimate_bf_model_paid' | AS57: cds/projections_beazley/detail_table/is_row_visible | AT57: is_row_visible | AU57: bool | AV57: output | AW57: n/a | AX57: is_row_visible | AY57: n/a | AZ57: n/a | BA57: [] | BB57: =",'"&beazley_detail[[#This Row],[Name]]&"'" -> ,'is_row_visible' | BD57: cds/projections_beazley/summary_table/ultimate_bf_model_paid | BE57: ultimate_bf_model_paid | BF57: float | BG57: output | BH57: n/a | BI57: Model Paid | BJ57: n/a | BK57: n/a | BL57: [] | BM57: =",'"&beazley_summary[[#This Row],[Name]]&"'" -> ,'ultimate_bf_model_paid'
A58: cds/projections_own_experience/detail_table/ultimate_incurred_cl_cat | B58: ultimate_incurred_cl_cat | C58: float | D58: output | E58: n/a | F58: Cat | G58: n/a | H58: ['calculate_profit_commission_task'] | I58: n/a | J58: =",'"&own_detail[[#This Row],[Name]]&"'" -> ,'ultimate_incurred_cl_cat' | L58: cds/projections_own_experience/summary_table/ovd_ielr | M58: ovd_ielr | N58: str | O58: output | P58: n/a | Q58: IELR | R58: n/a | S58: ['calculate_profit_commission_task'] | T58: n/a | U58: =",'"&own_summary[[#This Row],[Name]]&"'" -> ,'ovd_ielr' | W58: cds/projections_lloyds/detail_table/lob_visible_1 | X58: lob_visible_1 | Y58: bool | Z58: output | AA58: n/a | AB58: lob_visible_1 | AC58: n/a | AD58: n/a | AE58: [] | AF58: =",'"&lloyds_detail[[#This Row],[Name]]&"'" -> ,'lob_visible_1' | AH58: cds/projections_lloyds/summary_table/ultimate_bf_model_incurred | AI58: ultimate_bf_model_incurred | AJ58: float | AK58: output | AL58: n/a | AM58: Model Incurred | AN58: n/a | AO58: n/a | AP58: [] | AQ58: =",'"&lloyds_summary[[#This Row],[Name]]&"'" -> ,'ultimate_bf_model_incurred' | AS58: cds/projections_beazley/detail_table/lob_visible_1 | AT58: lob_visible_1 | AU58: bool | AV58: output | AW58: n/a | AX58: lob_visible_1 | AY58: n/a | AZ58: n/a | BA58: [] | BB58: =",'"&beazley_detail[[#This Row],[Name]]&"'" -> ,'lob_visible_1' | BD58: cds/projections_beazley/summary_table/ultimate_bf_model_incurred | BE58: ultimate_bf_model_incurred | BF58: float | BG58: output | BH58: n/a | BI58: Model Incurred | BJ58: n/a | BK58: n/a | BL58: [] | BM58: =",'"&beazley_summary[[#This Row],[Name]]&"'" -> ,'ultimate_bf_model_incurred'
A59: cds/projections_own_experience/detail_table/ielr_weighting_cl_cat | B59: ielr_weighting_cl_cat | C59: float | D59: override | E59: n/a | F59: Cat | G59: n/a | H59: ['calculate_profit_commission_task'] | I59: n/a | J59: =",'"&own_detail[[#This Row],[Name]]&"'" -> ,'ielr_weighting_cl_cat' | L59: cds/projections_own_experience/summary_table/ovd_ibnr | M59: ovd_ibnr | N59: str | O59: output | P59: n/a | Q59: IBNR add | R59: n/a | S59: ['calculate_profit_commission_task'] | T59: n/a | U59: =",'"&own_summary[[#This Row],[Name]]&"'" -> ,'ovd_ibnr' | W59: cds/projections_lloyds/detail_table/lob_visible_2 | X59: lob_visible_2 | Y59: bool | Z59: output | AA59: n/a | AB59: lob_visible_2 | AC59: n/a | AD59: n/a | AE59: [] | AF59: =",'"&lloyds_detail[[#This Row],[Name]]&"'" -> ,'lob_visible_2' | AH59: cds/projections_lloyds/summary_table/ultimate_bf_selected_paid | AI59: ultimate_bf_selected_paid | AJ59: float | AK59: output | AL59: n/a | AM59: Selected Paid | AN59: n/a | AO59: n/a | AP59: [] | AQ59: =",'"&lloyds_summary[[#This Row],[Name]]&"'" -> ,'ultimate_bf_selected_paid' | AS59: cds/projections_beazley/detail_table/lob_visible_2 | AT59: lob_visible_2 | AU59: bool | AV59: output | AW59: n/a | AX59: lob_visible_2 | AY59: n/a | AZ59: n/a | BA59: [] | BB59: =",'"&beazley_detail[[#This Row],[Name]]&"'" -> ,'lob_visible_2' | BD59: cds/projections_beazley/summary_table/ultimate_bf_selected_paid | BE59: ultimate_bf_selected_paid | BF59: float | BG59: output | BH59: n/a | BI59: Selected Paid | BJ59: n/a | BK59: n/a | BL59: [] | BM59: =",'"&beazley_summary[[#This Row],[Name]]&"'" -> ,'ultimate_bf_selected_paid'
A60: cds/projections_own_experience/detail_table/ultimate_incurred_selected_cat | B60: ultimate_incurred_selected_cat | C60: float | D60: override | E60: n/a | F60: Cat | G60: n/a | H60: ['calculate_profit_commission_task'] | I60: n/a | J60: =",'"&own_detail[[#This Row],[Name]]&"'" -> ,'ultimate_incurred_selected_cat' | L60: cds/projections_own_experience/summary_table/ovd_ultimate_method | M60: ovd_ultimate_method | N60: str | O60: output | P60: n/a | Q60: Ult Mtd | R60: n/a | S60: ['calculate_profit_commission_task'] | T60: n/a | U60: =",'"&own_summary[[#This Row],[Name]]&"'" -> ,'ovd_ultimate_method' | W60: cds/projections_lloyds/detail_table/lob_visible_3 | X60: lob_visible_3 | Y60: bool | Z60: output | AA60: n/a | AB60: lob_visible_3 | AC60: n/a | AD60: n/a | AE60: [] | AF60: =",'"&lloyds_detail[[#This Row],[Name]]&"'" -> ,'lob_visible_3' | AH60: cds/projections_lloyds/summary_table/ultimate_bf_selected_incurred | AI60: ultimate_bf_selected_incurred | AJ60: float | AK60: output | AL60: n/a | AM60: Selected Incurred | AN60: n/a | AO60: n/a | AP60: [] | AQ60: =",'"&lloyds_summary[[#This Row],[Name]]&"'" -> ,'ultimate_bf_selected_incurred' | AS60: cds/projections_beazley/detail_table/lob_visible_3 | AT60: lob_visible_3 | AU60: bool | AV60: output | AW60: n/a | AX60: lob_visible_3 | AY60: n/a | AZ60: n/a | BA60: [] | BB60: =",'"&beazley_detail[[#This Row],[Name]]&"'" -> ,'lob_visible_3' | BD60: cds/projections_beazley/summary_table/ultimate_bf_selected_incurred | BE60: ultimate_bf_selected_incurred | BF60: float | BG60: output | BH60: n/a | BI60: Selected Incurred | BJ60: n/a | BK60: n/a | BL60: [] | BM60: =",'"&beazley_summary[[#This Row],[Name]]&"'" -> ,'ultimate_bf_selected_incurred'
A61: cds/projections_own_experience/detail_table/ultimate_ulr_selected_cat | B61: ultimate_ulr_selected_cat | C61: float | D61: output | E61: n/a | F61: Cat | G61: n/a | H61: ['calculate_profit_commission_task'] | I61: n/a | J61: =",'"&own_detail[[#This Row],[Name]]&"'" -> ,'ultimate_ulr_selected_cat' | L61: cds/projections_own_experience/summary_table/ovd_ultimate | M61: ovd_ultimate | N61: str | O61: output | P61: n/a | Q61: Ult | R61: n/a | S61: ['calculate_profit_commission_task'] | T61: n/a | U61: =",'"&own_summary[[#This Row],[Name]]&"'" -> ,'ovd_ultimate' | AH61: cds/projections_lloyds/summary_table/ultimate_model | AI61: ultimate_model | AJ61: float | AK61: output | AL61: n/a | AM61: Model Ult. Incurred | AN61: n/a | AO61: n/a | AP61: [] | AQ61: =",'"&lloyds_summary[[#This Row],[Name]]&"'" -> ,'ultimate_model' | BD61: cds/projections_beazley/summary_table/ultimate_model | BE61: ultimate_model | BF61: float | BG61: output | BH61: n/a | BI61: Model Ult. Incurred | BJ61: n/a | BK61: n/a | BL61: [] | BM61: =",'"&beazley_summary[[#This Row],[Name]]&"'" -> ,'ultimate_model'
A62: cds/projections_own_experience/detail_table/ultimate_ulr_on_levelled_cat | B62: ultimate_ulr_on_levelled_cat | C62: float | D62: output | E62: n/a | F62: Cat | G62: n/a | H62: ['calculate_profit_commission_task'] | I62: n/a | J62: =",'"&own_detail[[#This Row],[Name]]&"'" -> ,'ultimate_ulr_on_levelled_cat' | L62: cds/projections_own_experience/summary_table/ovd_ulr_weights | M62: ovd_ulr_weights | N62: str | O62: output | P62: n/a | Q62: ULR Wgt | R62: n/a | S62: ['calculate_profit_commission_task'] | T62: n/a | U62: =",'"&own_summary[[#This Row],[Name]]&"'" -> ,'ovd_ulr_weights' | AH62: cds/projections_lloyds/summary_table/ultimate_model_ulr | AI62: ultimate_model_ulr | AJ62: float | AK62: output | AL62: n/a | AM62: Model Ult. ULR | AN62: n/a | AO62: n/a | AP62: [] | AQ62: =",'"&lloyds_summary[[#This Row],[Name]]&"'" -> ,'ultimate_model_ulr' | BD62: cds/projections_beazley/summary_table/ultimate_model_ulr | BE62: ultimate_model_ulr | BF62: float | BG62: output | BH62: n/a | BI62: Model Ult. ULR | BJ62: n/a | BK62: n/a | BL62: [] | BM62: =",'"&beazley_summary[[#This Row],[Name]]&"'" -> ,'ultimate_model_ulr'
A63: cds/projections_own_experience/detail_table/ielr_weighting_sel_cat | B63: ielr_weighting_sel_cat | C63: float | D63: override | E63: n/a | F63: Cat | G63: n/a | H63: ['calculate_profit_commission_task'] | I63: n/a | J63: =",'"&own_detail[[#This Row],[Name]]&"'" -> ,'ielr_weighting_sel_cat' | L63: cds/projections_own_experience/summary_table/ovd_ulr | M63: ovd_ulr | N63: str | O63: output | P63: n/a | Q63: ULR | R63: n/a | S63: ['calculate_profit_commission_task'] | T63: n/a | U63: =",'"&own_summary[[#This Row],[Name]]&"'" -> ,'ovd_ulr' | AH63: cds/projections_lloyds/summary_table/ultimate_selected | AI63: ultimate_selected | AJ63: float | AK63: output | AL63: n/a | AM63: Selected Ult. Incurred | AN63: n/a | AO63: n/a | AP63: [] | AQ63: =",'"&lloyds_summary[[#This Row],[Name]]&"'" -> ,'ultimate_selected' | BD63: cds/projections_beazley/summary_table/ultimate_selected | BE63: ultimate_selected | BF63: float | BG63: output | BH63: n/a | BI63: Selected Ult. Incurred | BJ63: n/a | BK63: n/a | BL63: [] | BM63: =",'"&beazley_summary[[#This Row],[Name]]&"'" -> ,'ultimate_selected'
A64: cds/projections_own_experience/detail_table/latest_incurred_open_claims_total | B64: latest_incurred_open_claims_total | C64: float | D64: output | E64: n/a | F64: Total | G64: n/a | H64: ['calculate_profit_commission_task'] | I64: n/a | J64: =",'"&own_detail[[#This Row],[Name]]&"'" -> ,'latest_incurred_open_claims_total' | L64: cds/projections_own_experience/summary_table/cov_attr | M64: cov_attr | N64: float | O64: output | P64: n/a | Q64: ATT COV | R64: n/a | S64: ['calculate_profit_commission_task'] | T64: n/a | U64: =",'"&own_summary[[#This Row],[Name]]&"'" -> ,'cov_attr' | AH64: cds/projections_lloyds/summary_table/ultimate_selected_ulr | AI64: ultimate_selected_ulr | AJ64: float | AK64: output | AL64: n/a | AM64: Selected Ult. ULR | AN64: n/a | AO64: n/a | AP64: [] | AQ64: =",'"&lloyds_summary[[#This Row],[Name]]&"'" -> ,'ultimate_selected_ulr' | BD64: cds/projections_beazley/summary_table/ultimate_selected_ulr | BE64: ultimate_selected_ulr | BF64: float | BG64: output | BH64: n/a | BI64: Selected Ult. ULR | BJ64: n/a | BK64: n/a | BL64: [] | BM64: =",'"&beazley_summary[[#This Row],[Name]]&"'" -> ,'ultimate_selected_ulr'
A65: cds/projections_own_experience/detail_table/latest_incurred_closed_claims_total | B65: latest_incurred_closed_claims_total | C65: float | D65: output | E65: n/a | F65: Total | G65: n/a | H65: ['calculate_profit_commission_task'] | I65: n/a | J65: =",'"&own_detail[[#This Row],[Name]]&"'" -> ,'latest_incurred_closed_claims_total' | L65: cds/projections_own_experience/summary_table/cov_large | M65: cov_large | N65: float | O65: output | P65: n/a | Q65: LRG COV | R65: n/a | S65: ['calculate_profit_commission_task'] | T65: n/a | U65: =",'"&own_summary[[#This Row],[Name]]&"'" -> ,'cov_large' | AH65: cds/projections_lloyds/summary_table/on_levelled_model_ulr | AI65: on_levelled_model_ulr | AJ65: float | AK65: output | AL65: n/a | AM65: Model ULR | AN65: n/a | AO65: n/a | AP65: [] | AQ65: =",'"&lloyds_summary[[#This Row],[Name]]&"'" -> ,'on_levelled_model_ulr' | BD65: cds/projections_beazley/summary_table/on_levelled_model_ulr | BE65: on_levelled_model_ulr | BF65: float | BG65: output | BH65: n/a | BI65: Model ULR | BJ65: n/a | BK65: n/a | BL65: [] | BM65: =",'"&beazley_summary[[#This Row],[Name]]&"'" -> ,'on_levelled_model_ulr'
A66: cds/projections_own_experience/detail_table/latest_incurred_total_claims_total | B66: latest_incurred_total_claims_total | C66: float | D66: output | E66: n/a | F66: Total | G66: n/a | H66: ['calculate_profit_commission_task'] | I66: n/a | J66: =",'"&own_detail[[#This Row],[Name]]&"'" -> ,'latest_incurred_total_claims_total' | L66: cds/projections_own_experience/summary_table/cov_cat | M66: cov_cat | N66: float | O66: output | P66: n/a | Q66: CAT COV | R66: n/a | S66: ['calculate_profit_commission_task'] | T66: n/a | U66: =",'"&own_summary[[#This Row],[Name]]&"'" -> ,'cov_cat' | AH66: cds/projections_lloyds/summary_table/on_levelled_selected_ulr | AI66: on_levelled_selected_ulr | AJ66: float | AK66: output | AL66: n/a | AM66: Selected ULR | AN66: n/a | AO66: n/a | AP66: [] | AQ66: =",'"&lloyds_summary[[#This Row],[Name]]&"'" -> ,'on_levelled_selected_ulr' | BD66: cds/projections_beazley/summary_table/on_levelled_selected_ulr | BE66: on_levelled_selected_ulr | BF66: float | BG66: output | BH66: n/a | BI66: Selected ULR | BJ66: n/a | BK66: n/a | BL66: [] | BM66: =",'"&beazley_summary[[#This Row],[Name]]&"'" -> ,'on_levelled_selected_ulr'
A67: cds/projections_own_experience/detail_table/last_year_position_total | B67: last_year_position_total | C67: float | D67: input | E67: optional | F67: Total | G67: 0 | H67: ['calculate_profit_commission_task'] | I67: n/a | J67: =",'"&own_detail[[#This Row],[Name]]&"'" -> ,'last_year_position_total' | L67: cds/projections_own_experience/summary_table/cov_total | M67: cov_total | N67: float | O67: output | P67: n/a | Q67: TOTAL COV | R67: n/a | S67: ['calculate_profit_commission_task'] | T67: n/a | U67: =",'"&own_summary[[#This Row],[Name]]&"'" -> ,'cov_total'
A68: cds/projections_own_experience/detail_table/movement_total | B68: movement_total | C68: float | D68: output | E68: n/a | F68: Total | G68: n/a | H68: ['calculate_profit_commission_task'] | I68: n/a | J68: =",'"&own_detail[[#This Row],[Name]]&"'" -> ,'movement_total' | L68: cds/projections_own_experience/summary_table/actuarial_notes | M68: actuarial_notes | N68: str | O68: input | P68: optional | Q68: Actuarial Notes | R68: None | S68: ['calculate_profit_commission_task', 'sync_lob_lists_task'] | T68: n/a | U68: =",'"&own_summary[[#This Row],[Name]]&"'" -> ,'actuarial_notes'
A69: cds/projections_own_experience/detail_table/gn_ilr_total | B69: gn_ilr_total | C69: float | D69: output | E69: n/a | F69: Total | G69: n/a | H69: ['calculate_profit_commission_task'] | I69: n/a | J69: =",'"&own_detail[[#This Row],[Name]]&"'" -> ,'gn_ilr_total' | L69: cds/projections_own_experience/summary_table/lob_number | M69: lob_number | N69: int | O69: output | P69: n/a | Q69: Number of Line of Business | R69: n/a | S69: ['calculate_profit_commission_task'] | T69: n/a | U69: =",'"&own_summary[[#This Row],[Name]]&"'" -> ,'lob_number'
A70: cds/projections_own_experience/detail_table/ultimate_incurred_ielr_total | B70: ultimate_incurred_ielr_total | C70: float | D70: output | E70: n/a | F70: Total | G70: n/a | H70: ['calculate_profit_commission_task'] | I70: n/a | J70: =",'"&own_detail[[#This Row],[Name]]&"'" -> ,'ultimate_incurred_ielr_total' | L70: cds/projections_own_experience/summary_table/selected_lob | M70: selected_lob | N70: str | O70: output | P70: n/a | Q70: Selected Line of Business | R70: n/a | S70: ['calculate_profit_commission_task'] | T70: n/a | U70: =",'"&own_summary[[#This Row],[Name]]&"'" -> ,'selected_lob'
A71: cds/projections_own_experience/detail_table/ultimate_incurred_bf_total | B71: ultimate_incurred_bf_total | C71: float | D71: output | E71: n/a | F71: Total | G71: n/a | H71: ['calculate_profit_commission_task'] | I71: n/a | J71: =",'"&own_detail[[#This Row],[Name]]&"'" -> ,'ultimate_incurred_bf_total' | L71: cds/projections_own_experience/summary_table/yoa | M71: yoa | N71: str | O71: output | P71: n/a | Q71: YoA | R71: n/a | S71: ['calculate_profit_commission_task'] | T71: n/a | U71: =",'"&own_summary[[#This Row],[Name]]&"'" -> ,'yoa'
A72: cds/projections_own_experience/detail_table/ultimate_incurred_cl_total | B72: ultimate_incurred_cl_total | C72: float | D72: output | E72: n/a | F72: Total | G72: n/a | H72: ['calculate_profit_commission_task'] | I72: n/a | J72: =",'"&own_detail[[#This Row],[Name]]&"'" -> ,'ultimate_incurred_cl_total' | L72: cds/projections_own_experience/summary_table/latest_gpi | M72: latest_gpi | N72: float | O72: output | P72: n/a | Q72: Latest GPI | R72: n/a | S72: ['calculate_profit_commission_task'] | T72: n/a | U72: =",'"&own_summary[[#This Row],[Name]]&"'" -> ,'latest_gpi'
A73: cds/projections_own_experience/detail_table/ielr_weighting_cl_total | B73: ielr_weighting_cl_total | C73: float | D73: override | E73: n/a | F73: Total | G73: n/a | H73: ['calculate_profit_commission_task'] | I73: n/a | J73: =",'"&own_detail[[#This Row],[Name]]&"'" -> ,'ielr_weighting_cl_total' | L73: cds/projections_own_experience/summary_table/latest_gnpi | M73: latest_gnpi | N73: float | O73: output | P73: n/a | Q73: Latest GNPI | R73: n/a | S73: ['calculate_profit_commission_task'] | T73: n/a | U73: =",'"&own_summary[[#This Row],[Name]]&"'" -> ,'latest_gnpi'
A74: cds/projections_own_experience/detail_table/ultimate_incurred_selected_total | B74: ultimate_incurred_selected_total | C74: float | D74: override | E74: n/a | F74: Total | G74: n/a | H74: ['calculate_profit_commission_task'] | I74: n/a | J74: =",'"&own_detail[[#This Row],[Name]]&"'" -> ,'ultimate_incurred_selected_total' | L74: cds/projections_own_experience/summary_table/acquisition_costs | M74: acquisition_costs | N74: float | O74: output | P74: n/a | Q74: Acquisition Costs % | R74: n/a | S74: ['calculate_profit_commission_task'] | T74: n/a | U74: =",'"&own_summary[[#This Row],[Name]]&"'" -> ,'acquisition_costs'
A75: cds/projections_own_experience/detail_table/ultimate_ulr_selected_total | B75: ultimate_ulr_selected_total | C75: float | D75: output | E75: n/a | F75: Total | G75: n/a | H75: ['calculate_profit_commission_task'] | I75: n/a | J75: =",'"&own_detail[[#This Row],[Name]]&"'" -> ,'ultimate_ulr_selected_total' | L75: cds/projections_own_experience/summary_table/ultimate_premium_selected_gnpi_cl | M75: ultimate_premium_selected_gnpi_cl | N75: float | O75: output | P75: n/a | Q75: Ultimate GNPI - CL | R75: n/a | S75: ['calculate_profit_commission_task'] | T75: n/a | U75: =",'"&own_summary[[#This Row],[Name]]&"'" -> ,'ultimate_premium_selected_gnpi_cl'
A76: cds/projections_own_experience/detail_table/ultimate_ulr_on_levelled_total | B76: ultimate_ulr_on_levelled_total | C76: float | D76: output | E76: n/a | F76: Total | G76: n/a | H76: ['calculate_profit_commission_task'] | I76: n/a | J76: =",'"&own_detail[[#This Row],[Name]]&"'" -> ,'ultimate_ulr_on_levelled_total' | L76: cds/projections_own_experience/summary_table/ultimate_premium_selected_gnpi_override | M76: ultimate_premium_selected_gnpi_override | N76: float | O76: output | P76: n/a | Q76: Ultimate GNPI - Override | R76: n/a | S76: ['calculate_profit_commission_task'] | T76: n/a | U76: =",'"&own_summary[[#This Row],[Name]]&"'" -> ,'ultimate_premium_selected_gnpi_override'
A77: cds/projections_own_experience/detail_table/ielr_weighting_sel_total | B77: ielr_weighting_sel_total | C77: float | D77: override | E77: n/a | F77: Total | G77: n/a | H77: ['calculate_profit_commission_task'] | I77: n/a | J77: =",'"&own_detail[[#This Row],[Name]]&"'" -> ,'ielr_weighting_sel_total' | L77: cds/projections_own_experience/summary_table/ultimate_premium_selected_gnpi_selected | M77: ultimate_premium_selected_gnpi_selected | N77: float | O77: output | P77: n/a | Q77: Ultimate GNPI - Selected | R77: n/a | S77: ['calculate_profit_commission_task'] | T77: n/a | U77: =",'"&own_summary[[#This Row],[Name]]&"'" -> ,'ultimate_premium_selected_gnpi_selected'
A78: cds/projections_own_experience/detail_table/ultimate_incurred_selected_total_x_cat | B78: ultimate_incurred_selected_total_x_cat | C78: float | D78: output | E78: n/a | F78: Total (excl. Cat) | G78: n/a | H78: ['calculate_profit_commission_task'] | I78: n/a | J78: =",'"&own_detail[[#This Row],[Name]]&"'" -> ,'ultimate_incurred_selected_total_x_cat' | L78: cds/projections_own_experience/summary_table/ultimate_premium_selected_gnpi_selected_ol | M78: ultimate_premium_selected_gnpi_selected_ol | N78: float | O78: output | P78: n/a | Q78: Ultimate GNPI On-level Selected | R78: n/a | S78: ['calculate_profit_commission_task'] | T78: n/a | U78: =",'"&own_summary[[#This Row],[Name]]&"'" -> ,'ultimate_premium_selected_gnpi_selected_ol'
A79: cds/projections_own_experience/detail_table/ultimate_ulr_selected_total_x_cat | B79: ultimate_ulr_selected_total_x_cat | C79: float | D79: output | E79: n/a | F79: Total (excl. Cat) | G79: n/a | H79: ['calculate_profit_commission_task'] | I79: n/a | J79: =",'"&own_detail[[#This Row],[Name]]&"'" -> ,'ultimate_ulr_selected_total_x_cat' | L79: cds/projections_own_experience/summary_table/ultimate_incurred_cl_ielr | M79: ultimate_incurred_cl_ielr | N79: float | O79: output | P79: n/a | Q79: CL - IELR | R79: n/a | S79: ['calculate_profit_commission_task'] | T79: n/a | U79: =",'"&own_summary[[#This Row],[Name]]&"'" -> ,'ultimate_incurred_cl_ielr'
... A112: cds/projections_own_experience/detail_table/adjustments_incurred_lloyds_actual | B112: adjustments_incurred_lloyds_actual | C112: float | D112: output | E112: n/a | F112: Incurred Lloyds Actual | G112: n/a | H112: ['calculate_profit_commission_task'] | I112: n/a | J112: =",'"&own_detail[[#This Row],[Name]]&"'" -> ,'adjustments_incurred_lloyds_actual' | L112: cds/projections_own_experience/summary_table/latest_incurred_open_claims_cat | M112: latest_incurred_open_claims_cat | N112: float | O112: output | P112: n/a | Q112: Cat | R112: n/a | S112: ['calculate_profit_commission_task'] | T112: n/a | U112: =",'"&own_summary[[#This Row],[Name]]&"'" -> ,'latest_incurred_open_claims_cat'
L113: cds/projections_own_experience/summary_table/latest_incurred_closed_claims_cat | M113: latest_incurred_closed_claims_cat | N113: float | O113: output | P113: n/a | Q113: Cat | R113: n/a | S113: ['calculate_profit_commission_task'] | T113: n/a | U113: =",'"&own_summary[[#This Row],[Name]]&"'" -> ,'latest_incurred_closed_claims_cat'
L114: cds/projections_own_experience/summary_table/latest_incurred_total_claims_cat | M114: latest_incurred_total_claims_cat | N114: float | O114: output | P114: n/a | Q114: Cat | R114: n/a | S114: ['calculate_profit_commission_task'] | T114: n/a | U114: =",'"&own_summary[[#This Row],[Name]]&"'" -> ,'latest_incurred_total_claims_cat'
L115: cds/projections_own_experience/summary_table/last_year_position_cat | M115: last_year_position_cat | N115: float | O115: output | P115: n/a | Q115: Cat | R115: n/a | S115: ['calculate_profit_commission_task'] | T115: n/a | U115: =",'"&own_summary[[#This Row],[Name]]&"'" -> ,'last_year_position_cat'
L116: cds/projections_own_experience/summary_table/movement_cat | M116: movement_cat | N116: float | O116: output | P116: n/a | Q116: Cat | R116: n/a | S116: ['calculate_profit_commission_task'] | T116: n/a | U116: =",'"&own_summary[[#This Row],[Name]]&"'" -> ,'movement_cat'
L117: cds/projections_own_experience/summary_table/gn_ilr_cat | M117: gn_ilr_cat | N117: float | O117: output | P117: n/a | Q117: Cat | R117: n/a | S117: ['calculate_profit_commission_task'] | T117: n/a | U117: =",'"&own_summary[[#This Row],[Name]]&"'" -> ,'gn_ilr_cat'
L118: cds/projections_own_experience/summary_table/ultimate_incurred_ielr_cat | M118: ultimate_incurred_ielr_cat | N118: float | O118: output | P118: n/a | Q118: Cat | R118: n/a | S118: ['calculate_profit_commission_task'] | T118: n/a | U118: =",'"&own_summary[[#This Row],[Name]]&"'" -> ,'ultimate_incurred_ielr_cat'
L119: cds/projections_own_experience/summary_table/ultimate_incurred_bf_cat | M119: ultimate_incurred_bf_cat | N119: float | O119: output | P119: n/a | Q119: Cat | R119: n/a | S119: ['calculate_profit_commission_task'] | T119: n/a | U119: =",'"&own_summary[[#This Row],[Name]]&"'" -> ,'ultimate_incurred_bf_cat'
L120: cds/projections_own_experience/summary_table/ultimate_incurred_cl_cat | M120: ultimate_incurred_cl_cat | N120: float | O120: output | P120: n/a | Q120: Cat | R120: n/a | S120: ['calculate_profit_commission_task'] | T120: n/a | U120: =",'"&own_summary[[#This Row],[Name]]&"'" -> ,'ultimate_incurred_cl_cat'
L121: cds/projections_own_experience/summary_table/ultimate_incurred_selected_cat | M121: ultimate_incurred_selected_cat | N121: float | O121: output | P121: n/a | Q121: Cat | R121: n/a | S121: ['calculate_profit_commission_task'] | T121: n/a | U121: =",'"&own_summary[[#This Row],[Name]]&"'" -> ,'ultimate_incurred_selected_cat'
L122: cds/projections_own_experience/summary_table/ultimate_ulr_selected_cat | M122: ultimate_ulr_selected_cat | N122: float | O122: output | P122: n/a | Q122: Cat | R122: n/a | S122: ['calculate_profit_commission_task'] | T122: n/a | U122: =",'"&own_summary[[#This Row],[Name]]&"'" -> ,'ultimate_ulr_selected_cat'
L123: cds/projections_own_experience/summary_table/ultimate_ulr_on_levelled_cat | M123: ultimate_ulr_on_levelled_cat | N123: float | O123: output | P123: n/a | Q123: Cat | R123: n/a | S123: ['calculate_profit_commission_task'] | T123: n/a | U123: =",'"&own_summary[[#This Row],[Name]]&"'" -> ,'ultimate_ulr_on_levelled_cat'
L124: cds/projections_own_experience/summary_table/latest_incurred_open_claims_total | M124: latest_incurred_open_claims_total | N124: float | O124: output | P124: n/a | Q124: Total | R124: n/a | S124: ['calculate_profit_commission_task'] | T124: n/a | U124: =",'"&own_summary[[#This Row],[Name]]&"'" -> ,'latest_incurred_open_claims_total'
... L138: cds/projections_own_experience/summary_table/ultimate_ulr_on_levelled_total_x_cat | M138: ultimate_ulr_on_levelled_total_x_cat | N138: float | O138: output | P138: n/a | Q138: Total (excl. Cat) | R138: n/a | S138: ['calculate_profit_commission_task'] | T138: n/a | U138: =",'"&own_summary[[#This Row],[Name]]&"'" -> ,'ultimate_ulr_on_levelled_total_x_cat'

Sheet data_oe_detail
A1: lob_number | B1: selected_lob | C1: yoa | D1: latest_gpi | E1: latest_gnpi | F1: acquisition_costs | G1: ultimate_premium_selected_gnpi_cl | H1: ultimate_premium_selected_gnpi_override | I1: ultimate_premium_selected_gnpi_selected | J1: ultimate_premium_selected_gnpi_selected_ol | K1: ultimate_incurred_cl_ielr | L1: additional_ibnr_attr | M1: additional_ibnr_large | N1: additional_ibnr_cat | O1: additional_ibnr_total | P1: is_row_visible | Q1: lob_visible_1 | R1: lob_visible_2 | S1: lob_visible_3 | T1: latest_incurred_open_claims_attr | U1: latest_incurred_closed_claims_attr | V1: latest_incurred_total_claims_attr | W1: last_year_position_attr | X1: movement_attr | Y1: gn_ilr_attr | Z1: ultimate_incurred_ielr_attr | AA1: ultimate_incurred_bf_attr | AB1: ultimate_incurred_cl_attr | AC1: ielr_weighting_cl_attr | AD1: ultimate_incurred_selected_attr | AE1: ultimate_ulr_selected_attr | AF1: ultimate_ulr_on_levelled_attr | AG1: ielr_weighting_sel_attr | AH1: latest_incurred_open_claims_large | AI1: latest_incurred_closed_claims_large | AJ1: latest_incurred_total_claims_large | AK1: last_year_position_large | AL1: movement_large | AM1: gn_ilr_large | AN1: ultimate_incurred_ielr_large | AO1: ultimate_incurred_bf_large | AP1: ultimate_incurred_cl_large | AQ1: ielr_weighting_cl_large | AR1: ultimate_incurred_selected_large | AS1: ultimate_ulr_selected_large | AT1: ultimate_ulr_on_levelled_large | AU1: ielr_weighting_sel_large | AV1: latest_incurred_open_claims_cat | AW1: latest_incurred_closed_claims_cat | AX1: latest_incurred_total_claims_cat | AY1: last_year_position_cat | AZ1: movement_cat | BA1: gn_ilr_cat | BB1: ultimate_incurred_ielr_cat | BC1: ultimate_incurred_bf_cat | BD1: ultimate_incurred_cl_cat | BE1: ielr_weighting_cl_cat | BF1: ultimate_incurred_selected_cat | BG1: ultimate_ulr_selected_cat | BH1: ultimate_ulr_on_levelled_cat | BI1: ielr_weighting_sel_cat | BJ1: latest_incurred_open_claims_total | BK1: latest_incurred_closed_claims_total | BL1: latest_incurred_total_claims_total | BM1: last_year_position_total | BN1: movement_total | BO1: gn_ilr_total | BP1: ultimate_incurred_ielr_total | BQ1: ultimate_incurred_bf_total | BR1: ultimate_incurred_cl_total | BS1: ielr_weighting_cl_total | BT1: ultimate_incurred_selected_total | BU1: ultimate_ulr_selected_total | BV1: ultimate_ulr_on_levelled_total | BW1: ielr_weighting_sel_total | BX1: ultimate_incurred_selected_total_x_cat | BY1: ultimate_ulr_selected_total_x_cat | BZ1: ultimate_ulr_on_levelled_total_x_cat | CA1: development_pattern_premium_lloyds_unadjusted | CB1: development_pattern_paid_lloyds_unadjusted | CC1: development_pattern_incurred_lloyds_unadjusted | CD1: development_pattern_premium_lloyds | CE1: development_pattern_paid_lloyds | CF1: development_pattern_incurred_lloyds | CG1: development_pattern_premium_override | CH1: development_pattern_incurred_override | CI1: development_pattern_premium_selected | CJ1: development_pattern_incurred_selected | CK1: method_incurred | CL1: applied_rate_change | CM1: applied_inflation | CN1: modelled_weighting | CO1: applied_rate_change_cumulative | CP1: applied_inflation_cumulative | CQ1: onlevel_factor_cumulative | CR1: exposure_weighting_onlevel_1 | CS1: decay_ratio_weighting_2 | CT1: developed_weighting_3 | CU1: overall_weighting_onlevel | CV1: exposure_weighting_nominal_1 | CW1: overall_weighting_nominal | CX1: adjustments_actual | CY1: adjustments_lower | CZ1: adjustments_upper | DA1: adjustments_prem_lloyds_lower | DB1: adjustments_prem_lloyds_upper | DC1: adjustments_prem_lloyds_actual | DD1: adjustments_incurred_lloyds_lower | DE1: adjustments_incurred_lloyds_upper | DF1: adjustments_incurred_lloyds_actual

Sheet data_oe_summary
A1: claim_source | B1: claim_basis | C1: claim_to_develop_to_ultimate | D1: cat_basis | E1: ielr_approach | F1: ielr_attr | G1: ielr_large | H1: ielr_cat | I1: ielr_total | J1: ielr_total_excl_cat | K1: lloyds_model_ielr | L1: lloyds_model_final_gn_ulr | M1: lloyds_selected_ielr | N1: lloyds_selected_final_gn_ulr | O1: beazley_model_ielr | P1: beazley_model_final_gn_ulr | Q1: beazley_selected_ielr | R1: beazley_selected_final_gn_ulr | S1: ielr_nominal_attr | T1: ielr_nominal_large | U1: ielr_nominal_cat | V1: ielr_nominal_total | W1: ielr_nominal_total_excl_cat | X1: ielr_ol_all_yr_attr | Y1: ielr_ol_all_yr_large | Z1: ielr_ol_all_yr_cat | AA1: ielr_ol_all_yr_total | AB1: ielr_ol_all_yr_total_excl_cat | AC1: ielr_ol_cl_yr_attr | AD1: ielr_ol_cl_yr_large | AE1: ielr_ol_cl_yr_cat | AF1: ielr_ol_cl_yr_total | AG1: ielr_ol_cl_yr_total_excl_cat | AH1: selected_attr | AI1: selected_large | AJ1: selected_cat | AK1: selected_total | AL1: selected_total_excl_cat | AM1: selected_cat_exp | AN1: selected_cat_bp | AO1: selected_cat_rms | AP1: selected_cat_basis | AQ1: model_default_attr | AR1: model_default_large | AS1: model_default_cat | AT1: model_default_total | AU1: model_default_total_excl_cat | AV1: model_default_cat_exp | AW1: model_default_cat_bp | AX1: model_default_cat_rms | AY1: model_default_cat_basis | AZ1: ovd_dev | BA1: ovd_index | BB1: ovd_premium | BC1: ovd_ielr_weights | BD1: ovd_ielr | BE1: ovd_ibnr | BF1: ovd_ultimate_method | BG1: ovd_ultimate | BH1: ovd_ulr_weights | BI1: ovd_ulr | BJ1: cov_attr | BK1: cov_large | BL1: cov_cat | BM1: cov_total | BN1: actuarial_notes | BO1: lob_number | BP1: selected_lob | BQ1: yoa | BR1: latest_gpi | BS1: latest_gnpi | BT1: acquisition_costs | BU1: ultimate_premium_selected_gnpi_cl | BV1: ultimate_premium_selected_gnpi_override | BW1: ultimate_premium_selected_gnpi_selected | BX1: ultimate_premium_selected_gnpi_selected_ol | BY1: ultimate_incurred_cl_ielr | BZ1: additional_ibnr_attr | CA1: additional_ibnr_large | CB1: additional_ibnr_cat | CC1: additional_ibnr_total | CD1: is_row_visible | CE1: lob_visible_1 | CF1: lob_visible_2 | CG1: lob_visible_3 | CH1: latest_incurred_open_claims_attr | CI1: latest_incurred_closed_claims_attr | CJ1: latest_incurred_total_claims_attr | CK1: last_year_position_attr | CL1: movement_attr | CM1: gn_ilr_attr | CN1: ultimate_incurred_ielr_attr | CO1: ultimate_incurred_bf_attr | CP1: ultimate_incurred_cl_attr | CQ1: ultimate_incurred_selected_attr | CR1: ultimate_ulr_selected_attr | CS1: ultimate_ulr_on_levelled_attr | CT1: latest_incurred_open_claims_large | CU1: latest_incurred_closed_claims_large | CV1: latest_incurred_total_claims_large | CW1: last_year_position_large | CX1: movement_large | CY1: gn_ilr_large | CZ1: ultimate_incurred_ielr_large | DA1: ultimate_incurred_bf_large | DB1: ultimate_incurred_cl_large | DC1: ultimate_incurred_selected_large | DD1: ultimate_ulr_selected_large | DE1: ultimate_ulr_on_levelled_large | DF1: latest_incurred_open_claims_cat | DG1: latest_incurred_closed_claims_cat | DH1: latest_incurred_total_claims_cat | DI1: last_year_position_cat | DJ1: movement_cat | DK1: gn_ilr_cat | DL1: ultimate_incurred_ielr_cat | DM1: ultimate_incurred_bf_cat | DN1: ultimate_incurred_cl_cat | DO1: ultimate_incurred_selected_cat | DP1: ultimate_ulr_selected_cat | DQ1: ultimate_ulr_on_levelled_cat | DR1: latest_incurred_open_claims_total | DS1: latest_incurred_closed_claims_total | DT1: latest_incurred_total_claims_total | DU1: last_year_position_total | DV1: movement_total | DW1: gn_ilr_total | DX1: ultimate_incurred_ielr_total | DY1: ultimate_incurred_bf_total | DZ1: ultimate_incurred_cl_total | EA1: ultimate_incurred_selected_total | EB1: ultimate_ulr_selected_total | EC1: ultimate_ulr_on_levelled_total | ED1: ultimate_incurred_selected_total_x_cat | EE1: ultimate_ulr_selected_total_x_cat | EF1: ultimate_ulr_on_levelled_total_x_cat

Sheet data_lloyds_detail
A1: yoa | B1: latest_gpi | C1: latest_gnpi | D1: latest_paid | E1: latest_incurred | F1: acquisition_ratio | G1: incurred_loss_ratio | H1: ultimate_gnpi | I1: ultimate_gnpi_ol_model | J1: ultimate_gnpi_ol_selected | K1: ultimate_cl_paid | L1: ultimate_cl_paid_ulr | M1: ultimate_cl_incurred | N1: ultimate_cl_incurred_ulr | O1: ultimate_ielr_model | P1: ultimate_ielr_model_ulr | Q1: ultimate_ielr_selected | R1: ultimate_ielr_selected_ulr | S1: ultimate_bf_model_paid | T1: ultimate_bf_model_incurred | U1: ultimate_bf_selected_paid | V1: ultimate_bf_selected_incurred | W1: ultimate_model | X1: ultimate_model_ulr | Y1: ultimate_selected | Z1: ultimate_selected_ulr | AA1: on_levelled_model_ulr | AB1: on_levelled_selected_ulr | AC1: lob_number | AD1: risk_code | AE1: selected_lob | AF1: lookup_lob | AG1: dev_patterns_gnpi | AH1: dev_patterns_paid | AI1: dev_patterns_incurred | AJ1: weighting_ielr | AK1: method_paid | AL1: method_incurred | AM1: inflation_model | AN1: rate_change_model | AO1: rate_change_selected | AP1: inflation_model_index | AQ1: rate_change_model_index | AR1: rate_change_selected_index | AS1: loss_ratio_model_index | AT1: loss_ratio_selected_index | AU1: weighting_model | AV1: weighting_selected | AW1: weighting_1_exposure_onlevel | AX1: weighting_2_decay_ratio | AY1: weighting_3_developed | AZ1: weighting_onlevel | BA1: weighting_1_exposure_nominal | BB1: weighting_nominal | BC1: is_row_visible | BD1: lob_visible_1 | BE1: lob_visible_2 | BF1: lob_visible_3

Sheet data_lloyds_summary
A1: lob_number | B1: risk_code | C1: selected_lob | D1: lookup_lob | E1: bp_class | F1: tracker_class | G1: projection_type | H1: ielr_approach | I1: ielr_source | J1: cat_lr_source | K1: lloyds_ielr | L1: composition | M1: model_ielr_nominal | N1: model_ielr_onlevel | O1: model_ielr_ol_allyr | P1: model_ielr | Q1: model_gn_ulr | R1: model_base_aqn | S1: model_acc_aqn | T1: model_adj_gn_ulr | U1: model_final_gn_ulr | V1: selected_ielr | W1: selected_gn_ulr | X1: selected_base_aqn | Y1: selected_acc_aqn | Z1: selected_adj_gn_ulr | AA1: selected_final_gn_ulr | AB1: bp_cat | AC1: bp_cat_load | AD1: actuarial_notes | AE1: is_row_visible | AF1: lob_visible_1 | AG1: lob_visible_2 | AH1: lob_visible_3 | AI1: comments | AJ1: checked | AK1: yoa | AL1: latest_gpi | AM1: latest_gnpi | AN1: latest_paid | AO1: latest_incurred | AP1: acquisition_ratio | AQ1: incurred_loss_ratio | AR1: ultimate_gnpi | AS1: ultimate_gnpi_ol_model | AT1: ultimate_gnpi_ol_selected | AU1: ultimate_cl_paid | AV1: ultimate_cl_paid_ulr | AW1: ultimate_cl_incurred | AX1: ultimate_cl_incurred_ulr | AY1: ultimate_ielr_model | AZ1: ultimate_ielr_model_ulr | BA1: ultimate_ielr_selected | BB1: ultimate_ielr_selected_ulr | BC1: ultimate_bf_model_paid | BD1: ultimate_bf_model_incurred | BE1: ultimate_bf_selected_paid | BF1: ultimate_bf_selected_incurred | BG1: ultimate_model | BH1: ultimate_model_ulr | BI1: ultimate_selected | BJ1: ultimate_selected_ulr | BK1: on_levelled_model_ulr | BL1: on_levelled_selected_ulr

Sheet data_beazley_detail
A1: yoa | B1: latest_gpi | C1: latest_gnpi | D1: latest_paid | E1: latest_incurred | F1: acquisition_ratio | G1: incurred_loss_ratio | H1: ultimate_gnpi | I1: ultimate_gnpi_ol_model | J1: ultimate_gnpi_ol_selected | K1: ultimate_cl_paid | L1: ultimate_cl_paid_ulr | M1: ultimate_cl_incurred | N1: ultimate_cl_incurred_ulr | O1: ultimate_ielr_model | P1: ultimate_ielr_model_ulr | Q1: ultimate_ielr_selected | R1: ultimate_ielr_selected_ulr | S1: ultimate_bf_model_paid | T1: ultimate_bf_model_incurred | U1: ultimate_bf_selected_paid | V1: ultimate_bf_selected_incurred | W1: ultimate_model | X1: ultimate_model_ulr | Y1: ultimate_selected | Z1: ultimate_selected_ulr | AA1: on_levelled_model_ulr | AB1: on_levelled_selected_ulr | AC1: lob_number | AD1: risk_code | AE1: selected_lob | AF1: lookup_lob | AG1: dev_patterns_gnpi | AH1: dev_patterns_paid | AI1: dev_patterns_incurred | AJ1: weighting_ielr | AK1: method_paid | AL1: method_incurred | AM1: inflation_model | AN1: rate_change_model | AO1: rate_change_selected | AP1: inflation_model_index | AQ1: rate_change_model_index | AR1: rate_change_selected_index | AS1: loss_ratio_model_index | AT1: loss_ratio_selected_index | AU1: weighting_model | AV1: weighting_selected | AW1: weighting_1_exposure_onlevel | AX1: weighting_2_decay_ratio | AY1: weighting_3_developed | AZ1: weighting_onlevel | BA1: weighting_1_exposure_nominal | BB1: weighting_nominal | BC1: is_row_visible | BD1: lob_visible_1 | BE1: lob_visible_2 | BF1: lob_visible_3

Sheet data_beazley_summary
A1: lob_number | B1: risk_code | C1: selected_lob | D1: lookup_lob | E1: bp_class | F1: tracker_class | G1: projection_type | H1: ielr_approach | I1: ielr_source | J1: cat_lr_source | K1: lloyds_ielr | L1: composition | M1: model_ielr_nominal | N1: model_ielr_onlevel | O1: model_ielr_ol_allyr | P1: model_ielr | Q1: model_gn_ulr | R1: model_base_aqn | S1: model_acc_aqn | T1: model_adj_gn_ulr | U1: model_final_gn_ulr | V1: selected_ielr | W1: selected_gn_ulr | X1: selected_base_aqn | Y1: selected_acc_aqn | Z1: selected_adj_gn_ulr | AA1: selected_final_gn_ulr | AB1: bp_cat | AC1: bp_cat_load | AD1: actuarial_notes | AE1: is_row_visible | AF1: lob_visible_1 | AG1: lob_visible_2 | AH1: lob_visible_3 | AI1: comments | AJ1: checked | AK1: yoa | AL1: latest_gpi | AM1: latest_gnpi | AN1: latest_paid | AO1: latest_incurred | AP1: acquisition_ratio | AQ1: incurred_loss_ratio | AR1: ultimate_gnpi | AS1: ultimate_gnpi_ol_model | AT1: ultimate_gnpi_ol_selected | AU1: ultimate_cl_paid | AV1: ultimate_cl_paid_ulr | AW1: ultimate_cl_incurred | AX1: ultimate_cl_incurred_ulr | AY1: ultimate_ielr_model | AZ1: ultimate_ielr_model_ulr | BA1: ultimate_ielr_selected | BB1: ultimate_ielr_selected_ulr | BC1: ultimate_bf_model_paid | BD1: ultimate_bf_model_incurred | BE1: ultimate_bf_selected_paid | BF1: ultimate_bf_selected_incurred | BG1: ultimate_model | BH1: ultimate_model_ulr | BI1: ultimate_selected | BJ1: ultimate_selected_ulr | BK1: on_levelled_model_ulr | BL1: on_levelled_selected_ulr
