Workbook
Name AggregatePolicyClaims.UniqueMapping: #REF!
Name anti_selection_total: 'Note Tables'!$G$152
Name anti_selection_uncertainty: 'Note Tables'!$C$29
Name avg_limit: 'Note Tables'!$C$17
Name BeazleyProjections.SummaryTable.OffsetFormulasCustom: #REF!,#REF!
Name Behavior.Inputs.KVRange: OFFSET(#REF!,0,0,COUNTA(#REF!),1),OFFSET(#REF!,0,0,COUNTA(#REF!),1)
Name best_estimate_excl_loads: 'Note Tables'!$E$31
Name best_estimate_gn_total: 'Note Tables'!$K$152
Name best_estimate_total: 'Note Tables'!$F$152
Name BI_SaveColumn: #REF!
Name bp_gn_ulr_total: 'Note Tables'!$G$94
Name bp_proj_total: 'Note Tables'!$J$94
Name bpi_excl_loads: 'Note Tables'!$E$32
Name bpi_final: 'Note Tables'!$E$212
Name bpi_pre_adj: 'Note Tables'!$I$212
Name ClassLookup: OFFSET(#REF!,0,0,COUNTA(#REF!),1)
Name climate_change_total: 'Note Tables'!$E$152
Name CoverDetails.tbl1_forProjectionsShts: #REF!
Name DB.AggregatePolicyClaims.AsAtDate: #REF!
Name DB.AggregatePolicyClaims.PriceAttritionalClaimsUpTo: #REF!
Name DB.ApplicationID: #REF!
Name DB.BzlProj.tbl1_IELROption1: #REF!
Name DB.BzlProj.tbl2_IELROption1: #REF!
Name DB.CatIndicator: #REF!
Name DB.Claim.ClaimDate: #REF!
Name DB.Claim.NetOfRetentions: #REF!
Name DB.CoverDetails.AggregatePolicyandClaimsIndicator: #REF!
Name DB.CoverDetails.Benchmarktrifocus1: #REF!
Name DB.CoverDetails.Benchmarktrifocus10: #REF!
Name DB.CoverDetails.Benchmarktrifocus2: #REF!
Name DB.CoverDetails.Benchmarktrifocus3: #REF!
Name DB.CoverDetails.Benchmarktrifocus4: #REF!
Name DB.CoverDetails.Benchmarktrifocus5: #REF!
Name DB.CoverDetails.Benchmarktrifocus6: #REF!
Name DB.CoverDetails.Benchmarktrifocus7: #REF!
Name DB.CoverDetails.Benchmarktrifocus8: #REF!
Name DB.CoverDetails.Benchmarktrifocus9: #REF!
Name DB.CoverDetails.Brokerage: #REF!
Name DB.CoverDetails.ClassOfBusiness1: #REF!
Name DB.CoverDetails.ClassOfBusiness10: #REF!
Name DB.CoverDetails.ClassOfBusiness2: #REF!
Name DB.CoverDetails.ClassOfBusiness3: #REF!
Name DB.CoverDetails.ClassOfBusiness4: #REF!
Name DB.CoverDetails.ClassOfBusiness5: #REF!
Name DB.CoverDetails.ClassOfBusiness6: #REF!
Name DB.CoverDetails.ClassOfBusiness7: #REF!
Name DB.CoverDetails.ClassOfBusiness8: #REF!
Name DB.CoverDetails.ClassOfBusiness9: #REF!
Name DB.CoverDetails.COBLineSize1: #REF!
Name DB.CoverDetails.COBLineSize10: #REF!
Name DB.CoverDetails.COBLineSize2: #REF!
Name DB.CoverDetails.COBLineSize3: #REF!
Name DB.CoverDetails.COBLineSize4: #REF!
Name DB.CoverDetails.COBLineSize5: #REF!
Name DB.CoverDetails.COBLineSize6: #REF!
Name DB.CoverDetails.COBLineSize7: #REF!
Name DB.CoverDetails.COBLineSize8: #REF!
Name DB.CoverDetails.COBLineSize9: #REF!
Name DB.CoverDetails.Commission: #REF!
Name DB.CoverDetails.ExpensesorFees: #REF!

Sheet LOG
A1: Version Control Log
B5: Index | C5: Version Name | D5: File Name | E5: Version Index | F5: Date | G5: Modified By | H5: Sheet | I5: Range | J5: Details
B6: 1 | C6: Initial version provided to Hx | D6: HX - Portfolio Underwriting MOCK RATER - v8 | E6: Initial version | F6: 45674 | G6: Dimitri Lyulik / Rita Zannetou | H6: Multiple | I6: Multiple | J6: Multiple
H7: Risk Information | J7: Brought in drop downs for currency, status, account type, insured name, broker name
J8: Adjusted settings section
H9: Policy Level Data | J9: Adjusted how the FX conversion works
H10: Claim Level Data | J10: Adjusted how the FX conversion works
H11: Rate Change | J11: Changed formula to pick up dominat risk code and remove depdendent on pivot table
H12: Premium and Limit profil | J12: Added ranking so that most material classes appear first from left to right on final selections
H13: RMS | J13: Changed lable to CAT
J14: Adjusted how the FX conversion works
H15: Own Experience | J15: Removed override of Large / Cat from LoB projection section -- override in summary available at the top
J16: Correction to Latest Incurred formula -- toggles werent working correctly
H17: PC | J17: Added COV basis separate for Attr / Lrg / Cat + total re-scaling depending on selection
J18: Adjust r Code for changed name ranges
J19: Corrected ULR input from final selections
H20: PC (BBT) | J20: Added PC calculation tab for if following BBT pricing
H21: Antiselection | J21: moved reference tables
H22: Uncertainty | J22: moved reference tables
H23: Final Selections | J23: Corrected formulas for some cells
J24: Added Trifocus Level summary at the bottom
B25: 2 | C25: =D25 -> HX - Portfolio Underwriting MOCK RATER - v9 | D25: HX - Portfolio Underwriting MOCK RATER - v9 | E25: =D25 -> HX - Portfolio Underwriting MOCK RATER - v9 | F25: 45681 | G25: Rita Zannetou | H25: Risk Code Composition | I25: Column W, Columns AD:AS | J25: In cases where certain risk codes are excluded (Model = No), the Final Selected Composition table should display only the 'modelled' risk codes along with their compositions. I modified the formulas and added additional calculation columns to support this adjustment. No change to UI.
B26: 3 | C26: =D26 -> HX - Portfolio Underwriting MOCK RATER - v10 | D26: HX - Portfolio Underwriting MOCK RATER - v10 | E26: =D26 -> HX - Portfolio Underwriting MOCK RATER - v10 | F26: 45687 | G26: Rita Zannetou | H26: Multiple | I26: Multiple | J26: Multiple
H27: Risk Code Composition | J27: Modified formula in cells AJ46:AJ65, to handle index match for risk codes with the same compositon percentage
J28: Connect the toggle in cell C5 to Risk Information tab: If Premium Data available = "Yes", set to "Data"; but allow for manual entry override. Manually overriding the value in cell C5 would replace any formula currently
J29: Modified the formula in columns O and U, "Exists in Data?" for both Data and Manual sections
H30: Risk Code Library | J30: Several changes to the Assigned Tracker Class and Assigned BP Class columns
J31: Adjusted the forumla for the "Do We Model?" column. The formula now results in "Yes" if the risk code is found in the Lloyds Risk Code Data tab and if the number of years of data is greater than 3. Added an additional helper column to support this adjustment.
H32: Policy Level Data | J32: Adjusted how the formulas in columns AT and AU work
H33: Claim Level Data | J33: Adjusted how the formulas in columns X and Y work
H34: Own Experience | J34: Correction to Latest Incurred formula - CLOSED CLAIMS
H35: Rate Change | J35: Added "Blend" method in Source dropdown and changed the formula for the selected rate change in 2025 to pick up values from the helper column if Blend is selected.
H36: BP Projections | I36: V31:V45 | J36: We have added a calculation and made these cells overridable. The formula checks for the 2025 rate change source. If 'Facility' is selected, it picks up the Selected Rate Change from the rate change tab; otherwise, it remains blank.
B37: 4 | C37: =D37 -> HX - Portfolio Underwriting MOCK RATER - v11 | D37: HX - Portfolio Underwriting MOCK RATER - v11 | E37: =D37 -> HX - Portfolio Underwriting MOCK RATER - v11 | F37: 45698 | G37: Rita Zannetou | H37: Deductions | I37: C5 | J37: Added a dropdown in cell C5 for Data/Manual options
H38: Risk Code Library | I38: Column BU | J38: Corrected the formula in column U (number of years of data) so that it counts the number of years with premium data looking up from the risk codes in column C.
H39: Inflation | I39: Column F | J39: Updated the column heading from 'Inflation Class' to 'BP Class'
I40: G21:AF40 | J40: Updated the formula to reference the latest inflation tables (R.Base.Inf and R.Excess.Inf)
H41: BP Projections | J41: Adjusted how the formula works in range V31:45. The formula checks for the 2025 rate change source. If 'Facility' OR ' Blend' is selected, it picks up the Selected Rate Change from the rate change tab; otherwise, it remains blank.
H42: R.Base.Inf | J42: Updated the inflation rates in the Base Inf table and removed the unnecessary columns
H43: R.Excess.Inf | J43: Updated the inflation rates in the Excess Inf table and removed the unnecessary columns
B44: 5 | C44: =D44 -> HX - Portfolio Underwriting MOCK RATER - v12 | D44: HX - Portfolio Underwriting MOCK RATER - v12 | E44: =D44 -> HX - Portfolio Underwriting MOCK RATER - v12 | F44: 45702 | G44: Frederick Shortland | H44: Rating Summary | I44: D33:E34 | J44: Altered the formulas to account for the situation where only total incurreds are provided (i.e. splits by attritional, large and cat incurreds are not provided).
F45: 45704 | G45: Rita Zannetou | H45: Portfolio Profile | I45: C20:D39 | J45: Adjusted the formula to handle different - sized arrays. The formula finds unique elements from two arrays, which change based on the selection criteria.
I46: E20:E39 | J46: Adjusted how the formula works in range E20:E96 for the Selected Premium. We aim to pull in the premium only for the Modelled Risk Codes and exclude the risk codes that we are not going to model.
I47: Multiple | J47: Removed the Lloyd's Lag Adjustments. For the development patterns, YOA has been converted to development years. The inception date year is always set to zero. The patterns are now a straightforward lookup based on the development year.
I48: Columns EL:EN & EP | J48: Added an IFERROR function to capture errors where the risk code is not being modelled.
H49: Own Experience | I49: Latest Incurred - CLOSED CLAIMS (No Development) | J49: Correted the formulas in columns K-N. If the source data for claims is policy data, then the incurred for closed claims is always 0.
H50: Rating Summary | I50: Multiple
J51: Added "Best Estimate GG ULR % (Post UW Adj.)" in rows 90 and 97
J52: Added a drop down boxin cell C103 to select the TPI Year. Can this be the distinct values of "YoA" from the table_tpi_parameters table in the R.ReferenceTables tab Default to max year of account
J53: Altered the formulas in the "Technical Premium" section to take into account the TPI Year.
B54: 6 | C54: =D54 -> HX - Portfolio Underwriting MOCK RATER - v13 | D54: HX - Portfolio Underwriting MOCK RATER - v13 | E54: =D54 -> HX - Portfolio Underwriting MOCK RATER - v13 | F54: 45714 | G54: Dimitri Lyulik / Rita Zannetou | H54: Policy Level Data | I54: Column AT | J54: changed initial IF condition to check that Account Name is populated
I55: Column AU | J55: changed initial IF condition to check that Account Name is populated
H56: Risk Code Composition | I56: Column C | J56: Put condition in to not consider blanks
H57: Rate Change | J57: Changed layout of each section to have gaps and include a YOA variable
H58: Portfolio Profile | J58: Increased formula to allow for 20 risk codes and 5 LoBs
H59: Own Experience | J59: Increased number of LoBs to 5
I60: Column BG to BJ | J60: Added Additional IBNR
I61: Column BK to BN | J61: Ultimate adds additional IBNR on top of projection
H62: Lloyds Projections | J62: Increased Modelling capacity to 10
H63: BP Projections | J63: Increased Risk Codes to 20
H64: Rating Summary | J64: Increase LoB Capacity to 5
I65: Row 38 | J65: Cat % Proportion - if weighting to own experience, but projection is not split by attritional / large / cat, then ignore own experience and default to plan
J66: Error catches
H67: R.ReferenceTables | J67: Updated table_bbt_parameters
H68: PC | I68: Row 79 | J68: Added dropdowns to select the "BBT" Class from the table_bbt_parameters
J69: Re-arranged layout so that inputs are all on top
J70: Each LoB can now now select a PC structure seperately if the LoBs are independent
H71: PC (BBT) | I71: ALL | J71: Ignore layout. Correct layout is in PC Tab
H72: Note Tables | J72: << This is a helper tab >> Tables to feed into Pricing Note
B74: 7 | C74: =D74 -> HX - Portfolio Underwriting MOCK RATER - v14 | D74: HX - Portfolio Underwriting MOCK RATER - v14 | E74: =D74 -> HX - Portfolio Underwriting MOCK RATER - v14 | F74: 45722 | G74: Dimitri Lyulik | H74: Reference Tables | I74: TPI | J74: Correct 2025 TPI factors (previously on 2.08, now on finalised 3.07)
G75: Rita Zannetou | H75: Premium and Limit Profile | I75: BST Deductions | J75: Changed formula to pick up Final Effective Deductions
B78: 8 | C78: =D78 -> HX - Portfolio Underwriting MOCK RATER - v15 | D78: HX - Portfolio Underwriting MOCK RATER - v15 | E78: =D78 -> HX - Portfolio Underwriting MOCK RATER - v15 | F78: 45734 | G78: Rita Zannetou | H78: R.BusinessPlan | I78: Columm B (Business Plan Class) | J78: Made the following changes to the Business Plan Class names in column B: London Professions >Large Client Professional Specialty (PT) >Specialty Reinsurance PE Misc Med >Small Business Misc Med
H79: Own Experiece | I79: Acquisition Costs % (Column F) | J79: Modified formula to link to the final selected deductions
H80: Beazley Projections | I80: GN ULR (Excl. CAT) | J80: Corrected the formula for the GN ULR (Excl. CAT) in the Summary table on top
H81: Rate Change | J81: Addded tables to align with the number of years found in the Own Experience tab
B82: 9 | C82: =D82 -> HX - Portfolio Underwriting MOCK RATER - v16 | D82: HX - Portfolio Underwriting MOCK RATER - v16 | E82: =D82 -> HX - Portfolio Underwriting MOCK RATER - v16 | F82: 45743 | G82: Rita Zannetou | H82: Own Experiece | J82: The formula for Total IELR (e.g., cell G26) has been updated to use the Total Selected Model Weighting in column CF (instead of the Model Weighting in column CB).
J83: Also the SUMPRODUCT formula now references the Ultimate GNPI - Selected (column AS) rather than Ultimate GNPI – CL
J84: The formula for Total GN ULR in cells C64 and C65 ( Selected and Mode Default) now references the Ultimate GNPI – Selected (column AS) rather than Ultimate GNPI – CL
J85: The formula for the Movement – Total in cell Z52 has been updated to calculate the sum of the column replacing the previous approach of subtracting last year’s position from the current position.
B86: 10 | C86: =D86 -> HX - Portfolio Underwriting MOCK RATER - v17 | D86: HX - Portfolio Underwriting MOCK RATER - v17 | E86: =D86 -> HX - Portfolio Underwriting MOCK RATER - v17 | F86: 45744 | G86: Dimitri Lyulik | H86: Note Tables | I86: Multiple | J86: linked risk codes to summary table
J87: brought in own experience summary
J88: brought in cat modelling summary
J89: fixed 5623 max / average limit + changed formatting to allow for thousands
J90: 5623 GN Premium - changed formatting to allow for thousands
J91: Changed PC wording to by dynamic depending on PC type
J92: fixed up deductions table + top table summary
J93: Added format rows macro and unhide all rows
H94: CAT | I94: Return Period | J94: changed return period to be an input (we get different curves depending on the broker)
H95: own experience | I95: Multiple | J95: corrected cell G50
J96: changed formula for Total GN ULR if projecting at total level to all add on CAT load if RMS modelling is selected
J97: paid development pattern -- do we need this or can remove?
J98: columns CS to DB do the development pattern adjustment for timing
J99: columns AJ and AL link to the new side working
J100: changed CAT GN ULR (RMS) to be a sumproduct rather than index match to allow for the aggregation of AALs if more than one curve is entered for a single COB
J101: set ordering of COBs to be the same as rating summary
J102: adjusted exposre weighting to weight on max premium, not latest
J103: add latest year to the modelling
J104: displayed weights as % of total weight column (to get % contribution for each year)
H105: Rating Summary | I105: Multiple | J105: Added "Last Year" metrics if the account is a renewal.
H106: Premium and Limit Profile | I106: cell G8 | J106: set to MAX
...

Sheet Schematic
S22: Open "Expiring Option" hidden section

Sheet Note Tables
A1: Pricing Note Tables | AJ1: 1
AJ2: 1 | AK2: 1 | AL2: start
AJ3: 1 | AK3: =COUNT(AJ1:AJ757) -> 358 | AL3: end
B4: Key Risk Details | C4: Comments | AJ4: 1
B5: Insured | AJ5: 1
B6: Policy Reference | AJ6: 1
B7: Underwriter | AJ7: 1
B8: Facility Type | AJ8: 1
B9: Deal Status
B10: key LOB | AJ10: 1
B11: Trifocus | AJ11: 1
B12: Lloyd's Risk Codes (Top 5) | AJ12: 1
B13: New Business / Renewal | AJ13: 1
B14: Inception | AJ14: 1
B15: Expiry
B16: % Line Size | AJ16: 1
B17: 100% Max / Average Limit | AJ17: 1
B18: 5623 GN Premium | AJ18: 1
B19: Total Deductions | AJ19: =IF(C368=0,0,1) -> 0
AJ20: =IF(D368=0,0,1) -> 0
AJ21: =IF(E368=0,0,1) -> 0
AJ22: =IF(F368=0,0,1) -> 0
AJ23: =IF(G368=0,0,1) -> 0
AJ24: =IF(H368=0,0,1) -> 0
B25: Profit Commission | AJ25: 1
AJ26: 1
AJ27: 1
B28: Pricing Outputs | C28: Pricing Basis | E28: Excluding A-S & Uncertainty Loads | AJ28: 1
B29: Anti-Selection / Uncertainty | E29: - / - | AJ29: 1
B30: PC impact on GN ULR | AJ30: 1
B31: GN ULR % net of PC | AJ31: 1
B32: BPI % | AJ32: 1
B33: TPI % | AJ33: 1
B34: RoC % | AJ34: 1
B35: Key Uncertainties | AJ35: 1
AJ36: 1
AJ37: 1
AJ38: 1
B39: Model GN ULR by Methodology | AJ39: 1
E40: Methodology 1 | F40: Methodology 2 | G40: Methodology 3 | H40: Weight 1 | I40: Weight 2 | J40: Weight 3 | AJ40: 1 | AO40: Methodology 1 | AP40: Methodology 2 | AQ40: Methodology 3 | AR40: Methodology 4 | AS40: Methodology 5 | AT40: Weight 1 | AU40: Weight 2 | AV40: Weight 3 | AW40: Weight 4 | AX40: Weight 5
E41: GN ULR % by method | H41: Weightings | AJ41: 1 | AO41: GN ULR % by method | AT41: Weightings
B42: Class of Business | C42: ="GN Premium (BST Share)" -> GN Premium (BST Share) | D42: % of Portfolio" | E42: Own Experience | F42: Lloyds Risk Code Projections | G42: Business Plan | H42: =E42 -> Own Experience | I42: =F42 -> Lloyds Risk Code Projections | J42: =G42 -> Business Plan | K42: Model GN ULR%¹ | AJ42: 1 | AL42: Class of Business | AM42: =YEAR(#REF!)&" GN Premium (BST Share)" -> #REF! | AN42: =YEAR(#REF!)&" Proportion of Portfolio" -> #REF! | AO42: Own Experience | AP42: Lloyds Risk Code Projections | AQ42: Beazley Risk Code Projections | AR42: Business Plan | AS42: Case Pricing | AT42: Own Experience | AU42: Lloyds Risk Code Projections | AV42: Beazley Risk Code Projections | AW42: Business Plan | AX42: Case Pricing | AY42: Model GN ULR%¹
AJ43: =IF(OR(B43="",B43=0),0,1) -> 0 | AL43: =#REF! -> #REF! | AM43: =G219 -> 0 | AN43: =IFERROR(AM43/$AM$94,"") | AO43: =#REF! -> #REF! | AP43: =#REF! -> #REF! | AQ43: =#REF! -> #REF! | AR43: =#REF! -> #REF! | AS43: =#REF! -> #REF! | AT43: =#REF! -> #REF! | AU43: =#REF! -> #REF! | AV43: =#REF! -> #REF! | ... AY43: =#REF! -> #REF!
AJ77: =IF(OR(B77="",B77=0),0,1) -> 0 | AL77: =#REF! -> #REF! | AM77: =G238 -> 0 | AN77: =IFERROR(AM77/$AM$94,"") | AO77: =#REF! -> #REF! | AP77: =#REF! -> #REF! | AQ77: =#REF! -> #REF! | AR77: =#REF! -> #REF! | AS77: =#REF! -> #REF! | AT77: =#REF! -> #REF! | AU77: =#REF! -> #REF! | AV77: =#REF! -> #REF! | ... AY77: =#REF! -> #REF!
AJ78: =IF(OR(B78="",B78=0),0,1) -> 0 | AL78: =#REF! -> #REF! | AM78: =G239 -> 0 | AN78: =IFERROR(AM78/$AM$94,"") | AO78: =#REF! -> #REF! | AP78: =#REF! -> #REF! | AQ78: =#REF! -> #REF! | AR78: =#REF! -> #REF! | AS78: =#REF! -> #REF! | AT78: =#REF! -> #REF! | AU78: =#REF! -> #REF! | AV78: =#REF! -> #REF! | ... AY78: =#REF! -> #REF!
AJ79: =IF(OR(B79="",B79=0),0,1) -> 0 | AL79: =#REF! -> #REF! | AM79: =G240 -> 0 | AN79: =IFERROR(AM79/$AM$94,"") | AO79: =#REF! -> #REF! | AP79: =#REF! -> #REF! | AR79: =#REF! -> #REF! | AT79: =#REF! -> #REF! | AU79: =#REF! -> #REF! | AV79: =#REF! -> #REF! | AW79: =#REF! -> #REF! | AX79: =#REF! -> #REF! | AY79: =#REF! -> #REF!
AJ80: =IF(OR(B80="",B80=0),0,1) -> 0 | AL80: =#REF! -> #REF! | AM80: =G241 -> 0 | AN80: =IFERROR(AM80/$AM$94,"") | AO80: =#REF! -> #REF! | AP80: =#REF! -> #REF! | AR80: =#REF! -> #REF! | AT80: =#REF! -> #REF! | AU80: =#REF! -> #REF! | AV80: =#REF! -> #REF! | AW80: =#REF! -> #REF! | AX80: =#REF! -> #REF! | AY80: =#REF! -> #REF!
AJ81: =IF(OR(B81="",B81=0),0,1) -> 0 | AM81: =G242 -> 0 | AN81: =IFERROR(AM81/$AM$94,"") | AO81: =#REF! -> #REF! | AP81: =#REF! -> #REF! | AR81: =#REF! -> #REF! | AT81: =#REF! -> #REF! | AU81: =#REF! -> #REF! | AV81: =#REF! -> #REF! | AW81: =#REF! -> #REF! | AX81: =#REF! -> #REF! | AY81: =#REF! -> #REF!
AJ82: =IF(OR(B82="",B82=0),0,1) -> 0
AJ83: =IF(OR(B83="",B83=0),0,1) -> 0
AJ84: =IF(OR(B84="",B84=0),0,1) -> 0
AJ85: =IF(OR(B85="",B85=0),0,1) -> 0
AJ86: =IF(OR(B86="",B86=0),0,1) -> 0
AJ87: =IF(OR(B87="",B87=0),0,1) -> 0
AJ88: =IF(OR(B88="",B88=0),0,1) -> 0
AJ89: =IF(OR(B89="",B89=0),0,1) -> 0
AJ90: =IF(OR(B90="",B90=0),0,1) -> 0
AJ91: =IF(OR(B91="",B91=0),0,1) -> 0
AJ93: =IF(OR(B93="",B93=0),0,1) -> 0
B94: Total | AJ94: =IF(OR(B94="",B94=0),0,1) -> 1 | AL94: Total | AM94: =#REF! -> #REF! | AN94: =#REF! -> #REF! | AO94: =#REF! -> #REF! | AP94: =#REF! -> #REF! | AQ94: =#REF! -> #REF! | AR94: =#REF! -> #REF! | AS94: =#REF! -> #REF! | AT94: =#REF! -> #REF! | ... AY94: =#REF! -> #REF!
B95: 1 Excl. NMP loadings, Anti-Selection Charge, Uncertainty Loading, UW Adjustments and impact of the profit commission | AJ95: =IF(OR(B95="",B95=0),0,1) -> 1
AJ96: 1
B97: Selected ULR % Final | AJ97: 1
AJ98: 1
C99: Pricing Output | AJ99: 1
B100: Class of Business | C100: Model GN ULR%1 | D100: NMP Loading | E100: Climate Change Load | F100: Selected GN ULR%² | G100: Anti-Selection | H100: Uncertainty | I100: PC Impact on GN ULR | J100: UW Adjustment | K100: Selected GN ULR%3 | AJ100: 1
AJ101: =IF(OR(B101="",B101=0),0,1) -> 0
AJ133: =IF(OR(B133="",B133=0),0,1) -> 0
AJ134: =IF(OR(B134="",B134=0),0,1) -> 0
AJ135: =IF(OR(B135="",B135=0),0,1) -> 0
AJ136: =IF(OR(B136="",B136=0),0,1) -> 0
AJ137: =IF(OR(B137="",B137=0),0,1) -> 0
AJ138: =IF(OR(B138="",B138=0),0,1) -> 0
AJ139: =IF(OR(B139="",B139=0),0,1) -> 0
AJ140: =IF(OR(B140="",B140=0),0,1) -> 0
AJ141: =IF(OR(B141="",B141=0),0,1) -> 0
AJ142: =IF(OR(B142="",B142=0),0,1) -> 0
AJ143: =IF(OR(B143="",B143=0),0,1) -> 0
... AJ151: =IF(OR(B151="",B151=0),0,1) -> 0
B152: Total | AJ152: =IF(OR(B152="",B152=0),0,1) -> 1
B153: 1 Excl. Anti-Selection, Uncertainty and NMP load | AJ153: 1
B154: 2Excl. Anti-selection and Uncertainty load; and after NMP load | AJ154: 1
B155: 3 Incl. Anti-selection, Uncertainty and NMP load, any UW Adjustments; and Impact of the profit commission | AJ155: 1
AJ156: 1
B157: Technical adequacy metrics | AJ157: 1
AJ158: 1
D159: Including Anti-Selection, Uncertainty Loading and UW Adjustment | H159: Excluding Anti-Selection & Uncertainty Load and UW Adjustment | AJ159: 1
B160: Class of Business | C160: GN Premium | D160: Selected GN ULR % | E160: BPI% | F160: TPI% | G160: RoC % | H160: GN ULR% | I160: BPI% | J160: TPI% | K160: RoC % | AJ160: 1
AJ161: =IF(OR(B161="",B161=0),0,1) -> 0
AJ180: =IF(OR(B180="",B180=0),0,1) -> 0
AJ181: =IF(OR(B181="",B181=0),0,1) -> 0
AJ182: =IF(OR(B182="",B182=0),0,1) -> 0
AJ183: =IF(OR(B183="",B183=0),0,1) -> 0
AJ192: =IF(OR(B192="",B192=0),0,1) -> 0
AJ193: =IF(OR(B193="",B193=0),0,1) -> 0
AJ194: =IF(OR(B194="",B194=0),0,1) -> 0
AJ195: =IF(OR(B195="",B195=0),0,1) -> 0
AJ196: =IF(OR(B196="",B196=0),0,1) -> 0
AJ197: =IF(OR(B197="",B197=0),0,1) -> 0
AJ198: =IF(OR(B198="",B198=0),0,1) -> 0
...

Sheet PC (BBT)
A1: PROFIT COMMISSION CALCS -- IF BENCHMARKING AGAINST 2623 / BBT
B3: PC Type | E3: Deficit Carry forward Option
B4: Standard | E4: $ Amount | G4: Input
B8: $ Amount | C8: Basis
B9: 10000 | C9: Total Contract | D9: Input
C18: 1 | F18: Total
B19: Line of Business | C19: =#REF! -> #REF!
E20: calculated
B21: 5623 GWP | C21: =C23/(1-C22) -> #REF! | E21: calculated | F21: =SUM(C21:D21) -> #REF!
B22: Total Deductions | C22: =#REF! -> #REF! | E22: calculated | F22: =1-F23/F21 -> #REF! | W22: R INPUTS | AI22: R OUTPUTS
B23: 5623 NWP | C23: =#REF! -> #REF! | E23: calculated | F23: =SUM(C23:D23) -> #REF!
W24: PC Options | AA24: distribution params | AE24: premium info
B25: Benchmark Class Auto | C25: =#REF! -> #REF! | I25: CoV Calibration and GN ULR Allocation | R25: Deficit Carry-forward calculation
B26: Benchmark Class Override | C26: Open Market | E26: Input | W26: option | X26: lob_1 | Y26: lob_2 | AE26: option | AF26: lob_1 | AG26: lob_2 | AI26: LoB | AJ26: avg_contract_attr | AK26: avg_contract_lrg | AL26: avg_contract_cat | AM26: avg_contract_total | AN26: avg_contract_p_l | AO26: avg_binder_total | AP26: avg_binder_p_l | AQ26: avg_binder_pc | AR26: avg_contract_pc | AS26: avg_total_pc | AT26: avg_gnp_less_pc | AU26: pc_impact | AV26: pc_impact_tot_ind | AW26: pc_impact_tot_interlock | AX26: pc_impact_scaled | AY26: avg_total_pc_scaled | AZ26: avg_gnp_less_pc_scaled
B27: Benchmark Class Applied | C27: =IF(C26="",C25,C26) -> Open Market | I27: SELECTED GN ULR Allocation | L27: BBT Parametrisation | O27: Experience Parametrisation | R27: Type | S27: =IF($E$4="Experience","Years",IF($E$4="$ Amount","$ Amount","")) -> $ Amount | T27: =IF($E$4="Experience",E9,IF($E$4="$ Amount",B9,"")) -> 10000 | U27: =F9 -> 0 | W27: pc_type | X27: =$B$4 -> Standard | Y27: =$B$4 -> Standard | AE27: gwp | AF27: =C21 -> #REF! | AG27: =D21 -> 0 | AI27: Lob_1 | AJ27: 376139.05 | AK27: 225274.12 | AL27: 315825.94 | AM27: 917239.11 | AN27: 110664.11 | AO27: 0 | AP27: 0 | AQ27: 0 | AR27: 44257.948 | AS27: 44257.948 | AT27: 1255742.1 | AU27: 0.024867381 | AV27: 0.024867381 | AW27: 0.024867381 | AX27: 0.024867381 | AY27: 44257.948 | AZ27: 1255742.1
B28: CoV Basis: Attritional | C28: BBT | E28: calculated | I28: =$C$27 -> Open Market | L28: =$C$27 -> Open Market | R28: LoB 1 Gross Premium | S28: =IF($S$27="Years", IF($U$27="Incurred",SUM(OFFSET(#REF!,0,0,1,-'PC (BBT)'!$T$27)),SUM(OFFSET(#REF!,0,0,-'PC (BBT)'!$T$27))/(1-C22)),"") | W28: pc_interlock | X28: No | Y28: No | AE28: deduct_perc | AF28: =C22 -> #REF! | AG28: =D22 -> 0 | AI28: Lob_2 | AJ28: 0 | AK28: 0 | AL28: 0 | AM28: 0 | AN28: 0 | AO28: 0 | AP28: 0 | AQ28: 0 | AR28: 0 | AS28: 0 | AT28: 0 | AU28: 0 | AV28: 0 | AW28: 0 | AX28: 0 | AY28: 0 | AZ28: 0
B29: CoV Basis: Large | C29: BBT | E29: calculated | I29: =IF(C28="Experience",O29,L29) -> #REF! | L29: =INDEX(#REF!,MATCH(L$28,#REF!,0))/L$32 -> #REF! | R29: LoB 2 Gross Premium | S29: =IF($S$27="Years", IF($U$27="Incurred",SUM(OFFSET(#REF!,0,0,1,-'PC (BBT)'!$T$27)),SUM(OFFSET(#REF!,0,0,-'PC (BBT)'!$T$27))/(1-C22)),"") | W29: underlying_pc | X29: No | Y29: No | AA29: param | AB29: lob_1 | AC29: lob_2 | AE29: nwp | AF29: =C23 -> #REF! | AG29: =D23 -> 0
B30: CoV Basis: CAT | C30: BBT | E30: calculated | I30: =IF(C29="Experience",O30,L30) -> #REF! | L30: =INDEX(#REF!,MATCH(L$28,#REF!,0))/L$32 -> #REF! | W30: prop_underlying | X30: 0 | Y30: 0 | AA30: rms | AB30: =IF(C43>0,"Yes","No") -> #REF! | AC30: =IF(D43>0,"Yes","No") -> No
B31: Attritional GG ULR % | C31: =C$34*(I29/I$32) -> #REF! | E31: calculated | F31: =SUMPRODUCT(C31:D31,$C$21:$D$21)/SUM($C$21:$D$21) -> #REF! | I31: =IF(C30="Experience",O31,L31) -> #REF! | L31: =INDEX(#REF!,MATCH(L$28,#REF!,0))/L$32 -> #REF! | R31: LoB 1 Market Brokerage | S31: =IF($S$27="Years",IF($U$27="Incurred",S28-SUM(OFFSET(#REF!,0,0,1,-'PC (BBT)'!$T$27)),""),"") | W31: underlying_pc_exp | X31: No | Y31: No | AA31: =K41 -> attr_mu | AB31: =IF(L41="",0,L41) -> #REF! | AC31: =IF(M41="",0,M41) -> 0
B32: Large GG ULR % | C32: =C$34*(I30/I$32) -> #REF! | E32: calculated | F32: =SUMPRODUCT(C32:D32,$C$21:$D$21)/SUM($C$21:$D$21) -> #REF! | I32: =SUM(I29:I31) -> #REF! | L32: =INDEX(#REF!,MATCH(L$28,#REF!,0))+INDEX(#REF!,MATCH(L$28,#REF!,0))+INDEX(#REF!,MATCH(L$28,#REF!,0)) -> #REF! | R32: LoB 2 Market Brokerage | S32: =IF($S$27="Years",IF($U$27="Incurred",S29-SUM(OFFSET(#REF!,0,0,1,-'PC (BBT)'!$T$27)),""),"") | AA32: =K42 -> attr_sigma | AB32: =IF(L42="",0,L42) -> #REF! | AC32: =IF(M42="",0,M42) -> 0 | AE32: EL Scale
B33: CAT GG ULR % | C33: =C$34*(I31/I$32) -> #REF! | E33: calculated | F33: =SUMPRODUCT(C33:D33,$C$21:$D$21)/SUM($C$21:$D$21) -> #REF! | W33: DCF | AA33: =K43 -> lrg_alpha | AB33: =IF(L43="",0,L43) -> #REF! | AC33: =IF(M43="",0,M43) -> 0
B34: Total GG ULR % | C34: =#REF!*(1-C22) -> #REF! | E34: calculated | F34: =SUMPRODUCT(C34:D34,$C$21:$D$21)/SUM($C$21:$D$21) -> #REF! | L34: =INDEX(#REF!,MATCH(L$28,#REF!,0)) -> #REF! | R34: LoB 1 Fees | S34: =IF($S$27="Years",IF($U$27="Incurred",S28*SUM(#REF!),""),"") | W34: option | X34: lob_1 | Y34: lob_2 | AA34: =K44 -> lrg_beta | AB34: =IF(L44="",0,L44) -> #REF! | AC34: =IF(M44="",0,M44) -> 0 | AE34: option | AF34: lob_1 | AG34: lob_2
L35: =INDEX(#REF!,MATCH(L$28,#REF!,0)) -> #REF! | R35: LoB 2 Fees | S35: =IF($S$27="Years",IF($U$27="Incurred",S29*SUM(#REF!),""),"") | W35: dcf | X35: =S52 -> #REF! | Y35: =S53 -> #REF! | AA35: =K45 -> cat_alpha | AB35: =IF(L45="",0,L45) -> 0 | AC35: =IF(M45="",0,M45) -> 0 | AE35: attr_scale | AF35: =C40 -> #REF! | AG35: =D40 -> 0
B36: Attritional CoV | C36: =IF(C28="Experience",O34,L34) -> #REF! | E36: calculated | F36: =SUMPRODUCT(C36:D36,$C$21:$D$21)/SUM($C$21:$D$21) -> #REF! | L36: =INDEX(#REF!,MATCH(L$28,#REF!,0)) -> #REF! | AA36: =K46 -> cat_beta | AB36: =IF(L46="",0,L46) -> 0 | AC36: =IF(M46="",0,M46) -> 0 | AE36: lrg_scale | AF36: =C41 -> #REF! | AG36: =D41 -> 0
B37: Large CoV | C37: =IF(C29="Experience",O35,L35) -> #REF! | E37: calculated | F37: =SUMPRODUCT(C37:D37,$C$21:$D$21)/SUM($C$21:$D$21) -> #REF! | R37: LoB 1 Gross Net Premium | S37: =IF($S$27="Years", IF($U$27="Incurred",S28-S31-S34, SUM(OFFSET(#REF!,0,0,-'PC (BBT)'!$T$27))),"") | W37: PC structure standard | AA37: =K47 -> cat_w_p1 | AB37: =IF(L47="",0,L47) -> #REF! | AC37: =IF(M47="",0,M47) -> 0 | AE37: cat_scale | AF37: =IF(C42=0,C43,C42) -> #REF! | AG37: =IF(D42=0,D43,D42) -> 0
B38: CAT CoV | C38: =IF(C30="Experience",O36,L36) -> #REF! | E38: calculated | F38: =SUMPRODUCT(C38:D38,$C$21:$D$21)/SUM($C$21:$D$21) -> #REF! | R38: LoB 2 Gross Net Premium | S38: =IF($S$27="Years", IF(U27="Incurred", S29-S32-S35,SUM(OFFSET(#REF!,0,0,-'PC (BBT)'!$T$27))),"") | AA38: =K48 -> cat_w_p2 | AB38: =IF(L48="",0,L48) -> #REF! | AC38: =IF(M48="",0,M48) -> 0
I39: Distribution Parameter Fitting | W39: option | X39: lob_1 | Y39: lob_2
B40: Attritional EL | C40: =C31*C$21 -> #REF! | E40: calculated | F40: =SUM(C40:D40) -> #REF! | L40: lob 1 | M40: lob 2 | R40: LoB 1 UW Expenses | S40: =IFERROR(IF(C74="Gross Premium",C73*S28,C73*S37),"") | W40: ew_exp | X40: =C73 -> 0.15 | Y40: =D73 -> 0 | AA40: correlation matrix
B41: Large EL | C41: =C32*C$21 -> #REF! | E41: calculated | F41: =SUM(C41:D41) -> #REF! | K41: attr_mu | L41: =LN((C40^2)/SQRT(C45^2+C40^2)) -> #REF! | O41: lognormal | R41: LoB 2 UW Expenses | S41: =IFERROR(IF(D74="Gross Premium",D73*S29,D73*S38),"") | W41: uw_exp_basis | X41: =C74 -> Gross Premium | Y41: =D74 -> 0
B42: CAT (Non-Weather) EL | C42: =IF(C43=0,C33*C21,0) -> #REF! | E42: calculated | F42: =SUM(C42:D42) -> #REF! | K42: attr_sigma | L42: =SQRT(LN(1+(C45^2)/(1+C40^2))) -> #REF! | O42: lognormal | W42: pc_perc | X42: =C75 -> 0.2 | Y42: =D75 -> 0 | AA42: LoB 1 | AB42: LoB 2
B43: CAT (Weather) EL | C43: =IF(AND(C30="Experience",#REF!="RMS"),C33*C$21,0) -> #REF! | E43: calculated | F43: =SUM(C43:D43) -> #REF! | K43: lrg_alpha | L43: =1+(C41/C46) -> #REF! | O43: pareto | R43: LoB 1 Expected Losses | S43: =IF($S$27="Years",IF($U$27="Incurred",SUM(OFFSET(#REF!,0,0,-'PC (BBT)'!$T$27)),SUM(OFFSET(#REF!,0,0,-'PC (BBT)'!$T$27))),"") | AA43: 1 | AB43: ='PC (BBT)'!D65 -> 0
K44: lrg_beta | L44: =(C41*(L43-1))/L43 -> #REF! | O44: pareto | R44: LoB 2 Expected Losses | S44: =IF($S$27="Years",IF($U$27="Incurred",SUM(OFFSET(#REF!,0,0,-'PC (BBT)'!$T$27)),SUM(OFFSET(#REF!,0,0,-'PC (BBT)'!$T$27))),"") | AA44: ='PC (BBT)'!C66 -> 0 | AB44: 1
B45: Attritional SD | C45: =C40*C36 -> #REF! | E45: calculated | F45: =SUM(C45:D45) -> #REF! | K45: cat_alpha | L45: =IFERROR(1+SQRT(1+(C42/C47)^2),"") | O45: pareto | W45: PC structure sliding 1
B46: Large SD | C46: =C41*C37 -> #REF! | E46: calculated | F46: =SUM(C46:D46) -> #REF! | K46: cat_beta | L46: =IFERROR(((L45-1)*C42)/L45,"") | O46: pareto | R46: LoB 1 P/L | S46: =IF($S$27="Years",S37-S40-S43,$T$27) -> 10000
B47: CAT (Non-Weather) SD | C47: =C42*C38 -> #REF! | E47: calculated | F47: =SUM(C47:D47) -> #REF! | K47: cat_w_p1 | L47: {=EXP(INDEX(LINEST(LN(#REF!),SQRT(#REF!)),1,2))} -> #REF! | O47: exponential | R47: LoB 2 P/L | S47: =IF($S$27="Years",S38-S41-S44,$T$27) -> 10000 | W47: option | X47: lob_1 | Y47: lob_2
B48: CAT (Weather) SD | C48: =C43*C38 -> #REF! | E48: calculated | F48: =SUM(C48:D48) -> #REF! | K48: cat_w_p2 | L48: {=INDEX(LINEST(LN(#REF!),SQRT(#REF!)),1)} -> #REF! | O48: exponential | W48: ew_exp | X48: =C79 -> 0.15 | Y48: =X48 -> 0.15
R49: LoB 1 Beazley Share | S49: {=IF(AND($E$4="$ Amount",$C$9="Total Contract"),1,SUMPRODUCT(#REF!,#REF!,--($C$19=#REF!))/SUMPRODUCT(#REF!,--($C$19=#REF!)))} -> 1 | W49: uw_exp_basis | X49: =C80 -> Gross Premium | Y49: =X49 -> Gross Premium
R50: LoB 2 Beazley Share | S50: {=IF(AND($E$4="$ Amount",$C$9="Total Contract"),1,SUMPRODUCT(#REF!,#REF!,--($D$19=#REF!))/SUMPRODUCT(#REF!,--($D$19=#REF!)))} -> 1
R52: LoB 1 DCF | S52: =IF($S$27="None",0,IF($S$27="$ Amount",-S46,IF(S46>0,0,S46)))*IF(S27="$ Amount",(C21/SUM(C21:D21)),1)*S49 -> #REF! | W52: PC structure sliding 2
R53: LoB 2 DCF | S53: =IF($S$27="None",0,IF($S$27="$ Amount",-S47,IF(S47>0,0,S47)))*IF(S27="$ Amount",(D21/SUM(C21:D21)),1)*S50 -> #REF!
W54: row | X54: gn_ulr | Y54: pc_perc
W55: =B83 -> 1 | X55: 0 | Y55: =D83 -> 0
W56: =B84 -> 2 | X56: =C83 -> 0.5 | Y56: =D84 -> 0
W57: =B85 -> 3 | X57: =C84 -> 0.6 | Y57: =D85 -> 0
W58: 4 | X58: =C85 -> 0.7 | Y58: =D86 -> 0
B72: For Standard PC | C72: 1
B73: UW Expense % | C73: 0.15 | E73: Input
B74: UW Expense Basis: | C74: Gross Premium | E74: Input
B75: PC % | C75: 0.2 | E75: Input
B78: For Sliding Scale
B79: UW Expense % | C79: 0.15
B80: UW Expense Basis: | C80: Gross Premium
C82: GN ULR Less than
B83: 1 | C83: 0.5 | E83: Input
B84: =1+B83 -> 2 | C84: 0.6 | E84: Input
B85: =1+B84 -> 3 | C85: 0.7 | E85: Input
B86: etc | E86: Input
C91: 1 | F91: Total
B92: =B21 -> 5623 GWP | C92: =C21 -> #REF! | E92: calculated | F92: =SUM(C92:D92) -> #REF!
B93: Total Deductions $ | C93: =C92*C22 -> #REF! | E93: calculated | F93: =SUM(C93:D93) -> #REF!
B94: =B23 -> 5623 NWP | C94: =C92-C93 -> #REF! | E94: calculated | F94: =SUM(C94:D94) -> #REF!
B96: Simulated Total Expected Losses $ | C96: =AM27 -> 917239.11 | E96: calculated | F96: =SUM(C96:D96) -> 917239.11
B97: UW Expense $ | C97: =IF(C74="Gross Premium",C73*C92,C73*C94) -> #REF! | E97: calculated | F97: =SUM(C97:D97) -> #REF!
B98: Deficit Carry-forward | C98: =S52 -> #REF! | E98: calculated | F98: =SUM(C98:D98) -> #REF!
B99: Expected P/L | C99: =AN27 -> 110664.11 | E99: calculated | F99: =SUM(C99:D99) -> 110664.11
B100: PC Payable on Underlying Binders | C100: =AQ27 -> 0 | E100: calculated | F100: =SUM(C100:D100) -> 0
B101: PC Payable on Contract | C101: =AY27 -> 44257.948 | E101: calculated | F101: =SUM(C101:D101) -> 44257.948
B102: 5623 NWP After PC | C102: =C94-C101 -> #REF! | E102: calculated | F102: =SUM(C102:D102) -> #REF!
B104: Total GN ULR (Pre PC) | C104: =SUM(C40:C43)/(C94) -> #REF! | E104: calculated | F104: =SUM(F40:F43)/(F94) -> #REF!
B105: Total GN ULR (Post PC) | C105: =SUM(C40:C43)/(C102) -> #REF! | E105: calculated | F105: =SUM(F40:F43)/(F102) -> #REF!
B106: PC impact on GN ULR | C106: =C105-C104 -> #REF! | E106: calculated | F106: =AW27 -> 0.024867381

Sheet OLD>>

Sheet Final Selections - wide
C7: Business Plan | D7: ULR Apportionment
AJ9: Excluding anti-selection, uncertainty and recessionary charge | AQ9: HIDE / UNHIDE THIS SECTION (IF DETAILS WANTD)
B10: Facility LoB Summary | H10: calculated | I10: calculated | J10: calculated | K10: calculated | L10: Input | M10: Input | N10: Input | O10: Input | P10: Input | Q10: Input | R10: Input | S10: Input | AB10: (-10% to +10%) | AY10: =AX13*AW13*(1-AU13) -> 0 | BA10: ULR apportionment | BF10: Attritional / Large / Cat
C11: calculated | D11: calculated | E11: calculated | F11: calculated | G11: calculated | H11: Methodology 1 | I11: Methodology 2 | J11: Methodology 3 | K11: Methodology 4 | L11: Methodology 5 | M11: Methodology 6 | N11: Weighting 1 | O11: Weighting 2 | P11: Weighting 3 | Q11: Weighting 4 | R11: Weighting 5 | S11: Weighting 6 | T11: calculated | U11: calculated | V11: calculated | W11: calculated | X11: calculated | Y11: calculated | Z11: Input | AA11: calculated | AB11: Input | AC11: calculated | AD11: calculated | AE11: calculated | AF11: calculated | AG11: calculated | AJ11: calculated | AK11: calculated | AL11: calculated | AM11: calculated | AN11: calculated
C12: Tracker Class | D12: Grouped Line of Business | E12: Line of Business | F12: 2025 GN Premium | G12: % of Portfolio | H12: Own Experience GN ULR % | I12: Lloyd's Risk Code GN ULR % | J12: Beazley Own Projections GN ULR % | K12: Business Plan GN ULR % | L12: Beazley 623 Pricing GN ULR % | M12: Case Pricing GN ULR % | N12: Own Experience GN ULR % | O12: Lloyd's Risk Code GN ULR % | P12: Beazley Own Projections GN ULR % | Q12: Business Plan GN ULR % | R12: Beazley 623 Pricing GN ULR % | S12: Case Pricing GN ULR % | T12: Weighting Check | U12: Best Estimate GN ULR % (Pre-Loading) | V12: Climate Change Loading % | W12: NMP Loading % | X12: Anti-Selection Charge % | Y12: Uncertainty Charge % | Z12: Recessionary Charge % | AA12: Best Estimate GN ULR % (Pre UW Adj) | AB12: UW Adjustment | AC12: Best Estimate GN ULR % (Post UW Adj) | AD12: PC % Impact on GN ULR | AE12: Best Estimate GN ULR % | AF12: BPI | AG12: TPI | AH12: RoC | AJ12: Best Estimate GN ULR % (Post UW Adj) | AK12: PC % Impact on GN ULR | AL12: Best Estimate GN ULR % | AM12: BPI | AN12: TPI | AO12: RoC | AQ12: EL | AR12: EL (Excl. Anti-selection load, after PC) | AS12: Net Expense/ GN Premium | AT12: Investment Income / NN Premium | AU12: RI Premium/GN Premium | AV12: RI Recoveries/ GN Premium | AW12: Capital Required / NN Premium | AX12: Target RoC | AY12: Technical Premium | AZ12: Technical Premium (exl. Loads) | BA12: Attritional | BB12: Large | BC12: Attritional + Large | BD12: Cat | BF12: Attritional | BG12: Large | BH12: Attritional + Large | BI12: Cat
B13: 1 | C13: =INDEX(#REF!,MATCH($E13,#REF!,0)) -> #REF! | D13: =INDEX(#REF!,MATCH($E13,#REF!,0)) -> #REF! | E13: {=_xlfn.UNIQUE(#REF!)} -> #REF! | F13: =SUMIFS(#REF!,_xlfn.ANCHORARRAY(#REF!),E13) -> #REF! | G13: =F13/$F$29 -> #REF! | H13: 0.93474633 | I13: 0.81989532 | J13: 0.43638317 | K13: 0.95308398 | L13: 0.23317539 | M13: 0.66451085 | N13: 0.5 | O13: 0.5 | P13: 0 | Q13: 0 | R13: 0 | S13: 0 | T13: =SUM(N13:S13)=1 -> TRUE | U13: =SUMPRODUCT(H13:M13,N13:S13) -> 0.87732082 | V13: =INDEX(#REF!,MATCH($E13,_xlfn.ANCHORARRAY(#REF!),0)) -> #REF! | W13: =INDEX(#REF!,MATCH($E13,_xlfn.ANCHORARRAY(#REF!),0))+INDEX(#REF!,MATCH($E13,_xlfn.ANCHORARRAY(#REF!),0)) -> #REF! | X13: 0.0125 | Y13: 0 | Z13: 0 | AA13: =U13*BC13+U13*BD13*(1+V13)+SUM(W13:Z13) -> #REF! | AB13: 0 | AC13: =AA13+AB13 -> #REF! | AD13: 0.012 | AE13: =AC13+AD13 -> #REF! | AF13: =0.7/AE13 -> #REF! | AG13: =IFERROR(F13/AY13,0) -> 0 | AH13: =(1-AE13-($AU13-$AV13)+($AT13*(1-$AU13))-$AS13)/(($AX13*$AW13*(1-$AU13))/$AX13) -> #REF! | AJ13: =AC13-SUM(X13:Z13) -> #REF! | AK13: 0.013 | AL13: =AJ13+AK13 -> #REF! | AM13: =0.7/AL13 -> #REF! | AN13: =IFERROR(F13/AZ13,0) -> 0 | AO13: =(1-AL13-($AU13-$AV13)+($AT13*(1-$AU13))-$AS13)/(($AX13*$AW13*(1-$AU13))/$AX13) -> #REF! | AQ13: =F13*AE13 -> #REF! | AR13: =F13*AL13 -> #REF! | AS13: 0 | AT13: 0 | AU13: 0 | AV13: 0 | AW13: 0 | AX13: 0 | AY13: =AQ13/(1-AS13-(AU13-AV13)+AT13*(1-AU13)-AX13*AW13*(1-AU13)) -> #REF! | AZ13: =AR13/(1-AS13-(AU13-AV13)+AT13*(1-AU13)-AX13*AW13*(1-AU13)) -> #REF! | BA13: =IF($C$7="Business Plan",0,"placeholder") -> 0 | BB13: =IF($C$7="Business Plan",0,"placeholder") -> 0 | BC13: =IF($C$7="Business Plan",INDEX(#REF!,MATCH($E13,_xlfn.ANCHORARRAY(#REF!),0))/(INDEX(#REF!,MATCH($E13,_xlfn.ANCHORARRAY(#REF!),0))+INDEX(#REF!,MATCH($E13,_xlfn.ANCHORARRAY(#REF!),0))),BA13+BB13) -> #REF! | BD13: =IF($C$7="Business Plan",1-BC13,0) -> #REF! | BF13: =BA13*$AE13 -> #REF! | BG13: =BB13*$AE13 -> #REF! | BH13: =BC13*$AE13 -> #REF! | BI13: =BD13*$AE13 -> #REF!
B14: =1+B13 -> 2 | C14: =INDEX(#REF!,MATCH($E14,#REF!,0)) -> #REF! | D14: =INDEX(#REF!,MATCH($E14,#REF!,0)) -> #REF! | F14: =SUMIFS(#REF!,_xlfn.ANCHORARRAY(#REF!),E14) -> #REF! | G14: =F14/$F$29 -> #REF! | H14: 0.49068832 | I14: 0.26743869 | J14: 0.48952564 | K14: 0.5232361 | L14: 0.7892051 | M14: 0.86205085 | N14: 0.5 | O14: 0.5 | P14: 0 | Q14: 0 | R14: 0 | S14: 0 | T14: =SUM(N14:S14)=1 -> TRUE | U14: =SUMPRODUCT(H14:M14,N14:S14) -> 0.3790635 | V14: =INDEX(#REF!,MATCH($E14,_xlfn.ANCHORARRAY(#REF!),0)) -> #REF! | W14: =INDEX(#REF!,MATCH($E14,_xlfn.ANCHORARRAY(#REF!),0))+INDEX(#REF!,MATCH($E14,_xlfn.ANCHORARRAY(#REF!),0)) -> #REF! | X14: 0.0125 | Y14: 0 | Z14: 0 | AA14: =U14*BC14+U14*BD14*(1+V14)+SUM(W14:Z14) -> #REF! | AB14: 0 | AC14: =AA14+AB14 -> #REF! | AD14: 0.012 | AE14: =AC14+AD14 -> #REF! | AF14: =0.7/AE14 -> #REF! | AG14: =IFERROR(F14/AY14,0) -> 0 | AH14: =(1-AE14-($AU14-$AV14)+($AT14*(1-$AU14))-$AS14)/(($AX14*$AW14*(1-$AU14))/$AX14) -> #REF! | AJ14: =AC14-SUM(X14:Z14) -> #REF! | AK14: 0.013 | AL14: =AJ14+AK14 -> #REF! | AM14: =0.7/AL14 -> #REF! | AN14: =IFERROR(F14/AZ14,0) -> 0 | AO14: =(1-AL14-($AU14-$AV14)+($AT14*(1-$AU14))-$AS14)/(($AX14*$AW14*(1-$AU14))/$AX14) -> #REF! | AQ14: =F14*AE14 -> #REF! | AR14: =F14*AL14 -> #REF! | AS14: 0 | AT14: 0 | AU14: 0 | AV14: 0 | AW14: 0 | AX14: 0 | AY14: =AQ14/(1-AS14-(AU14-AV14)+AT14*(1-AU14)-AX14*AW14*(1-AU14)) -> #REF! | AZ14: =AR14/(1-AS14-(AU14-AV14)+AT14*(1-AU14)-AX14*AW14*(1-AU14)) -> #REF! | BA14: =IF($C$7="Business Plan",0,"placeholder") -> 0 | BB14: =IF($C$7="Business Plan",0,"placeholder") -> 0 | BC14: =IF($C$7="Business Plan",INDEX(#REF!,MATCH($E14,_xlfn.ANCHORARRAY(#REF!),0))/(INDEX(#REF!,MATCH($E14,_xlfn.ANCHORARRAY(#REF!),0))+INDEX(#REF!,MATCH($E14,_xlfn.ANCHORARRAY(#REF!),0))),BA14+BB14) -> #REF! | BD14: =IF($C$7="Business Plan",1-BC14,0) -> #REF! | BF14: =BA14*$AE14 -> #REF! | BG14: =BB14*$AE14 -> #REF! | BH14: =BC14*$AE14 -> #REF! | BI14: =BD14*$AE14 -> #REF!
B15: =1+B14 -> 3 | C15: =INDEX(#REF!,MATCH($E15,#REF!,0)) -> #REF! | D15: =INDEX(#REF!,MATCH($E15,#REF!,0)) -> #REF! | F15: =SUMIFS(#REF!,_xlfn.ANCHORARRAY(#REF!),E15) -> #REF! | G15: =F15/$F$29 -> #REF! | H15: 0.84362686 | I15: 0.59321658 | J15: 0.066182925 | K15: 0.69554769 | L15: 0.01907216 | M15: 0.64527096 | N15: 0.5 | O15: 0.5 | P15: 0 | Q15: 0 | R15: 0 | S15: 0 | T15: =SUM(N15:S15)=1 -> TRUE | U15: =SUMPRODUCT(H15:M15,N15:S15) -> 0.71842172 | V15: =INDEX(#REF!,MATCH($E15,_xlfn.ANCHORARRAY(#REF!),0)) -> #REF! | W15: =INDEX(#REF!,MATCH($E15,_xlfn.ANCHORARRAY(#REF!),0))+INDEX(#REF!,MATCH($E15,_xlfn.ANCHORARRAY(#REF!),0)) -> #REF! | X15: 0.0125 | Y15: 0 | Z15: 0 | AA15: =U15*BC15+U15*BD15*(1+V15)+SUM(W15:Z15) -> #REF! | AB15: 0 | AC15: =AA15+AB15 -> #REF! | AD15: 0.012 | AE15: =AC15+AD15 -> #REF! | AF15: =0.7/AE15 -> #REF! | AG15: =IFERROR(F15/AY15,0) -> 0 | AH15: =(1-AE15-($AU15-$AV15)+($AT15*(1-$AU15))-$AS15)/(($AX15*$AW15*(1-$AU15))/$AX15) -> #REF! | AJ15: =AC15-SUM(X15:Z15) -> #REF! | AK15: 0.013 | AL15: =AJ15+AK15 -> #REF! | AM15: =0.7/AL15 -> #REF! | AN15: =IFERROR(F15/AZ15,0) -> 0 | AO15: =(1-AL15-($AU15-$AV15)+($AT15*(1-$AU15))-$AS15)/(($AX15*$AW15*(1-$AU15))/$AX15) -> #REF! | AQ15: =F15*AE15 -> #REF! | AR15: =F15*AL15 -> #REF! | AS15: 0 | AT15: 0 | AU15: 0 | AV15: 0 | AW15: 0 | AX15: 0 | AY15: =AQ15/(1-AS15-(AU15-AV15)+AT15*(1-AU15)-AX15*AW15*(1-AU15)) -> #REF! | AZ15: =AR15/(1-AS15-(AU15-AV15)+AT15*(1-AU15)-AX15*AW15*(1-AU15)) -> #REF! | BA15: =IF($C$7="Business Plan",0,"placeholder") -> 0 | BB15: =IF($C$7="Business Plan",0,"placeholder") -> 0 | BC15: =IF($C$7="Business Plan",INDEX(#REF!,MATCH($E15,_xlfn.ANCHORARRAY(#REF!),0))/(INDEX(#REF!,MATCH($E15,_xlfn.ANCHORARRAY(#REF!),0))+INDEX(#REF!,MATCH($E15,_xlfn.ANCHORARRAY(#REF!),0))),BA15+BB15) -> #REF! | BD15: =IF($C$7="Business Plan",1-BC15,0) -> #REF! | BF15: =BA15*$AE15 -> #REF! | BG15: =BB15*$AE15 -> #REF! | BH15: =BC15*$AE15 -> #REF! | BI15: =BD15*$AE15 -> #REF!
B16: =1+B15 -> 4 | C16: =INDEX(#REF!,MATCH($E16,#REF!,0)) -> #REF! | D16: =INDEX(#REF!,MATCH($E16,#REF!,0)) -> #REF! | F16: =SUMIFS(#REF!,_xlfn.ANCHORARRAY(#REF!),E16) -> #REF! | G16: =F16/$F$29 -> #REF! | H16: 0.50624371 | I16: 0.7992696 | J16: 0.65949517 | K16: 0.58486715 | L16: 0.027589592 | M16: 0.71970193 | N16: 0.5 | O16: 0.5 | P16: 0 | Q16: 0 | R16: 0 | S16: 0 | T16: =SUM(N16:S16)=1 -> TRUE | U16: =SUMPRODUCT(H16:M16,N16:S16) -> 0.65275665 | V16: =INDEX(#REF!,MATCH($E16,_xlfn.ANCHORARRAY(#REF!),0)) -> #REF! | W16: =INDEX(#REF!,MATCH($E16,_xlfn.ANCHORARRAY(#REF!),0))+INDEX(#REF!,MATCH($E16,_xlfn.ANCHORARRAY(#REF!),0)) -> #REF! | X16: 0.0125 | Y16: 0 | Z16: 0 | AA16: =U16*BC16+U16*BD16*(1+V16)+SUM(W16:Z16) -> #REF! | AB16: 0 | AC16: =AA16+AB16 -> #REF! | AD16: 0.012 | AE16: =AC16+AD16 -> #REF! | AF16: =0.7/AE16 -> #REF! | AG16: =IFERROR(F16/AY16,0) -> 0 | AH16: =(1-AE16-($AU16-$AV16)+($AT16*(1-$AU16))-$AS16)/(($AX16*$AW16*(1-$AU16))/$AX16) -> #REF! | AJ16: =AC16-SUM(X16:Z16) -> #REF! | AK16: 0.013 | AL16: =AJ16+AK16 -> #REF! | AM16: =0.7/AL16 -> #REF! | AN16: =IFERROR(F16/AZ16,0) -> 0 | AO16: =(1-AL16-($AU16-$AV16)+($AT16*(1-$AU16))-$AS16)/(($AX16*$AW16*(1-$AU16))/$AX16) -> #REF! | AQ16: =F16*AE16 -> #REF! | AR16: =F16*AL16 -> #REF! | AS16: 0 | AT16: 0 | AU16: 0 | AV16: 0 | AW16: 0 | AX16: 0 | AY16: =AQ16/(1-AS16-(AU16-AV16)+AT16*(1-AU16)-AX16*AW16*(1-AU16)) -> #REF! | AZ16: =AR16/(1-AS16-(AU16-AV16)+AT16*(1-AU16)-AX16*AW16*(1-AU16)) -> #REF! | BA16: =IF($C$7="Business Plan",0,"placeholder") -> 0 | BB16: =IF($C$7="Business Plan",0,"placeholder") -> 0 | BC16: =IF($C$7="Business Plan",INDEX(#REF!,MATCH($E16,_xlfn.ANCHORARRAY(#REF!),0))/(INDEX(#REF!,MATCH($E16,_xlfn.ANCHORARRAY(#REF!),0))+INDEX(#REF!,MATCH($E16,_xlfn.ANCHORARRAY(#REF!),0))),BA16+BB16) -> #REF! | BD16: =IF($C$7="Business Plan",1-BC16,0) -> #REF! | BF16: =BA16*$AE16 -> #REF! | BG16: =BB16*$AE16 -> #REF! | BH16: =BC16*$AE16 -> #REF! | BI16: =BD16*$AE16 -> #REF!
B17: =1+B16 -> 5 | C17: =INDEX(#REF!,MATCH($E17,#REF!,0)) -> #REF! | D17: =INDEX(#REF!,MATCH($E17,#REF!,0)) -> #REF! | F17: =SUMIFS(#REF!,_xlfn.ANCHORARRAY(#REF!),E17) -> #REF! | G17: =F17/$F$29 -> #REF! | H17: 0.63713272 | I17: 0.65704101 | J17: 0.57358046 | K17: 0.46666842 | L17: 0.19349556 | M17: 0.71627394 | N17: 0.5 | O17: 0.5 | P17: 0 | Q17: 0 | R17: 0 | S17: 0 | T17: =SUM(N17:S17)=1 -> TRUE | U17: =SUMPRODUCT(H17:M17,N17:S17) -> 0.64708686 | V17: =INDEX(#REF!,MATCH($E17,_xlfn.ANCHORARRAY(#REF!),0)) -> #REF! | W17: =INDEX(#REF!,MATCH($E17,_xlfn.ANCHORARRAY(#REF!),0))+INDEX(#REF!,MATCH($E17,_xlfn.ANCHORARRAY(#REF!),0)) -> #REF! | X17: 0.0125 | Y17: 0 | Z17: 0 | AA17: =U17*BC17+U17*BD17*(1+V17)+SUM(W17:Z17) -> #REF! | AB17: 0 | AC17: =AA17+AB17 -> #REF! | AD17: 0.012 | AE17: =AC17+AD17 -> #REF! | AF17: =0.7/AE17 -> #REF! | AG17: =IFERROR(F17/AY17,0) -> 0 | AH17: =(1-AE17-($AU17-$AV17)+($AT17*(1-$AU17))-$AS17)/(($AX17*$AW17*(1-$AU17))/$AX17) -> #REF! | AJ17: =AC17-SUM(X17:Z17) -> #REF! | AK17: 0.013 | AL17: =AJ17+AK17 -> #REF! | AM17: =0.7/AL17 -> #REF! | AN17: =IFERROR(F17/AZ17,0) -> 0 | AO17: =(1-AL17-($AU17-$AV17)+($AT17*(1-$AU17))-$AS17)/(($AX17*$AW17*(1-$AU17))/$AX17) -> #REF! | AQ17: =F17*AE17 -> #REF! | AR17: =F17*AL17 -> #REF! | AS17: 0 | AT17: 0 | AU17: 0 | AV17: 0 | AW17: 0 | AX17: 0 | AY17: =AQ17/(1-AS17-(AU17-AV17)+AT17*(1-AU17)-AX17*AW17*(1-AU17)) -> #REF! | AZ17: =AR17/(1-AS17-(AU17-AV17)+AT17*(1-AU17)-AX17*AW17*(1-AU17)) -> #REF! | BA17: =IF($C$7="Business Plan",0,"placeholder") -> 0 | BB17: =IF($C$7="Business Plan",0,"placeholder") -> 0 | BC17: =IF($C$7="Business Plan",INDEX(#REF!,MATCH($E17,_xlfn.ANCHORARRAY(#REF!),0))/(INDEX(#REF!,MATCH($E17,_xlfn.ANCHORARRAY(#REF!),0))+INDEX(#REF!,MATCH($E17,_xlfn.ANCHORARRAY(#REF!),0))),BA17+BB17) -> #REF! | BD17: =IF($C$7="Business Plan",1-BC17,0) -> #REF! | BF17: =BA17*$AE17 -> #REF! | BG17: =BB17*$AE17 -> #REF! | BH17: =BC17*$AE17 -> #REF! | BI17: =BD17*$AE17 -> #REF!
B18: =1+B17 -> 6 | C18: =INDEX(#REF!,MATCH($E18,#REF!,0)) -> #REF! | D18: =INDEX(#REF!,MATCH($E18,#REF!,0)) -> #REF! | F18: =SUMIFS(#REF!,_xlfn.ANCHORARRAY(#REF!),E18) -> #REF! | G18: =F18/$F$29 -> #REF! | H18: 0.0042186091 | I18: 0.94192651 | J18: 0.0883427 | K18: 0.46457897 | L18: 0.018058164 | M18: 0.38704387 | N18: 0.5 | O18: 0.5 | P18: 0 | Q18: 0 | R18: 0 | S18: 0 | T18: =SUM(N18:S18)=1 -> TRUE | U18: =SUMPRODUCT(H18:M18,N18:S18) -> 0.47307256 | V18: =INDEX(#REF!,MATCH($E18,_xlfn.ANCHORARRAY(#REF!),0)) -> #REF! | W18: =INDEX(#REF!,MATCH($E18,_xlfn.ANCHORARRAY(#REF!),0))+INDEX(#REF!,MATCH($E18,_xlfn.ANCHORARRAY(#REF!),0)) -> #REF! | X18: 0.0125 | Y18: 0 | Z18: 0 | AA18: =U18*BC18+U18*BD18*(1+V18)+SUM(W18:Z18) -> #REF! | AB18: 0 | AC18: =AA18+AB18 -> #REF! | AD18: 0.012 | AE18: =AC18+AD18 -> #REF! | AF18: =0.7/AE18 -> #REF! | AG18: =IFERROR(F18/AY18,0) -> 0 | AH18: =(1-AE18-($AU18-$AV18)+($AT18*(1-$AU18))-$AS18)/(($AX18*$AW18*(1-$AU18))/$AX18) -> #REF! | AJ18: =AC18-SUM(X18:Z18) -> #REF! | AK18: 0.013 | AL18: =AJ18+AK18 -> #REF! | AM18: =0.7/AL18 -> #REF! | AN18: =IFERROR(F18/AZ18,0) -> 0 | AO18: =(1-AL18-($AU18-$AV18)+($AT18*(1-$AU18))-$AS18)/(($AX18*$AW18*(1-$AU18))/$AX18) -> #REF! | AQ18: =F18*AE18 -> #REF! | AR18: =F18*AL18 -> #REF! | AS18: 0 | AT18: 0 | AU18: 0 | AV18: 0 | AW18: 0 | AX18: 0 | AY18: =AQ18/(1-AS18-(AU18-AV18)+AT18*(1-AU18)-AX18*AW18*(1-AU18)) -> #REF! | AZ18: =AR18/(1-AS18-(AU18-AV18)+AT18*(1-AU18)-AX18*AW18*(1-AU18)) -> #REF! | BA18: =IF($C$7="Business Plan",0,"placeholder") -> 0 | BB18: =IF($C$7="Business Plan",0,"placeholder") -> 0 | BC18: =IF($C$7="Business Plan",INDEX(#REF!,MATCH($E18,_xlfn.ANCHORARRAY(#REF!),0))/(INDEX(#REF!,MATCH($E18,_xlfn.ANCHORARRAY(#REF!),0))+INDEX(#REF!,MATCH($E18,_xlfn.ANCHORARRAY(#REF!),0))),BA18+BB18) -> #REF! | BD18: =IF($C$7="Business Plan",1-BC18,0) -> #REF! | BF18: =BA18*$AE18 -> #REF! | BG18: =BB18*$AE18 -> #REF! | BH18: =BC18*$AE18 -> #REF! | BI18: =BD18*$AE18 -> #REF!
B19: =1+B18 -> 7 | C19: =INDEX(#REF!,MATCH($E19,#REF!,0)) -> #REF! | D19: =INDEX(#REF!,MATCH($E19,#REF!,0)) -> #REF! | F19: =SUMIFS(#REF!,_xlfn.ANCHORARRAY(#REF!),E19) -> #REF! | G19: =F19/$F$29 -> #REF! | H19: 0.42659245 | I19: 0.27785508 | J19: 0.7519618 | K19: 0.31242525 | L19: 0.052955392 | M19: 0.7842719 | N19: 0.5 | O19: 0.5 | P19: 0 | Q19: 0 | R19: 0 | S19: 0 | T19: =SUM(N19:S19)=1 -> TRUE | U19: =SUMPRODUCT(H19:M19,N19:S19) -> 0.35222377 | V19: =INDEX(#REF!,MATCH($E19,_xlfn.ANCHORARRAY(#REF!),0)) -> #REF! | W19: =INDEX(#REF!,MATCH($E19,_xlfn.ANCHORARRAY(#REF!),0))+INDEX(#REF!,MATCH($E19,_xlfn.ANCHORARRAY(#REF!),0)) -> #REF! | X19: 0.0125 | Y19: 0 | Z19: 0 | AA19: =U19*BC19+U19*BD19*(1+V19)+SUM(W19:Z19) -> #REF! | AB19: 0 | AC19: =AA19+AB19 -> #REF! | AD19: 0.012 | AE19: =AC19+AD19 -> #REF! | AF19: =0.7/AE19 -> #REF! | AG19: =IFERROR(F19/AY19,0) -> 0 | AH19: =(1-AE19-($AU19-$AV19)+($AT19*(1-$AU19))-$AS19)/(($AX19*$AW19*(1-$AU19))/$AX19) -> #REF! | AJ19: =AC19-SUM(X19:Z19) -> #REF! | AK19: 0.013 | AL19: =AJ19+AK19 -> #REF! | AM19: =0.7/AL19 -> #REF! | AN19: =IFERROR(F19/AZ19,0) -> 0 | AO19: =(1-AL19-($AU19-$AV19)+($AT19*(1-$AU19))-$AS19)/(($AX19*$AW19*(1-$AU19))/$AX19) -> #REF! | AQ19: =F19*AE19 -> #REF! | AR19: =F19*AL19 -> #REF! | AS19: 0 | AT19: 0 | AU19: 0 | AV19: 0 | AW19: 0 | AX19: 0 | AY19: =AQ19/(1-AS19-(AU19-AV19)+AT19*(1-AU19)-AX19*AW19*(1-AU19)) -> #REF! | AZ19: =AR19/(1-AS19-(AU19-AV19)+AT19*(1-AU19)-AX19*AW19*(1-AU19)) -> #REF! | BA19: =IF($C$7="Business Plan",0,"placeholder") -> 0 | BB19: =IF($C$7="Business Plan",0,"placeholder") -> 0 | BC19: =IF($C$7="Business Plan",INDEX(#REF!,MATCH($E19,_xlfn.ANCHORARRAY(#REF!),0))/(INDEX(#REF!,MATCH($E19,_xlfn.ANCHORARRAY(#REF!),0))+INDEX(#REF!,MATCH($E19,_xlfn.ANCHORARRAY(#REF!),0))),BA19+BB19) -> #REF! | BD19: =IF($C$7="Business Plan",1-BC19,0) -> #REF! | BF19: =BA19*$AE19 -> #REF! | BG19: =BB19*$AE19 -> #REF! | BH19: =BC19*$AE19 -> #REF! | BI19: =BD19*$AE19 -> #REF!
B20: =1+B19 -> 8 | C20: =INDEX(#REF!,MATCH($E20,#REF!,0)) -> #REF! | D20: =INDEX(#REF!,MATCH($E20,#REF!,0)) -> #REF! | F20: =SUMIFS(#REF!,_xlfn.ANCHORARRAY(#REF!),E20) -> #REF! | G20: =F20/$F$29 -> #REF! | H20: 0.52204155 | I20: 0.63754796 | J20: 0.013224759 | K20: 0.85222253 | L20: 0.31789589 | M20: 0.98967945 | N20: 0.5 | O20: 0.5 | P20: 0 | Q20: 0 | R20: 0 | S20: 0 | T20: =SUM(N20:S20)=1 -> TRUE | U20: =SUMPRODUCT(H20:M20,N20:S20) -> 0.57979476 | V20: =INDEX(#REF!,MATCH($E20,_xlfn.ANCHORARRAY(#REF!),0)) -> #REF! | W20: =INDEX(#REF!,MATCH($E20,_xlfn.ANCHORARRAY(#REF!),0))+INDEX(#REF!,MATCH($E20,_xlfn.ANCHORARRAY(#REF!),0)) -> #REF! | X20: 0.0125 | Y20: 0 | Z20: 0 | AA20: =U20*BC20+U20*BD20*(1+V20)+SUM(W20:Z20) -> #REF! | AB20: 0 | AC20: =AA20+AB20 -> #REF! | AD20: 0.012 | AE20: =AC20+AD20 -> #REF! | AF20: =0.7/AE20 -> #REF! | AG20: =IFERROR(F20/AY20,0) -> 0 | AH20: =(1-AE20-($AU20-$AV20)+($AT20*(1-$AU20))-$AS20)/(($AX20*$AW20*(1-$AU20))/$AX20) -> #REF! | AJ20: =AC20-SUM(X20:Z20) -> #REF! | AK20: 0.013 | AL20: =AJ20+AK20 -> #REF! | AM20: =0.7/AL20 -> #REF! | AN20: =IFERROR(F20/AZ20,0) -> 0 | AO20: =(1-AL20-($AU20-$AV20)+($AT20*(1-$AU20))-$AS20)/(($AX20*$AW20*(1-$AU20))/$AX20) -> #REF! | AQ20: =F20*AE20 -> #REF! | AR20: =F20*AL20 -> #REF! | AS20: 0 | AT20: 0 | AU20: 0 | AV20: 0 | AW20: 0 | AX20: 0 | AY20: =AQ20/(1-AS20-(AU20-AV20)+AT20*(1-AU20)-AX20*AW20*(1-AU20)) -> #REF! | AZ20: =AR20/(1-AS20-(AU20-AV20)+AT20*(1-AU20)-AX20*AW20*(1-AU20)) -> #REF! | BA20: =IF($C$7="Business Plan",0,"placeholder") -> 0 | BB20: =IF($C$7="Business Plan",0,"placeholder") -> 0 | BC20: =IF($C$7="Business Plan",INDEX(#REF!,MATCH($E20,_xlfn.ANCHORARRAY(#REF!),0))/(INDEX(#REF!,MATCH($E20,_xlfn.ANCHORARRAY(#REF!),0))+INDEX(#REF!,MATCH($E20,_xlfn.ANCHORARRAY(#REF!),0))),BA20+BB20) -> #REF! | BD20: =IF($C$7="Business Plan",1-BC20,0) -> #REF! | BF20: =BA20*$AE20 -> #REF! | BG20: =BB20*$AE20 -> #REF! | BH20: =BC20*$AE20 -> #REF! | BI20: =BD20*$AE20 -> #REF!
B21: =1+B20 -> 9 | C21: =INDEX(#REF!,MATCH($E21,#REF!,0)) -> #REF! | D21: =INDEX(#REF!,MATCH($E21,#REF!,0)) -> #REF! | F21: =SUMIFS(#REF!,_xlfn.ANCHORARRAY(#REF!),E21) -> #REF! | G21: =F21/$F$29 -> #REF! | H21: 0.09559264 | I21: 0.7273133 | J21: 0.10365666 | K21: 0.28208612 | L21: 0.40005888 | M21: 0.26163835 | N21: 0.5 | O21: 0.5 | P21: 0 | Q21: 0 | R21: 0 | S21: 0 | T21: =SUM(N21:S21)=1 -> TRUE | U21: =SUMPRODUCT(H21:M21,N21:S21) -> 0.41145297 | V21: =INDEX(#REF!,MATCH($E21,_xlfn.ANCHORARRAY(#REF!),0)) -> #REF! | W21: =INDEX(#REF!,MATCH($E21,_xlfn.ANCHORARRAY(#REF!),0))+INDEX(#REF!,MATCH($E21,_xlfn.ANCHORARRAY(#REF!),0)) -> #REF! | X21: 0.0125 | Y21: 0 | Z21: 0 | AA21: =U21*BC21+U21*BD21*(1+V21)+SUM(W21:Z21) -> #REF! | AB21: 0 | AC21: =AA21+AB21 -> #REF! | AD21: 0.012 | AE21: =AC21+AD21 -> #REF! | AF21: =0.7/AE21 -> #REF! | AG21: =IFERROR(F21/AY21,0) -> 0 | AH21: =(1-AE21-($AU21-$AV21)+($AT21*(1-$AU21))-$AS21)/(($AX21*$AW21*(1-$AU21))/$AX21) -> #REF! | AJ21: =AC21-SUM(X21:Z21) -> #REF! | AK21: 0.013 | AL21: =AJ21+AK21 -> #REF! | AM21: =0.7/AL21 -> #REF! | AN21: =IFERROR(F21/AZ21,0) -> 0 | AO21: =(1-AL21-($AU21-$AV21)+($AT21*(1-$AU21))-$AS21)/(($AX21*$AW21*(1-$AU21))/$AX21) -> #REF! | AQ21: =F21*AE21 -> #REF! | AR21: =F21*AL21 -> #REF! | AS21: 0 | AT21: 0 | AU21: 0 | AV21: 0 | AW21: 0 | AX21: 0 | AY21: =AQ21/(1-AS21-(AU21-AV21)+AT21*(1-AU21)-AX21*AW21*(1-AU21)) -> #REF! | AZ21: =AR21/(1-AS21-(AU21-AV21)+AT21*(1-AU21)-AX21*AW21*(1-AU21)) -> #REF! | BA21: =IF($C$7="Business Plan",0,"placeholder") -> 0 | BB21: =IF($C$7="Business Plan",0,"placeholder") -> 0 | BC21: =IF($C$7="Business Plan",INDEX(#REF!,MATCH($E21,_xlfn.ANCHORARRAY(#REF!),0))/(INDEX(#REF!,MATCH($E21,_xlfn.ANCHORARRAY(#REF!),0))+INDEX(#REF!,MATCH($E21,_xlfn.ANCHORARRAY(#REF!),0))),BA21+BB21) -> #REF! | BD21: =IF($C$7="Business Plan",1-BC21,0) -> #REF! | BF21: =BA21*$AE21 -> #REF! | BG21: =BB21*$AE21 -> #REF! | BH21: =BC21*$AE21 -> #REF! | BI21: =BD21*$AE21 -> #REF!
B22: =1+B21 -> 10 | C22: =INDEX(#REF!,MATCH($E22,#REF!,0)) -> #REF! | D22: =INDEX(#REF!,MATCH($E22,#REF!,0)) -> #REF! | F22: =SUMIFS(#REF!,_xlfn.ANCHORARRAY(#REF!),E22) -> #REF! | G22: =F22/$F$29 -> #REF! | H22: 0.22762355 | I22: 0.023743624 | J22: 0.42840363 | K22: 0.13686879 | L22: 0.27549434 | M22: 0.35271026 | N22: 0.5 | O22: 0.5 | P22: 0 | Q22: 0 | R22: 0 | S22: 0 | T22: =SUM(N22:S22)=1 -> TRUE | U22: =SUMPRODUCT(H22:M22,N22:S22) -> 0.12568359 | V22: =INDEX(#REF!,MATCH($E22,_xlfn.ANCHORARRAY(#REF!),0)) -> #REF! | W22: =INDEX(#REF!,MATCH($E22,_xlfn.ANCHORARRAY(#REF!),0))+INDEX(#REF!,MATCH($E22,_xlfn.ANCHORARRAY(#REF!),0)) -> #REF! | X22: 0.0125 | Y22: 0 | Z22: 0 | AA22: =U22*BC22+U22*BD22*(1+V22)+SUM(W22:Z22) -> #REF! | AB22: 0 | AC22: =AA22+AB22 -> #REF! | AD22: 0.012 | AE22: =AC22+AD22 -> #REF! | AF22: =0.7/AE22 -> #REF! | AG22: =IFERROR(F22/AY22,0) -> 0 | AH22: =(1-AE22-($AU22-$AV22)+($AT22*(1-$AU22))-$AS22)/(($AX22*$AW22*(1-$AU22))/$AX22) -> #REF! | AJ22: =AC22-SUM(X22:Z22) -> #REF! | AK22: 0.013 | AL22: =AJ22+AK22 -> #REF! | AM22: =0.7/AL22 -> #REF! | AN22: =IFERROR(F22/AZ22,0) -> 0 | AO22: =(1-AL22-($AU22-$AV22)+($AT22*(1-$AU22))-$AS22)/(($AX22*$AW22*(1-$AU22))/$AX22) -> #REF! | AQ22: =F22*AE22 -> #REF! | AR22: =F22*AL22 -> #REF! | AS22: 0 | AT22: 0 | AU22: 0 | AV22: 0 | AW22: 0 | AX22: 0 | AY22: =AQ22/(1-AS22-(AU22-AV22)+AT22*(1-AU22)-AX22*AW22*(1-AU22)) -> #REF! | AZ22: =AR22/(1-AS22-(AU22-AV22)+AT22*(1-AU22)-AX22*AW22*(1-AU22)) -> #REF! | BA22: =IF($C$7="Business Plan",0,"placeholder") -> 0 | BB22: =IF($C$7="Business Plan",0,"placeholder") -> 0 | BC22: =IF($C$7="Business Plan",INDEX(#REF!,MATCH($E22,_xlfn.ANCHORARRAY(#REF!),0))/(INDEX(#REF!,MATCH($E22,_xlfn.ANCHORARRAY(#REF!),0))+INDEX(#REF!,MATCH($E22,_xlfn.ANCHORARRAY(#REF!),0))),BA22+BB22) -> #REF! | BD22: =IF($C$7="Business Plan",1-BC22,0) -> #REF! | BF22: =BA22*$AE22 -> #REF! | BG22: =BB22*$AE22 -> #REF! | BH22: =BC22*$AE22 -> #REF! | BI22: =BD22*$AE22 -> #REF!
B23: =1+B22 -> 11 | C23: =INDEX(#REF!,MATCH($E23,#REF!,0)) -> #REF! | D23: =INDEX(#REF!,MATCH($E23,#REF!,0)) -> #REF! | F23: =SUMIFS(#REF!,_xlfn.ANCHORARRAY(#REF!),E23) -> #REF! | G23: =F23/$F$29 -> #REF! | H23: 0.59962889 | I23: 0.54105462 | J23: 0.11030512 | K23: 0.3989057 | L23: 0.84258574 | M23: 0.49930302 | N23: 0.5 | O23: 0.5 | P23: 0 | Q23: 0 | R23: 0 | S23: 0 | T23: =SUM(N23:S23)=1 -> TRUE | U23: =SUMPRODUCT(H23:M23,N23:S23) -> 0.57034175 | V23: =INDEX(#REF!,MATCH($E23,_xlfn.ANCHORARRAY(#REF!),0)) -> #REF! | W23: =INDEX(#REF!,MATCH($E23,_xlfn.ANCHORARRAY(#REF!),0))+INDEX(#REF!,MATCH($E23,_xlfn.ANCHORARRAY(#REF!),0)) -> #REF! | X23: 0.0125 | Y23: 0 | Z23: 0 | AA23: =U23*BC23+U23*BD23*(1+V23)+SUM(W23:Z23) -> #REF! | AB23: 0 | AC23: =AA23+AB23 -> #REF! | AD23: 0.012 | AE23: =AC23+AD23 -> #REF! | AF23: =0.7/AE23 -> #REF! | AG23: =IFERROR(F23/AY23,0) -> 0 | AH23: =(1-AE23-($AU23-$AV23)+($AT23*(1-$AU23))-$AS23)/(($AX23*$AW23*(1-$AU23))/$AX23) -> #REF! | AJ23: =AC23-SUM(X23:Z23) -> #REF! | AK23: 0.013 | AL23: =AJ23+AK23 -> #REF! | AM23: =0.7/AL23 -> #REF! | AN23: =IFERROR(F23/AZ23,0) -> 0 | AO23: =(1-AL23-($AU23-$AV23)+($AT23*(1-$AU23))-$AS23)/(($AX23*$AW23*(1-$AU23))/$AX23) -> #REF! | AQ23: =F23*AE23 -> #REF! | AR23: =F23*AL23 -> #REF! | AS23: 0 | AT23: 0 | AU23: 0 | AV23: 0 | AW23: 0 | AX23: 0 | AY23: =AQ23/(1-AS23-(AU23-AV23)+AT23*(1-AU23)-AX23*AW23*(1-AU23)) -> #REF! | AZ23: =AR23/(1-AS23-(AU23-AV23)+AT23*(1-AU23)-AX23*AW23*(1-AU23)) -> #REF! | BA23: =IF($C$7="Business Plan",0,"placeholder") -> 0 | BB23: =IF($C$7="Business Plan",0,"placeholder") -> 0 | BC23: =IF($C$7="Business Plan",INDEX(#REF!,MATCH($E23,_xlfn.ANCHORARRAY(#REF!),0))/(INDEX(#REF!,MATCH($E23,_xlfn.ANCHORARRAY(#REF!),0))+INDEX(#REF!,MATCH($E23,_xlfn.ANCHORARRAY(#REF!),0))),BA23+BB23) -> #REF! | BD23: =IF($C$7="Business Plan",1-BC23,0) -> #REF! | BF23: =BA23*$AE23 -> #REF! | BG23: =BB23*$AE23 -> #REF! | BH23: =BC23*$AE23 -> #REF! | BI23: =BD23*$AE23 -> #REF!
B24: =1+B23 -> 12 | C24: =INDEX(#REF!,MATCH($E24,#REF!,0)) -> #REF! | D24: =INDEX(#REF!,MATCH($E24,#REF!,0)) -> #REF! | F24: =SUMIFS(#REF!,_xlfn.ANCHORARRAY(#REF!),E24) -> #REF! | G24: =F24/$F$29 -> #REF! | H24: 0.91025018 | I24: 0.6660594 | J24: 0.10090556 | K24: 0.64816096 | L24: 0.38602254 | M24: 0.85713058 | N24: 0.5 | O24: 0.5 | P24: 0 | Q24: 0 | R24: 0 | S24: 0 | T24: =SUM(N24:S24)=1 -> TRUE | U24: =SUMPRODUCT(H24:M24,N24:S24) -> 0.78815479 | V24: =INDEX(#REF!,MATCH($E24,_xlfn.ANCHORARRAY(#REF!),0)) -> #REF! | W24: =INDEX(#REF!,MATCH($E24,_xlfn.ANCHORARRAY(#REF!),0))+INDEX(#REF!,MATCH($E24,_xlfn.ANCHORARRAY(#REF!),0)) -> #REF! | X24: 0.0125 | Y24: 0 | Z24: 0 | AA24: =U24*BC24+U24*BD24*(1+V24)+SUM(W24:Z24) -> #REF! | AB24: 0 | AC24: =AA24+AB24 -> #REF! | AD24: 0.012 | AE24: =AC24+AD24 -> #REF! | AF24: =0.7/AE24 -> #REF! | AG24: =IFERROR(F24/AY24,0) -> 0 | AH24: =(1-AE24-($AU24-$AV24)+($AT24*(1-$AU24))-$AS24)/(($AX24*$AW24*(1-$AU24))/$AX24) -> #REF! | AJ24: =AC24-SUM(X24:Z24) -> #REF! | AK24: 0.013 | AL24: =AJ24+AK24 -> #REF! | AM24: =0.7/AL24 -> #REF! | AN24: =IFERROR(F24/AZ24,0) -> 0 | AO24: =(1-AL24-($AU24-$AV24)+($AT24*(1-$AU24))-$AS24)/(($AX24*$AW24*(1-$AU24))/$AX24) -> #REF! | AQ24: =F24*AE24 -> #REF! | AR24: =F24*AL24 -> #REF! | AS24: 0 | AT24: 0 | AU24: 0 | AV24: 0 | AW24: 0 | AX24: 0 | AY24: =AQ24/(1-AS24-(AU24-AV24)+AT24*(1-AU24)-AX24*AW24*(1-AU24)) -> #REF! | AZ24: =AR24/(1-AS24-(AU24-AV24)+AT24*(1-AU24)-AX24*AW24*(1-AU24)) -> #REF! | BA24: =IF($C$7="Business Plan",0,"placeholder") -> 0 | BB24: =IF($C$7="Business Plan",0,"placeholder") -> 0 | BC24: =IF($C$7="Business Plan",INDEX(#REF!,MATCH($E24,_xlfn.ANCHORARRAY(#REF!),0))/(INDEX(#REF!,MATCH($E24,_xlfn.ANCHORARRAY(#REF!),0))+INDEX(#REF!,MATCH($E24,_xlfn.ANCHORARRAY(#REF!),0))),BA24+BB24) -> #REF! | BD24: =IF($C$7="Business Plan",1-BC24,0) -> #REF! | BF24: =BA24*$AE24 -> #REF! | BG24: =BB24*$AE24 -> #REF! | BH24: =BC24*$AE24 -> #REF! | BI24: =BD24*$AE24 -> #REF!
B25: =1+B24 -> 13 | C25: =INDEX(#REF!,MATCH($E25,#REF!,0)) -> #REF! | D25: =INDEX(#REF!,MATCH($E25,#REF!,0)) -> #REF! | F25: =SUMIFS(#REF!,_xlfn.ANCHORARRAY(#REF!),E25) -> #REF! | G25: =F25/$F$29 -> #REF! | H25: 0.95703344 | I25: 0.89377708 | J25: 0.55490265 | K25: 0.013589204 | L25: 0.19233823 | M25: 0.3824693 | N25: 0.5 | O25: 0.5 | P25: 0 | Q25: 0 | R25: 0 | S25: 0 | T25: =SUM(N25:S25)=1 -> TRUE | U25: =SUMPRODUCT(H25:M25,N25:S25) -> 0.92540526 | V25: =INDEX(#REF!,MATCH($E25,_xlfn.ANCHORARRAY(#REF!),0)) -> #REF! | W25: =INDEX(#REF!,MATCH($E25,_xlfn.ANCHORARRAY(#REF!),0))+INDEX(#REF!,MATCH($E25,_xlfn.ANCHORARRAY(#REF!),0)) -> #REF! | X25: 0.0125 | Y25: 0 | Z25: 0 | AA25: =U25*BC25+U25*BD25*(1+V25)+SUM(W25:Z25) -> #REF! | AB25: 0 | AC25: =AA25+AB25 -> #REF! | AD25: 0.012 | AE25: =AC25+AD25 -> #REF! | AF25: =0.7/AE25 -> #REF! | AG25: =IFERROR(F25/AY25,0) -> 0 | AH25: =(1-AE25-($AU25-$AV25)+($AT25*(1-$AU25))-$AS25)/(($AX25*$AW25*(1-$AU25))/$AX25) -> #REF! | AJ25: =AC25-SUM(X25:Z25) -> #REF! | AK25: 0.013 | AL25: =AJ25+AK25 -> #REF! | AM25: =0.7/AL25 -> #REF! | AN25: =IFERROR(F25/AZ25,0) -> 0 | AO25: =(1-AL25-($AU25-$AV25)+($AT25*(1-$AU25))-$AS25)/(($AX25*$AW25*(1-$AU25))/$AX25) -> #REF! | AQ25: =F25*AE25 -> #REF! | AR25: =F25*AL25 -> #REF! | AS25: 0 | AT25: 0 | AU25: 0 | AV25: 0 | AW25: 0 | AX25: 0 | AY25: =AQ25/(1-AS25-(AU25-AV25)+AT25*(1-AU25)-AX25*AW25*(1-AU25)) -> #REF! | AZ25: =AR25/(1-AS25-(AU25-AV25)+AT25*(1-AU25)-AX25*AW25*(1-AU25)) -> #REF! | BA25: =IF($C$7="Business Plan",0,"placeholder") -> 0 | BB25: =IF($C$7="Business Plan",0,"placeholder") -> 0 | BC25: =IF($C$7="Business Plan",INDEX(#REF!,MATCH($E25,_xlfn.ANCHORARRAY(#REF!),0))/(INDEX(#REF!,MATCH($E25,_xlfn.ANCHORARRAY(#REF!),0))+INDEX(#REF!,MATCH($E25,_xlfn.ANCHORARRAY(#REF!),0))),BA25+BB25) -> #REF! | BD25: =IF($C$7="Business Plan",1-BC25,0) -> #REF! | BF25: =BA25*$AE25 -> #REF! | BG25: =BB25*$AE25 -> #REF! | BH25: =BC25*$AE25 -> #REF! | BI25: =BD25*$AE25 -> #REF!
... B28: =1+B27 -> 16 | C28: =INDEX(#REF!,MATCH($E28,#REF!,0)) -> #REF! | D28: =INDEX(#REF!,MATCH($E28,#REF!,0)) -> #REF! | F28: =SUMIFS(#REF!,_xlfn.ANCHORARRAY(#REF!),E28) -> #REF! | G28: =F28/$F$29 -> #REF! | H28: 0.61556683 | I28: 0.4025456 | J28: 0.30532662 | K28: 0.59523475 | L28: 0.21903932 | M28: 0.12859678 | N28: 0.5 | O28: 0.5 | P28: 0 | Q28: 0 | R28: 0 | S28: 0 | T28: =SUM(N28:S28)=1 -> TRUE | U28: =SUMPRODUCT(H28:M28,N28:S28) -> 0.50905621 | V28: =INDEX(#REF!,MATCH($E28,_xlfn.ANCHORARRAY(#REF!),0)) -> #REF! | W28: =INDEX(#REF!,MATCH($E28,_xlfn.ANCHORARRAY(#REF!),0))+INDEX(#REF!,MATCH($E28,_xlfn.ANCHORARRAY(#REF!),0)) -> #REF! | X28: 0.0125 | Y28: 0 | Z28: 0 | AA28: =U28*BC28+U28*BD28*(1+V28)+SUM(W28:Z28) -> #REF! | AB28: 0 | AC28: =AA28+AB28 -> #REF! | AD28: 0.012 | AE28: =AC28+AD28 -> #REF! | AF28: =0.7/AE28 -> #REF! | AG28: =IFERROR(F28/AY28,0) -> 0 | AH28: =(1-AE28-($AU28-$AV28)+($AT28*(1-$AU28))-$AS28)/(($AX28*$AW28*(1-$AU28))/$AX28) -> #REF! | AJ28: =AC28-SUM(X28:Z28) -> #REF! | AK28: 0.013 | AL28: =AJ28+AK28 -> #REF! | AM28: =0.7/AL28 -> #REF! | AN28: =IFERROR(F28/AZ28,0) -> 0 | AO28: =(1-AL28-($AU28-$AV28)+($AT28*(1-$AU28))-$AS28)/(($AX28*$AW28*(1-$AU28))/$AX28) -> #REF! | AQ28: =F28*AE28 -> #REF! | AR28: =F28*AL28 -> #REF! | AS28: 0 | AT28: 0 | AU28: 0 | AV28: 0 | AW28: 0 | AX28: 0 | AY28: =AQ28/(1-AS28-(AU28-AV28)+AT28*(1-AU28)-AX28*AW28*(1-AU28)) -> #REF! | AZ28: =AR28/(1-AS28-(AU28-AV28)+AT28*(1-AU28)-AX28*AW28*(1-AU28)) -> #REF! | BA28: =IF($C$7="Business Plan",0,"placeholder") -> 0 | BB28: =IF($C$7="Business Plan",0,"placeholder") -> 0 | BC28: =IF($C$7="Business Plan",INDEX(#REF!,MATCH($E28,_xlfn.ANCHORARRAY(#REF!),0))/(INDEX(#REF!,MATCH($E28,_xlfn.ANCHORARRAY(#REF!),0))+INDEX(#REF!,MATCH($E28,_xlfn.ANCHORARRAY(#REF!),0))),BA28+BB28) -> #REF! | BD28: =IF($C$7="Business Plan",1-BC28,0) -> #REF! | BF28: =BA28*$AE28 -> #REF! | BG28: =BB28*$AE28 -> #REF! | BH28: =BC28*$AE28 -> #REF! | BI28: =BD28*$AE28 -> #REF!
B29: TOTAL | F29: =SUM(F13:F28) -> #REF! | G29: =SUM(G13:G28) -> #REF! | H29: =SUMPRODUCT($G$13:$G$28,H$13:H$28) -> #REF! | I29: =SUMPRODUCT($G$13:$G$28,I$13:I$28) -> #REF! | J29: =SUMPRODUCT($G$13:$G$28,J$13:J$28) -> #REF! | K29: =SUMPRODUCT($G$13:$G$28,K$13:K$28) -> #REF! | L29: =SUMPRODUCT($G$13:$G$28,L$13:L$28) -> #REF! | M29: =SUMPRODUCT($G$13:$G$28,M$13:M$28) -> #REF! | U29: =SUMPRODUCT($G$13:$G$28,U$13:U$28) -> #REF! | V29: =SUMPRODUCT($G$13:$G$28,V$13:V$28) -> #REF! | W29: =SUMPRODUCT($G$13:$G$28,W$13:W$28) -> #REF! | X29: =SUMPRODUCT($G$13:$G$28,X$13:X$28) -> #REF! | Y29: =SUMPRODUCT($G$13:$G$28,Y$13:Y$28) -> #REF! | Z29: =SUMPRODUCT($G$13:$G$28,Z$13:Z$28) -> #REF! | AA29: =SUMPRODUCT($G$13:$G$28,AA$13:AA$28) -> #REF! | AB29: =SUMPRODUCT($G$13:$G$28,AB$13:AB$28) -> #REF! | ... AE29: =SUMPRODUCT($G$13:$G$28,AE$13:AE$28) -> #REF! | AF29: =0.7/AE29 -> #REF! | AG29: =IFERROR(F29/AY29,0) -> 0 | AH29: =(1-AE29-($AU29-$AV29)+($AT29*(1-$AU29))-$AS29)/(($AX29*$AW29*(1-$AU29))/$AX29) -> #REF! | AJ29: =SUMPRODUCT($G$13:$G$28,AJ$13:AJ$28) -> #REF! | AK29: =SUMPRODUCT($G$13:$G$28,AK$13:AK$28) -> #REF! | AL29: =SUMPRODUCT($G$13:$G$28,AL$13:AL$28) -> #REF! | AM29: 1 | AN29: =IFERROR(F29/AZ29,0) -> 0 | AO29: =(1-AL29-($AU29-$AV29)+($AT29*(1-$AU29))-$AS29)/(($AX29*$AW29*(1-$AU29))/$AX29) -> #REF! | AQ29: =SUM(AQ13:AQ28) -> #REF! | AR29: =SUM(AR13:AR28) -> #REF! | AS29: =SUMPRODUCT($G$13:$G$28,AS$13:AS$28) -> #REF! | AT29: =SUMPRODUCT($G$13:$G$28,AT$13:AT$28) -> #REF! | AU29: =SUMPRODUCT($G$13:$G$28,AU$13:AU$28) -> #REF! | AV29: =SUMPRODUCT($G$13:$G$28,AV$13:AV$28) -> #REF! | AW29: =SUMPRODUCT($G$13:$G$28,AW$13:AW$28) -> #REF! | AX29: =SUMPRODUCT($G$13:$G$28,AX$13:AX$28) -> #REF! | AY29: =AQ29/(1-AS29-(AU29-AV29)+AT29*(1-AU29)-AX29*AW29*(1-AU29)) -> #REF! | AZ29: =AR29/(1-AS29-(AU29-AV29)+AT29*(1-AU29)-AX29*AW29*(1-AU29)) -> #REF! | BA29: =SUMPRODUCT($G$13:$G$28,BA$13:BA$28) -> #REF! | BB29: =SUMPRODUCT($G$13:$G$28,BB$13:BB$28) -> #REF! | BC29: =SUMPRODUCT($G$13:$G$28,BC$13:BC$28) -> #REF! | BD29: =SUMPRODUCT($G$13:$G$28,BD$13:BD$28) -> #REF! | BF29: =SUMPRODUCT($G$13:$G$28,BF$13:BF$28) -> #REF! | BG29: =SUMPRODUCT($G$13:$G$28,BG$13:BG$28) -> #REF! | BH29: =SUMPRODUCT($G$13:$G$28,BH$13:BH$28) -> #REF! | BI29: =SUMPRODUCT($G$13:$G$28,BI$13:BI$28) -> #REF!
B32: Grouped LoB | H32: calculated | I32: calculated | J32: calculated | K32: calculated | L32: Input | M32: Input | N32: Input | O32: Input | P32: Input | Q32: Input | R32: Input | S32: Input | BA32: ULR apportionment | BF32: Attritional / Large / Cat
C33: calculated | D33: calculated | E33: calculated | F33: calculated | G33: calculated | H33: Methodology 1 | I33: Methodology 2 | J33: Methodology 3 | K33: Methodology 4 | L33: Methodology 5 | M33: Methodology 6 | N33: Weighting 1 | O33: Weighting 2 | P33: Weighting 3 | Q33: Weighting 4 | R33: Weighting 5 | S33: Weighting 6 | T33: calculated | U33: calculated | V33: calculated | W33: calculated | X33: calculated | Y33: calculated | Z33: Input | AA33: calculated | AB33: Input | AC33: calculated | AD33: calculated | AE33: calculated | AF33: calculated | AG33: calculated | AJ33: calculated | AK33: calculated | AL33: calculated | AM33: calculated | AN33: calculated
C34: Tracker Class | D34: Grouped Line of Business | E34: Line of Business | F34: 2025 GN Premium | G34: % of Portfolio | H34: Own Experience GN ULR % | I34: Lloyd's Risk Code GN ULR % | J34: Beazley Own Projections GN ULR % | K34: Business Plan GN ULR % | L34: Beazley 623 Pricing GN ULR % | M34: Case Pricing GN ULR % | N34: Own Experience GN ULR % | O34: Lloyd's Risk Code GN ULR % | P34: Beazley Own Projections GN ULR % | Q34: Business Plan GN ULR % | R34: Beazley 623 Pricing GN ULR % | S34: Case Pricing GN ULR % | T34: Weighting Check | U34: Best Estimate GN ULR % (Pre-Loading) | V34: Climate Change Loading % | W34: NMP Loading % | X34: Anti-Selection Charge % | Y34: Uncertainty Charge % | Z34: Recessionary Charge % | AA34: Best Estimate GN ULR % (Pre UW Adj) | AB34: UW Adj. (-10% to +10%) | AC34: Best Estimate GN ULR % (Post UW Adj) | AD34: PC % Impact on GN ULR | AE34: Best Estimate GN ULR % | AF34: BPI | AG34: TPI | AH34: RoC | AJ34: Best Estimate GN ULR % (Post UW Adj) | AK34: PC % Impact on GN ULR | AL34: Best Estimate GN ULR % | AM34: BPI | AN34: TPI | AO34: RoC | AQ34: EL | AR34: EL (Excl. Anti-selection load, after PC) | AS34: Net Expense/ GN Premium | AT34: Investment Income / NN Premium | AU34: RI Premium/GN Premium | AV34: RI Recoveries/ GN Premium | AW34: Capital Required / NN Premium | AX34: Target RoC | AY34: Technical Premium | AZ34: Technical Premium (exl. Loads) | BA34: Attritional | BB34: Large | BC34: Attritional + Large | BD34: Cat | BF34: Attritional | BG34: Large | BH34: Attritional + Large | BI34: Cat
B35: 1 | C35: =INDEX($C$13:$C$28,MATCH(D35,$D$13:$D$28,0)) -> #REF! | D35: {=_xlfn.UNIQUE(D13:D28)} -> #REF! | F35: =SUMIFS(#REF!,#REF!,D35) -> #REF! | G35: =F35/$F$43 -> #REF! | H35: 0.78110923 | I35: 0.63219195 | J35: 0.43335978 | K35: 0.7875556 | L35: 0.23317539 | M35: 0.66451085 | N35: 0.5 | O35: 0.5 | P35: 0 | Q35: 0 | R35: 0 | S35: 0 | T35: =SUM(N35:S35)=1 -> TRUE | U35: =SUMPRODUCT(H35:M35,N35:S35) -> 0.70665059 | V35: =INDEX(#REF!,MATCH($D35,_xlfn.ANCHORARRAY(#REF!),0)) -> #REF! | W35: =INDEX(#REF!,MATCH($D35,_xlfn.ANCHORARRAY(#REF!),0))+INDEX(#REF!,MATCH($D35,_xlfn.ANCHORARRAY(#REF!),0)) -> #REF! | X35: 0.0125 | Y35: 0 | Z35: 0 | AA35: =U35*BC35+U35*BD35*(1+V35)+SUM(W35:Z35) -> #REF! | AB35: 0 | AC35: =AA35+AB35 -> #REF! | AD35: 0.012 | AE35: =AC35+AD35 -> #REF! | AF35: =0.7/AE35 -> #REF! | AG35: =IFERROR(F35/AY35,0) -> 0 | AH35: =(1-AE35-($AU35-$AV35)+($AT35*(1-$AU35))-$AS35)/(($AX35*$AW35*(1-$AU35))/$AX35) -> #REF! | AJ35: {=IFERROR(SUMPRODUCT(AJ$13:AJ$28,$G$13:$G$28,--($D35=$D$13:$D$28))/$G35,0)} -> 0 | AK35: {=IFERROR(SUMPRODUCT(AK$13:AK$28,$G$13:$G$28,--($D35=$D$13:$D$28))/$G35,0)} -> 0 | AL35: 0.788 | AM35: =0.7/AL35 -> 0.88832487 | AN35: =IFERROR(F35/AZ35,0) -> 0 | AO35: =(1-AL35-($AU35-$AV35)+($AT35*(1-$AU35))-$AS35)/(($AX35*$AW35*(1-$AU35))/$AX35) -> #DIV/0! | AQ35: =F35*AE35 -> #REF! | AR35: =F35*AL35 -> #REF! | AS35: =IFERROR(INDEX(#REF!,MATCH($C35,#REF!,0)),0) -> 0 | AT35: =IFERROR(INDEX(#REF!,MATCH($C35,#REF!,0)),0) -> 0 | AU35: =IFERROR(INDEX(#REF!,MATCH($C35,#REF!,0)),0) -> 0 | AV35: =IFERROR(INDEX(#REF!,MATCH($C35,#REF!,0)),0) -> 0 | AW35: =IFERROR(INDEX(#REF!,MATCH($C35,#REF!,0)),0) -> 0 | AX35: =IFERROR(INDEX(#REF!,MATCH($C35,#REF!,0)),0) -> 0 | AY35: =AQ35/(1-AS35-(AU35-AV35)+AT35*(1-AU35)-AX35*AW35*(1-AU35)) -> #REF! | AZ35: =AR35/(1-AS35-(AU35-AV35)+AT35*(1-AU35)-AX35*AW35*(1-AU35)) -> #REF! | BA35: =IF($C$7="Business Plan",0,"placeholder") -> 0 | BB35: =IF($C$7="Business Plan",0,"placeholder") -> 0 | BC35: =IF($C$7="Business Plan",INDEX(#REF!,MATCH($D35,_xlfn.ANCHORARRAY(#REF!),0))/(INDEX(#REF!,MATCH($D35,_xlfn.ANCHORARRAY(#REF!),0))+INDEX(#REF!,MATCH($D35,_xlfn.ANCHORARRAY(#REF!),0))),BA35+BB35) -> #REF! | BD35: =IF($C$7="Business Plan",1-BC35,0) -> #REF! | BF35: =BA35*$AE35 -> #REF! | BG35: =BB35*$AE35 -> #REF! | BH35: =BC35*$AE35 -> #REF! | BI35: =BD35*$AE35 -> #REF!
B36: =1+B35 -> 2 | C36: =INDEX($C$13:$C$28,MATCH(D36,$D$13:$D$28,0)) -> #N/A | F36: =SUMIFS(#REF!,#REF!,D36) -> #REF! | G36: =F36/$F$43 -> #REF! | H36: 0.39546096 | I36: 0.79104886 | J36: 0.50913942 | K36: 0.50651758 | L36: 0.7892051 | M36: 0.86205085 | N36: 0.5 | O36: 0.5 | P36: 0 | Q36: 0 | R36: 0 | S36: 0 | T36: =SUM(N36:S36)=1 -> TRUE | U36: =SUMPRODUCT(H36:M36,N36:S36) -> 0.59325491 | V36: =INDEX(#REF!,MATCH($D36,_xlfn.ANCHORARRAY(#REF!),0)) -> #REF! | W36: =INDEX(#REF!,MATCH($D36,_xlfn.ANCHORARRAY(#REF!),0))+INDEX(#REF!,MATCH($D36,_xlfn.ANCHORARRAY(#REF!),0)) -> #REF! | X36: 0.0125 | Y36: 0 | Z36: 0 | AA36: =U36*BC36+U36*BD36*(1+V36)+SUM(W36:Z36) -> #REF! | AB36: 0 | AC36: =AA36+AB36 -> #REF! | AD36: 0.012 | AE36: =AC36+AD36 -> #REF! | AF36: =0.7/AE36 -> #REF! | AG36: =IFERROR(F36/AY36,0) -> 0 | AH36: =(1-AE36-($AU36-$AV36)+($AT36*(1-$AU36))-$AS36)/(($AX36*$AW36*(1-$AU36))/$AX36) -> #REF! | AJ36: {=IFERROR(SUMPRODUCT(AJ$13:AJ$28,$G$13:$G$28,--($D36=$D$13:$D$28))/$G36,0)} -> 0 | AK36: {=IFERROR(SUMPRODUCT(AK$13:AK$28,$G$13:$G$28,--($D36=$D$13:$D$28))/$G36,0)} -> 0 | AL36: {=IFERROR(SUMPRODUCT(AL$13:AL$28,$G$13:$G$28,--($D36=$D$13:$D$28))/$G36,0)} -> 0 | AM36: =0.7/AL36 -> #DIV/0! | AN36: =IFERROR(F36/AZ36,0) -> 0 | AO36: =(1-AL36-($AU36-$AV36)+($AT36*(1-$AU36))-$AS36)/(($AX36*$AW36*(1-$AU36))/$AX36) -> #DIV/0! | AQ36: =F36*AE36 -> #REF! | AR36: =F36*AL36 -> #REF! | AS36: =IFERROR(INDEX(#REF!,MATCH($C36,#REF!,0)),0) -> 0 | AT36: =IFERROR(INDEX(#REF!,MATCH($C36,#REF!,0)),0) -> 0 | AU36: =IFERROR(INDEX(#REF!,MATCH($C36,#REF!,0)),0) -> 0 | AV36: =IFERROR(INDEX(#REF!,MATCH($C36,#REF!,0)),0) -> 0 | AW36: =IFERROR(INDEX(#REF!,MATCH($C36,#REF!,0)),0) -> 0 | AX36: =IFERROR(INDEX(#REF!,MATCH($C36,#REF!,0)),0) -> 0 | AY36: =AQ36/(1-AS36-(AU36-AV36)+AT36*(1-AU36)-AX36*AW36*(1-AU36)) -> #REF! | AZ36: =AR36/(1-AS36-(AU36-AV36)+AT36*(1-AU36)-AX36*AW36*(1-AU36)) -> #REF! | BA36: =IF($C$7="Business Plan",0,"placeholder") -> 0 | BB36: {=IFERROR(SUMPRODUCT(BB$13:BB$28,$G$13:$G$28,--($D36=$D$13:$D$28))/$G36,0)} -> 0 | BC36: =IF($C$7="Business Plan",INDEX(#REF!,MATCH($D36,_xlfn.ANCHORARRAY(#REF!),0))/(INDEX(#REF!,MATCH($D36,_xlfn.ANCHORARRAY(#REF!),0))+INDEX(#REF!,MATCH($D36,_xlfn.ANCHORARRAY(#REF!),0))),BA36+BB36) -> #REF! | BD36: {=IFERROR(SUMPRODUCT(BD$13:BD$28,$G$13:$G$28,--($D36=$D$13:$D$28))/$G36,0)} -> 0 | BF36: =BA36*$AE36 -> #REF! | BG36: =BB36*$AE36 -> #REF! | BH36: =BC36*$AE36 -> #REF! | BI36: =BD36*$AE36 -> #REF!
B37: =1+B36 -> 3 | C37: =INDEX($C$13:$C$28,MATCH(D37,$D$13:$D$28,0)) -> #N/A | F37: =SUMIFS(#REF!,#REF!,D37) -> #REF! | G37: =F37/$F$43 -> #REF! | H37: 0.37517363 | I37: 0.73875168 | J37: 0.035931152 | K37: 0.74954407 | L37: 0.01907216 | M37: 0.64527096 | N37: 0.5 | O37: 0.5 | P37: 0 | Q37: 0 | R37: 0 | S37: 0 | T37: =SUM(N37:S37)=1 -> TRUE | U37: =SUMPRODUCT(H37:M37,N37:S37) -> 0.55696265 | V37: =INDEX(#REF!,MATCH($D37,_xlfn.ANCHORARRAY(#REF!),0)) -> #REF! | W37: =INDEX(#REF!,MATCH($D37,_xlfn.ANCHORARRAY(#REF!),0))+INDEX(#REF!,MATCH($D37,_xlfn.ANCHORARRAY(#REF!),0)) -> #REF! | X37: 0.0125 | Y37: 0 | Z37: 0 | AA37: =U37*BC37+U37*BD37*(1+V37)+SUM(W37:Z37) -> #REF! | AB37: 0 | AC37: =AA37+AB37 -> #REF! | AD37: 0.012 | AE37: =AC37+AD37 -> #REF! | AF37: =0.7/AE37 -> #REF! | AG37: =IFERROR(F37/AY37,0) -> 0 | AH37: =(1-AE37-($AU37-$AV37)+($AT37*(1-$AU37))-$AS37)/(($AX37*$AW37*(1-$AU37))/$AX37) -> #REF! | AJ37: {=IFERROR(SUMPRODUCT(AJ$13:AJ$28,$G$13:$G$28,--($D37=$D$13:$D$28))/$G37,0)} -> 0 | AK37: {=IFERROR(SUMPRODUCT(AK$13:AK$28,$G$13:$G$28,--($D37=$D$13:$D$28))/$G37,0)} -> 0 | AL37: {=IFERROR(SUMPRODUCT(AL$13:AL$28,$G$13:$G$28,--($D37=$D$13:$D$28))/$G37,0)} -> 0 | AM37: =0.7/AL37 -> #DIV/0! | AN37: =IFERROR(F37/AZ37,0) -> 0 | AO37: =(1-AL37-($AU37-$AV37)+($AT37*(1-$AU37))-$AS37)/(($AX37*$AW37*(1-$AU37))/$AX37) -> #DIV/0! | AQ37: =F37*AE37 -> #REF! | AR37: =F37*AL37 -> #REF! | AS37: =IFERROR(INDEX(#REF!,MATCH($C37,#REF!,0)),0) -> 0 | AT37: =IFERROR(INDEX(#REF!,MATCH($C37,#REF!,0)),0) -> 0 | AU37: =IFERROR(INDEX(#REF!,MATCH($C37,#REF!,0)),0) -> 0 | AV37: =IFERROR(INDEX(#REF!,MATCH($C37,#REF!,0)),0) -> 0 | AW37: =IFERROR(INDEX(#REF!,MATCH($C37,#REF!,0)),0) -> 0 | AX37: =IFERROR(INDEX(#REF!,MATCH($C37,#REF!,0)),0) -> 0 | AY37: =AQ37/(1-AS37-(AU37-AV37)+AT37*(1-AU37)-AX37*AW37*(1-AU37)) -> #REF! | AZ37: =AR37/(1-AS37-(AU37-AV37)+AT37*(1-AU37)-AX37*AW37*(1-AU37)) -> #REF! | BA37: =IF($C$7="Business Plan",0,"placeholder") -> 0 | BB37: {=IFERROR(SUMPRODUCT(BB$13:BB$28,$G$13:$G$28,--($D37=$D$13:$D$28))/$G37,0)} -> 0 | BC37: =IF($C$7="Business Plan",INDEX(#REF!,MATCH($D37,_xlfn.ANCHORARRAY(#REF!),0))/(INDEX(#REF!,MATCH($D37,_xlfn.ANCHORARRAY(#REF!),0))+INDEX(#REF!,MATCH($D37,_xlfn.ANCHORARRAY(#REF!),0))),BA37+BB37) -> #REF! | BD37: {=IFERROR(SUMPRODUCT(BD$13:BD$28,$G$13:$G$28,--($D37=$D$13:$D$28))/$G37,0)} -> 0 | BF37: =BA37*$AE37 -> #REF! | BG37: =BB37*$AE37 -> #REF! | BH37: =BC37*$AE37 -> #REF! | BI37: =BD37*$AE37 -> #REF!
B38: =1+B37 -> 4 | C38: =INDEX($C$13:$C$28,MATCH(D38,$D$13:$D$28,0)) -> #N/A | F38: =SUMIFS(#REF!,#REF!,D38) -> #REF! | G38: =F38/$F$43 -> #REF! | H38: 0.4218969 | I38: 0.31703744 | J38: 0.47797391 | K38: 0.29768987 | L38: 0.027589592 | M38: 0.71970193 | N38: 0.5 | O38: 0.5 | P38: 0 | Q38: 0 | R38: 0 | S38: 0 | T38: =SUM(N38:S38)=1 -> TRUE | U38: =SUMPRODUCT(H38:M38,N38:S38) -> 0.36946717 | V38: =INDEX(#REF!,MATCH($D38,_xlfn.ANCHORARRAY(#REF!),0)) -> #REF! | W38: =INDEX(#REF!,MATCH($D38,_xlfn.ANCHORARRAY(#REF!),0))+INDEX(#REF!,MATCH($D38,_xlfn.ANCHORARRAY(#REF!),0)) -> #REF! | X38: 0.0125 | Y38: 0 | Z38: 0 | AA38: =U38*BC38+U38*BD38*(1+V38)+SUM(W38:Z38) -> #REF! | AB38: 0 | AC38: =AA38+AB38 -> #REF! | AD38: 0.012 | AE38: =AC38+AD38 -> #REF! | AF38: =0.7/AE38 -> #REF! | AG38: =IFERROR(F38/AY38,0) -> 0 | AH38: =(1-AE38-($AU38-$AV38)+($AT38*(1-$AU38))-$AS38)/(($AX38*$AW38*(1-$AU38))/$AX38) -> #REF! | AJ38: {=IFERROR(SUMPRODUCT(AJ$13:AJ$28,$G$13:$G$28,--($D38=$D$13:$D$28))/$G38,0)} -> 0 | AK38: {=IFERROR(SUMPRODUCT(AK$13:AK$28,$G$13:$G$28,--($D38=$D$13:$D$28))/$G38,0)} -> 0 | AL38: {=IFERROR(SUMPRODUCT(AL$13:AL$28,$G$13:$G$28,--($D38=$D$13:$D$28))/$G38,0)} -> 0 | AM38: =0.7/AL38 -> #DIV/0! | AN38: =IFERROR(F38/AZ38,0) -> 0 | AO38: =(1-AL38-($AU38-$AV38)+($AT38*(1-$AU38))-$AS38)/(($AX38*$AW38*(1-$AU38))/$AX38) -> #DIV/0! | AQ38: =F38*AE38 -> #REF! | AR38: =F38*AL38 -> #REF! | AS38: =IFERROR(INDEX(#REF!,MATCH($C38,#REF!,0)),0) -> 0 | AT38: =IFERROR(INDEX(#REF!,MATCH($C38,#REF!,0)),0) -> 0 | AU38: =IFERROR(INDEX(#REF!,MATCH($C38,#REF!,0)),0) -> 0 | AV38: =IFERROR(INDEX(#REF!,MATCH($C38,#REF!,0)),0) -> 0 | AW38: =IFERROR(INDEX(#REF!,MATCH($C38,#REF!,0)),0) -> 0 | AX38: =IFERROR(INDEX(#REF!,MATCH($C38,#REF!,0)),0) -> 0 | AY38: =AQ38/(1-AS38-(AU38-AV38)+AT38*(1-AU38)-AX38*AW38*(1-AU38)) -> #REF! | AZ38: =AR38/(1-AS38-(AU38-AV38)+AT38*(1-AU38)-AX38*AW38*(1-AU38)) -> #REF! | BA38: =IF($C$7="Business Plan",0,"placeholder") -> 0 | BB38: {=IFERROR(SUMPRODUCT(BB$13:BB$28,$G$13:$G$28,--($D38=$D$13:$D$28))/$G38,0)} -> 0 | BC38: =IF($C$7="Business Plan",INDEX(#REF!,MATCH($D38,_xlfn.ANCHORARRAY(#REF!),0))/(INDEX(#REF!,MATCH($D38,_xlfn.ANCHORARRAY(#REF!),0))+INDEX(#REF!,MATCH($D38,_xlfn.ANCHORARRAY(#REF!),0))),BA38+BB38) -> #REF! | BD38: {=IFERROR(SUMPRODUCT(BD$13:BD$28,$G$13:$G$28,--($D38=$D$13:$D$28))/$G38,0)} -> 0 | BF38: =BA38*$AE38 -> #REF! | BG38: =BB38*$AE38 -> #REF! | BH38: =BC38*$AE38 -> #REF! | BI38: =BD38*$AE38 -> #REF!
B39: =1+B38 -> 5 | C39: =INDEX($C$13:$C$28,MATCH(D39,$D$13:$D$28,0)) -> #N/A | F39: =SUMIFS(#REF!,#REF!,D39) -> #REF! | G39: =F39/$F$43 -> #REF! | H39: 0.23120855 | I39: 0.024117579 | J39: 0.43515086 | K39: 0.13902443 | L39: 0.19349556 | M39: 0.71627394 | N39: 0.5 | O39: 0.5 | P39: 0 | Q39: 0 | R39: 0 | S39: 0 | T39: =SUM(N39:S39)=1 -> TRUE | U39: =SUMPRODUCT(H39:M39,N39:S39) -> 0.12766307 | V39: =INDEX(#REF!,MATCH($D39,_xlfn.ANCHORARRAY(#REF!),0)) -> #REF! | W39: =INDEX(#REF!,MATCH($D39,_xlfn.ANCHORARRAY(#REF!),0))+INDEX(#REF!,MATCH($D39,_xlfn.ANCHORARRAY(#REF!),0)) -> #REF! | X39: 0.0125 | Y39: 0 | Z39: 0 | AA39: =U39*BC39+U39*BD39*(1+V39)+SUM(W39:Z39) -> #REF! | AB39: 0 | AC39: =AA39+AB39 -> #REF! | AD39: 0.012 | AE39: =AC39+AD39 -> #REF! | AF39: =0.7/AE39 -> #REF! | AG39: =IFERROR(F39/AY39,0) -> 0 | AH39: =(1-AE39-($AU39-$AV39)+($AT39*(1-$AU39))-$AS39)/(($AX39*$AW39*(1-$AU39))/$AX39) -> #REF! | AJ39: {=IFERROR(SUMPRODUCT(AJ$13:AJ$28,$G$13:$G$28,--($D39=$D$13:$D$28))/$G39,0)} -> 0 | AK39: {=IFERROR(SUMPRODUCT(AK$13:AK$28,$G$13:$G$28,--($D39=$D$13:$D$28))/$G39,0)} -> 0 | AL39: {=IFERROR(SUMPRODUCT(AL$13:AL$28,$G$13:$G$28,--($D39=$D$13:$D$28))/$G39,0)} -> 0 | AM39: =0.7/AL39 -> #DIV/0! | AN39: =IFERROR(F39/AZ39,0) -> 0 | AO39: =(1-AL39-($AU39-$AV39)+($AT39*(1-$AU39))-$AS39)/(($AX39*$AW39*(1-$AU39))/$AX39) -> #DIV/0! | AQ39: =F39*AE39 -> #REF! | AR39: =F39*AL39 -> #REF! | AS39: =IFERROR(INDEX(#REF!,MATCH($C39,#REF!,0)),0) -> 0 | AT39: =IFERROR(INDEX(#REF!,MATCH($C39,#REF!,0)),0) -> 0 | AU39: =IFERROR(INDEX(#REF!,MATCH($C39,#REF!,0)),0) -> 0 | AV39: =IFERROR(INDEX(#REF!,MATCH($C39,#REF!,0)),0) -> 0 | AW39: =IFERROR(INDEX(#REF!,MATCH($C39,#REF!,0)),0) -> 0 | AX39: =IFERROR(INDEX(#REF!,MATCH($C39,#REF!,0)),0) -> 0 | AY39: =AQ39/(1-AS39-(AU39-AV39)+AT39*(1-AU39)-AX39*AW39*(1-AU39)) -> #REF! | AZ39: =AR39/(1-AS39-(AU39-AV39)+AT39*(1-AU39)-AX39*AW39*(1-AU39)) -> #REF! | BA39: =IF($C$7="Business Plan",0,"placeholder") -> 0 | BB39: {=IFERROR(SUMPRODUCT(BB$13:BB$28,$G$13:$G$28,--($D39=$D$13:$D$28))/$G39,0)} -> 0 | BC39: =IF($C$7="Business Plan",INDEX(#REF!,MATCH($D39,_xlfn.ANCHORARRAY(#REF!),0))/(INDEX(#REF!,MATCH($D39,_xlfn.ANCHORARRAY(#REF!),0))+INDEX(#REF!,MATCH($D39,_xlfn.ANCHORARRAY(#REF!),0))),BA39+BB39) -> #REF! | BD39: {=IFERROR(SUMPRODUCT(BD$13:BD$28,$G$13:$G$28,--($D39=$D$13:$D$28))/$G39,0)} -> 0 | BF39: =BA39*$AE39 -> #REF! | BG39: =BB39*$AE39 -> #REF! | BH39: =BC39*$AE39 -> #REF! | BI39: =BD39*$AE39 -> #REF!
B40: =1+B39 -> 6 | C40: =INDEX($C$13:$C$28,MATCH(D40,$D$13:$D$28,0)) -> #N/A | F40: =SUMIFS(#REF!,#REF!,D40) -> #REF! | G40: =F40/$F$43 -> #REF! | H40: 0.94029833 | I40: 0.75302772 | J40: 0.25496791 | K40: 0.4452509 | L40: 0.018058164 | M40: 0.38704387 | N40: 0.5 | O40: 0.5 | P40: 0 | Q40: 0 | R40: 0 | S40: 0 | T40: =SUM(N40:S40)=1 -> TRUE | U40: =SUMPRODUCT(H40:M40,N40:S40) -> 0.84666302 | V40: =INDEX(#REF!,MATCH($D40,_xlfn.ANCHORARRAY(#REF!),0)) -> #REF! | W40: =INDEX(#REF!,MATCH($D40,_xlfn.ANCHORARRAY(#REF!),0))+INDEX(#REF!,MATCH($D40,_xlfn.ANCHORARRAY(#REF!),0)) -> #REF! | X40: 0.0125 | Y40: 0 | Z40: 0 | AA40: =U40*BC40+U40*BD40*(1+V40)+SUM(W40:Z40) -> #REF! | AB40: 0 | AC40: =AA40+AB40 -> #REF! | AD40: 0.012 | AE40: =AC40+AD40 -> #REF! | AF40: =0.7/AE40 -> #REF! | AG40: =IFERROR(F40/AY40,0) -> 0 | AH40: =(1-AE40-($AU40-$AV40)+($AT40*(1-$AU40))-$AS40)/(($AX40*$AW40*(1-$AU40))/$AX40) -> #REF! | AJ40: {=IFERROR(SUMPRODUCT(AJ$13:AJ$28,$G$13:$G$28,--($D40=$D$13:$D$28))/$G40,0)} -> 0 | AK40: {=IFERROR(SUMPRODUCT(AK$13:AK$28,$G$13:$G$28,--($D40=$D$13:$D$28))/$G40,0)} -> 0 | AL40: {=IFERROR(SUMPRODUCT(AL$13:AL$28,$G$13:$G$28,--($D40=$D$13:$D$28))/$G40,0)} -> 0 | AM40: =0.7/AL40 -> #DIV/0! | AN40: =IFERROR(F40/AZ40,0) -> 0 | AO40: =(1-AL40-($AU40-$AV40)+($AT40*(1-$AU40))-$AS40)/(($AX40*$AW40*(1-$AU40))/$AX40) -> #DIV/0! | AQ40: =F40*AE40 -> #REF! | AR40: =F40*AL40 -> #REF! | AS40: =IFERROR(INDEX(#REF!,MATCH($C40,#REF!,0)),0) -> 0 | AT40: =IFERROR(INDEX(#REF!,MATCH($C40,#REF!,0)),0) -> 0 | AU40: =IFERROR(INDEX(#REF!,MATCH($C40,#REF!,0)),0) -> 0 | AV40: =IFERROR(INDEX(#REF!,MATCH($C40,#REF!,0)),0) -> 0 | AW40: =IFERROR(INDEX(#REF!,MATCH($C40,#REF!,0)),0) -> 0 | AX40: =IFERROR(INDEX(#REF!,MATCH($C40,#REF!,0)),0) -> 0 | AY40: =AQ40/(1-AS40-(AU40-AV40)+AT40*(1-AU40)-AX40*AW40*(1-AU40)) -> #REF! | AZ40: =AR40/(1-AS40-(AU40-AV40)+AT40*(1-AU40)-AX40*AW40*(1-AU40)) -> #REF! | BA40: =IF($C$7="Business Plan",0,"placeholder") -> 0 | BB40: {=IFERROR(SUMPRODUCT(BB$13:BB$28,$G$13:$G$28,--($D40=$D$13:$D$28))/$G40,0)} -> 0 | BC40: =IF($C$7="Business Plan",INDEX(#REF!,MATCH($D40,_xlfn.ANCHORARRAY(#REF!),0))/(INDEX(#REF!,MATCH($D40,_xlfn.ANCHORARRAY(#REF!),0))+INDEX(#REF!,MATCH($D40,_xlfn.ANCHORARRAY(#REF!),0))),BA40+BB40) -> #REF! | BD40: {=IFERROR(SUMPRODUCT(BD$13:BD$28,$G$13:$G$28,--($D40=$D$13:$D$28))/$G40,0)} -> 0 | BF40: =BA40*$AE40 -> #REF! | BG40: =BB40*$AE40 -> #REF! | BH40: =BC40*$AE40 -> #REF! | BI40: =BD40*$AE40 -> #REF!
B41: =1+B40 -> 7 | C41: =INDEX($C$13:$C$28,MATCH(D41,$D$13:$D$28,0)) -> #N/A | F41: =SUMIFS(#REF!,#REF!,D41) -> #REF! | G41: =F41/$F$43 -> #REF! | H41: 0.54739143 | I41: 0.31654973 | J41: 0.40121948 | K41: 0.4600953 | L41: 0.052955392 | M41: 0.7842719 | N41: 0.5 | O41: 0.5 | P41: 0 | Q41: 0 | R41: 0 | S41: 0 | T41: =SUM(N41:S41)=1 -> TRUE | U41: =SUMPRODUCT(H41:M41,N41:S41) -> 0.43197058 | V41: =INDEX(#REF!,MATCH($D41,_xlfn.ANCHORARRAY(#REF!),0)) -> #REF! | W41: =INDEX(#REF!,MATCH($D41,_xlfn.ANCHORARRAY(#REF!),0))+INDEX(#REF!,MATCH($D41,_xlfn.ANCHORARRAY(#REF!),0)) -> #REF! | X41: 0.0125 | Y41: 0 | Z41: 0 | AA41: =U41*BC41+U41*BD41*(1+V41)+SUM(W41:Z41) -> #REF! | AB41: 0 | AC41: =AA41+AB41 -> #REF! | AD41: 0.012 | AE41: =AC41+AD41 -> #REF! | AF41: =0.7/AE41 -> #REF! | AG41: =IFERROR(F41/AY41,0) -> 0 | AH41: =(1-AE41-($AU41-$AV41)+($AT41*(1-$AU41))-$AS41)/(($AX41*$AW41*(1-$AU41))/$AX41) -> #REF! | AJ41: {=IFERROR(SUMPRODUCT(AJ$13:AJ$28,$G$13:$G$28,--($D41=$D$13:$D$28))/$G41,0)} -> 0 | AK41: {=IFERROR(SUMPRODUCT(AK$13:AK$28,$G$13:$G$28,--($D41=$D$13:$D$28))/$G41,0)} -> 0 | AL41: {=IFERROR(SUMPRODUCT(AL$13:AL$28,$G$13:$G$28,--($D41=$D$13:$D$28))/$G41,0)} -> 0 | AM41: =0.7/AL41 -> #DIV/0! | AN41: =IFERROR(F41/AZ41,0) -> 0 | AO41: =(1-AL41-($AU41-$AV41)+($AT41*(1-$AU41))-$AS41)/(($AX41*$AW41*(1-$AU41))/$AX41) -> #DIV/0! | AQ41: =F41*AE41 -> #REF! | AR41: =F41*AL41 -> #REF! | AS41: =IFERROR(INDEX(#REF!,MATCH($C41,#REF!,0)),0) -> 0 | AT41: =IFERROR(INDEX(#REF!,MATCH($C41,#REF!,0)),0) -> 0 | AU41: =IFERROR(INDEX(#REF!,MATCH($C41,#REF!,0)),0) -> 0 | AV41: =IFERROR(INDEX(#REF!,MATCH($C41,#REF!,0)),0) -> 0 | AW41: =IFERROR(INDEX(#REF!,MATCH($C41,#REF!,0)),0) -> 0 | AX41: =IFERROR(INDEX(#REF!,MATCH($C41,#REF!,0)),0) -> 0 | AY41: =AQ41/(1-AS41-(AU41-AV41)+AT41*(1-AU41)-AX41*AW41*(1-AU41)) -> #REF! | AZ41: =AR41/(1-AS41-(AU41-AV41)+AT41*(1-AU41)-AX41*AW41*(1-AU41)) -> #REF! | BA41: =IF($C$7="Business Plan",0,"placeholder") -> 0 | BB41: {=IFERROR(SUMPRODUCT(BB$13:BB$28,$G$13:$G$28,--($D41=$D$13:$D$28))/$G41,0)} -> 0 | BC41: =IF($C$7="Business Plan",INDEX(#REF!,MATCH($D41,_xlfn.ANCHORARRAY(#REF!),0))/(INDEX(#REF!,MATCH($D41,_xlfn.ANCHORARRAY(#REF!),0))+INDEX(#REF!,MATCH($D41,_xlfn.ANCHORARRAY(#REF!),0))),BA41+BB41) -> #REF! | BD41: {=IFERROR(SUMPRODUCT(BD$13:BD$28,$G$13:$G$28,--($D41=$D$13:$D$28))/$G41,0)} -> 0 | BF41: =BA41*$AE41 -> #REF! | BG41: =BB41*$AE41 -> #REF! | BH41: =BC41*$AE41 -> #REF! | BI41: =BD41*$AE41 -> #REF!
B42: =1+B41 -> 8 | C42: =INDEX($C$13:$C$28,MATCH(D42,$D$13:$D$28,0)) -> #N/A | F42: =SUMIFS(#REF!,#REF!,D42) -> #REF! | G42: =F42/$F$43 -> #REF! | H42: 0.23497727 | I42: 0.18139063 | J42: 0.48647506 | K42: 0.53358387 | L42: 0.31789589 | M42: 0.98967945 | N42: 0.5 | O42: 0.5 | P42: 0 | Q42: 0 | R42: 0 | S42: 0 | T42: =SUM(N42:S42)=1 -> TRUE | U42: =SUMPRODUCT(H42:M42,N42:S42) -> 0.20818395 | V42: =INDEX(#REF!,MATCH($D42,_xlfn.ANCHORARRAY(#REF!),0)) -> #REF! | W42: =INDEX(#REF!,MATCH($D42,_xlfn.ANCHORARRAY(#REF!),0))+INDEX(#REF!,MATCH($D42,_xlfn.ANCHORARRAY(#REF!),0)) -> #REF! | X42: 0.0125 | Y42: 0 | Z42: 0 | AA42: =U42*BC42+U42*BD42*(1+V42)+SUM(W42:Z42) -> #REF! | AB42: 0 | AC42: =AA42+AB42 -> #REF! | AD42: 0.012 | AE42: =AC42+AD42 -> #REF! | AF42: =0.7/AE42 -> #REF! | AG42: =IFERROR(F42/AY42,0) -> 0 | AH42: =(1-AE42-($AU42-$AV42)+($AT42*(1-$AU42))-$AS42)/(($AX42*$AW42*(1-$AU42))/$AX42) -> #REF! | AJ42: {=IFERROR(SUMPRODUCT(AJ$13:AJ$28,$G$13:$G$28,--($D42=$D$13:$D$28))/$G42,0)} -> 0 | AK42: {=IFERROR(SUMPRODUCT(AK$13:AK$28,$G$13:$G$28,--($D42=$D$13:$D$28))/$G42,0)} -> 0 | AL42: {=IFERROR(SUMPRODUCT(AL$13:AL$28,$G$13:$G$28,--($D42=$D$13:$D$28))/$G42,0)} -> 0 | AM42: =0.7/AL42 -> #DIV/0! | AN42: =IFERROR(F42/AZ42,0) -> 0 | AO42: =(1-AL42-($AU42-$AV42)+($AT42*(1-$AU42))-$AS42)/(($AX42*$AW42*(1-$AU42))/$AX42) -> #DIV/0! | AQ42: =F42*AE42 -> #REF! | AR42: =F42*AL42 -> #REF! | AS42: =IFERROR(INDEX(#REF!,MATCH($C42,#REF!,0)),0) -> 0 | AT42: =IFERROR(INDEX(#REF!,MATCH($C42,#REF!,0)),0) -> 0 | AU42: =IFERROR(INDEX(#REF!,MATCH($C42,#REF!,0)),0) -> 0 | AV42: =IFERROR(INDEX(#REF!,MATCH($C42,#REF!,0)),0) -> 0 | AW42: =IFERROR(INDEX(#REF!,MATCH($C42,#REF!,0)),0) -> 0 | AX42: =IFERROR(INDEX(#REF!,MATCH($C42,#REF!,0)),0) -> 0 | AY42: =AQ42/(1-AS42-(AU42-AV42)+AT42*(1-AU42)-AX42*AW42*(1-AU42)) -> #REF! | AZ42: =AR42/(1-AS42-(AU42-AV42)+AT42*(1-AU42)-AX42*AW42*(1-AU42)) -> #REF! | BA42: =IF($C$7="Business Plan",0,"placeholder") -> 0 | BB42: {=IFERROR(SUMPRODUCT(BB$13:BB$28,$G$13:$G$28,--($D42=$D$13:$D$28))/$G42,0)} -> 0 | BC42: =IF($C$7="Business Plan",INDEX(#REF!,MATCH($D42,_xlfn.ANCHORARRAY(#REF!),0))/(INDEX(#REF!,MATCH($D42,_xlfn.ANCHORARRAY(#REF!),0))+INDEX(#REF!,MATCH($D42,_xlfn.ANCHORARRAY(#REF!),0))),BA42+BB42) -> #REF! | BD42: {=IFERROR(SUMPRODUCT(BD$13:BD$28,$G$13:$G$28,--($D42=$D$13:$D$28))/$G42,0)} -> 0 | BF42: =BA42*$AE42 -> #REF! | BG42: =BB42*$AE42 -> #REF! | BH42: =BC42*$AE42 -> #REF! | BI42: =BD42*$AE42 -> #REF!
B43: TOTAL | F43: =SUM(F35:F42) -> #REF! | G43: =SUM(G35:G42) -> #REF! | H43: =SUMPRODUCT($G$35:$G$42,H$35:H$42) -> #REF! | I43: =SUMPRODUCT($G$35:$G$42,I$35:I$42) -> #REF! | J43: =SUMPRODUCT($G$35:$G$42,J$35:J$42) -> #REF! | K43: =SUMPRODUCT($G$35:$G$42,K$35:K$42) -> #REF! | L43: =SUMPRODUCT($G$35:$G$42,L$35:L$42) -> #REF! | M43: =SUMPRODUCT($G$35:$G$42,M$35:M$42) -> #REF! | U43: =SUMPRODUCT($G$35:$G$42,U$35:U$42) -> #REF! | V43: =SUMPRODUCT($G$35:$G$42,V$35:V$42) -> #REF! | W43: =SUMPRODUCT($G$35:$G$42,W$35:W$42) -> #REF! | X43: =SUMPRODUCT($G$35:$G$42,X$35:X$42) -> #REF! | Y43: =SUMPRODUCT($G$35:$G$42,Y$35:Y$42) -> #REF! | Z43: =SUMPRODUCT($G$35:$G$42,Z$35:Z$42) -> #REF! | AA43: =SUMPRODUCT($G$35:$G$42,AA$35:AA$42) -> #REF! | AB43: =SUMPRODUCT($G$35:$G$42,AB$35:AB$42) -> #REF! | ... AE43: =SUMPRODUCT($G$35:$G$42,AE$35:AE$42) -> #REF! | AF43: =0.7/AE43 -> #REF! | AG43: =IFERROR(F43/AY43,0) -> 0 | AH43: =(1-AE43-($AU43-$AV43)+($AT43*(1-$AU43))-$AS43)/(($AX43*$AW43*(1-$AU43))/$AX43) -> #REF! | AJ43: =SUMPRODUCT($G$35:$G$42,AJ$35:AJ$42) -> #REF! | AK43: =SUMPRODUCT($G$35:$G$42,AK$35:AK$42) -> #REF! | AL43: =SUMPRODUCT($G$35:$G$42,AL$35:AL$42) -> #REF! | AM43: 1 | AN43: =IFERROR(F43/AZ43,0) -> 0 | AO43: =(1-AL43-($AU43-$AV43)+($AT43*(1-$AU43))-$AS43)/(($AX43*$AW43*(1-$AU43))/$AX43) -> #REF! | AQ43: =SUM(AQ32:AQ42) -> #REF! | AR43: =SUM(AR32:AR42) -> #REF! | AS43: =SUMPRODUCT($G$35:$G$42,AS$35:AS$42) -> #REF! | AT43: =SUMPRODUCT($G$35:$G$42,AT$35:AT$42) -> #REF! | AU43: =SUMPRODUCT($G$35:$G$42,AU$35:AU$42) -> #REF! | AV43: =SUMPRODUCT($G$35:$G$42,AV$35:AV$42) -> #REF! | AW43: =SUMPRODUCT($G$35:$G$42,AW$35:AW$42) -> #REF! | AX43: =SUMPRODUCT($G$35:$G$42,AX$35:AX$42) -> #REF! | AY43: =AQ43/(1-AS43-(AU43-AV43)+AT43*(1-AU43)-AX43*AW43*(1-AU43)) -> #REF! | AZ43: =AR43/(1-AS43-(AU43-AV43)+AT43*(1-AU43)-AX43*AW43*(1-AU43)) -> #REF! | BA43: =SUMPRODUCT($G$35:$G$42,BA$35:BA$42) -> #REF! | BB43: =SUMPRODUCT($G$35:$G$42,BB$35:BB$42) -> #REF! | BC43: =SUMPRODUCT($G$35:$G$42,BC$35:BC$42) -> #REF! | BD43: =SUMPRODUCT($G$35:$G$42,BD$35:BD$42) -> #REF! | BF43: =SUMPRODUCT($G$13:$G$28,BF$13:BF$28) -> #REF! | BG43: =SUMPRODUCT($G$13:$G$28,BG$13:BG$28) -> #REF! | BH43: =SUMPRODUCT($G$13:$G$28,BH$13:BH$28) -> #REF! | BI43: =SUMPRODUCT($G$13:$G$28,BI$13:BI$28) -> #REF!
G48: =G43=1 -> #REF!
AJ50: Excluding anti-selection, uncertainty and recessionary charge | AQ50: HIDE / UNHIDE THIS SECTION (IF DETAILS WANTD)
B51: Granular LoB Summary | H51: calculated | I51: calculated | J51: calculated | K51: calculated | L51: Input | M51: Input | N51: Input | O51: Input | P51: Input | Q51: Input | R51: Input | S51: Input | BA51: ULR apportionment | BF51: Attritional / Large / Cat
C52: calculated | D52: calculated | E52: calculated | F52: calculated | G52: calculated | H52: Methodology 1 | I52: Methodology 2 | J52: Methodology 3 | K52: Methodology 4 | L52: Methodology 5 | M52: Methodology 6 | N52: Weighting 1 | O52: Weighting 2 | P52: Weighting 3 | Q52: Weighting 4 | R52: Weighting 5 | S52: Weighting 6 | T52: calculated | U52: calculated | V52: calculated | W52: calculated | X52: calculated | Y52: calculated | Z52: Input | AA52: calculated | AB52: Input | AC52: calculated | AD52: calculated | AE52: calculated | AF52: calculated | AG52: calculated | AJ52: calculated | AK52: calculated | AL52: calculated | AM52: calculated | AN52: calculated
C53: Tracker Class | D53: Grouped Line of Business | E53: Line of Business | F53: 2025 GN Premium | G53: % of Portfolio | H53: Own Experience GN ULR % | I53: Lloyd's Risk Code GN ULR % | J53: Beazley Own Projections GN ULR % | K53: Business Plan GN ULR % | L53: Beazley 623 Pricing GN ULR % | M53: Case Pricing GN ULR % | N53: Own Experience GN ULR % | O53: Lloyd's Risk Code GN ULR % | P53: Beazley Own Projections GN ULR % | Q53: Business Plan GN ULR % | R53: Beazley 623 Pricing GN ULR % | S53: Case Pricing GN ULR % | T53: Weighting Check | U53: Best Estimate GN ULR % (Pre-Loading) | V53: Climate Change Loading % | W53: NMP Loading % | X53: Anti-Selection Charge % | Y53: Uncertainty Charge % | Z53: Recessionary Charge % | AA53: Best Estimate GN ULR % (Pre UW Adj) | AB53: UW Adjustment | AC53: Best Estimate GN ULR % (Post UW Adj) | AD53: PC % Impact on GN ULR | AE53: Best Estimate GN ULR % | AF53: BPI | AG53: TPI | AH53: RoC | AJ53: Best Estimate GN ULR % (Post UW Adj) | AK53: PC % Impact on GN ULR | AL53: Best Estimate GN ULR % | AM53: BPI | AN53: TPI | AO53: RoC | AQ53: EL | AR53: EL (Excl. Anti-selection load, after PC) | AS53: Net Expense/ GN Premium | AT53: Investment Income / NN Premium | AU53: RI Premium/GN Premium | AV53: RI Recoveries/ GN Premium | AW53: Capital Required / NN Premium | AX53: Target RoC | AY53: Technical Premium | AZ53: Technical Premium (exl. Loads) | BA53: Attritional | BB53: Large | BC53: Attritional + Large | BD53: Cat | BF53: Attritional | BG53: Large | BH53: Attritional + Large | BI53: Cat
B54: 1 | C54: Tracker Property | F54: =SUMIFS(F$13:F$28,$C$13:$C$28,$C54) -> 0 | G54: =F54/$F$59 -> #DIV/0! | H54: {=IFERROR(SUMPRODUCT(H$13:H$28,$G$13:$G$28,--($C54=$C$13:$C$28))/$G54,0)} -> 0 | I54: {=IFERROR(SUMPRODUCT(I$13:I$28,$G$13:$G$28,--($C54=$C$13:$C$28))/$G54,0)} -> 0 | J54: {=IFERROR(SUMPRODUCT(J$13:J$28,$G$13:$G$28,--($C54=$C$13:$C$28))/$G54,0)} -> 0 | K54: {=IFERROR(SUMPRODUCT(K$13:K$28,$G$13:$G$28,--($C54=$C$13:$C$28))/$G54,0)} -> 0 | L54: {=IFERROR(SUMPRODUCT(L$13:L$28,$G$13:$G$28,--($C54=$C$13:$C$28))/$G54,0)} -> 0 | M54: {=IFERROR(SUMPRODUCT(M$13:M$28,$G$13:$G$28,--($C54=$C$13:$C$28))/$G54,0)} -> 0 | N54: {=IFERROR(SUMPRODUCT(N$13:N$28,$G$13:$G$28,--($C54=$C$13:$C$28))/$G54,0)} -> 0 | O54: {=IFERROR(SUMPRODUCT(O$13:O$28,$G$13:$G$28,--($C54=$C$13:$C$28))/$G54,0)} -> 0 | ... S54: {=IFERROR(SUMPRODUCT(S$13:S$28,$G$13:$G$28,--($C54=$C$13:$C$28))/$G54,0)} -> 0 | T54: =SUM(N54:S54)=1 -> FALSE | U54: {=IFERROR(SUMPRODUCT(U$13:U$28,$G$13:$G$28,--($C54=$C$13:$C$28))/$G54,0)} -> 0 | V54: {=IFERROR(SUMPRODUCT(V$13:V$28,$G$13:$G$28,--($C54=$C$13:$C$28))/$G54,0)} -> 0 | W54: {=IFERROR(SUMPRODUCT(W$13:W$28,$G$13:$G$28,--($C54=$C$13:$C$28))/$G54,0)} -> 0 | X54: {=IFERROR(SUMPRODUCT(X$13:X$28,$G$13:$G$28,--($C54=$C$13:$C$28))/$G54,0)} -> 0 | Y54: {=IFERROR(SUMPRODUCT(Y$13:Y$28,$G$13:$G$28,--($C54=$C$13:$C$28))/$G54,0)} -> 0 | Z54: {=IFERROR(SUMPRODUCT(Z$13:Z$28,$G$13:$G$28,--($C54=$C$13:$C$28))/$G54,0)} -> 0 | AA54: {=IFERROR(SUMPRODUCT(AA$13:AA$28,$G$13:$G$28,--($C54=$C$13:$C$28))/$G54,0)} -> 0 | AB54: {=IFERROR(SUMPRODUCT(AB$13:AB$28,$G$13:$G$28,--($C54=$C$13:$C$28))/$G54,0)} -> 0 | ... AF54: {=IFERROR(SUMPRODUCT(AF$13:AF$28,$G$13:$G$28,--($C54=$C$13:$C$28))/$G54,0)} -> 0 | AG54: =IFERROR(F54/AY54,0) -> 0 | AH54: =(1-AE54-($AU54-$AV54)+($AT54*(1-$AU54))-$AS54)/(($AX54*$AW54*(1-$AU54))/$AX54) -> #DIV/0! | AJ54: {=IFERROR(SUMPRODUCT(AJ$13:AJ$28,$G$13:$G$28,--($C54=$C$13:$C$28))/$G54,0)} -> 0 | AK54: {=IFERROR(SUMPRODUCT(AK$13:AK$28,$G$13:$G$28,--($C54=$C$13:$C$28))/$G54,0)} -> 0 | AL54: {=IFERROR(SUMPRODUCT(AL$13:AL$28,$G$13:$G$28,--($C54=$C$13:$C$28))/$G54,0)} -> 0 | AM54: =0.7/AL54 -> #DIV/0! | AN54: =IFERROR(F54/AZ54,0) -> 0 | AO54: =(1-AL54-($AU54-$AV54)+($AT54*(1-$AU54))-$AS54)/(($AX54*$AW54*(1-$AU54))/$AX54) -> #DIV/0! | AQ54: =F54*AE54 -> 0 | AR54: =F54*AL54 -> 0 | AS54: {=IFERROR(SUMPRODUCT(AS$13:AS$28,$G$13:$G$28,--($C54=$C$13:$C$28))/$G54,0)} -> 0 | AT54: {=IFERROR(SUMPRODUCT(AT$13:AT$28,$G$13:$G$28,--($C54=$C$13:$C$28))/$G54,0)} -> 0 | AU54: {=IFERROR(SUMPRODUCT(AU$13:AU$28,$G$13:$G$28,--($C54=$C$13:$C$28))/$G54,0)} -> 0 | AV54: {=IFERROR(SUMPRODUCT(AV$13:AV$28,$G$13:$G$28,--($C54=$C$13:$C$28))/$G54,0)} -> 0 | AW54: {=IFERROR(SUMPRODUCT(AW$13:AW$28,$G$13:$G$28,--($C54=$C$13:$C$28))/$G54,0)} -> 0 | AX54: {=IFERROR(SUMPRODUCT(AX$13:AX$28,$G$13:$G$28,--($C54=$C$13:$C$28))/$G54,0)} -> 0 | AY54: =AQ54/(1-AS54-(AU54-AV54)+AT54*(1-AU54)-AX54*AW54*(1-AU54)) -> 0 | AZ54: =AR54/(1-AS54-(AU54-AV54)+AT54*(1-AU54)-AX54*AW54*(1-AU54)) -> 0 | BA54: {=IFERROR(SUMPRODUCT(BA$13:BA$28,$G$13:$G$28,--($C54=$C$13:$C$28))/$G54,0)} -> 0 | BB54: {=IFERROR(SUMPRODUCT(BB$13:BB$28,$G$13:$G$28,--($C54=$C$13:$C$28))/$G54,0)} -> 0 | BC54: {=IFERROR(SUMPRODUCT(BC$13:BC$28,$G$13:$G$28,--($C54=$C$13:$C$28))/$G54,0)} -> 0 | BD54: {=IFERROR(SUMPRODUCT(BD$13:BD$28,$G$13:$G$28,--($C54=$C$13:$C$28))/$G54,0)} -> 0 | BF54: =BA54*$AE54 -> 0 | BG54: =BB54*$AE54 -> 0 | BH54: =BC54*$AE54 -> 0 | BI54: =BD54*$AE54 -> 0
B55: =1+B54 -> 2 | C55: Tracker Marine | F55: =SUMIFS(F$13:F$28,$C$13:$C$28,$C55) -> 0 | G55: =F55/$F$59 -> #DIV/0! | H55: {=IFERROR(SUMPRODUCT(H$13:H$28,$G$13:$G$28,--($C55=$C$13:$C$28))/$G55,0)} -> 0 | I55: {=IFERROR(SUMPRODUCT(I$13:I$28,$G$13:$G$28,--($C55=$C$13:$C$28))/$G55,0)} -> 0 | J55: {=IFERROR(SUMPRODUCT(J$13:J$28,$G$13:$G$28,--($C55=$C$13:$C$28))/$G55,0)} -> 0 | K55: {=IFERROR(SUMPRODUCT(K$13:K$28,$G$13:$G$28,--($C55=$C$13:$C$28))/$G55,0)} -> 0 | L55: {=IFERROR(SUMPRODUCT(L$13:L$28,$G$13:$G$28,--($C55=$C$13:$C$28))/$G55,0)} -> 0 | M55: {=IFERROR(SUMPRODUCT(M$13:M$28,$G$13:$G$28,--($C55=$C$13:$C$28))/$G55,0)} -> 0 | N55: {=IFERROR(SUMPRODUCT(N$13:N$28,$G$13:$G$28,--($C55=$C$13:$C$28))/$G55,0)} -> 0 | O55: {=IFERROR(SUMPRODUCT(O$13:O$28,$G$13:$G$28,--($C55=$C$13:$C$28))/$G55,0)} -> 0 | ... S55: {=IFERROR(SUMPRODUCT(S$13:S$28,$G$13:$G$28,--($C55=$C$13:$C$28))/$G55,0)} -> 0 | T55: =SUM(N55:S55)=1 -> FALSE | U55: {=IFERROR(SUMPRODUCT(U$13:U$28,$G$13:$G$28,--($C55=$C$13:$C$28))/$G55,0)} -> 0 | V55: {=IFERROR(SUMPRODUCT(V$13:V$28,$G$13:$G$28,--($C55=$C$13:$C$28))/$G55,0)} -> 0 | W55: {=IFERROR(SUMPRODUCT(W$13:W$28,$G$13:$G$28,--($C55=$C$13:$C$28))/$G55,0)} -> 0 | X55: {=IFERROR(SUMPRODUCT(X$13:X$28,$G$13:$G$28,--($C55=$C$13:$C$28))/$G55,0)} -> 0 | Y55: {=IFERROR(SUMPRODUCT(Y$13:Y$28,$G$13:$G$28,--($C55=$C$13:$C$28))/$G55,0)} -> 0 | Z55: {=IFERROR(SUMPRODUCT(Z$13:Z$28,$G$13:$G$28,--($C55=$C$13:$C$28))/$G55,0)} -> 0 | AA55: {=IFERROR(SUMPRODUCT(AA$13:AA$28,$G$13:$G$28,--($C55=$C$13:$C$28))/$G55,0)} -> 0 | AB55: {=IFERROR(SUMPRODUCT(AB$13:AB$28,$G$13:$G$28,--($C55=$C$13:$C$28))/$G55,0)} -> 0 | ... AF55: {=IFERROR(SUMPRODUCT(AF$13:AF$28,$G$13:$G$28,--($C55=$C$13:$C$28))/$G55,0)} -> 0 | AG55: =IFERROR(F55/AY55,0) -> 0 | AH55: =(1-AE55-($AU55-$AV55)+($AT55*(1-$AU55))-$AS55)/(($AX55*$AW55*(1-$AU55))/$AX55) -> #DIV/0! | AJ55: {=IFERROR(SUMPRODUCT(AJ$13:AJ$28,$G$13:$G$28,--($C55=$C$13:$C$28))/$G55,0)} -> 0 | AK55: {=IFERROR(SUMPRODUCT(AK$13:AK$28,$G$13:$G$28,--($C55=$C$13:$C$28))/$G55,0)} -> 0 | AL55: {=IFERROR(SUMPRODUCT(AL$13:AL$28,$G$13:$G$28,--($C55=$C$13:$C$28))/$G55,0)} -> 0 | AM55: =0.7/AL55 -> #DIV/0! | AN55: =IFERROR(F55/AZ55,0) -> 0 | AO55: =(1-AL55-($AU55-$AV55)+($AT55*(1-$AU55))-$AS55)/(($AX55*$AW55*(1-$AU55))/$AX55) -> #DIV/0! | AQ55: =F55*AE55 -> 0 | AR55: =F55*AL55 -> 0 | AS55: {=IFERROR(SUMPRODUCT(AS$13:AS$28,$G$13:$G$28,--($C55=$C$13:$C$28))/$G55,0)} -> 0 | AT55: {=IFERROR(SUMPRODUCT(AT$13:AT$28,$G$13:$G$28,--($C55=$C$13:$C$28))/$G55,0)} -> 0 | AU55: {=IFERROR(SUMPRODUCT(AU$13:AU$28,$G$13:$G$28,--($C55=$C$13:$C$28))/$G55,0)} -> 0 | AV55: {=IFERROR(SUMPRODUCT(AV$13:AV$28,$G$13:$G$28,--($C55=$C$13:$C$28))/$G55,0)} -> 0 | AW55: {=IFERROR(SUMPRODUCT(AW$13:AW$28,$G$13:$G$28,--($C55=$C$13:$C$28))/$G55,0)} -> 0 | AX55: {=IFERROR(SUMPRODUCT(AX$13:AX$28,$G$13:$G$28,--($C55=$C$13:$C$28))/$G55,0)} -> 0 | AY55: =AQ55/(1-AS55-(AU55-AV55)+AT55*(1-AU55)-AX55*AW55*(1-AU55)) -> 0 | AZ55: =AR55/(1-AS55-(AU55-AV55)+AT55*(1-AU55)-AX55*AW55*(1-AU55)) -> 0 | BA55: {=IFERROR(SUMPRODUCT(BA$13:BA$28,$G$13:$G$28,--($C55=$C$13:$C$28))/$G55,0)} -> 0 | BB55: {=IFERROR(SUMPRODUCT(BB$13:BB$28,$G$13:$G$28,--($C55=$C$13:$C$28))/$G55,0)} -> 0 | BC55: {=IFERROR(SUMPRODUCT(BC$13:BC$28,$G$13:$G$28,--($C55=$C$13:$C$28))/$G55,0)} -> 0 | BD55: {=IFERROR(SUMPRODUCT(BD$13:BD$28,$G$13:$G$28,--($C55=$C$13:$C$28))/$G55,0)} -> 0 | BF55: =BA55*$AE55 -> 0 | BG55: =BB55*$AE55 -> 0 | BH55: =BC55*$AE55 -> 0 | BI55: =BD55*$AE55 -> 0
B56: =1+B55 -> 3 | C56: Tracker SR | F56: =SUMIFS(F$13:F$28,$C$13:$C$28,$C56) -> 0 | G56: =F56/$F$59 -> #DIV/0! | H56: {=IFERROR(SUMPRODUCT(H$13:H$28,$G$13:$G$28,--($C56=$C$13:$C$28))/$G56,0)} -> 0 | I56: {=IFERROR(SUMPRODUCT(I$13:I$28,$G$13:$G$28,--($C56=$C$13:$C$28))/$G56,0)} -> 0 | J56: {=IFERROR(SUMPRODUCT(J$13:J$28,$G$13:$G$28,--($C56=$C$13:$C$28))/$G56,0)} -> 0 | K56: {=IFERROR(SUMPRODUCT(K$13:K$28,$G$13:$G$28,--($C56=$C$13:$C$28))/$G56,0)} -> 0 | L56: {=IFERROR(SUMPRODUCT(L$13:L$28,$G$13:$G$28,--($C56=$C$13:$C$28))/$G56,0)} -> 0 | M56: {=IFERROR(SUMPRODUCT(M$13:M$28,$G$13:$G$28,--($C56=$C$13:$C$28))/$G56,0)} -> 0 | N56: {=IFERROR(SUMPRODUCT(N$13:N$28,$G$13:$G$28,--($C56=$C$13:$C$28))/$G56,0)} -> 0 | O56: {=IFERROR(SUMPRODUCT(O$13:O$28,$G$13:$G$28,--($C56=$C$13:$C$28))/$G56,0)} -> 0 | ... S56: {=IFERROR(SUMPRODUCT(S$13:S$28,$G$13:$G$28,--($C56=$C$13:$C$28))/$G56,0)} -> 0 | T56: =SUM(N56:S56)=1 -> FALSE | U56: {=IFERROR(SUMPRODUCT(U$13:U$28,$G$13:$G$28,--($C56=$C$13:$C$28))/$G56,0)} -> 0 | V56: {=IFERROR(SUMPRODUCT(V$13:V$28,$G$13:$G$28,--($C56=$C$13:$C$28))/$G56,0)} -> 0 | W56: {=IFERROR(SUMPRODUCT(W$13:W$28,$G$13:$G$28,--($C56=$C$13:$C$28))/$G56,0)} -> 0 | X56: {=IFERROR(SUMPRODUCT(X$13:X$28,$G$13:$G$28,--($C56=$C$13:$C$28))/$G56,0)} -> 0 | Y56: {=IFERROR(SUMPRODUCT(Y$13:Y$28,$G$13:$G$28,--($C56=$C$13:$C$28))/$G56,0)} -> 0 | Z56: {=IFERROR(SUMPRODUCT(Z$13:Z$28,$G$13:$G$28,--($C56=$C$13:$C$28))/$G56,0)} -> 0 | AA56: {=IFERROR(SUMPRODUCT(AA$13:AA$28,$G$13:$G$28,--($C56=$C$13:$C$28))/$G56,0)} -> 0 | AB56: {=IFERROR(SUMPRODUCT(AB$13:AB$28,$G$13:$G$28,--($C56=$C$13:$C$28))/$G56,0)} -> 0 | ... AF56: {=IFERROR(SUMPRODUCT(AF$13:AF$28,$G$13:$G$28,--($C56=$C$13:$C$28))/$G56,0)} -> 0 | AG56: =IFERROR(F56/AY56,0) -> 0 | AH56: =(1-AE56-($AU56-$AV56)+($AT56*(1-$AU56))-$AS56)/(($AX56*$AW56*(1-$AU56))/$AX56) -> #DIV/0! | AJ56: {=IFERROR(SUMPRODUCT(AJ$13:AJ$28,$G$13:$G$28,--($C56=$C$13:$C$28))/$G56,0)} -> 0 | AK56: {=IFERROR(SUMPRODUCT(AK$13:AK$28,$G$13:$G$28,--($C56=$C$13:$C$28))/$G56,0)} -> 0 | AL56: {=IFERROR(SUMPRODUCT(AL$13:AL$28,$G$13:$G$28,--($C56=$C$13:$C$28))/$G56,0)} -> 0 | AM56: =0.7/AL56 -> #DIV/0! | AN56: =IFERROR(F56/AZ56,0) -> 0 | AO56: =(1-AL56-($AU56-$AV56)+($AT56*(1-$AU56))-$AS56)/(($AX56*$AW56*(1-$AU56))/$AX56) -> #DIV/0! | AQ56: =F56*AE56 -> 0 | AR56: =F56*AL56 -> 0 | AS56: {=IFERROR(SUMPRODUCT(AS$13:AS$28,$G$13:$G$28,--($C56=$C$13:$C$28))/$G56,0)} -> 0 | AT56: {=IFERROR(SUMPRODUCT(AT$13:AT$28,$G$13:$G$28,--($C56=$C$13:$C$28))/$G56,0)} -> 0 | AU56: {=IFERROR(SUMPRODUCT(AU$13:AU$28,$G$13:$G$28,--($C56=$C$13:$C$28))/$G56,0)} -> 0 | AV56: {=IFERROR(SUMPRODUCT(AV$13:AV$28,$G$13:$G$28,--($C56=$C$13:$C$28))/$G56,0)} -> 0 | AW56: {=IFERROR(SUMPRODUCT(AW$13:AW$28,$G$13:$G$28,--($C56=$C$13:$C$28))/$G56,0)} -> 0 | AX56: {=IFERROR(SUMPRODUCT(AX$13:AX$28,$G$13:$G$28,--($C56=$C$13:$C$28))/$G56,0)} -> 0 | AY56: =AQ56/(1-AS56-(AU56-AV56)+AT56*(1-AU56)-AX56*AW56*(1-AU56)) -> 0 | AZ56: =AR56/(1-AS56-(AU56-AV56)+AT56*(1-AU56)-AX56*AW56*(1-AU56)) -> 0 | BA56: {=IFERROR(SUMPRODUCT(BA$13:BA$28,$G$13:$G$28,--($C56=$C$13:$C$28))/$G56,0)} -> 0 | BB56: {=IFERROR(SUMPRODUCT(BB$13:BB$28,$G$13:$G$28,--($C56=$C$13:$C$28))/$G56,0)} -> 0 | BC56: {=IFERROR(SUMPRODUCT(BC$13:BC$28,$G$13:$G$28,--($C56=$C$13:$C$28))/$G56,0)} -> 0 | BD56: {=IFERROR(SUMPRODUCT(BD$13:BD$28,$G$13:$G$28,--($C56=$C$13:$C$28))/$G56,0)} -> 0 | BF56: =BA56*$AE56 -> 0 | BG56: =BB56*$AE56 -> 0 | BH56: =BC56*$AE56 -> 0 | BI56: =BD56*$AE56 -> 0
B57: =1+B56 -> 4 | C57: Tracker Cyber | F57: =SUMIFS(F$13:F$28,$C$13:$C$28,$C57) -> 0 | G57: =F57/$F$59 -> #DIV/0! | H57: {=IFERROR(SUMPRODUCT(H$13:H$28,$G$13:$G$28,--($C57=$C$13:$C$28))/$G57,0)} -> 0 | I57: {=IFERROR(SUMPRODUCT(I$13:I$28,$G$13:$G$28,--($C57=$C$13:$C$28))/$G57,0)} -> 0 | J57: {=IFERROR(SUMPRODUCT(J$13:J$28,$G$13:$G$28,--($C57=$C$13:$C$28))/$G57,0)} -> 0 | K57: {=IFERROR(SUMPRODUCT(K$13:K$28,$G$13:$G$28,--($C57=$C$13:$C$28))/$G57,0)} -> 0 | L57: {=IFERROR(SUMPRODUCT(L$13:L$28,$G$13:$G$28,--($C57=$C$13:$C$28))/$G57,0)} -> 0 | M57: {=IFERROR(SUMPRODUCT(M$13:M$28,$G$13:$G$28,--($C57=$C$13:$C$28))/$G57,0)} -> 0 | N57: {=IFERROR(SUMPRODUCT(N$13:N$28,$G$13:$G$28,--($C57=$C$13:$C$28))/$G57,0)} -> 0 | O57: {=IFERROR(SUMPRODUCT(O$13:O$28,$G$13:$G$28,--($C57=$C$13:$C$28))/$G57,0)} -> 0 | ... S57: {=IFERROR(SUMPRODUCT(S$13:S$28,$G$13:$G$28,--($C57=$C$13:$C$28))/$G57,0)} -> 0 | T57: =SUM(N57:S57)=1 -> FALSE | U57: {=IFERROR(SUMPRODUCT(U$13:U$28,$G$13:$G$28,--($C57=$C$13:$C$28))/$G57,0)} -> 0 | V57: {=IFERROR(SUMPRODUCT(V$13:V$28,$G$13:$G$28,--($C57=$C$13:$C$28))/$G57,0)} -> 0 | W57: {=IFERROR(SUMPRODUCT(W$13:W$28,$G$13:$G$28,--($C57=$C$13:$C$28))/$G57,0)} -> 0 | X57: {=IFERROR(SUMPRODUCT(X$13:X$28,$G$13:$G$28,--($C57=$C$13:$C$28))/$G57,0)} -> 0 | Y57: {=IFERROR(SUMPRODUCT(Y$13:Y$28,$G$13:$G$28,--($C57=$C$13:$C$28))/$G57,0)} -> 0 | Z57: {=IFERROR(SUMPRODUCT(Z$13:Z$28,$G$13:$G$28,--($C57=$C$13:$C$28))/$G57,0)} -> 0 | AA57: {=IFERROR(SUMPRODUCT(AA$13:AA$28,$G$13:$G$28,--($C57=$C$13:$C$28))/$G57,0)} -> 0 | AB57: {=IFERROR(SUMPRODUCT(AB$13:AB$28,$G$13:$G$28,--($C57=$C$13:$C$28))/$G57,0)} -> 0 | ... AF57: {=IFERROR(SUMPRODUCT(AF$13:AF$28,$G$13:$G$28,--($C57=$C$13:$C$28))/$G57,0)} -> 0 | AG57: =IFERROR(F57/AY57,0) -> 0 | AH57: =(1-AE57-($AU57-$AV57)+($AT57*(1-$AU57))-$AS57)/(($AX57*$AW57*(1-$AU57))/$AX57) -> #DIV/0! | AJ57: {=IFERROR(SUMPRODUCT(AJ$13:AJ$28,$G$13:$G$28,--($C57=$C$13:$C$28))/$G57,0)} -> 0 | AK57: {=IFERROR(SUMPRODUCT(AK$13:AK$28,$G$13:$G$28,--($C57=$C$13:$C$28))/$G57,0)} -> 0 | AL57: {=IFERROR(SUMPRODUCT(AL$13:AL$28,$G$13:$G$28,--($C57=$C$13:$C$28))/$G57,0)} -> 0 | AM57: =0.7/AL57 -> #DIV/0! | AN57: =IFERROR(F57/AZ57,0) -> 0 | AO57: =(1-AL57-($AU57-$AV57)+($AT57*(1-$AU57))-$AS57)/(($AX57*$AW57*(1-$AU57))/$AX57) -> #DIV/0! | AQ57: =F57*AE57 -> 0 | AR57: =F57*AL57 -> 0 | AS57: {=IFERROR(SUMPRODUCT(AS$13:AS$28,$G$13:$G$28,--($C57=$C$13:$C$28))/$G57,0)} -> 0 | AT57: {=IFERROR(SUMPRODUCT(AT$13:AT$28,$G$13:$G$28,--($C57=$C$13:$C$28))/$G57,0)} -> 0 | AU57: {=IFERROR(SUMPRODUCT(AU$13:AU$28,$G$13:$G$28,--($C57=$C$13:$C$28))/$G57,0)} -> 0 | AV57: {=IFERROR(SUMPRODUCT(AV$13:AV$28,$G$13:$G$28,--($C57=$C$13:$C$28))/$G57,0)} -> 0 | AW57: {=IFERROR(SUMPRODUCT(AW$13:AW$28,$G$13:$G$28,--($C57=$C$13:$C$28))/$G57,0)} -> 0 | AX57: {=IFERROR(SUMPRODUCT(AX$13:AX$28,$G$13:$G$28,--($C57=$C$13:$C$28))/$G57,0)} -> 0 | AY57: =AQ57/(1-AS57-(AU57-AV57)+AT57*(1-AU57)-AX57*AW57*(1-AU57)) -> 0 | AZ57: =AR57/(1-AS57-(AU57-AV57)+AT57*(1-AU57)-AX57*AW57*(1-AU57)) -> 0 | BA57: {=IFERROR(SUMPRODUCT(BA$13:BA$28,$G$13:$G$28,--($C57=$C$13:$C$28))/$G57,0)} -> 0 | BB57: {=IFERROR(SUMPRODUCT(BB$13:BB$28,$G$13:$G$28,--($C57=$C$13:$C$28))/$G57,0)} -> 0 | BC57: {=IFERROR(SUMPRODUCT(BC$13:BC$28,$G$13:$G$28,--($C57=$C$13:$C$28))/$G57,0)} -> 0 | BD57: {=IFERROR(SUMPRODUCT(BD$13:BD$28,$G$13:$G$28,--($C57=$C$13:$C$28))/$G57,0)} -> 0 | BF57: =BA57*$AE57 -> 0 | BG57: =BB57*$AE57 -> 0 | BH57: =BC57*$AE57 -> 0 | BI57: =BD57*$AE57 -> 0
B58: =1+B57 -> 5 | C58: Tracker PAC | F58: =SUMIFS(F$13:F$28,$C$13:$C$28,$C58) -> 0 | G58: =F58/$F$59 -> #DIV/0! | H58: {=IFERROR(SUMPRODUCT(H$13:H$28,$G$13:$G$28,--($C58=$C$13:$C$28))/$G58,0)} -> 0 | I58: {=IFERROR(SUMPRODUCT(I$13:I$28,$G$13:$G$28,--($C58=$C$13:$C$28))/$G58,0)} -> 0 | J58: {=IFERROR(SUMPRODUCT(J$13:J$28,$G$13:$G$28,--($C58=$C$13:$C$28))/$G58,0)} -> 0 | K58: {=IFERROR(SUMPRODUCT(K$13:K$28,$G$13:$G$28,--($C58=$C$13:$C$28))/$G58,0)} -> 0 | L58: {=IFERROR(SUMPRODUCT(L$13:L$28,$G$13:$G$28,--($C58=$C$13:$C$28))/$G58,0)} -> 0 | M58: {=IFERROR(SUMPRODUCT(M$13:M$28,$G$13:$G$28,--($C58=$C$13:$C$28))/$G58,0)} -> 0 | N58: {=IFERROR(SUMPRODUCT(N$13:N$28,$G$13:$G$28,--($C58=$C$13:$C$28))/$G58,0)} -> 0 | O58: {=IFERROR(SUMPRODUCT(O$13:O$28,$G$13:$G$28,--($C58=$C$13:$C$28))/$G58,0)} -> 0 | ... S58: {=IFERROR(SUMPRODUCT(S$13:S$28,$G$13:$G$28,--($C58=$C$13:$C$28))/$G58,0)} -> 0 | T58: =SUM(N58:S58)=1 -> FALSE | U58: {=IFERROR(SUMPRODUCT(U$13:U$28,$G$13:$G$28,--($C58=$C$13:$C$28))/$G58,0)} -> 0 | V58: {=IFERROR(SUMPRODUCT(V$13:V$28,$G$13:$G$28,--($C58=$C$13:$C$28))/$G58,0)} -> 0 | W58: {=IFERROR(SUMPRODUCT(W$13:W$28,$G$13:$G$28,--($C58=$C$13:$C$28))/$G58,0)} -> 0 | X58: {=IFERROR(SUMPRODUCT(X$13:X$28,$G$13:$G$28,--($C58=$C$13:$C$28))/$G58,0)} -> 0 | Y58: {=IFERROR(SUMPRODUCT(Y$13:Y$28,$G$13:$G$28,--($C58=$C$13:$C$28))/$G58,0)} -> 0 | Z58: {=IFERROR(SUMPRODUCT(Z$13:Z$28,$G$13:$G$28,--($C58=$C$13:$C$28))/$G58,0)} -> 0 | AA58: {=IFERROR(SUMPRODUCT(AA$13:AA$28,$G$13:$G$28,--($C58=$C$13:$C$28))/$G58,0)} -> 0 | AB58: {=IFERROR(SUMPRODUCT(AB$13:AB$28,$G$13:$G$28,--($C58=$C$13:$C$28))/$G58,0)} -> 0 | ... AF58: {=IFERROR(SUMPRODUCT(AF$13:AF$28,$G$13:$G$28,--($C58=$C$13:$C$28))/$G58,0)} -> 0 | AG58: =IFERROR(F58/AY58,0) -> 0 | AH58: =(1-AE58-($AU58-$AV58)+($AT58*(1-$AU58))-$AS58)/(($AX58*$AW58*(1-$AU58))/$AX58) -> #DIV/0! | AJ58: {=IFERROR(SUMPRODUCT(AJ$13:AJ$28,$G$13:$G$28,--($C58=$C$13:$C$28))/$G58,0)} -> 0 | AK58: {=IFERROR(SUMPRODUCT(AK$13:AK$28,$G$13:$G$28,--($C58=$C$13:$C$28))/$G58,0)} -> 0 | AL58: {=IFERROR(SUMPRODUCT(AL$13:AL$28,$G$13:$G$28,--($C58=$C$13:$C$28))/$G58,0)} -> 0 | AM58: =0.7/AL58 -> #DIV/0! | AN58: =IFERROR(F58/AZ58,0) -> 0 | AO58: =(1-AL58-($AU58-$AV58)+($AT58*(1-$AU58))-$AS58)/(($AX58*$AW58*(1-$AU58))/$AX58) -> #DIV/0! | AQ58: =F58*AE58 -> 0 | AR58: =F58*AL58 -> 0 | AS58: {=IFERROR(SUMPRODUCT(AS$13:AS$28,$G$13:$G$28,--($C58=$C$13:$C$28))/$G58,0)} -> 0 | AT58: {=IFERROR(SUMPRODUCT(AT$13:AT$28,$G$13:$G$28,--($C58=$C$13:$C$28))/$G58,0)} -> 0 | AU58: {=IFERROR(SUMPRODUCT(AU$13:AU$28,$G$13:$G$28,--($C58=$C$13:$C$28))/$G58,0)} -> 0 | AV58: {=IFERROR(SUMPRODUCT(AV$13:AV$28,$G$13:$G$28,--($C58=$C$13:$C$28))/$G58,0)} -> 0 | AW58: {=IFERROR(SUMPRODUCT(AW$13:AW$28,$G$13:$G$28,--($C58=$C$13:$C$28))/$G58,0)} -> 0 | AX58: {=IFERROR(SUMPRODUCT(AX$13:AX$28,$G$13:$G$28,--($C58=$C$13:$C$28))/$G58,0)} -> 0 | AY58: =AQ58/(1-AS58-(AU58-AV58)+AT58*(1-AU58)-AX58*AW58*(1-AU58)) -> 0 | AZ58: =AR58/(1-AS58-(AU58-AV58)+AT58*(1-AU58)-AX58*AW58*(1-AU58)) -> 0 | BA58: {=IFERROR(SUMPRODUCT(BA$13:BA$28,$G$13:$G$28,--($C58=$C$13:$C$28))/$G58,0)} -> 0 | BB58: {=IFERROR(SUMPRODUCT(BB$13:BB$28,$G$13:$G$28,--($C58=$C$13:$C$28))/$G58,0)} -> 0 | BC58: {=IFERROR(SUMPRODUCT(BC$13:BC$28,$G$13:$G$28,--($C58=$C$13:$C$28))/$G58,0)} -> 0 | BD58: {=IFERROR(SUMPRODUCT(BD$13:BD$28,$G$13:$G$28,--($C58=$C$13:$C$28))/$G58,0)} -> 0 | BF58: =BA58*$AE58 -> 0 | BG58: =BB58*$AE58 -> 0 | BH58: =BC58*$AE58 -> 0 | BI58: =BD58*$AE58 -> 0
B59: TOTAL | F59: =SUM(F54:F58) -> 0 | G59: =SUM(G54:G58) -> #DIV/0! | H59: =SUMPRODUCT($G$35:$G$42,H$35:H$42) -> #REF! | I59: =SUMPRODUCT($G$35:$G$42,I$35:I$42) -> #REF! | J59: =SUMPRODUCT($G$35:$G$42,J$35:J$42) -> #REF! | K59: =SUMPRODUCT($G$35:$G$42,K$35:K$42) -> #REF! | L59: =SUMPRODUCT($G$35:$G$42,L$35:L$42) -> #REF! | M59: =SUMPRODUCT($G$35:$G$42,M$35:M$42) -> #REF! | N59: =SUMPRODUCT($G$35:$G$42,N$35:N$42) -> #REF! | O59: =SUMPRODUCT($G$35:$G$42,O$35:O$42) -> #REF! | ... S59: =SUMPRODUCT($G$35:$G$42,S$35:S$42) -> #REF! | U59: =SUMPRODUCT($G$35:$G$42,U$35:U$42) -> #REF! | V59: =SUMPRODUCT($G$35:$G$42,V$35:V$42) -> #REF! | W59: =SUMPRODUCT($G$35:$G$42,W$35:W$42) -> #REF! | X59: =SUMPRODUCT($G$35:$G$42,X$35:X$42) -> #REF! | Y59: =SUMPRODUCT($G$35:$G$42,Y$35:Y$42) -> #REF! | Z59: =SUMPRODUCT($G$35:$G$42,Z$35:Z$42) -> #REF! | AA59: =SUMPRODUCT($G$35:$G$42,AA$35:AA$42) -> #REF! | AB59: =SUMPRODUCT($G$35:$G$42,AB$35:AB$42) -> #REF! | ... AF59: =SUMPRODUCT($G$35:$G$42,AF$35:AF$42) -> #REF! | AG59: =IFERROR(F59/AY59,0) -> 0 | AH59: =(1-AE59-($AU59-$AV59)+($AT59*(1-$AU59))-$AS59)/(($AX59*$AW59*(1-$AU59))/$AX59) -> #REF! | AJ59: =SUMPRODUCT($G$35:$G$42,AJ$35:AJ$42) -> #REF! | AK59: =SUMPRODUCT($G$35:$G$42,AK$35:AK$42) -> #REF! | AL59: =SUMPRODUCT($G$35:$G$42,AL$35:AL$42) -> #REF! | AM59: 1 | AN59: =IFERROR(F59/AZ59,0) -> 0 | AO59: =(1-AL59-($AU59-$AV59)+($AT59*(1-$AU59))-$AS59)/(($AX59*$AW59*(1-$AU59))/$AX59) -> #REF! | AQ59: =SUM(AQ54:AQ58) -> 0 | AR59: =SUM(AR54:AR58) -> 0 | AS59: =SUMPRODUCT($G$35:$G$42,AS$35:AS$42) -> #REF! | AT59: =SUMPRODUCT($G$35:$G$42,AT$35:AT$42) -> #REF! | AU59: =SUMPRODUCT($G$35:$G$42,AU$35:AU$42) -> #REF! | AV59: =SUMPRODUCT($G$35:$G$42,AV$35:AV$42) -> #REF! | AW59: =SUMPRODUCT($G$35:$G$42,AW$35:AW$42) -> #REF! | AX59: =SUMPRODUCT($G$35:$G$42,AX$35:AX$42) -> #REF! | AY59: =SUM(AY54:AY58) -> 0 | AZ59: =SUM(AZ54:AZ58) -> 0 | BA59: =SUMPRODUCT($G$35:$G$42,BA$35:BA$42) -> #REF! | BB59: =SUMPRODUCT($G$35:$G$42,BB$35:BB$42) -> #REF! | BC59: =SUMPRODUCT($G$35:$G$42,BC$35:BC$42) -> #REF! | BD59: =SUMPRODUCT($G$35:$G$42,BD$35:BD$42) -> #REF! | BF59: =SUMPRODUCT($G$13:$G$28,BF$13:BF$28) -> #REF! | BG59: =SUMPRODUCT($G$13:$G$28,BG$13:BG$28) -> #REF! | BH59: =SUMPRODUCT($G$13:$G$28,BH$13:BH$28) -> #REF! | BI59: =SUMPRODUCT($G$13:$G$28,BI$13:BI$28) -> #REF!
G61: =G59=1 -> #DIV/0!

Sheet BeazleyData New - OLD
A1: key | B1: RiskClassCode | C1: YOA | D1: WEP | E1: Acq_costs | F1: Cat_paid | G1: Cat_incurred | H1: paid_exc_cat | I1: incurred_exc_cat | J1: total_RC | K1: paid_inc_cat | L1: incurred_inc_cat | M1: total_RC2 | P1: key | Q1: WEP (NEW) | R1: WEP (OLD) | S1: Difference | U1: Acq_costs (NEW) | V1: Acq_costs (OLD) | W1: Difference | Y1: total_RC (NEW) | Z1: total_RC (OLD) | AA1: Difference | AD1: incurred_inc_cat (NEW) | AE1: incurred_inc_cat (OLD) | AF1: Difference | AJ1: =AJ3&AJ2 -> 2000RC | AK1: =AK3&AK2 -> 2001RC | AL1: =AL3&AL2 -> 2002RC | AM1: =AM3&AM2 -> 2003RC | AN1: =AN3&AN2 -> 2004RC | AO1: =AO3&AO2 -> 2005RC | AP1: =AP3&AP2 -> 2006RC | AQ1: =AQ3&AQ2 -> 2007RC | ... FQ1: =FQ3&FQ2 -> 2022Total Paid (Cat)
A2: 002017 | B2: 00 | C2: 2017 | D2: 428097.99 | E2: 150103.82 | F2: 0 | G2: 0 | H2: 0 | I2: 0 | K2: 0 | L2: 0 | M2: =IF(OR(Beazley_data[[#This Row],[total_RC]]<0.6,Beazley_data[[#This Row],[total_RC]]>2),1,Beazley_data[[#This Row],[total_RC]]) -> 1 | P2: =Beazley_data[[#This Row],[key]] -> 002017 | Q2: =Beazley_data[[#This Row],[WEP]] -> 428097.99 | R2: =IFERROR(INDEX($AJ$4:$CZ$182,MATCH($B2,$AI$4:$AI$182,0),MATCH($C2&"WEP",$AJ$1:$FQ$1,0)),0) -> 0 | S2: =IFERROR((R2-Q2)/R2,"no values") -> no values | U2: =Beazley_data[[#This Row],[Acq_costs]] -> 150103.82 | V2: =IFERROR(INDEX($AJ$4:$FQ$182,MATCH($B2,$AI$4:$AI$182,0),MATCH($C2&"Acquisition Cost",$AJ$1:$FQ$1,0)),0) -> 0 | W2: =IFERROR((V2-U2)/V2,"no values") -> no values | Y2: =Beazley_data[[#This Row],[total_RC]] -> 0 | Z2: =IFERROR(INDEX($AJ$4:$FQ$182,MATCH($B2,$AI$4:$AI$182,0),MATCH($C2&"RC",$AJ$1:$FQ$1,0)),0) -> 0 | AA2: =IFERROR((Z2-Y2)/Z2,"no values") -> no values | AD2: =Beazley_data[[#This Row],[Cat_incurred]]+Beazley_data[[#This Row],[incurred_exc_cat]] -> 0 | AE2: =IFERROR(INDEX($AJ$4:$FQ$182,MATCH($B2,$AI$4:$AI$182,0),MATCH($C2&"Total Incurred (Cat)",$AJ$1:$FQ$1,0)),0)+IFERROR(INDEX($AJ$4:$FQ$182,MATCH($B2,$AI$4:$AI$182,0),MATCH($C2&"Total Incurred (Non Cat)",$AJ$1:$FQ$1,0)),0) -> 0 | AF2: =IFERROR((AE2-AD2)/AE2,"no values") -> no values | AJ2: RC | AK2: RC | AL2: RC | AM2: RC | AN2: RC | AO2: RC | AP2: RC | AQ2: RC | AR2: RC | AS2: RC | AT2: RC | AU2: RC | AV2: RC | AW2: RC | AX2: RC | AY2: RC | AZ2: RC | BA2: RC | BB2: RC | BC2: RC | BD2: RC | BE2: RC | BF2: RC | BG2: WEP | BH2: WEP | BI2: WEP | BJ2: WEP | BK2: WEP | BL2: WEP | BM2: WEP | BN2: WEP | BO2: WEP | BP2: WEP | BQ2: WEP | BR2: WEP | BS2: WEP | BT2: WEP | BU2: WEP | BV2: WEP | BW2: WEP | BX2: WEP | BY2: WEP | BZ2: WEP | CA2: WEP | CB2: WEP | CC2: WEP | CD2: Total Incurred (Cat) | CE2: Total Incurred (Cat) | CF2: Total Incurred (Cat) | CG2: Total Incurred (Cat) | CH2: Total Incurred (Cat) | CI2: Total Incurred (Cat) | CJ2: Total Incurred (Cat) | CK2: Total Incurred (Cat) | CL2: Total Incurred (Cat) | CM2: Total Incurred (Cat) | CN2: Total Incurred (Cat) | CO2: Total Incurred (Cat) | CP2: Total Incurred (Cat) | CQ2: Total Incurred (Cat) | CR2: Total Incurred (Cat) | CS2: Total Incurred (Cat) | CT2: Total Incurred (Cat) | CU2: Total Incurred (Cat) | CV2: Total Incurred (Cat) | CW2: Total Incurred (Cat) | CX2: Total Incurred (Cat) | CY2: Total Incurred (Cat) | CZ2: Total Incurred (Cat) | DA2: Total Incurred (Non Cat) | DB2: Total Incurred (Non Cat) | DC2: Total Incurred (Non Cat) | DD2: Total Incurred (Non Cat) | DE2: Total Incurred (Non Cat) | DF2: Total Incurred (Non Cat) | DG2: Total Incurred (Non Cat) | DH2: Total Incurred (Non Cat) | DI2: Total Incurred (Non Cat) | DJ2: Total Incurred (Non Cat) | DK2: Total Incurred (Non Cat) | DL2: Total Incurred (Non Cat) | DM2: Total Incurred (Non Cat) | DN2: Total Incurred (Non Cat) | DO2: Total Incurred (Non Cat) | DP2: Total Incurred (Non Cat) | DQ2: Total Incurred (Non Cat) | DR2: Total Incurred (Non Cat) | DS2: Total Incurred (Non Cat) | DT2: Total Incurred (Non Cat) | DU2: Total Incurred (Non Cat) | DV2: Total Incurred (Non Cat) | DW2: Total Incurred (Non Cat) | DX2: Acquisition Cost | DY2: Acquisition Cost | DZ2: Acquisition Cost | EA2: Acquisition Cost | EB2: Acquisition Cost | EC2: Acquisition Cost | ED2: Acquisition Cost | EE2: Acquisition Cost | EF2: Acquisition Cost | EG2: Acquisition Cost | EH2: Acquisition Cost | EI2: Acquisition Cost | EJ2: Acquisition Cost | EK2: Acquisition Cost | EL2: Acquisition Cost | EM2: Acquisition Cost | EN2: Acquisition Cost | EO2: Acquisition Cost | EP2: Acquisition Cost | EQ2: Acquisition Cost | ER2: Acquisition Cost | ES2: Acquisition Cost | ET2: Acquisition Cost | EU2: Total Paid (Cat) | EV2: Total Paid (Cat) | EW2: Total Paid (Cat) | EX2: Total Paid (Cat) | EY2: Total Paid (Cat) | EZ2: Total Paid (Cat) | FA2: Total Paid (Cat) | FB2: Total Paid (Cat) | FC2: Total Paid (Cat) | FD2: Total Paid (Cat) | FE2: Total Paid (Cat) | FF2: Total Paid (Cat) | FG2: Total Paid (Cat) | FH2: Total Paid (Cat) | FI2: Total Paid (Cat) | FJ2: Total Paid (Cat) | FK2: Total Paid (Cat) | FL2: Total Paid (Cat) | FM2: Total Paid (Cat) | FN2: Total Paid (Cat) | FO2: Total Paid (Cat) | FP2: Total Paid (Cat) | FQ2: Total Paid (Cat)
A3: 002018 | B3: 00 | C3: 2018 | D3: 5572573.5 | E3: 838954.23 | F3: 419878.05 | G3: 441057 | H3: 0 | I3: 0 | J3: 1.0279805 | K3: 419878.05 | L3: 441057 | M3: =IF(OR(Beazley_data[[#This Row],[total_RC]]<0.6,Beazley_data[[#This Row],[total_RC]]>2),1,Beazley_data[[#This Row],[total_RC]]) -> 1.0279805 | P3: =Beazley_data[[#This Row],[key]] -> 002018 | Q3: =Beazley_data[[#This Row],[WEP]] -> 5572573.5 | R3: =IFERROR(INDEX($AJ$4:$CZ$182,MATCH($B3,$AI$4:$AI$182,0),MATCH($C3&"WEP",$AJ$1:$FQ$1,0)),0) -> 0 | S3: =IFERROR((R3-Q3)/R3,"no values") -> no values | U3: =Beazley_data[[#This Row],[Acq_costs]] -> 838954.23 | V3: =IFERROR(INDEX($AJ$4:$FQ$182,MATCH($B3,$AI$4:$AI$182,0),MATCH($C3&"Acquisition Cost",$AJ$1:$FQ$1,0)),0) -> 0 | W3: =IFERROR((V3-U3)/V3,"no values") -> no values | Y3: =Beazley_data[[#This Row],[total_RC]] -> 1.0279805 | Z3: =IFERROR(INDEX($AJ$4:$FQ$182,MATCH($B3,$AI$4:$AI$182,0),MATCH($C3&"RC",$AJ$1:$FQ$1,0)),0) -> 0 | AA3: =IFERROR((Z3-Y3)/Z3,"no values") -> no values | AD3: =Beazley_data[[#This Row],[Cat_incurred]]+Beazley_data[[#This Row],[incurred_exc_cat]] -> 441057 | AE3: =IFERROR(INDEX($AJ$4:$FQ$182,MATCH($B3,$AI$4:$AI$182,0),MATCH($C3&"Total Incurred (Cat)",$AJ$1:$FQ$1,0)),0)+IFERROR(INDEX($AJ$4:$FQ$182,MATCH($B3,$AI$4:$AI$182,0),MATCH($C3&"Total Incurred (Non Cat)",$AJ$1:$FQ$1,0)),0) -> 0 | AF3: =IFERROR((AE3-AD3)/AE3,"no values") -> no values | AI3: Risk Code | AJ3: 2000 | AK3: 2001 | AL3: 2002 | AM3: 2003 | AN3: 2004 | AO3: 2005 | AP3: 2006 | AQ3: 2007 | AR3: 2008 | AS3: 2009 | AT3: 2010 | AU3: 2011 | AV3: 2012 | AW3: 2013 | AX3: 2014 | AY3: 2015 | AZ3: 2016 | BA3: 2017 | BB3: 2018 | BC3: 2019 | BD3: 2020 | BE3: 2021 | BF3: 2022 | BG3: 2000 | BH3: 2001 | BI3: 2002 | BJ3: 2003 | BK3: 2004 | BL3: 2005 | BM3: 2006 | BN3: 2007 | BO3: 2008 | BP3: 2009 | BQ3: 2010 | BR3: 2011 | BS3: 2012 | BT3: 2013 | BU3: 2014 | BV3: 2015 | BW3: 2016 | BX3: 2017 | BY3: 2018 | BZ3: 2019 | CA3: 2020 | CB3: 2021 | CC3: 2022 | CD3: 2000 | CE3: 2001 | CF3: 2002 | CG3: 2003 | CH3: 2004 | CI3: 2005 | CJ3: 2006 | CK3: 2007 | CL3: 2008 | CM3: 2009 | CN3: 2010 | CO3: 2011 | CP3: 2012 | CQ3: 2013 | CR3: 2014 | CS3: 2015 | CT3: 2016 | CU3: 2017 | CV3: 2018 | CW3: 2019 | CX3: 2020 | CY3: 2021 | CZ3: 2022 | DA3: 2000 | DB3: 2001 | DC3: 2002 | DD3: 2003 | DE3: 2004 | DF3: 2005 | DG3: 2006 | DH3: 2007 | DI3: 2008 | DJ3: 2009 | DK3: 2010 | DL3: 2011 | DM3: 2012 | DN3: 2013 | DO3: 2014 | DP3: 2015 | DQ3: 2016 | DR3: 2017 | DS3: 2018 | DT3: 2019 | DU3: 2020 | DV3: 2021 | DW3: 2022 | DX3: 2000 | DY3: 2001 | DZ3: 2002 | EA3: 2003 | EB3: 2004 | EC3: 2005 | ED3: 2006 | EE3: 2007 | EF3: 2008 | EG3: 2009 | EH3: 2010 | EI3: 2011 | EJ3: 2012 | EK3: 2013 | EL3: 2014 | EM3: 2015 | EN3: 2016 | EO3: 2017 | EP3: 2018 | EQ3: 2019 | ER3: 2020 | ES3: 2021 | ET3: 2022 | EU3: 2000 | EV3: 2001 | EW3: 2002 | EX3: 2003 | EY3: 2004 | EZ3: 2005 | FA3: 2006 | FB3: 2007 | FC3: 2008 | FD3: 2009 | FE3: 2010 | FF3: 2011 | FG3: 2012 | FH3: 2013 | FI3: 2014 | FJ3: 2015 | FK3: 2016 | FL3: 2017 | FM3: 2018 | FN3: 2019 | FO3: 2020 | FP3: 2021 | FQ3: 2022
A4: 002019 | B4: 00 | C4: 2019 | D4: 36699208 | E4: 4844432.3 | F4: 1459403.9 | G4: 2117193.3 | H4: 1355833.6 | I4: 3629984 | J4: 1.1270142 | K4: 2815237.5 | L4: 5747177.2 | M4: =IF(OR(Beazley_data[[#This Row],[total_RC]]<0.6,Beazley_data[[#This Row],[total_RC]]>2),1,Beazley_data[[#This Row],[total_RC]]) -> 1.1270142 | P4: =Beazley_data[[#This Row],[key]] -> 002019 | Q4: =Beazley_data[[#This Row],[WEP]] -> 36699208 | R4: =IFERROR(INDEX($AJ$4:$CZ$182,MATCH($B4,$AI$4:$AI$182,0),MATCH($C4&"WEP",$AJ$1:$FQ$1,0)),0) -> 0 | S4: =IFERROR((R4-Q4)/R4,"no values") -> no values | U4: =Beazley_data[[#This Row],[Acq_costs]] -> 4844432.3 | V4: =IFERROR(INDEX($AJ$4:$FQ$182,MATCH($B4,$AI$4:$AI$182,0),MATCH($C4&"Acquisition Cost",$AJ$1:$FQ$1,0)),0) -> 0 | W4: =IFERROR((V4-U4)/V4,"no values") -> no values | Y4: =Beazley_data[[#This Row],[total_RC]] -> 1.1270142 | Z4: =IFERROR(INDEX($AJ$4:$FQ$182,MATCH($B4,$AI$4:$AI$182,0),MATCH($C4&"RC",$AJ$1:$FQ$1,0)),0) -> 0 | AA4: =IFERROR((Z4-Y4)/Z4,"no values") -> no values | AD4: =Beazley_data[[#This Row],[Cat_incurred]]+Beazley_data[[#This Row],[incurred_exc_cat]] -> 5747177.2 | AE4: =IFERROR(INDEX($AJ$4:$FQ$182,MATCH($B4,$AI$4:$AI$182,0),MATCH($C4&"Total Incurred (Cat)",$AJ$1:$FQ$1,0)),0)+IFERROR(INDEX($AJ$4:$FQ$182,MATCH($B4,$AI$4:$AI$182,0),MATCH($C4&"Total Incurred (Non Cat)",$AJ$1:$FQ$1,0)),0) -> 0 | AF4: =IFERROR((AE4-AD4)/AE4,"no values") -> no values | AI4: 1E | AJ4: 0 | AK4: 0 | AL4: 0 | AM4: 1.0892026 | AN4: 0.97983986 | AO4: 1.0676428 | AP4: 1.5229507 | AQ4: 0.93991392 | AR4: 0.88534978 | AS4: 1.4305557 | AT4: 0.82677352 | AU4: 1.0467928 | AV4: 0.99551526 | AW4: 1 | AX4: 0.87844352 | AY4: 0.98626798 | AZ4: 0.96666264 | BA4: 0.99246869 | BB4: 1.0132216 | BC4: 1.0086546 | BD4: 1.0193108 | BE4: 1.0248445 | BF4: 1.0000116 | BG4: 0 | BH4: 0 | BI4: 722.6964 | BJ4: 48100.95 | BK4: 84725.561 | BL4: 111715.57 | BM4: 207452.83 | BN4: 119738.72 | BO4: 134954.19 | BP4: 139446.56 | BQ4: 198471.1 | BR4: 24691.016 | BS4: 16794.928 | BT4: 82634.414 | BU4: 80695.202 | BV4: 61408.62 | BW4: 9314.3054 | BX4: 56500.836 | BY4: 44765.211 | BZ4: 966372.52 | CA4: 31179.072 | CB4: 238816.77 | CC4: 171.6927 | CD4: 0 | CE4: 0 | CF4: 0 | CG4: 0 | CH4: 0 | CI4: 0 | CJ4: 0 | CK4: 0 | CL4: 0 | CM4: 0 | CN4: 0 | CO4: 0 | CP4: 0 | CQ4: 0 | CR4: 0 | CS4: 0 | CT4: 0 | CU4: 0 | CV4: 0 | CW4: 961144.24 | CX4: 0 | CY4: 500.4665 | CZ4: 0 | DX4: 0 | DY4: 0 | DZ4: 209.8151 | EA4: 10723.942 | EB4: 19069.752 | EC4: 21377.02 | ED4: 31346.982 | EE4: 18203.796 | EF4: 15726.826 | EG4: 19658.622 | EH4: 26920.395 | EI4: 4177.1811 | EJ4: 336.2082 | EK4: 2131.1681 | EL4: 1304.0375 | EM4: 2215.1798 | EN4: 145.5241 | EO4: 3840.8662 | EP4: 1268.5253 | EQ4: 202137.67 | ER4: 1297.9806 | ES4: 55254.22 | ET4: 36.4279 | EU4: 0 | EV4: 0 | EW4: 0 | EX4: 0 | EY4: 0 | EZ4: 0 | FA4: 0 | FB4: 0 | FC4: 0 | FD4: 0 | FE4: 0 | FF4: 0 | FG4: 0 | FH4: 0 | FI4: 0 | FJ4: 0 | FK4: 0 | FL4: 0 | FM4: 0 | FN4: 272575.75 | FO4: 0 | FP4: 500.4665 | FQ4: 0
A5: 002020 | B5: 00 | C5: 2020 | D5: 77786275 | E5: 8921205.5 | F5: 22414611 | G5: 23922641 | H5: 843671.25 | I5: 1135393.1 | J5: 1.4116221 | K5: 23258282 | L5: 25058034 | M5: =IF(OR(Beazley_data[[#This Row],[total_RC]]<0.6,Beazley_data[[#This Row],[total_RC]]>2),1,Beazley_data[[#This Row],[total_RC]]) -> 1.4116221 | P5: =Beazley_data[[#This Row],[key]] -> 002020 | Q5: =Beazley_data[[#This Row],[WEP]] -> 77786275 | R5: =IFERROR(INDEX($AJ$4:$CZ$182,MATCH($B5,$AI$4:$AI$182,0),MATCH($C5&"WEP",$AJ$1:$FQ$1,0)),0) -> 0 | S5: =IFERROR((R5-Q5)/R5,"no values") -> no values | U5: =Beazley_data[[#This Row],[Acq_costs]] -> 8921205.5 | V5: =IFERROR(INDEX($AJ$4:$FQ$182,MATCH($B5,$AI$4:$AI$182,0),MATCH($C5&"Acquisition Cost",$AJ$1:$FQ$1,0)),0) -> 0 | W5: =IFERROR((V5-U5)/V5,"no values") -> no values | Y5: =Beazley_data[[#This Row],[total_RC]] -> 1.4116221 | Z5: =IFERROR(INDEX($AJ$4:$FQ$182,MATCH($B5,$AI$4:$AI$182,0),MATCH($C5&"RC",$AJ$1:$FQ$1,0)),0) -> 0 | AA5: =IFERROR((Z5-Y5)/Z5,"no values") -> no values | AD5: =Beazley_data[[#This Row],[Cat_incurred]]+Beazley_data[[#This Row],[incurred_exc_cat]] -> 25058034 | AE5: =IFERROR(INDEX($AJ$4:$FQ$182,MATCH($B5,$AI$4:$AI$182,0),MATCH($C5&"Total Incurred (Cat)",$AJ$1:$FQ$1,0)),0)+IFERROR(INDEX($AJ$4:$FQ$182,MATCH($B5,$AI$4:$AI$182,0),MATCH($C5&"Total Incurred (Non Cat)",$AJ$1:$FQ$1,0)),0) -> 0 | AF5: =IFERROR((AE5-AD5)/AE5,"no values") -> no values | AI5: 1T | AJ5: 0 | AK5: 0 | AL5: 0 | AM5: 0 | AN5: 0 | AO5: 0 | AP5: 0 | AQ5: 0 | AR5: 0 | AS5: 0 | AT5: 0 | AU5: 0 | AV5: 0 | AW5: 0 | AX5: 0 | AY5: 0 | AZ5: 0 | BA5: 0 | BB5: 0 | BC5: 0 | BD5: 0 | BE5: 0 | BF5: 0 | BG5: 0 | BH5: 0 | BI5: 0 | BJ5: 0 | BK5: 0 | BL5: 0 | BM5: 0 | BN5: 0 | BO5: 0 | BP5: 0 | BQ5: 0 | BR5: 0 | BS5: 0 | BT5: 0 | BU5: 0 | BV5: 0 | BW5: 0 | BX5: 0 | BY5: 0 | BZ5: 0 | CA5: 0 | CB5: 0 | CC5: 0 | CD5: 0 | CE5: 0 | CF5: 0 | CG5: 0 | CH5: 0 | CI5: 0 | CJ5: 0 | CK5: 0 | CL5: 0 | CM5: 0 | CN5: 0 | CO5: 0 | CP5: 0 | CQ5: 0 | CR5: 0 | CS5: 0 | CT5: 0 | CU5: 0 | CV5: 0 | CW5: 0 | CX5: 0 | CY5: 0 | CZ5: 0 | DX5: 0 | DY5: 0 | DZ5: 0 | EA5: 0 | EB5: 0 | EC5: 0 | ED5: 0 | EE5: 0 | EF5: 0 | EG5: 0 | EH5: 0 | EI5: 0 | EJ5: 0 | EK5: 0 | EL5: 0 | EM5: 0 | EN5: 0 | EO5: 0 | EP5: 0 | EQ5: 0 | ER5: 0 | ES5: 0 | ET5: 0 | EU5: 0 | EV5: 0 | EW5: 0 | EX5: 0 | EY5: 0 | EZ5: 0 | FA5: 0 | FB5: 0 | FC5: 0 | FD5: 0 | FE5: 0 | FF5: 0 | FG5: 0 | FH5: 0 | FI5: 0 | FJ5: 0 | FK5: 0 | FL5: 0 | FM5: 0 | FN5: 0 | FO5: 0 | FP5: 0 | FQ5: 0
A6: 002021 | B6: 00 | C6: 2021 | D6: 1.6707404e+08 | E6: 20861929 | F6: 37141949 | G6: 44204682 | H6: 3473629.3 | I6: 5393897 | J6: 1.3470761 | K6: 40615578 | L6: 49598579 | M6: =IF(OR(Beazley_data[[#This Row],[total_RC]]<0.6,Beazley_data[[#This Row],[total_RC]]>2),1,Beazley_data[[#This Row],[total_RC]]) -> 1.3470761 | P6: =Beazley_data[[#This Row],[key]] -> 002021 | Q6: =Beazley_data[[#This Row],[WEP]] -> 1.6707404e+08 | R6: =IFERROR(INDEX($AJ$4:$CZ$182,MATCH($B6,$AI$4:$AI$182,0),MATCH($C6&"WEP",$AJ$1:$FQ$1,0)),0) -> 0 | S6: =IFERROR((R6-Q6)/R6,"no values") -> no values | U6: =Beazley_data[[#This Row],[Acq_costs]] -> 20861929 | V6: =IFERROR(INDEX($AJ$4:$FQ$182,MATCH($B6,$AI$4:$AI$182,0),MATCH($C6&"Acquisition Cost",$AJ$1:$FQ$1,0)),0) -> 0 | W6: =IFERROR((V6-U6)/V6,"no values") -> no values | Y6: =Beazley_data[[#This Row],[total_RC]] -> 1.3470761 | Z6: =IFERROR(INDEX($AJ$4:$FQ$182,MATCH($B6,$AI$4:$AI$182,0),MATCH($C6&"RC",$AJ$1:$FQ$1,0)),0) -> 0 | AA6: =IFERROR((Z6-Y6)/Z6,"no values") -> no values | AD6: =Beazley_data[[#This Row],[Cat_incurred]]+Beazley_data[[#This Row],[incurred_exc_cat]] -> 49598579 | AE6: =IFERROR(INDEX($AJ$4:$FQ$182,MATCH($B6,$AI$4:$AI$182,0),MATCH($C6&"Total Incurred (Cat)",$AJ$1:$FQ$1,0)),0)+IFERROR(INDEX($AJ$4:$FQ$182,MATCH($B6,$AI$4:$AI$182,0),MATCH($C6&"Total Incurred (Non Cat)",$AJ$1:$FQ$1,0)),0) -> 0 | AF6: =IFERROR((AE6-AD6)/AE6,"no values") -> no values | AI6: 2E | AJ6: 0 | AK6: 0 | AL6: 0 | AM6: 0.98999961 | AN6: 1.0991369 | AO6: 2.0925928 | AP6: 1.7 | AQ6: 0.77198375 | AR6: 0.92000003 | AS6: 0 | AT6: 0.96999999 | AU6: 0 | AV6: 1 | AW6: 0.95998825 | AX6: 0.99474145 | AY6: 1 | AZ6: 0.99999845 | BA6: 0.96890677 | BB6: 1.0252261 | BC6: 1.0160034 | BD6: 1.2412132 | BE6: 1.1589764 | BF6: 0 | BG6: 0 | BH6: 0 | BI6: 0 | BJ6: 117.647 | BK6: 2467.5462 | BL6: 10828.774 | BM6: 16544.066 | BN6: 5095.316 | BO6: 1300.117 | BP6: 0 | BQ6: 2675 | BR6: 0 | BS6: 0.064 | BT6: 9950.9164 | BU6: 1.0215 | BV6: 517.994 | BW6: 10091.267 | BX6: 5353.2135 | BY6: 4538.2772 | BZ6: 77064.396 | CA6: 7386.8277 | CB6: 3565.6634 | CC6: 0 | CD6: 0 | CE6: 0 | CF6: 0 | CG6: 0 | CH6: 0 | CI6: 0 | CJ6: 0 | CK6: 25541.459 | CL6: 0 | CM6: 0 | CN6: 0 | CO6: 0 | CP6: 0 | CQ6: 0 | CR6: 0 | CS6: 0 | CT6: 0 | CU6: 0 | CV6: 0 | CW6: 0 | CX6: 0 | CY6: 0 | CZ6: 0 | DX6: 0 | DY6: 0 | DZ6: 0 | EA6: 29.4118 | EB6: 616.8867 | EC6: 2719.4387 | ED6: 3386.0165 | EE6: 394.3266 | EF6: 325.0293 | EG6: 0 | EH6: 0 | EI6: 0 | EJ6: 0.0166 | EK6: 455.3868 | EL6: 0.2582 | EM6: 0 | EN6: 0.2 | EO6: 0.2 | EP6: 40.8023 | EQ6: 32500 | ER6: 399.4699 | ES6: 0 | ET6: 0 | EU6: 0 | EV6: 0 | EW6: 0 | EX6: 0 | EY6: 0 | EZ6: 0 | FA6: 0 | FB6: 25541.459 | FC6: 0 | FD6: 0 | FE6: 0 | FF6: 0 | FG6: 0 | FH6: 0 | FI6: 0 | FJ6: 0 | FK6: 0 | FL6: 0 | FM6: 0 | FN6: 0 | FO6: 0 | FP6: 0 | FQ6: 0
A7: 002022 | B7: 00 | C7: 2022 | D7: 2.2559881e+08 | E7: 28991245 | F7: 3844183.8 | G7: 5265016.8 | H7: 6122337.1 | I7: 8574449.2 | J7: 1.1465335 | K7: 9966520.9 | L7: 13839466 | M7: =IF(OR(Beazley_data[[#This Row],[total_RC]]<0.6,Beazley_data[[#This Row],[total_RC]]>2),1,Beazley_data[[#This Row],[total_RC]]) -> 1.1465335 | P7: =Beazley_data[[#This Row],[key]] -> 002022 | Q7: =Beazley_data[[#This Row],[WEP]] -> 2.2559881e+08 | R7: =IFERROR(INDEX($AJ$4:$CZ$182,MATCH($B7,$AI$4:$AI$182,0),MATCH($C7&"WEP",$AJ$1:$FQ$1,0)),0) -> 0 | S7: =IFERROR((R7-Q7)/R7,"no values") -> no values | U7: =Beazley_data[[#This Row],[Acq_costs]] -> 28991245 | V7: =IFERROR(INDEX($AJ$4:$FQ$182,MATCH($B7,$AI$4:$AI$182,0),MATCH($C7&"Acquisition Cost",$AJ$1:$FQ$1,0)),0) -> 0 | W7: =IFERROR((V7-U7)/V7,"no values") -> no values | Y7: =Beazley_data[[#This Row],[total_RC]] -> 1.1465335 | Z7: =IFERROR(INDEX($AJ$4:$FQ$182,MATCH($B7,$AI$4:$AI$182,0),MATCH($C7&"RC",$AJ$1:$FQ$1,0)),0) -> 0 | AA7: =IFERROR((Z7-Y7)/Z7,"no values") -> no values | AD7: =Beazley_data[[#This Row],[Cat_incurred]]+Beazley_data[[#This Row],[incurred_exc_cat]] -> 13839466 | AE7: =IFERROR(INDEX($AJ$4:$FQ$182,MATCH($B7,$AI$4:$AI$182,0),MATCH($C7&"Total Incurred (Cat)",$AJ$1:$FQ$1,0)),0)+IFERROR(INDEX($AJ$4:$FQ$182,MATCH($B7,$AI$4:$AI$182,0),MATCH($C7&"Total Incurred (Non Cat)",$AJ$1:$FQ$1,0)),0) -> 0 | AF7: =IFERROR((AE7-AD7)/AE7,"no values") -> no values | AI7: 2T | AJ7: 0 | AK7: 0 | AL7: 0 | AM7: 0.44055491 | AN7: 1 | AO7: 0 | AP7: 1 | AQ7: 0.84148253 | AR7: 0.90655845 | AS7: 1 | AT7: 0.98662464 | AU7: 0.92489615 | AV7: 1 | AW7: 0.83004395 | AX7: 0.97960845 | AY7: 0.99342998 | AZ7: 0.9999572 | BA7: 0.99625852 | BB7: 0 | BC7: 1.1000014 | BD7: 1.2501567 | BE7: 0 | BF7: 0 | BG7: 0 | BH7: 0 | BI7: 0 | BJ7: 6734.9492 | BK7: 4538.503 | BL7: 110000 | BM7: 198691.74 | BN7: 153311.51 | BO7: 138411.37 | BP7: 60437.108 | BQ7: 133897.16 | BR7: 93649.329 | BS7: 47709.751 | BT7: 45328.408 | BU7: 62216.207 | BV7: 111393.18 | BW7: 59076.38 | BX7: 75859.937 | BY7: 73807.728 | BZ7: 132526.02 | CA7: 1.5952 | CB7: 0 | CC7: 0 | CD7: 0 | CE7: 0 | CF7: 0 | CG7: 0 | CH7: 0 | CI7: 0 | CJ7: 0 | CK7: 0 | CL7: 0 | CM7: 0 | CN7: 0 | CO7: 0 | CP7: 0 | CQ7: 0 | CR7: 0 | CS7: 0 | CT7: 0 | CU7: 0 | CV7: 0 | CW7: 0 | CX7: 0 | CY7: 0 | CZ7: 0 | DX7: 0 | DY7: 0 | DZ7: 0 | EA7: 1103.9864 | EB7: 1496.657 | EC7: 0 | ED7: 21592.488 | EE7: 17191.803 | EF7: 18956.682 | EG7: 12133.644 | EH7: 11915.132 | EI7: 8726.4903 | EJ7: 3688.6619 | EK7: 5422.3396 | EL7: 26664.873 | EM7: 14557.807 | EN7: 3146.1059 | EO7: 5760.9388 | EP7: 7747.7726 | EQ7: 14868.856 | ER7: 0.4052 | ES7: 0 | ET7: 0 | EU7: 0 | EV7: 0 | EW7: 0 | EX7: 0 | EY7: 0 | EZ7: 0 | FA7: 0 | FB7: 0 | FC7: 0 | FD7: 0 | FE7: 0 | FF7: 0 | FG7: 0 | FH7: 0 | FI7: 0 | FJ7: 0 | FK7: 0 | FL7: 0 | FM7: 0 | FN7: 0 | FO7: 0 | FP7: 0 | FQ7: 0
A8: 002023 | B8: 00 | C8: 2023 | D8: 2.5944887e+08 | E8: 35192904 | F8: 6251962.9 | G8: 21318659 | H8: 1617362.8 | I8: 4107867 | J8: 1.0164919 | K8: 7869325.6 | L8: 25426526 | M8: =IF(OR(Beazley_data[[#This Row],[total_RC]]<0.6,Beazley_data[[#This Row],[total_RC]]>2),1,Beazley_data[[#This Row],[total_RC]]) -> 1.0164919 | P8: =Beazley_data[[#This Row],[key]] -> 002023 | Q8: =Beazley_data[[#This Row],[WEP]] -> 2.5944887e+08 | R8: =IFERROR(INDEX($AJ$4:$CZ$182,MATCH($B8,$AI$4:$AI$182,0),MATCH($C8&"WEP",$AJ$1:$FQ$1,0)),0) -> 0 | S8: =IFERROR((R8-Q8)/R8,"no values") -> no values | U8: =Beazley_data[[#This Row],[Acq_costs]] -> 35192904 | V8: =IFERROR(INDEX($AJ$4:$FQ$182,MATCH($B8,$AI$4:$AI$182,0),MATCH($C8&"Acquisition Cost",$AJ$1:$FQ$1,0)),0) -> 0 | W8: =IFERROR((V8-U8)/V8,"no values") -> no values | Y8: =Beazley_data[[#This Row],[total_RC]] -> 1.0164919 | Z8: =IFERROR(INDEX($AJ$4:$FQ$182,MATCH($B8,$AI$4:$AI$182,0),MATCH($C8&"RC",$AJ$1:$FQ$1,0)),0) -> 0 | AA8: =IFERROR((Z8-Y8)/Z8,"no values") -> no values | AD8: =Beazley_data[[#This Row],[Cat_incurred]]+Beazley_data[[#This Row],[incurred_exc_cat]] -> 25426526 | AE8: =IFERROR(INDEX($AJ$4:$FQ$182,MATCH($B8,$AI$4:$AI$182,0),MATCH($C8&"Total Incurred (Cat)",$AJ$1:$FQ$1,0)),0)+IFERROR(INDEX($AJ$4:$FQ$182,MATCH($B8,$AI$4:$AI$182,0),MATCH($C8&"Total Incurred (Non Cat)",$AJ$1:$FQ$1,0)),0) -> 0 | AF8: =IFERROR((AE8-AD8)/AE8,"no values") -> no values | AI8: 3E | AJ8: 0 | AK8: 0 | AL8: 0 | AM8: 0 | AN8: 0.85331676 | AO8: 1.1726083 | AP8: 0.37409438 | AQ8: 0.83760881 | AR8: 0 | AS8: 1.0799996 | AT8: 0.99214601 | AU8: 0 | AV8: 1.0065453 | AW8: 1.0499994 | AX8: 0.44551252 | AY8: 0.86503609 | AZ8: 0.98877665 | BA8: 0.98452179 | BB8: 1.0024698 | BC8: 1.0234928 | BD8: 1.0251625 | BE8: 1.0120236 | BF8: 1.105729 | BG8: 0 | BH8: 0 | BI8: 227.4607 | BJ8: 21767.245 | BK8: 20002.144 | BL8: 3180.0909 | BM8: 21690.449 | BN8: 54899.993 | BO8: 1387.3158 | BP8: 225.71978 | BQ8: 1996.2562 | BR8: 1696.0711 | BS8: 3177.0761 | BT8: 6606.752 | BU8: 7870.5386 | BV8: 8155.8407 | BW8: 7882.115 | BX8: 8760.309 | BY8: 4727.5601 | BZ8: 15996.449 | CA8: 89851.529 | CB8: 6515.4821 | CC8: 164.67712 | CD8: 0 | CE8: 0 | CF8: 0 | CG8: 0 | CH8: 0 | CI8: 0 | CJ8: 0 | CK8: 0 | CL8: 0 | CM8: 0 | CN8: 0 | CO8: 0 | CP8: 0 | CQ8: 0 | CR8: 0 | CS8: 0 | CT8: 0 | CU8: 0 | CV8: 0 | CW8: 0 | CX8: 42.854 | CY8: 67475.502 | CZ8: 0 | DX8: 0 | DY8: 0 | DZ8: 125.1915 | EA8: 1304.4402 | EB8: 4162.2196 | EC8: 808.30723 | ED8: 2172.9466 | EE8: 29690.795 | EF8: 368.7802 | EG8: 57.068212 | EH8: 499.0641 | EI8: 192.2289 | EJ8: 862.703 | EK8: 2120.1229 | EL8: 2849.4261 | EM8: 2896.2442 | EN8: 2740.7818 | EO8: 2342.8152 | EP8: 1779.4333 | EQ8: 4111.7538 | ER8: 4572.0227 | ES8: 1231.9245 | ET8: 54.324932 | EU8: 0 | EV8: 0 | EW8: 0 | EX8: 0 | EY8: 0 | EZ8: 0 | FA8: 0 | FB8: 0 | FC8: 0 | FD8: 0 | FE8: 0 | FF8: 0 | FG8: 0 | FH8: 0 | FI8: 0 | FJ8: 0 | FK8: 0 | FL8: 0 | FM8: 0 | FN8: 0 | FO8: 42.854 | FP8: 8793.293 | FQ8: 0
A9: 002024 | B9: 00 | C9: 2024 | D9: 1.2925254e+08 | E9: 17883469 | F9: 0 | G9: 0 | H9: 25128.521 | I9: 268473.87 | J9: 0.93619509 | K9: 25128.521 | L9: 268473.87 | M9: =IF(OR(Beazley_data[[#This Row],[total_RC]]<0.6,Beazley_data[[#This Row],[total_RC]]>2),1,Beazley_data[[#This Row],[total_RC]]) -> 0.93619509 | P9: =Beazley_data[[#This Row],[key]] -> 002024 | Q9: =Beazley_data[[#This Row],[WEP]] -> 1.2925254e+08 | R9: =IFERROR(INDEX($AJ$4:$CZ$182,MATCH($B9,$AI$4:$AI$182,0),MATCH($C9&"WEP",$AJ$1:$FQ$1,0)),0) -> 0 | S9: =IFERROR((R9-Q9)/R9,"no values") -> no values | U9: =Beazley_data[[#This Row],[Acq_costs]] -> 17883469 | V9: =IFERROR(INDEX($AJ$4:$FQ$182,MATCH($B9,$AI$4:$AI$182,0),MATCH($C9&"Acquisition Cost",$AJ$1:$FQ$1,0)),0) -> 0 | W9: =IFERROR((V9-U9)/V9,"no values") -> no values | Y9: =Beazley_data[[#This Row],[total_RC]] -> 0.93619509 | Z9: =IFERROR(INDEX($AJ$4:$FQ$182,MATCH($B9,$AI$4:$AI$182,0),MATCH($C9&"RC",$AJ$1:$FQ$1,0)),0) -> 0 | AA9: =IFERROR((Z9-Y9)/Z9,"no values") -> no values | AD9: =Beazley_data[[#This Row],[Cat_incurred]]+Beazley_data[[#This Row],[incurred_exc_cat]] -> 268473.87 | AE9: =IFERROR(INDEX($AJ$4:$FQ$182,MATCH($B9,$AI$4:$AI$182,0),MATCH($C9&"Total Incurred (Cat)",$AJ$1:$FQ$1,0)),0)+IFERROR(INDEX($AJ$4:$FQ$182,MATCH($B9,$AI$4:$AI$182,0),MATCH($C9&"Total Incurred (Non Cat)",$AJ$1:$FQ$1,0)),0) -> 0 | AF9: =IFERROR((AE9-AD9)/AE9,"no values") -> no values | AI9: 3T | AJ9: 0 | AK9: 0 | AL9: 1.0215023 | AM9: 0.99809574 | AN9: 1.2194445 | AO9: 0.9967035 | AP9: 0.86410076 | AQ9: 0.96793796 | AR9: 0.9938348 | AS9: 1.0080403 | AT9: 0.98166246 | AU9: 0.99703572 | AV9: 0.97356694 | AW9: 0.99614045 | AX9: 1.0142777 | AY9: 0.97984017 | AZ9: 0.98264476 | BA9: 0.99071691 | BB9: 1.0251648 | BC9: 1.0030896 | BD9: 1.0485957 | BE9: 1.0976888 | BF9: 1.0623362 | BG9: 0 | BH9: 90.8 | BI9: 4237.8998 | BJ9: 254888.92 | BK9: 287689.17 | BL9: 175648.44 | BM9: 252026.98 | BN9: 451713.12 | BO9: 232482.09 | BP9: 177658.34 | BQ9: 76676.951 | BR9: 37568.782 | BS9: 41676.607 | BT9: 70524.204 | BU9: 59800.046 | BV9: 87474.17 | BW9: 59850.942 | BX9: 46267.353 | BY9: 20502.919 | BZ9: 15496.94 | CA9: 55580.411 | CB9: 38024.297 | CC9: 10450.874 | CD9: 0 | CE9: 0 | CF9: 0 | CG9: 0 | CH9: 0 | CI9: 0 | CJ9: 718.2426 | CK9: 0 | CL9: 0 | CM9: 0 | CN9: 0 | CO9: 0 | CP9: 0 | CQ9: 0 | CR9: 0 | CS9: 0 | CT9: 0 | CU9: 748.7008 | CV9: 0 | CW9: 0 | CX9: 0 | CY9: 0 | CZ9: 0 | DX9: 0 | DY9: 30.2 | DZ9: 1350.9816 | EA9: 90487.037 | EB9: 106172.25 | EC9: 58674.398 | ED9: 85637.521 | EE9: 181449.19 | EF9: 90417.165 | EG9: 27038.336 | EH9: 20490.576 | EI9: 10782.227 | EJ9: 3578.1187 | EK9: 7175.0384 | EL9: 19339.008 | EM9: 31114.584 | EN9: 18628.672 | EO9: 15609.954 | EP9: 3438.295 | EQ9: 3258.0007 | ER9: 7666.7913 | ES9: 7384.2691 | ET9: 1557.835 | EU9: 0 | EV9: 0 | EW9: 0 | EX9: 0 | EY9: 0 | EZ9: 0 | FA9: 718.2426 | FB9: 0 | FC9: 0 | FD9: 0 | FE9: 0 | FF9: 0 | FG9: 0 | FH9: 0 | FI9: 0 | FJ9: 0 | FK9: 0 | FL9: 748.7008 | FM9: 0 | FN9: 0 | FO9: 0 | FP9: 0 | FQ9: 0
A10: 002025 | B10: 00 | C10: 2025 | D10: 1313389.9 | E10: 145932.21 | F10: 0 | G10: 0 | H10: 0 | I10: 0 | J10: 1.0800087 | K10: 0 | L10: 0 | M10: =IF(OR(Beazley_data[[#This Row],[total_RC]]<0.6,Beazley_data[[#This Row],[total_RC]]>2),1,Beazley_data[[#This Row],[total_RC]]) -> 1.0800087 | P10: =Beazley_data[[#This Row],[key]] -> 002025 | Q10: =Beazley_data[[#This Row],[WEP]] -> 1313389.9 | R10: =IFERROR(INDEX($AJ$4:$CZ$182,MATCH($B10,$AI$4:$AI$182,0),MATCH($C10&"WEP",$AJ$1:$FQ$1,0)),0) -> 0 | S10: =IFERROR((R10-Q10)/R10,"no values") -> no values | U10: =Beazley_data[[#This Row],[Acq_costs]] -> 145932.21 | V10: =IFERROR(INDEX($AJ$4:$FQ$182,MATCH($B10,$AI$4:$AI$182,0),MATCH($C10&"Acquisition Cost",$AJ$1:$FQ$1,0)),0) -> 0 | W10: =IFERROR((V10-U10)/V10,"no values") -> no values | Y10: =Beazley_data[[#This Row],[total_RC]] -> 1.0800087 | Z10: =IFERROR(INDEX($AJ$4:$FQ$182,MATCH($B10,$AI$4:$AI$182,0),MATCH($C10&"RC",$AJ$1:$FQ$1,0)),0) -> 0 | AA10: =IFERROR((Z10-Y10)/Z10,"no values") -> no values | AD10: =Beazley_data[[#This Row],[Cat_incurred]]+Beazley_data[[#This Row],[incurred_exc_cat]] -> 0 | AE10: =IFERROR(INDEX($AJ$4:$FQ$182,MATCH($B10,$AI$4:$AI$182,0),MATCH($C10&"Total Incurred (Cat)",$AJ$1:$FQ$1,0)),0)+IFERROR(INDEX($AJ$4:$FQ$182,MATCH($B10,$AI$4:$AI$182,0),MATCH($C10&"Total Incurred (Non Cat)",$AJ$1:$FQ$1,0)),0) -> 0 | AF10: =IFERROR((AE10-AD10)/AE10,"no values") -> no values | AI10: 4E | AJ10: 0 | AK10: 0 | AL10: 0 | AM10: 0 | AN10: 1 | AO10: 0 | AP10: 1.03 | AQ10: 0 | AR10: 0 | AS10: 0 | AT10: 0 | AU10: 0 | AV10: 0 | AW10: 0 | AX10: 0 | AY10: 0 | AZ10: 0 | BA10: 0 | BB10: 0 | BC10: 0 | BD10: 0 | BE10: 0 | BF10: 0 | BG10: 0 | BH10: 0 | BI10: 0 | BJ10: 24280.192 | BK10: 1469.52 | BL10: 0 | BM10: 3442.9783 | BN10: 0 | BO10: 21375 | BP10: 0 | BQ10: 0 | BR10: 0 | BS10: 0 | BT10: 0 | BU10: 0 | BV10: 0 | BW10: 0 | BX10: 0 | BY10: 0 | BZ10: 0.0094 | CA10: 0 | CB10: 0 | CC10: 0 | CD10: 0 | CE10: 0 | CF10: 0 | CG10: 0 | CH10: 0 | CI10: 0 | CJ10: 0 | CK10: 0 | CL10: 0 | CM10: 0 | CN10: 0 | CO10: 0 | CP10: 0 | CQ10: 0 | CR10: 0 | CS10: 0 | CT10: 0 | CU10: 0 | CV10: 0 | CW10: 0 | CX10: 0 | CY10: 0 | CZ10: 0 | DX10: 0 | DY10: 0 | DZ10: 0 | EA10: 5900.434 | EB10: 367.38 | EC10: 0 | ED10: 854.30554 | EE10: 0 | EF10: 5343.75 | EG10: 0 | EH10: 0 | EI10: 0 | EJ10: 0 | EK10: 0 | EL10: 0 | EM10: 0 | EN10: 0 | EO10: 0 | EP10: 0 | EQ10: 0.0015 | ER10: 0 | ES10: 0 | ET10: 0 | EU10: 0 | EV10: 0 | EW10: 0 | EX10: 0 | EY10: 0 | EZ10: 0 | FA10: 0 | FB10: 0 | FC10: 0 | FD10: 0 | FE10: 0 | FF10: 0 | FG10: 0 | FH10: 0 | FI10: 0 | FJ10: 0 | FK10: 0 | FL10: 0 | FM10: 0 | FN10: 0 | FO10: 0 | FP10: 0 | FQ10: 0
A11: 02022 | B11: 0 | C11: 2022 | D11: 1302563.8 | E11: 13157.21 | F11: 0 | G11: 0 | H11: 0 | I11: 0 | J11: 1.4001019 | K11: 0 | L11: 0 | M11: =IF(OR(Beazley_data[[#This Row],[total_RC]]<0.6,Beazley_data[[#This Row],[total_RC]]>2),1,Beazley_data[[#This Row],[total_RC]]) -> 1.4001019 | P11: =Beazley_data[[#This Row],[key]] -> 02022 | Q11: =Beazley_data[[#This Row],[WEP]] -> 1302563.8 | R11: =IFERROR(INDEX($AJ$4:$CZ$182,MATCH($B11,$AI$4:$AI$182,0),MATCH($C11&"WEP",$AJ$1:$FQ$1,0)),0) -> 0 | S11: =IFERROR((R11-Q11)/R11,"no values") -> no values | U11: =Beazley_data[[#This Row],[Acq_costs]] -> 13157.21 | V11: =IFERROR(INDEX($AJ$4:$FQ$182,MATCH($B11,$AI$4:$AI$182,0),MATCH($C11&"Acquisition Cost",$AJ$1:$FQ$1,0)),0) -> 0 | W11: =IFERROR((V11-U11)/V11,"no values") -> no values | Y11: =Beazley_data[[#This Row],[total_RC]] -> 1.4001019 | Z11: =IFERROR(INDEX($AJ$4:$FQ$182,MATCH($B11,$AI$4:$AI$182,0),MATCH($C11&"RC",$AJ$1:$FQ$1,0)),0) -> 0 | AA11: =IFERROR((Z11-Y11)/Z11,"no values") -> no values | AD11: =Beazley_data[[#This Row],[Cat_incurred]]+Beazley_data[[#This Row],[incurred_exc_cat]] -> 0 | AE11: =IFERROR(INDEX($AJ$4:$FQ$182,MATCH($B11,$AI$4:$AI$182,0),MATCH($C11&"Total Incurred (Cat)",$AJ$1:$FQ$1,0)),0)+IFERROR(INDEX($AJ$4:$FQ$182,MATCH($B11,$AI$4:$AI$182,0),MATCH($C11&"Total Incurred (Non Cat)",$AJ$1:$FQ$1,0)),0) -> 0 | AF11: =IFERROR((AE11-AD11)/AE11,"no values") -> no values | AI11: 4T | AJ11: 0 | AK11: 0 | AL11: 1.4240958 | AM11: 1.0237346 | AN11: 1.0028799 | AO11: 0.94067992 | AP11: 0.93262123 | AQ11: 0.98057531 | AR11: 0.95258249 | AS11: 0.96003847 | AT11: 0.90131428 | AU11: 0.98965287 | AV11: 0.99898729 | AW11: 0.99920047 | AX11: 0.98964937 | AY11: 0.96341573 | AZ11: 0.97836086 | BA11: 0.99975286 | BB11: 1.0509787 | BC11: 1.0341589 | BD11: 1.6229333 | BE11: 1.2393279 | BF11: 1.0270101 | BG11: 0 | BH11: 0 | BI11: 303272.59 | BJ11: 296672.27 | BK11: 420832.95 | BL11: 341927.43 | BM11: 257995.34 | BN11: 365250.13 | BO11: 328074.72 | BP11: 276057.84 | BQ11: 230889.48 | BR11: 180979.28 | BS11: 214801.13 | BT11: 472582.85 | BU11: 282303.74 | BV11: 331013.15 | BW11: 129413.08 | BX11: 338269.29 | BY11: 298564.87 | BZ11: 806539.63 | CA11: 627208.93 | CB11: 1417225.2 | CC11: 684488.7 | CD11: 0 | CE11: 0 | CF11: 0 | CG11: 0 | CH11: 0 | CI11: 0 | CJ11: 465.185 | CK11: 0 | CL11: 0 | CM11: 0 | CN11: 0 | CO11: 0 | CP11: 0 | CQ11: 0 | CR11: 0 | CS11: -3486.2587 | CT11: 0 | CU11: 0.0001 | CV11: 0 | CW11: 0 | CX11: 0 | CY11: 0 | CZ11: 0 | DX11: 0 | DY11: 0 | DZ11: 114935.61 | EA11: 116030.7 | EB11: 158047.37 | EC11: 181306.06 | ED11: 113487.34 | EE11: 183372.7 | EF11: 159960.13 | EG11: 132007.05 | EH11: 115414.05 | EI11: 88650.158 | EJ11: 106075.48 | EK11: 243625.59 | EL11: 120273.11 | EM11: 150735.48 | EN11: 60593.09 | EO11: 177463.42 | EP11: 163923.34 | EQ11: 366475.9 | ER11: 230467.6 | ES11: 659965.81 | ET11: 394919.03 | EU11: 0 | EV11: 0 | EW11: 0 | EX11: 0 | EY11: 0 | EZ11: 0 | FA11: 465.185 | FB11: 0 | FC11: 0 | FD11: 0 | FE11: 0 | FF11: 0 | FG11: 0 | FH11: 0 | FI11: 0 | FJ11: -3486.2587 | FK11: 0 | FL11: 0.0001 | FM11: 0 | FN11: 0 | FO11: 0 | FP11: 0 | FQ11: 0
A12: 02023 | B12: 0 | C12: 2023 | D12: 919935.83 | E12: 8771.4748 | F12: 0 | G12: 0 | H12: 0 | I12: 0 | J12: 0.57823593 | K12: 0 | L12: 0 | M12: =IF(OR(Beazley_data[[#This Row],[total_RC]]<0.6,Beazley_data[[#This Row],[total_RC]]>2),1,Beazley_data[[#This Row],[total_RC]]) -> 1 | P12: =Beazley_data[[#This Row],[key]] -> 02023 | Q12: =Beazley_data[[#This Row],[WEP]] -> 919935.83 | R12: =IFERROR(INDEX($AJ$4:$CZ$182,MATCH($B12,$AI$4:$AI$182,0),MATCH($C12&"WEP",$AJ$1:$FQ$1,0)),0) -> 0 | S12: =IFERROR((R12-Q12)/R12,"no values") -> no values | U12: =Beazley_data[[#This Row],[Acq_costs]] -> 8771.4748 | V12: =IFERROR(INDEX($AJ$4:$FQ$182,MATCH($B12,$AI$4:$AI$182,0),MATCH($C12&"Acquisition Cost",$AJ$1:$FQ$1,0)),0) -> 0 | W12: =IFERROR((V12-U12)/V12,"no values") -> no values | Y12: =Beazley_data[[#This Row],[total_RC]] -> 0.57823593 | Z12: =IFERROR(INDEX($AJ$4:$FQ$182,MATCH($B12,$AI$4:$AI$182,0),MATCH($C12&"RC",$AJ$1:$FQ$1,0)),0) -> 0 | AA12: =IFERROR((Z12-Y12)/Z12,"no values") -> no values | AD12: =Beazley_data[[#This Row],[Cat_incurred]]+Beazley_data[[#This Row],[incurred_exc_cat]] -> 0 | AE12: =IFERROR(INDEX($AJ$4:$FQ$182,MATCH($B12,$AI$4:$AI$182,0),MATCH($C12&"Total Incurred (Cat)",$AJ$1:$FQ$1,0)),0)+IFERROR(INDEX($AJ$4:$FQ$182,MATCH($B12,$AI$4:$AI$182,0),MATCH($C12&"Total Incurred (Non Cat)",$AJ$1:$FQ$1,0)),0) -> 0 | AF12: =IFERROR((AE12-AD12)/AE12,"no values") -> no values | AI12: 5T | AJ12: 0 | AK12: 0 | AL12: 1.1627252 | AM12: 1.1039476 | AN12: 1.0241016 | AO12: 0.99990643 | AP12: 1 | AQ12: 1 | AR12: 0.85 | AS12: 0 | AT12: 0 | AU12: 0 | AV12: 0 | AW12: 0 | AX12: 0 | AY12: 0 | AZ12: 0 | BA12: 0 | BB12: 0 | BC12: 0 | BD12: 0 | BE12: 0 | BF12: 0 | BG12: 0 | BH12: 0 | BI12: 83.774 | BJ12: 3863.02 | BK12: 4578.4884 | BL12: 40815.456 | BM12: 2423.925 | BN12: 4480 | BO12: 2700 | BP12: 0 | BQ12: 0 | BR12: 0 | BS12: 0 | BT12: 0 | BU12: 0 | BV12: 0 | BW12: 0 | BX12: 0 | BY12: 0 | BZ12: 0 | CA12: 0 | CB12: 0 | CC12: 0 | CD12: 0 | CE12: 0 | CF12: 0 | CG12: 0 | CH12: 0 | CI12: 0 | CJ12: 0 | CK12: 0 | CL12: 0 | CM12: 0 | CN12: 0 | CO12: 0 | CP12: 0 | CQ12: 0 | CR12: 0 | CS12: 0 | CT12: 0 | CU12: 0 | CV12: 0 | CW12: 0 | CX12: 0 | CY12: 0 | CZ12: 0 | DX12: 0 | DY12: 0 | DZ12: 28.7191 | EA12: 1322.1288 | EB12: 1622.2222 | EC12: 17460.524 | ED12: 1038.825 | EE12: 1920 | EF12: 1300 | EG12: 0 | EH12: 0 | EI12: 0 | EJ12: 0 | EK12: 0 | EL12: 0 | EM12: 0 | EN12: 0 | EO12: 0 | EP12: 0 | EQ12: 0 | ER12: 0 | ES12: 0 | ET12: 0 | EU12: 0 | EV12: 0 | EW12: 0 | EX12: 0 | EY12: 0 | EZ12: 0 | FA12: 0 | FB12: 0 | FC12: 0 | FD12: 0 | FE12: 0 | FF12: 0 | FG12: 0 | FH12: 0 | FI12: 0 | FJ12: 0 | FK12: 0 | FL12: 0 | FM12: 0 | FN12: 0 | FO12: 0 | FP12: 0 | FQ12: 0
A13: 11995 | B13: 1 | C13: 1995 | D13: 2650.8235 | E13: 837.10216 | F13: 0 | G13: 0 | H13: 0 | I13: 0 | J13: 1 | K13: 0 | L13: 0 | M13: =IF(OR(Beazley_data[[#This Row],[total_RC]]<0.6,Beazley_data[[#This Row],[total_RC]]>2),1,Beazley_data[[#This Row],[total_RC]]) -> 1 | P13: =Beazley_data[[#This Row],[key]] -> 11995 | Q13: =Beazley_data[[#This Row],[WEP]] -> 2650.8235 | R13: =IFERROR(INDEX($AJ$4:$CZ$182,MATCH($B13,$AI$4:$AI$182,0),MATCH($C13&"WEP",$AJ$1:$FQ$1,0)),0) -> 0 | S13: =IFERROR((R13-Q13)/R13,"no values") -> no values | U13: =Beazley_data[[#This Row],[Acq_costs]] -> 837.10216 | V13: =IFERROR(INDEX($AJ$4:$FQ$182,MATCH($B13,$AI$4:$AI$182,0),MATCH($C13&"Acquisition Cost",$AJ$1:$FQ$1,0)),0) -> 0 | W13: =IFERROR((V13-U13)/V13,"no values") -> no values | Y13: =Beazley_data[[#This Row],[total_RC]] -> 1 | Z13: =IFERROR(INDEX($AJ$4:$FQ$182,MATCH($B13,$AI$4:$AI$182,0),MATCH($C13&"RC",$AJ$1:$FQ$1,0)),0) -> 0 | AA13: =IFERROR((Z13-Y13)/Z13,"no values") -> no values | AD13: =Beazley_data[[#This Row],[Cat_incurred]]+Beazley_data[[#This Row],[incurred_exc_cat]] -> 0 | AE13: =IFERROR(INDEX($AJ$4:$FQ$182,MATCH($B13,$AI$4:$AI$182,0),MATCH($C13&"Total Incurred (Cat)",$AJ$1:$FQ$1,0)),0)+IFERROR(INDEX($AJ$4:$FQ$182,MATCH($B13,$AI$4:$AI$182,0),MATCH($C13&"Total Incurred (Non Cat)",$AJ$1:$FQ$1,0)),0) -> 0 | AF13: =IFERROR((AE13-AD13)/AE13,"no values") -> no values | AI13: 6T | AJ13: 0 | AK13: 1 | AL13: 1.3268969 | AM13: 0.85679694 | AN13: 0.84123113 | AO13: 0.93327443 | AP13: 0.92076093 | AQ13: 0.88465618 | AR13: 0.85947032 | AS13: 0.96622457 | AT13: 0.93588217 | AU13: 0.96156256 | AV13: 0.96519649 | AW13: 0.95806439 | AX13: 0.93655083 | AY13: 0.9583481 | AZ13: 0.88080845 | BA13: 0.88531746 | BB13: 0.98256067 | BC13: 0.9588639 | BD13: 1.0039288 | BE13: 1.0018478 | BF13: 1.1185654 | BG13: 0 | BH13: 477.1571 | BI13: 711010.19 | BJ13: 3408473.3 | BK13: 2931246.8 | BL13: 4104918.9 | BM13: 5207339.1 | BN13: 6171692.8 | BO13: 5525406.8 | BP13: 5928332.7 | BQ13: 5644193.7 | BR13: 4559867.5 | BS13: 4740581.5 | BT13: 4895450.5 | BU13: 4940095.5 | BV13: 4182773.5 | BW13: 5322078.9 | BX13: 2416480 | BY13: 2635335.4 | BZ13: 1972956.5 | CA13: 2157890.9 | CB13: 6654727.1 | CC13: 4748877.4 | CD13: 0 | CE13: 0 | CF13: 0 | CG13: -8737.973 | CH13: 260.64628 | CI13: 341.682 | CJ13: 0 | CK13: 107.4669 | CL13: 2716.2769 | CM13: 0 | CN13: 5962.45 | CO13: 420.18992 | CP13: -7.2759576e-12 | CQ13: -15.18858 | CR13: 0 | CS13: -1.6164847e-13 | CT13: 42075.174 | CU13: 328444.83 | CV13: 97546.571 | CW13: 104234.23 | CX13: 1164.705 | CY13: 4250527.3 | CZ13: 0 | DX13: 0 | DY13: 204.4959 | DZ13: 129261.47 | EA13: 578476.78 | EB13: 542689.4 | EC13: 840590.46 | ED13: 869699.63 | EE13: 1059182.1 | EF13: 976453.37 | EG13: 968235.88 | EH13: 1024607.9 | EI13: 696431.01 | EJ13: 711783.66 | EK13: 669453.21 | EL13: 886729.13 | EM13: 696888.82 | EN13: 930198.49 | EO13: 455446.45 | EP13: 535803.15 | EQ13: 436609.02 | ER13: 467083.99 | ES13: 2396362.7 | ET13: 1895797.2 | EU13: 0 | EV13: 0 | EW13: 0 | EX13: -8737.973 | EY13: 260.64628 | EZ13: 341.682 | FA13: 0 | FB13: 107.4669 | FC13: 2716.2769 | FD13: 0 | FE13: 5962.45 | FF13: 420.18992 | FG13: 0 | FH13: -15.18858 | FI13: 0 | FJ13: 0 | FK13: 33859.344 | FL13: 100674.1 | FM13: 87546.571 | FN13: 99756.762 | FO13: 1164.705 | FP13: 2802185.9 | FQ13: 0
A14: 12022 | B14: 1 | C14: 2022 | D14: 4344.3218 | E14: 240.7144 | F14: 0 | G14: 0 | H14: 0 | I14: 0 | J14: 0.82836899 | K14: 0 | L14: 0 | M14: =IF(OR(Beazley_data[[#This Row],[total_RC]]<0.6,Beazley_data[[#This Row],[total_RC]]>2),1,Beazley_data[[#This Row],[total_RC]]) -> 0.82836899 | P14: =Beazley_data[[#This Row],[key]] -> 12022 | Q14: =Beazley_data[[#This Row],[WEP]] -> 4344.3218 | R14: =IFERROR(INDEX($AJ$4:$CZ$182,MATCH($B14,$AI$4:$AI$182,0),MATCH($C14&"WEP",$AJ$1:$FQ$1,0)),0) -> 0 | S14: =IFERROR((R14-Q14)/R14,"no values") -> no values | U14: =Beazley_data[[#This Row],[Acq_costs]] -> 240.7144 | V14: =IFERROR(INDEX($AJ$4:$FQ$182,MATCH($B14,$AI$4:$AI$182,0),MATCH($C14&"Acquisition Cost",$AJ$1:$FQ$1,0)),0) -> 0 | W14: =IFERROR((V14-U14)/V14,"no values") -> no values | Y14: =Beazley_data[[#This Row],[total_RC]] -> 0.82836899 | Z14: =IFERROR(INDEX($AJ$4:$FQ$182,MATCH($B14,$AI$4:$AI$182,0),MATCH($C14&"RC",$AJ$1:$FQ$1,0)),0) -> 0 | AA14: =IFERROR((Z14-Y14)/Z14,"no values") -> no values | AD14: =Beazley_data[[#This Row],[Cat_incurred]]+Beazley_data[[#This Row],[incurred_exc_cat]] -> 0 | AE14: =IFERROR(INDEX($AJ$4:$FQ$182,MATCH($B14,$AI$4:$AI$182,0),MATCH($C14&"Total Incurred (Cat)",$AJ$1:$FQ$1,0)),0)+IFERROR(INDEX($AJ$4:$FQ$182,MATCH($B14,$AI$4:$AI$182,0),MATCH($C14&"Total Incurred (Non Cat)",$AJ$1:$FQ$1,0)),0) -> 0 | AF14: =IFERROR((AE14-AD14)/AE14,"no values") -> no values | AI14: 7T | AJ14: 0 | AK14: 0 | AL14: 1.2947924 | AM14: 1.2204607 | AN14: 0.97840146 | AO14: 1.0223773 | AP14: 1.0447881 | AQ14: 0.94107927 | AR14: 0.90994359 | AS14: 0.96162286 | AT14: 0.94277203 | AU14: 0.96663766 | AV14: 1.0290268 | AW14: 0.98605469 | AX14: 0.93324641 | AY14: 0.89753846 | AZ14: 0.96981588 | BA14: 0.98131248 | BB14: 1.0003333 | BC14: 1.0729386 | BD14: 1.1540282 | BE14: 1.0085449 | BF14: 1.0040106 | BG14: 0 | BH14: 0 | BI14: 162742.36 | BJ14: 1813054.3 | BK14: 1580280.1 | BL14: 1714436.1 | BM14: 791223.69 | BN14: 909423.98 | BO14: 1024566.8 | BP14: 1260546.8 | BQ14: 901532.26 | BR14: 1033124.1 | BS14: 1147362.7 | BT14: 992644.33 | BU14: 964680.32 | BV14: 913550.28 | BW14: 833829.56 | BX14: 1284004.5 | BY14: 2281195.4 | BZ14: 1655145.8 | CA14: 1315804.2 | CB14: 1078123.8 | CC14: 654010.12 | CD14: 0 | CE14: 0 | CF14: 0 | CG14: 1034.7512 | CH14: 3725.41 | CI14: 0 | CJ14: 0 | CK14: 8338.75 | CL14: 25370.275 | CM14: 5614791.1 | CN14: 0 | CO14: 136866.51 | CP14: 17891 | CQ14: 5328.75 | CR14: 7464.4015 | CS14: 9649.77 | CT14: 383258.63 | CU14: 40449.4 | CV14: 77258.8 | CW14: 178772.05 | CX14: 329159.28 | CY14: 16000.58 | CZ14: 0 | DX14: 0 | DY14: 0 | DZ14: 34840.159 | EA14: 333201.79 | EB14: 259136.85 | EC14: 338444.91 | ED14: 111221.69 | EE14: 154194.49 | EF14: 155976.52 | EG14: 207363.89 | EH14: 126921.94 | EI14: 114279.03 | EJ14: 170670.07 | EK14: 128488.02 | EL14: 145356.39 | EM14: 142095.04 | EN14: 138553.39 | EO14: 285596.6 | EP14: 179081.74 | EQ14: 270469.26 | ER14: 223758.79 | ES14: 348695.28 | ET14: 369601.8 | EU14: 0 | EV14: 0 | EW14: 0 | EX14: 1034.7512 | EY14: 3725.41 | EZ14: 0 | FA14: 0 | FB14: 8338.75 | FC14: 25370.275 | FD14: 5614791.1 | FE14: 0 | FF14: 136866.51 | FG14: 17891 | FH14: 5328.75 | FI14: 7464.4015 | FJ14: 9649.77 | FK14: 22681.63 | FL14: 40449.4 | FM14: 74623.3 | FN14: 146860.05 | FO14: 329159.28 | FP14: 10244.58 | FQ14: 0
A15: 1E2002 | B15: 1E | C15: 2002 | D15: 722.6964 | E15: 209.81508 | F15: 0 | G15: 0 | H15: 0 | I15: 0 | K15: 0 | L15: 0 | M15: =IF(OR(Beazley_data[[#This Row],[total_RC]]<0.6,Beazley_data[[#This Row],[total_RC]]>2),1,Beazley_data[[#This Row],[total_RC]]) -> 1 | P15: =Beazley_data[[#This Row],[key]] -> 1E2002 | Q15: =Beazley_data[[#This Row],[WEP]] -> 722.6964 | R15: =IFERROR(INDEX($AJ$4:$CZ$182,MATCH($B15,$AI$4:$AI$182,0),MATCH($C15&"WEP",$AJ$1:$FQ$1,0)),0) -> 722.6964 | S15: =IFERROR((R15-Q15)/R15,"no values") -> 0 | U15: =Beazley_data[[#This Row],[Acq_costs]] -> 209.81508 | V15: =IFERROR(INDEX($AJ$4:$FQ$182,MATCH($B15,$AI$4:$AI$182,0),MATCH($C15&"Acquisition Cost",$AJ$1:$FQ$1,0)),0) -> 209.8151 | W15: =IFERROR((V15-U15)/V15,"no values") -> 7.6872599e-08 | Y15: =Beazley_data[[#This Row],[total_RC]] -> 0 | Z15: =IFERROR(INDEX($AJ$4:$FQ$182,MATCH($B15,$AI$4:$AI$182,0),MATCH($C15&"RC",$AJ$1:$FQ$1,0)),0) -> 0 | AA15: =IFERROR((Z15-Y15)/Z15,"no values") -> no values | AD15: =Beazley_data[[#This Row],[Cat_incurred]]+Beazley_data[[#This Row],[incurred_exc_cat]] -> 0 | AE15: =IFERROR(INDEX($AJ$4:$FQ$182,MATCH($B15,$AI$4:$AI$182,0),MATCH($C15&"Total Incurred (Cat)",$AJ$1:$FQ$1,0)),0)+IFERROR(INDEX($AJ$4:$FQ$182,MATCH($B15,$AI$4:$AI$182,0),MATCH($C15&"Total Incurred (Non Cat)",$AJ$1:$FQ$1,0)),0) -> 0 | AF15: =IFERROR((AE15-AD15)/AE15,"no values") -> no values | AI15: 8T | AJ15: 0 | AK15: 0 | AL15: 1.0100001 | AM15: 1.0233097 | AN15: 0.97887614 | AO15: 0.97775976 | AP15: 1.0211507 | AQ15: 0.96512416 | AR15: 0.99609936 | AS15: 1.010447 | AT15: 0.92887812 | AU15: 0.99627889 | AV15: 1.0304749 | AW15: 1.0162172 | AX15: 0.98618428 | AY15: 0.97632364 | AZ15: 0.96198259 | BA15: 0.99504076 | BB15: 1.0996219 | BC15: 1.0481851 | BD15: 1.1900738 | BE15: 1.1155618 | BF15: 1.0533697 | BG15: 0 | BH15: 0 | BI15: 227.5812 | BJ15: 36518.197 | BK15: 108032.13 | BL15: 118467.4 | BM15: 81208.576 | BN15: 98716.715 | BO15: 131859.66 | BP15: 99165.252 | BQ15: 81158.929 | BR15: 92889.518 | BS15: 99128.453 | BT15: 105702.55 | BU15: 104779.97 | BV15: 61611.46 | BW15: 64403.232 | BX15: 39325.349 | BY15: 55041.984 | BZ15: 143227.65 | CA15: 48693.472 | CB15: 75794.348 | CC15: 99669.527 | CD15: 0 | CE15: 0 | CF15: 0 | CG15: 1497.625 | CH15: 1288.1948 | CI15: 0 | CJ15: 0 | CK15: 172.3292 | CL15: 4200.7219 | CM15: 0 | CN15: 9079.3773 | CO15: 0 | CP15: 545.8828 | CQ15: 1.8189894e-12 | CR15: 0 | CS15: 36851.275 | CT15: 0 | CU15: 0 | CV15: 0 | CW15: 0 | CX15: 0 | CY15: 0 | CZ15: 0 | DX15: 0 | DY15: 0 | DZ15: 75.8604 | EA15: 12785.604 | EB15: 34250.765 | EC15: 30833.041 | ED15: 24722.616 | EE15: 29319.07 | EF15: 37374.433 | EG15: 32805.618 | EH15: 27188.583 | EI15: 30480.884 | EJ15: 30086.985 | EK15: 33747.519 | EL15: 29751.196 | EM15: 16896.019 | EN15: 24454.426 | EO15: 12788.707 | EP15: 17113.606 | EQ15: 70837.062 | ER15: 15829.583 | ES15: 26244.412 | ET15: 41596.3 | EU15: 0 | EV15: 0 | EW15: 0 | EX15: 1497.625 | EY15: 1288.1948 | EZ15: 0 | FA15: 0 | FB15: 172.3292 | FC15: 4200.7219 | FD15: 0 | FE15: 9079.3773 | FF15: 0 | FG15: 545.8828 | FH15: 0 | FI15: 0 | FJ15: 36851.275 | FK15: 0 | FL15: 0 | FM15: 0 | FN15: 0 | FO15: 0 | FP15: 0 | FQ15: 0
A16: 1E2003 | B16: 1E | C16: 2003 | D16: 48098.473 | E16: 10723.116 | F16: 0 | G16: 0 | H16: 0 | I16: 0 | J16: 1.0892026 | K16: 0 | L16: 0 | M16: =IF(OR(Beazley_data[[#This Row],[total_RC]]<0.6,Beazley_data[[#This Row],[total_RC]]>2),1,Beazley_data[[#This Row],[total_RC]]) -> 1.0892026 | P16: =Beazley_data[[#This Row],[key]] -> 1E2003 | Q16: =Beazley_data[[#This Row],[WEP]] -> 48098.473 | R16: =IFERROR(INDEX($AJ$4:$CZ$182,MATCH($B16,$AI$4:$AI$182,0),MATCH($C16&"WEP",$AJ$1:$FQ$1,0)),0) -> 48100.95 | S16: =IFERROR((R16-Q16)/R16,"no values") -> 5.149312e-05 | U16: =Beazley_data[[#This Row],[Acq_costs]] -> 10723.116 | V16: =IFERROR(INDEX($AJ$4:$FQ$182,MATCH($B16,$AI$4:$AI$182,0),MATCH($C16&"Acquisition Cost",$AJ$1:$FQ$1,0)),0) -> 10723.942 | W16: =IFERROR((V16-U16)/V16,"no values") -> 7.6994235e-05 | Y16: =Beazley_data[[#This Row],[total_RC]] -> 1.0892026 | Z16: =IFERROR(INDEX($AJ$4:$FQ$182,MATCH($B16,$AI$4:$AI$182,0),MATCH($C16&"RC",$AJ$1:$FQ$1,0)),0) -> 1.0892026 | AA16: =IFERROR((Z16-Y16)/Z16,"no values") -> -2.2085699e-09 | AD16: =Beazley_data[[#This Row],[Cat_incurred]]+Beazley_data[[#This Row],[incurred_exc_cat]] -> 0 | AE16: =IFERROR(INDEX($AJ$4:$FQ$182,MATCH($B16,$AI$4:$AI$182,0),MATCH($C16&"Total Incurred (Cat)",$AJ$1:$FQ$1,0)),0)+IFERROR(INDEX($AJ$4:$FQ$182,MATCH($B16,$AI$4:$AI$182,0),MATCH($C16&"Total Incurred (Non Cat)",$AJ$1:$FQ$1,0)),0) -> 0 | AF16: =IFERROR((AE16-AD16)/AE16,"no values") -> no values | AI16: AG | AJ16: 1 | AK16: 1 | AL16: 1.0049163 | AM16: 0.96145434 | AN16: 1.01 | AO16: 1 | AP16: 1.0114316 | AQ16: 0.92840862 | AR16: 0.95383057 | AS16: 1.0769091 | AT16: 0.9718376 | AU16: 0.92670927 | AV16: 0.95752912 | AW16: 1.1284078 | AX16: 0.91524624 | AY16: 0.91651417 | AZ16: 0.9181804 | BA16: 1.0329949 | BB16: 1.0112027 | BC16: 0.99620305 | BD16: 1.045728 | BE16: 1.011382 | BF16: 1.1534108 | BG16: 13665.304 | BH16: 31329.189 | BI16: 63729.97 | BJ16: 18674.032 | BK16: 100302.03 | BL16: 81273.709 | BM16: 111650.52 | BN16: 137258.76 | BO16: 324022.81 | BP16: 351581.67 | BQ16: 337320.36 | BR16: 414546.4 | BS16: 272413.37 | BT16: 879921.73 | BU16: 1617812.1 | BV16: 1920470.3 | BW16: 5594167.3 | BX16: 4690242.4 | BY16: 3905656 | BZ16: 2794884.4 | CA16: 948740.52 | CB16: 1099142.4 | CC16: 254888.76 | CD16: 4317.804 | CE16: 0 | CF16: 0 | CG16: 0 | CH16: 0 | CI16: 0 | CJ16: 0 | CK16: 0 | CL16: 0 | CM16: 0 | CN16: 0 | CO16: 413652.26 | CP16: 2579058 | CQ16: 7.2759576e-12 | CR16: 375535.02 | CS16: 129212.45 | CT16: 3491785.4 | CU16: 4143642.8 | CV16: 2345172.9 | CW16: 2244548.5 | CX16: 56631.353 | CY16: 369541.9 | CZ16: 0 | DX16: 5867.635 | DY16: 3481.0211 | DZ16: 7081.1078 | EA16: 2074.8926 | EB16: 16922.377 | EC16: 14342.419 | ED16: 19703.033 | EE16: 24222.134 | EF16: 57180.495 | EG16: 62043.823 | EH16: 59527.122 | EI16: 73151.768 | EJ16: 48072.947 | EK16: 127956.91 | EL16: 191384.27 | EM16: 258046.74 | EN16: 707974.5 | EO16: 816337.02 | EP16: 549237.01 | EQ16: 284425.58 | ER16: 100339.42 | ES16: 117219.17 | ET16: 35871.667 | EU16: 4317.804 | EV16: 0 | EW16: 0 | EX16: 0 | EY16: 0 | EZ16: 0 | FA16: 0 | FB16: 0 | FC16: 0 | FD16: 0 | FE16: 0 | FF16: 413652.26 | FG16: 2579058 | FH16: 0 | FI16: 371847.48 | FJ16: 124285.61 | FK16: 3491750.1 | FL16: 3832452.5 | FM16: 2325822.1 | FN16: 2243022.4 | FO16: 0 | FP16: 369541.9 | FQ16: 0
A17: 1E2004 | B17: 1E | C17: 2004 | D17: 84551.073 | E17: 19004.728 | F17: 0 | G17: 0 | H17: 0 | I17: 0 | J17: 0.97983956 | K17: 0 | L17: 0 | M17: =IF(OR(Beazley_data[[#This Row],[total_RC]]<0.6,Beazley_data[[#This Row],[total_RC]]>2),1,Beazley_data[[#This Row],[total_RC]]) -> 0.97983956 | P17: =Beazley_data[[#This Row],[key]] -> 1E2004 | Q17: =Beazley_data[[#This Row],[WEP]] -> 84551.073 | R17: =IFERROR(INDEX($AJ$4:$CZ$182,MATCH($B17,$AI$4:$AI$182,0),MATCH($C17&"WEP",$AJ$1:$FQ$1,0)),0) -> 84725.561 | S17: =IFERROR((R17-Q17)/R17,"no values") -> 0.0020594515 | U17: =Beazley_data[[#This Row],[Acq_costs]] -> 19004.728 | V17: =IFERROR(INDEX($AJ$4:$FQ$182,MATCH($B17,$AI$4:$AI$182,0),MATCH($C17&"Acquisition Cost",$AJ$1:$FQ$1,0)),0) -> 19069.752 | W17: =IFERROR((V17-U17)/V17,"no values") -> 0.0034098254 | Y17: =Beazley_data[[#This Row],[total_RC]] -> 0.97983956 | Z17: =IFERROR(INDEX($AJ$4:$FQ$182,MATCH($B17,$AI$4:$AI$182,0),MATCH($C17&"RC",$AJ$1:$FQ$1,0)),0) -> 0.97983986 | AA17: =IFERROR((Z17-Y17)/Z17,"no values") -> 3.1148518e-07 | AD17: =Beazley_data[[#This Row],[Cat_incurred]]+Beazley_data[[#This Row],[incurred_exc_cat]] -> 0 | AE17: =IFERROR(INDEX($AJ$4:$FQ$182,MATCH($B17,$AI$4:$AI$182,0),MATCH($C17&"Total Incurred (Cat)",$AJ$1:$FQ$1,0)),0)+IFERROR(INDEX($AJ$4:$FQ$182,MATCH($B17,$AI$4:$AI$182,0),MATCH($C17&"Total Incurred (Non Cat)",$AJ$1:$FQ$1,0)),0) -> 0 | AF17: =IFERROR((AE17-AD17)/AE17,"no values") -> no values | AI17: AO | AJ17: 0 | AK17: 0 | AL17: 0 | AM17: 0 | AN17: 0 | AO17: 0 | AP17: 0 | AQ17: 0 | AR17: 0 | AS17: 0 | AT17: 0 | AU17: 0 | AV17: 1 | AW17: 0.965 | AX17: 0.95 | AY17: 0.99361099 | AZ17: 0.95419306 | BA17: 0.95 | BB17: 0.97380115 | BC17: 1.1593853 | BD17: 1.4143259 | BE17: 1.099213 | BF17: 1.0718118 | BG17: 0 | BH17: 0 | BI17: 0 | BJ17: 0 | BK17: 0 | BL17: 0 | BM17: 0 | BN17: 0 | BO17: 20680.717 | BP17: 0 | BQ17: 4286.9925 | BR17: 0 | BS17: 411044.38 | BT17: 274174.1 | BU17: 257598.16 | BV17: 82929.932 | BW17: 316277.5 | BX17: 290206.43 | BY17: 453477.33 | BZ17: 428075.54 | CA17: 642015.59 | CB17: 839237.39 | CC17: 121576.92 | CD17: 0 | CE17: 0 | CF17: 0 | CG17: 0 | CH17: 0 | CI17: 0 | CJ17: 0 | CK17: 0 | CL17: 0 | CM17: 0 | CN17: 0 | CO17: 0 | CP17: 0 | CQ17: 0 | CR17: 0 | CS17: 5430.2093 | CT17: 2203.1005 | CU17: 5951.328 | CV17: 480105.7 | CW17: 22343.28 | CX17: 56088.858 | CY17: 18996.245 | CZ17: 0 | DX17: 0 | DY17: 0 | DZ17: 0 | EA17: 0 | EB17: 0 | EC17: 0 | ED17: 0 | EE17: 0 | EF17: 6893.5725 | EG17: 0 | EH17: 1428.9975 | EI17: 0 | EJ17: 83643.125 | EK17: 113655.9 | EL17: 94456.294 | EM17: 48480.237 | EN17: 112931.22 | EO17: 109800.71 | EP17: 189140.32 | EQ17: 110080.1 | ER17: 130247.5 | ES17: 138427.46 | ET17: 43719.645 | EU17: 0 | EV17: 0 | EW17: 0 | EX17: 0 | EY17: 0 | EZ17: 0 | FA17: 0 | FB17: 0 | FC17: 0 | FD17: 0 | FE17: 0 | FF17: 0 | FG17: 0 | FH17: 0 | FI17: 0 | FJ17: 2413.4297 | FK17: 2203.1005 | FL17: 5951.328 | FM17: 99391.433 | FN17: 9399.5404 | FO17: 4397.3982 | FP17: 4406.1311 | FQ17: 0
A18: 1E2005 | B18: 1E | C18: 2005 | D18: 111698.81 | E18: 21371.434 | F18: 0 | G18: 0 | H18: 0 | I18: 0 | J18: 1.0676581 | K18: 0 | L18: 0 | M18: =IF(OR(Beazley_data[[#This Row],[total_RC]]<0.6,Beazley_data[[#This Row],[total_RC]]>2),1,Beazley_data[[#This Row],[total_RC]]) -> 1.0676581 | P18: =Beazley_data[[#This Row],[key]] -> 1E2005 | Q18: =Beazley_data[[#This Row],[WEP]] -> 111698.81 | R18: =IFERROR(INDEX($AJ$4:$CZ$182,MATCH($B18,$AI$4:$AI$182,0),MATCH($C18&"WEP",$AJ$1:$FQ$1,0)),0) -> 111715.57 | S18: =IFERROR((R18-Q18)/R18,"no values") -> 0.00015001759 | U18: =Beazley_data[[#This Row],[Acq_costs]] -> 21371.434 | V18: =IFERROR(INDEX($AJ$4:$FQ$182,MATCH($B18,$AI$4:$AI$182,0),MATCH($C18&"Acquisition Cost",$AJ$1:$FQ$1,0)),0) -> 21377.02 | W18: =IFERROR((V18-U18)/V18,"no values") -> 0.00026131979 | Y18: =Beazley_data[[#This Row],[total_RC]] -> 1.0676581 | Z18: =IFERROR(INDEX($AJ$4:$FQ$182,MATCH($B18,$AI$4:$AI$182,0),MATCH($C18&"RC",$AJ$1:$FQ$1,0)),0) -> 1.0676428 | AA18: =IFERROR((Z18-Y18)/Z18,"no values") -> -1.441262e-05 | AD18: =Beazley_data[[#This Row],[Cat_incurred]]+Beazley_data[[#This Row],[incurred_exc_cat]] -> 0 | AE18: =IFERROR(INDEX($AJ$4:$FQ$182,MATCH($B18,$AI$4:$AI$182,0),MATCH($C18&"Total Incurred (Cat)",$AJ$1:$FQ$1,0)),0)+IFERROR(INDEX($AJ$4:$FQ$182,MATCH($B18,$AI$4:$AI$182,0),MATCH($C18&"Total Incurred (Non Cat)",$AJ$1:$FQ$1,0)),0) -> 0 | AF18: =IFERROR((AE18-AD18)/AE18,"no values") -> no values | AI18: AP | AJ18: 0 | AK18: 0 | AL18: 0 | AM18: 0 | AN18: 0 | AO18: 0 | AP18: 0 | AQ18: 0 | AR18: 0 | AS18: 0 | AT18: 0 | AU18: 0 | AV18: 0 | AW18: 1 | AX18: 1.0904281 | AY18: 0.99906597 | AZ18: 0.97832864 | BA18: 0.94290893 | BB18: 1.0053355 | BC18: 1.1768197 | BD18: 1.2018585 | BE18: 1.1441242 | BF18: 1.0466913 | BG18: 0 | BH18: 0 | BI18: 0 | BJ18: 0 | BK18: 0 | BL18: 0 | BM18: 0 | BN18: 0 | BO18: 0 | BP18: 0 | BQ18: 0 | BR18: 0 | BS18: 0 | BT18: 23377.332 | BU18: 21042.386 | BV18: 133997.74 | BW18: 247969.36 | BX18: 267531.26 | BY18: 469705.57 | BZ18: 1908354.3 | CA18: 1897574.9 | CB18: 1996954.5 | CC18: 562204.86 | CD18: 0 | CE18: 0 | CF18: 0 | CG18: 0 | CH18: 0 | CI18: 0 | CJ18: 0 | CK18: 0 | CL18: 0 | CM18: 0 | CN18: 0 | CO18: 0 | CP18: 0 | CQ18: 9890.2732 | CR18: 1871.2432 | CS18: 40237.636 | CT18: 24313.655 | CU18: 35298.664 | CV18: 281388.04 | CW18: 379734.34 | CX18: 575020.3 | CY18: 79397.522 | CZ18: 0 | DX18: 0 | DY18: 0 | DZ18: 0 | EA18: 0 | EB18: 0 | EC18: 0 | ED18: 0 | EE18: 0 | EF18: 0 | EG18: 0 | EH18: 0 | EI18: 0 | EJ18: 0 | EK18: 7149.3893 | EL18: 7147.4678 | EM18: 62303.703 | EN18: 115592.29 | EO18: 106284.76 | EP18: 123507.46 | EQ18: 503289.48 | ER18: 631442.04 | ES18: 684448.34 | ET18: 170647.47 | EU18: 0 | EV18: 0 | EW18: 0 | EX18: 0 | EY18: 0 | EZ18: 0 | FA18: 0 | FB18: 0 | FC18: 0 | FD18: 0 | FE18: 0 | FF18: 0 | FG18: 0 | FH18: 9890.2732 | FI18: 1871.2432 | FJ18: 29357.402 | FK18: 23953.393 | FL18: 6652.7807 | FM18: 106157.42 | FN18: 283381.98 | FO18: 213999.82 | FP18: 897.44736 | FQ18: 0
A19: 1E2006 | B19: 1E | C19: 2006 | D19: 207434.87 | E19: 31342.052 | F19: 0 | G19: 0 | H19: 0 | I19: 0 | J19: 1.5229713 | K19: 0 | L19: 0 | M19: =IF(OR(Beazley_data[[#This Row],[total_RC]]<0.6,Beazley_data[[#This Row],[total_RC]]>2),1,Beazley_data[[#This Row],[total_RC]]) -> 1.5229713 | P19: =Beazley_data[[#This Row],[key]] -> 1E2006 | Q19: =Beazley_data[[#This Row],[WEP]] -> 207434.87 | R19: =IFERROR(INDEX($AJ$4:$CZ$182,MATCH($B19,$AI$4:$AI$182,0),MATCH($C19&"WEP",$AJ$1:$FQ$1,0)),0) -> 207452.83 | S19: =IFERROR((R19-Q19)/R19,"no values") -> 8.6613461e-05 | U19: =Beazley_data[[#This Row],[Acq_costs]] -> 31342.052 | V19: =IFERROR(INDEX($AJ$4:$FQ$182,MATCH($B19,$AI$4:$AI$182,0),MATCH($C19&"Acquisition Cost",$AJ$1:$FQ$1,0)),0) -> 31346.982 | W19: =IFERROR((V19-U19)/V19,"no values") -> 0.00015726101 | Y19: =Beazley_data[[#This Row],[total_RC]] -> 1.5229713 | Z19: =IFERROR(INDEX($AJ$4:$FQ$182,MATCH($B19,$AI$4:$AI$182,0),MATCH($C19&"RC",$AJ$1:$FQ$1,0)),0) -> 1.5229507 | AA19: =IFERROR((Z19-Y19)/Z19,"no values") -> -1.3530699e-05 | AD19: =Beazley_data[[#This Row],[Cat_incurred]]+Beazley_data[[#This Row],[incurred_exc_cat]] -> 0 | AE19: =IFERROR(INDEX($AJ$4:$FQ$182,MATCH($B19,$AI$4:$AI$182,0),MATCH($C19&"Total Incurred (Cat)",$AJ$1:$FQ$1,0)),0)+IFERROR(INDEX($AJ$4:$FQ$182,MATCH($B19,$AI$4:$AI$182,0),MATCH($C19&"Total Incurred (Non Cat)",$AJ$1:$FQ$1,0)),0) -> 0 | AF19: =IFERROR((AE19-AD19)/AE19,"no values") -> no values | AI19: AW | AJ19: 0.99808647 | AK19: 1.0547062 | AL19: 0.98856959 | AM19: 0.92206127 | AN19: 1.0015879 | AO19: 0.97404068 | AP19: 0.99923842 | AQ19: 0.92492929 | AR19: 0.90747739 | AS19: 1.00132 | AT19: 0.99723847 | AU19: 0.93231268 | AV19: 0.91967847 | AW19: 0.87247099 | AX19: 0.95569366 | AY19: 1.0939235 | AZ19: 0.98673776 | BA19: 0.9388698 | BB19: 0.98047728 | BC19: 1.1 | BD19: 1.1942308 | BE19: 1.2487048 | BF19: 1 | BG19: 391941.61 | BH19: 8344061.7 | BI19: 6983519 | BJ19: 3123839.7 | BK19: 1951470.1 | BL19: 4374905.7 | BM19: 4103140.3 | BN19: 6586121.8 | BO19: 5394230.9 | BP19: 7555582.7 | BQ19: 6411479.6 | BR19: 5929191.9 | BS19: 4529650.2 | BT19: 4645787.8 | BU19: 4481952.4 | BV19: 6008215.9 | BW19: 5254355.8 | BX19: 5229827.8 | BY19: 3924137.7 | BZ19: 4855447.2 | CA19: 5484757.9 | CB19: 5923419.8 | CC19: 5713719.9 | CD19: 182076.33 | CE19: 1472816 | CF19: 632009.74 | CG19: 2076854 | CH19: 409063.37 | CI19: 52384.312 | CJ19: 3016572.3 | CK19: 103244.48 | CL19: 368288.85 | CM19: 1743473 | CN19: 1363657.8 | CO19: 1235737.1 | CP19: 778254.87 | CQ19: 20916078 | CR19: 851855.7 | CS19: 2378727.3 | CT19: 937587.94 | CU19: 2126798.9 | CV19: 227976.92 | CW19: 1961663.5 | CX19: 117002.45 | CY19: 0 | CZ19: 0 | DX19: 79475.525 | DY19: 955416.63 | DZ19: 1120498.9 | EA19: 520210.49 | EB19: 394519.94 | EC19: 374544.93 | ED19: 504840.3 | EE19: 794223.11 | EF19: 652253.37 | EG19: 1008718.5 | EH19: 730914.23 | EI19: 665182.89 | EJ19: 466599.37 | EK19: 613158.77 | EL19: 649654.9 | EM19: 813899.16 | EN19: 680897.59 | EO19: 765496.48 | EP19: 1786676.5 | EQ19: 2288199.5 | ER19: 2822295.8 | ES19: 2638574.3 | ET19: 2328659.5 | EU19: 182076.33 | EV19: 1472816 | EW19: 632009.74 | EX19: 2076854 | EY19: 409063.37 | EZ19: 52384.312 | FA19: 3016572.3 | FB19: 103244.48 | FC19: 368288.85 | FD19: 1743473 | FE19: 1363657.8 | FF19: 1235737.1 | FG19: 764539.72 | FH19: 20898511 | FI19: 536211.46 | FJ19: 2376263.3 | FK19: 933587.94 | FL19: 1874014.1 | FM19: 215696.99 | FN19: 1862775.6 | FO19: 4189.8267 | FP19: 0 | FQ19: 0
A20: 1E2007 | B20: 1E | C20: 2007 | D20: 119738.72 | E20: 18203.796 | F20: 0 | G20: 0 | H20: 0 | I20: 0 | J20: 0.93991392 | K20: 0 | L20: 0 | M20: =IF(OR(Beazley_data[[#This Row],[total_RC]]<0.6,Beazley_data[[#This Row],[total_RC]]>2),1,Beazley_data[[#This Row],[total_RC]]) -> 0.93991392 | P20: =Beazley_data[[#This Row],[key]] -> 1E2007 | Q20: =Beazley_data[[#This Row],[WEP]] -> 119738.72 | R20: =IFERROR(INDEX($AJ$4:$CZ$182,MATCH($B20,$AI$4:$AI$182,0),MATCH($C20&"WEP",$AJ$1:$FQ$1,0)),0) -> 119738.72 | S20: =IFERROR((R20-Q20)/R20,"no values") -> 0 | U20: =Beazley_data[[#This Row],[Acq_costs]] -> 18203.796 | V20: =IFERROR(INDEX($AJ$4:$FQ$182,MATCH($B20,$AI$4:$AI$182,0),MATCH($C20&"Acquisition Cost",$AJ$1:$FQ$1,0)),0) -> 18203.796 | W20: =IFERROR((V20-U20)/V20,"no values") -> -1.3127591e-09 | Y20: =Beazley_data[[#This Row],[total_RC]] -> 0.93991392 | Z20: =IFERROR(INDEX($AJ$4:$FQ$182,MATCH($B20,$AI$4:$AI$182,0),MATCH($C20&"RC",$AJ$1:$FQ$1,0)),0) -> 0.93991392 | AA20: =IFERROR((Z20-Y20)/Z20,"no values") -> 2.1792208e-09 | AD20: =Beazley_data[[#This Row],[Cat_incurred]]+Beazley_data[[#This Row],[incurred_exc_cat]] -> 0 | AE20: =IFERROR(INDEX($AJ$4:$FQ$182,MATCH($B20,$AI$4:$AI$182,0),MATCH($C20&"Total Incurred (Cat)",$AJ$1:$FQ$1,0)),0)+IFERROR(INDEX($AJ$4:$FQ$182,MATCH($B20,$AI$4:$AI$182,0),MATCH($C20&"Total Incurred (Non Cat)",$AJ$1:$FQ$1,0)),0) -> 0 | AF20: =IFERROR((AE20-AD20)/AE20,"no values") -> no values | AI20: B | AJ20: 0.99327256 | AK20: 1.1547525 | AL20: 1.0741593 | AM20: 1.1201207 | AN20: 1.0288179 | AO20: 0.99930478 | AP20: 0.99589957 | AQ20: 0.9490757 | AR20: 0.96491412 | AS20: 1.0047261 | AT20: 0.99340217 | AU20: 0.98731287 | AV20: 1.0072366 | AW20: 0.97933761 | AX20: 0.97865719 | AY20: 0.91784752 | AZ20: 0.92011292 | BA20: 0.91815533 | BB20: 1.0040519 | BC20: 1.0841974 | BD20: 1.1592017 | BE20: 1.0315752 | BF20: 1.0460635 | BG20: 153289.13 | BH20: 341935.09 | BI20: 2584142.5 | BJ20: 3841438.2 | BK20: 8739557 | BL20: 8238583.2 | BM20: 8769801.5 | BN20: 13011459 | BO20: 12133492 | BP20: 8895700.9 | BQ20: 7694409.5 | BR20: 7155870.2 | BS20: 5813494.5 | BT20: 5062587 | BU20: 5160010.2 | BV20: 3399022.1 | BW20: 2299355.8 | BX20: 2771675 | BY20: 2692925.7 | BZ20: 3827449.6 | CA20: 3399771.6 | CB20: 5272935.6 | CC20: 8309913.2 | CD20: 10774.639 | CE20: 112801.27 | CF20: 1335636.1 | CG20: 360239.04 | CH20: 6664436.6 | CI20: 1253014.1 | CJ20: 349919.6 | CK20: 2663651.4 | CL20: 4015246 | CM20: 4954052.7 | CN20: 2509741.8 | CO20: 661705.07 | CP20: 6393281.2 | CQ20: 6649129.8 | CR20: 38068.443 | CS20: 3226386.2 | CT20: 11841.6 | CU20: 81918.646 | CV20: 2799970.2 | CW20: 1880507.8 | CX20: 41853.619 | CY20: 39010.636 | CZ20: 2149.3712 | DX20: 25908.927 | DY20: 46178.155 | DZ20: 672106.11 | EA20: 1064707.1 | EB20: 2450160.1 | EC20: 2465129.9 | ED20: 2347515.7 | EE20: 3875304 | EF20: 3648967.1 | EG20: 2664019.4 | EH20: 2292330.1 | EI20: 2108172.1 | EJ20: 1748995.9 | EK20: 1466695.9 | EL20: 1447917.5 | EM20: 909088.25 | EN20: 608095.31 | EO20: 752766.77 | EP20: 704919.79 | EQ20: 1181788.9 | ER20: 882536.28 | ES20: 1087206 | ET20: 1477908.6 | EU20: 10774.639 | EV20: 112801.27 | EW20: 1335636.1 | EX20: 360239.04 | EY20: 6664436.6 | EZ20: 1253014.1 | FA20: 349919.6 | FB20: 2663651.4 | FC20: 4015246 | FD20: 4954052.7 | FE20: 2509741.8 | FF20: 661705.07 | FG20: 6393281.2 | FH20: 6649129.8 | FI20: 9695.1195 | FJ20: 3226386.2 | FK20: 6801.6 | FL20: 81918.646 | FM20: 2661490.7 | FN20: 1145725.4 | FO20: 24778.29 | FP20: 4703.03 | FQ20: 0
A21: 1E2008 | B21: 1E | C21: 2008 | D21: 134954.19 | E21: 15726.825 | F21: 0 | G21: 0 | H21: 0 | I21: 0 | J21: 0.88534978 | K21: 0 | L21: 0 | M21: =IF(OR(Beazley_data[[#This Row],[total_RC]]<0.6,Beazley_data[[#This Row],[total_RC]]>2),1,Beazley_data[[#This Row],[total_RC]]) -> 0.88534978 | P21: =Beazley_data[[#This Row],[key]] -> 1E2008 | Q21: =Beazley_data[[#This Row],[WEP]] -> 134954.19 | R21: =IFERROR(INDEX($AJ$4:$CZ$182,MATCH($B21,$AI$4:$AI$182,0),MATCH($C21&"WEP",$AJ$1:$FQ$1,0)),0) -> 134954.19 | S21: =IFERROR((R21-Q21)/R21,"no values") -> 0 | U21: =Beazley_data[[#This Row],[Acq_costs]] -> 15726.825 | V21: =IFERROR(INDEX($AJ$4:$FQ$182,MATCH($B21,$AI$4:$AI$182,0),MATCH($C21&"Acquisition Cost",$AJ$1:$FQ$1,0)),0) -> 15726.826 | W21: =IFERROR((V21-U21)/V21,"no values") -> 4.6679414e-09 | Y21: =Beazley_data[[#This Row],[total_RC]] -> 0.88534978 | Z21: =IFERROR(INDEX($AJ$4:$FQ$182,MATCH($B21,$AI$4:$AI$182,0),MATCH($C21&"RC",$AJ$1:$FQ$1,0)),0) -> 0.88534978 | AA21: =IFERROR((Z21-Y21)/Z21,"no values") -> 3.0524212e-10 | AD21: =Beazley_data[[#This Row],[Cat_incurred]]+Beazley_data[[#This Row],[incurred_exc_cat]] -> 0 | AE21: =IFERROR(INDEX($AJ$4:$FQ$182,MATCH($B21,$AI$4:$AI$182,0),MATCH($C21&"Total Incurred (Cat)",$AJ$1:$FQ$1,0)),0)+IFERROR(INDEX($AJ$4:$FQ$182,MATCH($B21,$AI$4:$AI$182,0),MATCH($C21&"Total Incurred (Non Cat)",$AJ$1:$FQ$1,0)),0) -> 0 | AF21: =IFERROR((AE21-AD21)/AE21,"no values") -> no values | AI21: B2 | AJ21: 0 | AK21: 0 | AL21: 0 | AM21: 0 | AN21: 1.0300684 | AO21: 1.0217054 | AP21: 1.1634052 | AQ21: 1.0074794 | AR21: 0.91353933 | AS21: 1.0217865 | AT21: 0.98849705 | AU21: 1.0335811 | AV21: 1.0323119 | AW21: 1.0571795 | AX21: 1.0055202 | AY21: 0.97849756 | AZ21: 0.96457103 | BA21: 0.97894008 | BB21: 1.0143112 | BC21: 1.0470465 | BD21: 1.0859075 | BE21: 1.1104724 | BF21: 1.075945 | BG21: 0 | BH21: 0 | BI21: 0 | BJ21: 0 | BK21: 11493640 | BL21: 7551424.1 | BM21: 17237416 | BN21: 19501490 | BO21: 22346199 | BP21: 17597504 | BQ21: 19998989 | BR21: 19528545 | BS21: 26048349 | BT21: 28314394 | BU21: 29005498 | BV21: 30253808 | BW21: 36534581 | BX21: 39580132 | BY21: 50662765 | BZ21: 44353679 | CA21: 51653110 | CB21: 46042949 | CC21: 47668922 | CD21: 0 | CE21: 0 | CF21: 0 | CG21: 0 | CH21: 8144529.9 | CI21: 4653378.1 | CJ21: 6169029.3 | CK21: 8923612.1 | CL21: 18171310 | CM21: 8347375.1 | CN21: 12905135 | CO21: 10829528 | CP21: 19199161 | CQ21: 13355941 | CR21: 14897771 | CS21: 18542294 | CT21: 40494406 | CU21: 46023657 | CV21: 42621037 | CW21: 27943079 | CX21: 50902821 | CY21: 28679081 | CZ21: 2198.3601 | DX21: 0 | DY21: 0 | DZ21: 0 | EA21: 0 | EB21: 4325330.1 | EC21: 3050303.9 | ED21: 6980985.7 | EE21: 8843428.3 | EF21: 11347093 | EG21: 8530046.9 | EH21: 9659562 | EI21: 9652991.8 | EJ21: 12891047 | EK21: 13553338 | EL21: 13665388 | EM21: 14379754 | EN21: 11624356 | EO21: 12727378 | EP21: 16509622 | EQ21: 13347190 | ER21: 2455099.1 | ES21: 13747843 | ET21: 13635508 | EU21: 0 | EV21: 0 | EW21: 0 | EX21: 0 | EY21: 8144529.9 | EZ21: 4653378.1 | FA21: 6169029.3 | FB21: 8923612.1 | FC21: 18171310 | FD21: 8347375.1 | FE21: 12897588 | FF21: 10829348 | FG21: 19195682 | FH21: 13303788 | FI21: 14866470 | FJ21: 18486911 | FK21: 39427696 | FL21: 44864768 | FM21: 41789097 | FN21: 26201154 | FO21: 41642328 | FP21: 17559846 | FQ21: 2198.3601
A22: 1E2009 | B22: 1E | C22: 2009 | D22: 139446.56 | E22: 19658.622 | F22: 0 | G22: 0 | H22: 0 | I22: 0 | J22: 1.4305557 | K22: 0 | L22: 0 | M22: =IF(OR(Beazley_data[[#This Row],[total_RC]]<0.6,Beazley_data[[#This Row],[total_RC]]>2),1,Beazley_data[[#This Row],[total_RC]]) -> 1.4305557 | P22: =Beazley_data[[#This Row],[key]] -> 1E2009 | Q22: =Beazley_data[[#This Row],[WEP]] -> 139446.56 | R22: =IFERROR(INDEX($AJ$4:$CZ$182,MATCH($B22,$AI$4:$AI$182,0),MATCH($C22&"WEP",$AJ$1:$FQ$1,0)),0) -> 139446.56 | S22: =IFERROR((R22-Q22)/R22,"no values") -> 0 | U22: =Beazley_data[[#This Row],[Acq_costs]] -> 19658.622 | V22: =IFERROR(INDEX($AJ$4:$FQ$182,MATCH($B22,$AI$4:$AI$182,0),MATCH($C22&"Acquisition Cost",$AJ$1:$FQ$1,0)),0) -> 19658.622 | W22: =IFERROR((V22-U22)/V22,"no values") -> 2.2907201e-09 | Y22: =Beazley_data[[#This Row],[total_RC]] -> 1.4305557 | Z22: =IFERROR(INDEX($AJ$4:$FQ$182,MATCH($B22,$AI$4:$AI$182,0),MATCH($C22&"RC",$AJ$1:$FQ$1,0)),0) -> 1.4305557 | AA22: =IFERROR((Z22-Y22)/Z22,"no values") -> 1.319627e-09 | AD22: =Beazley_data[[#This Row],[Cat_incurred]]+Beazley_data[[#This Row],[incurred_exc_cat]] -> 0 | AE22: =IFERROR(INDEX($AJ$4:$FQ$182,MATCH($B22,$AI$4:$AI$182,0),MATCH($C22&"Total Incurred (Cat)",$AJ$1:$FQ$1,0)),0)+IFERROR(INDEX($AJ$4:$FQ$182,MATCH($B22,$AI$4:$AI$182,0),MATCH($C22&"Total Incurred (Non Cat)",$AJ$1:$FQ$1,0)),0) -> 0 | AF22: =IFERROR((AE22-AD22)/AE22,"no values") -> no values | AI22: B3 | AJ22: 0 | AK22: 0 | AL22: 0 | AM22: 0 | AN22: 1.0311998 | AO22: 1.0286444 | AP22: 1.0772312 | AQ22: 0.9826011 | AR22: 0.89738343 | AS22: 1.0495285 | AT22: 0.99588149 | AU22: 1.0076439 | AV22: 1.0180808 | AW22: 1.0291785 | AX22: 1.0005822 | AY22: 0.99410019 | AZ22: 0.97130388 | BA22: 1.000537 | BB22: 1.0547363 | BC22: 1.0716791 | BD22: 1.0856716 | BE22: 1.0677106 | BF22: 1.056186 | BG22: 0 | BH22: 0 | BI22: 0 | BJ22: 0 | BK22: 18275476 | BL22: 31054261 | BM22: 33920754 | BN22: 42488807 | BO22: 38247970 | BP22: 82059310 | BQ22: 1.1747841e+08 | BR22: 1.1024859e+08 | BS22: 1.1678568e+08 | BT22: 1.2224121e+08 | BU22: 1.21984e+08 | BV22: 43039285 | BW22: 43345316 | BX22: 33808986 | BY22: 30966028 | BZ22: 24524927 | CA22: 26984505 | CB22: 54766355 | CC22: 60307205 | CD22: 0 | CE22: 0 | CF22: 0 | CG22: 0 | CH22: 26295095 | CI22: 33663775 | CJ22: 16310541 | CK22: 27501739 | CL22: 20855340 | CM22: 20301762 | CN22: 35694142 | CO22: 46362953 | CP22: 47607482 | CQ22: 70117709 | CR22: 51905940 | CS22: 26100507 | CT22: 45238094 | CU22: 51109591 | CV22: 28866129 | CW22: 30812323 | CX22: 40261795 | CY22: 30914096 | CZ22: 112122.56 | DX22: 0 | DY22: 0 | DZ22: 0 | EA22: 0 | EB22: 5628832.6 | EC22: 10830011 | ED22: 11815639 | EE22: 15267384 | EF22: 14702728 | EG22: 22433754 | EH22: 30495336 | EI22: 28160839 | EJ22: 29059012 | EK22: 30225643 | EL22: 30189482 | EM22: 13587122 | EN22: 14528871 | EO22: 12934169 | EP22: 11811087 | EQ22: 9842194 | ER22: 10154738 | ES22: 20858061 | ET22: 19942622 | EU22: 0 | EV22: 0 | EW22: 0 | EX22: 0 | EY22: 26295095 | EZ22: 33663693 | FA22: 16310541 | FB22: 27501739 | FC22: 20855340 | FD22: 20296336 | FE22: 35694142 | FF22: 46327938 | FG22: 47195230 | FH22: 70005454 | FI22: 51461410 | FJ22: 24130767 | FK22: 43677818 | FL22: 47669939 | FM22: 27685234 | FN22: 27509857 | FO22: 34239981 | FP22: 20914116 | FQ22: 93181.439
A23: 1E2010 | B23: 1E | C23: 2010 | D23: 198471.1 | E23: 26920.395 | F23: 0 | G23: 0 | H23: 0 | I23: 0 | J23: 0.82677352 | K23: 0 | L23: 0 | M23: =IF(OR(Beazley_data[[#This Row],[total_RC]]<0.6,Beazley_data[[#This Row],[total_RC]]>2),1,Beazley_data[[#This Row],[total_RC]]) -> 0.82677352 | P23: =Beazley_data[[#This Row],[key]] -> 1E2010 | Q23: =Beazley_data[[#This Row],[WEP]] -> 198471.1 | R23: =IFERROR(INDEX($AJ$4:$CZ$182,MATCH($B23,$AI$4:$AI$182,0),MATCH($C23&"WEP",$AJ$1:$FQ$1,0)),0) -> 198471.1 | S23: =IFERROR((R23-Q23)/R23,"no values") -> 0 | U23: =Beazley_data[[#This Row],[Acq_costs]] -> 26920.395 | V23: =IFERROR(INDEX($AJ$4:$FQ$182,MATCH($B23,$AI$4:$AI$182,0),MATCH($C23&"Acquisition Cost",$AJ$1:$FQ$1,0)),0) -> 26920.395 | W23: =IFERROR((V23-U23)/V23,"no values") -> 7.0829493e-09 | Y23: =Beazley_data[[#This Row],[total_RC]] -> 0.82677352 | Z23: =IFERROR(INDEX($AJ$4:$FQ$182,MATCH($B23,$AI$4:$AI$182,0),MATCH($C23&"RC",$AJ$1:$FQ$1,0)),0) -> 0.82677352 | AA23: =IFERROR((Z23-Y23)/Z23,"no values") -> 3.8537709e-11 | AD23: =Beazley_data[[#This Row],[Cat_incurred]]+Beazley_data[[#This Row],[incurred_exc_cat]] -> 0 | AE23: =IFERROR(INDEX($AJ$4:$FQ$182,MATCH($B23,$AI$4:$AI$182,0),MATCH($C23&"Total Incurred (Cat)",$AJ$1:$FQ$1,0)),0)+IFERROR(INDEX($AJ$4:$FQ$182,MATCH($B23,$AI$4:$AI$182,0),MATCH($C23&"Total Incurred (Non Cat)",$AJ$1:$FQ$1,0)),0) -> 0 | AF23: =IFERROR((AE23-AD23)/AE23,"no values") -> no values | AI23: B4 | AJ23: 0 | AK23: 0 | AL23: 0 | AM23: 0 | AN23: 1.0116082 | AO23: 1 | AP23: 1.0072639 | AQ23: 1.0095056 | AR23: 1.0316874 | AS23: 1.030452 | AT23: 1.0044909 | AU23: 1.0102125 | AV23: 1.0082621 | AW23: 1.0042919 | AX23: 1.000566 | AY23: 1 | AZ23: 1 | BA23: 1.0015108 | BB23: 1.0208155 | BC23: 1.0170855 | BD23: 1.0223041 | BE23: 1.010688 | BF23: 1.0097773 | BG23: 0 | BH23: 0 | BI23: 0 | BJ23: 0 | BK23: 9088736.2 | BL23: 8015792.4 | BM23: 9671265.6 | BN23: 9764562.1 | BO23: 12813032 | BP23: 7281472.1 | BQ23: 10066348 | BR23: 10292742 | BS23: 9205993.2 | BT23: 7761505.5 | BU23: 7930191.1 | BV23: 7056441.4 | BW23: 8385393.2 | BX23: 8789845.1 | BY23: 12084337 | BZ23: 8480596.9 | CA23: 11346595 | CB23: 12396808 | CC23: 12704465 | CD23: 0 | CE23: 0 | CF23: 0 | CG23: 0 | CH23: 6753600.2 | CI23: 3049982.7 | CJ23: 6198693.4 | CK23: 9057527.1 | CL23: 11465204 | CM23: 4828235 | CN23: 16099405 | CO23: 9417124.3 | CP23: 5912309.9 | CQ23: 5885152.3 | CR23: 5466523.6 | CS23: 4567375.4 | CT23: 7092788.6 | CU23: 6126491.4 | CV23: 9106418.2 | CW23: 5012084.8 | CX23: 4115393.1 | CY23: 3641491.9 | CZ23: 5609.8284 | DX23: 0 | DY23: 0 | DZ23: 0 | EA23: 0 | EB23: 3875325.2 | EC23: 4127688.4 | ED23: 5054490.2 | EE23: 4726438.1 | EF23: 6975411 | EG23: 3968030.7 | EH23: 5211547.4 | EI23: 5188243.5 | EJ23: 4574099.7 | EK23: 3822122.3 | EL23: 4111209 | EM23: 3777582.1 | EN23: 4509705.7 | EO23: 4751936.2 | EP23: 6571310.4 | EQ23: 4543542.3 | ER23: 5761693.4 | ES23: 6440285.4 | ET23: 6270446.8 | EU23: 0 | EV23: 0 | EW23: 0 | EX23: 0 | EY23: 6753600.2 | EZ23: 3049982.7 | FA23: 6198693.4 | FB23: 9057527.1 | FC23: 11464345 | FD23: 4828235 | FE23: 16086782 | FF23: 7681214.4 | FG23: 5843297.7 | FH23: 5739873.6 | FI23: 5311640.2 | FJ23: 4553607.9 | FK23: 7025561.4 | FL23: 6046579.9 | FM23: 8768997.2 | FN23: 4382127.5 | FO23: 3170177.3 | FP23: 1653546.5 | FQ23: 243.9756
A24: 1E2011 | B24: 1E | C24: 2011 | D24: 24691.016 | E24: 4177.181 | F24: 0 | G24: 0 | H24: 0 | I24: 0 | J24: 1.0467928 | K24: 0 | L24: 0 | M24: =IF(OR(Beazley_data[[#This Row],[total_RC]]<0.6,Beazley_data[[#This Row],[total_RC]]>2),1,Beazley_data[[#This Row],[total_RC]]) -> 1.0467928 | P24: =Beazley_data[[#This Row],[key]] -> 1E2011 | Q24: =Beazley_data[[#This Row],[WEP]] -> 24691.016 | R24: =IFERROR(INDEX($AJ$4:$CZ$182,MATCH($B24,$AI$4:$AI$182,0),MATCH($C24&"WEP",$AJ$1:$FQ$1,0)),0) -> 24691.016 | S24: =IFERROR((R24-Q24)/R24,"no values") -> 0 | U24: =Beazley_data[[#This Row],[Acq_costs]] -> 4177.181 | V24: =IFERROR(INDEX($AJ$4:$FQ$182,MATCH($B24,$AI$4:$AI$182,0),MATCH($C24&"Acquisition Cost",$AJ$1:$FQ$1,0)),0) -> 4177.1811 | W24: =IFERROR((V24-U24)/V24,"no values") -> 2.7495631e-08 | Y24: =Beazley_data[[#This Row],[total_RC]] -> 1.0467928 | Z24: =IFERROR(INDEX($AJ$4:$FQ$182,MATCH($B24,$AI$4:$AI$182,0),MATCH($C24&"RC",$AJ$1:$FQ$1,0)),0) -> 1.0467928 | AA24: =IFERROR((Z24-Y24)/Z24,"no values") -> 2.8997908e-09 | AD24: =Beazley_data[[#This Row],[Cat_incurred]]+Beazley_data[[#This Row],[incurred_exc_cat]] -> 0 | AE24: =IFERROR(INDEX($AJ$4:$FQ$182,MATCH($B24,$AI$4:$AI$182,0),MATCH($C24&"Total Incurred (Cat)",$AJ$1:$FQ$1,0)),0)+IFERROR(INDEX($AJ$4:$FQ$182,MATCH($B24,$AI$4:$AI$182,0),MATCH($C24&"Total Incurred (Non Cat)",$AJ$1:$FQ$1,0)),0) -> 0 | AF24: =IFERROR((AE24-AD24)/AE24,"no values") -> no values | AI24: B5 | AJ24: 0 | AK24: 0 | AL24: 0 | AM24: 0 | AN24: 1.0104181 | AO24: 0.95114558 | AP24: 0.99803677 | AQ24: 0.98098205 | AR24: 0.94253987 | AS24: 1.0304054 | AT24: 0.99895207 | AU24: 1.0364731 | AV24: 1.0353569 | AW24: 1.017556 | AX24: 1.0078016 | AY24: 0.98214347 | AZ24: 0.97695361 | BA24: 1.0032142 | BB24: 1.0511231 | BC24: 1.0461779 | BD24: 1.1351214 | BE24: 1.1016947 | BF24: 1.0482405 | BG24: 0 | BH24: 0 | BI24: 0 | BJ24: 0 | BK24: 7271399.7 | BL24: 9617545.5 | BM24: 12974857 | BN24: 6641773.9 | BO24: 7029648 | BP24: 11166982 | BQ24: 9795775.8 | BR24: 8288188.2 | BS24: 8154604 | BT24: 7816612.6 | BU24: 8133103.5 | BV24: 9151391.1 | BW24: 14089377 | BX24: 18090357 | BY24: 18302497 | BZ24: 15130108 | CA24: 20588410 | CB24: 28443878 | CC24: 26250780 | CD24: 0 | CE24: 0 | CF24: 0 | CG24: 0 | CH24: 8051437.9 | CI24: 6680162.6 | CJ24: 6909039.5 | CK24: 6682460.4 | CL24: 6604499.9 | CM24: 7757520.8 | CN24: 11235330 | CO24: 6176997.2 | CP24: 4971147.7 | CQ24: 3953057.7 | CR24: 5290391 | CS24: 7605660.1 | CT24: 13693282 | CU24: 15607638 | CV24: 13180109 | CW24: 6663801.6 | CX24: 8254620.6 | CY24: 5780423.7 | CZ24: 95489.709 | DX24: 0 | DY24: 0 | DZ24: 0 | EA24: 0 | EB24: 2263982.6 | EC24: 3081110.1 | ED24: 4824498.3 | EE24: 3043999.2 | EF24: 2669212.2 | EG24: 4303875.9 | EH24: 4039996.6 | EI24: 3206533.9 | EJ24: 3223380.3 | EK24: 3023712.3 | EL24: 3211704.5 | EM24: 3415937.5 | EN24: 5180680.4 | EO24: 6750183.4 | EP24: 6841551.1 | EQ24: 4862522.8 | ER24: 6774043.8 | ES24: 8939718.2 | ET24: 8427044.3 | EU24: 0 | EV24: 0 | EW24: 0 | EX24: 0 | EY24: 8051437.9 | EZ24: 6679048 | FA24: 6767460.5 | FB24: 6626929 | FC24: 6586043.2 | FD24: 7747437.2 | FE24: 11233166 | FF24: 6149584.6 | FG24: 4942809.6 | FH24: 3884539.2 | FI24: 5165976.1 | FJ24: 7414126.3 | FK24: 13135159 | FL24: 14947462 | FM24: 12562911 | FN24: 5676917.6 | FO24: 4983246.5 | FP24: 2739030.9 | FQ24: 93489.346
A25: 1E2012 | B25: 1E | C25: 2012 | D25: 16794.928 | E25: 336.20817 | F25: 0 | G25: 0 | H25: 0 | I25: 0 | J25: 0.99551527 | K25: 0 | L25: 0 | M25: =IF(OR(Beazley_data[[#This Row],[total_RC]]<0.6,Beazley_data[[#This Row],[total_RC]]>2),1,Beazley_data[[#This Row],[total_RC]]) -> 0.99551527 | P25: =Beazley_data[[#This Row],[key]] -> 1E2012 | Q25: =Beazley_data[[#This Row],[WEP]] -> 16794.928 | R25: =IFERROR(INDEX($AJ$4:$CZ$182,MATCH($B25,$AI$4:$AI$182,0),MATCH($C25&"WEP",$AJ$1:$FQ$1,0)),0) -> 16794.928 | S25: =IFERROR((R25-Q25)/R25,"no values") -> 0 | U25: =Beazley_data[[#This Row],[Acq_costs]] -> 336.20817 | V25: =IFERROR(INDEX($AJ$4:$FQ$182,MATCH($B25,$AI$4:$AI$182,0),MATCH($C25&"Acquisition Cost",$AJ$1:$FQ$1,0)),0) -> 336.2082 | W25: =IFERROR((V25-U25)/V25,"no values") -> 9.1723887e-08 | Y25: =Beazley_data[[#This Row],[total_RC]] -> 0.99551527 | Z25: =IFERROR(INDEX($AJ$4:$FQ$182,MATCH($B25,$AI$4:$AI$182,0),MATCH($C25&"RC",$AJ$1:$FQ$1,0)),0) -> 0.99551526 | AA25: =IFERROR((Z25-Y25)/Z25,"no values") -> -6.8392526e-10 | AD25: =Beazley_data[[#This Row],[Cat_incurred]]+Beazley_data[[#This Row],[incurred_exc_cat]] -> 0 | AE25: =IFERROR(INDEX($AJ$4:$FQ$182,MATCH($B25,$AI$4:$AI$182,0),MATCH($C25&"Total Incurred (Cat)",$AJ$1:$FQ$1,0)),0)+IFERROR(INDEX($AJ$4:$FQ$182,MATCH($B25,$AI$4:$AI$182,0),MATCH($C25&"Total Incurred (Non Cat)",$AJ$1:$FQ$1,0)),0) -> 0 | AF25: =IFERROR((AE25-AD25)/AE25,"no values") -> no values | AI25: BB | AJ25: 1.0609111 | AK25: 1.0926896 | AL25: 1.2864798 | AM25: 1.6342239 | AN25: 0.99874495 | AO25: 1.0059898 | AP25: 1.0439582 | AQ25: 0.96096017 | AR25: 0.96479988 | AS25: 1.0204124 | AT25: 1.0037161 | AU25: 0.95768465 | AV25: 1.0059613 | AW25: 0.99470521 | AX25: 0.99926963 | AY25: 0.9997221 | AZ25: 0.99705138 | BA25: 1.0067776 | BB25: 0.83734275 | BC25: 1.113545 | BD25: 1.1893887 | BE25: 1.1655354 | BF25: 1.0562561 | BG25: 5270734.9 | BH25: 3916037.8 | BI25: 1739205.1 | BJ25: 2357306 | BK25: 2706480.1 | BL25: 3314733.7 | BM25: 2644859.5 | BN25: 2774127.3 | BO25: 3456095.5 | BP25: 4193241 | BQ25: 3027023.6 | BR25: 2952282.5 | BS25: 3935053.3 | BT25: 5583826.3 | BU25: 6855952 | BV25: 10951646 | BW25: 8768946.5 | BX25: 17485592 | BY25: 14623425 | BZ25: 20120442 | CA25: 29254606 | CB25: 32240397 | CC25: 13762140 | CD25: 6871982.7 | CE25: 3482483.4 | CF25: 19710.4 | CG25: 673774.33 | CH25: 255802.09 | CI25: 828430.06 | CJ25: 107716.63 | CK25: 1033431.8 | CL25: 4545914.2 | CM25: 727753.87 | CN25: 375301.28 | CO25: 606961.04 | CP25: 3932677.4 | CQ25: 2535315.9 | CR25: 9880559 | CS25: 5072359 | CT25: 2513866.6 | CU25: 10126740 | CV25: 2059163.5 | CW25: 9956373.2 | CX25: 652979.34 | CY25: 84001.229 | CZ25: 0 | DX25: 1460655.2 | DY25: 1077877.1 | DZ25: 360117.11 | EA25: 492545.52 | EB25: 442615.91 | EC25: 521783.97 | ED25: 872040.62 | EE25: 1073477.7 | EF25: 1267133.4 | EG25: 1468551.5 | EH25: 1054704.9 | EI25: 584577.3 | EJ25: 914283.83 | EK25: 1535602.3 | EL25: 1447927.6 | EM25: 2981381.3 | EN25: 1191438.6 | EO25: 2014690.7 | EP25: 2430154.3 | EQ25: 3675894.5 | ER25: 5614153.7 | ES25: 6037229.3 | ET25: 3349919.3 | EU25: 6871982.7 | EV25: 3482483.4 | EW25: 19710.4 | EX25: 673774.33 | EY25: 255356.05 | EZ25: 828430.06 | FA25: 107716.63 | FB25: 563150.8 | FC25: 4545914.2 | FD25: 611622.87 | FE25: 337801.28 | FF25: 525846.91 | FG25: 3932677.4 | FH25: 2512814.9 | FI25: 9630157.8 | FJ25: 1051254 | FK25: 2511451.6 | FL25: 10117908 | FM25: 1795485 | FN25: 9854993.9 | FO25: 581175.73 | FP25: 18126.254 | FQ25: 0
A26: 1E2013 | B26: 1E | C26: 2013 | D26: 82634.414 | E26: 2131.168 | F26: 0 | G26: 0 | H26: 0 | I26: 0 | J26: 1 | K26: 0 | L26: 0 | M26: =IF(OR(Beazley_data[[#This Row],[total_RC]]<0.6,Beazley_data[[#This Row],[total_RC]]>2),1,Beazley_data[[#This Row],[total_RC]]) -> 1 | P26: =Beazley_data[[#This Row],[key]] -> 1E2013 | Q26: =Beazley_data[[#This Row],[WEP]] -> 82634.414 | R26: =IFERROR(INDEX($AJ$4:$CZ$182,MATCH($B26,$AI$4:$AI$182,0),MATCH($C26&"WEP",$AJ$1:$FQ$1,0)),0) -> 82634.414 | S26: =IFERROR((R26-Q26)/R26,"no values") -> 0 | U26: =Beazley_data[[#This Row],[Acq_costs]] -> 2131.168 | V26: =IFERROR(INDEX($AJ$4:$FQ$182,MATCH($B26,$AI$4:$AI$182,0),MATCH($C26&"Acquisition Cost",$AJ$1:$FQ$1,0)),0) -> 2131.1681 | W26: =IFERROR((V26-U26)/V26,"no values") -> 2.8347646e-08 | Y26: =Beazley_data[[#This Row],[total_RC]] -> 1 | Z26: =IFERROR(INDEX($AJ$4:$FQ$182,MATCH($B26,$AI$4:$AI$182,0),MATCH($C26&"RC",$AJ$1:$FQ$1,0)),0) -> 1 | AA26: =IFERROR((Z26-Y26)/Z26,"no values") -> 0 | AD26: =Beazley_data[[#This Row],[Cat_incurred]]+Beazley_data[[#This Row],[incurred_exc_cat]] -> 0 | AE26: =IFERROR(INDEX($AJ$4:$FQ$182,MATCH($B26,$AI$4:$AI$182,0),MATCH($C26&"Total Incurred (Cat)",$AJ$1:$FQ$1,0)),0)+IFERROR(INDEX($AJ$4:$FQ$182,MATCH($B26,$AI$4:$AI$182,0),MATCH($C26&"Total Incurred (Non Cat)",$AJ$1:$FQ$1,0)),0) -> 0 | AF26: =IFERROR((AE26-AD26)/AE26,"no values") -> no values | AI26: BD | AJ26: 1 | AK26: 0 | AL26: 0 | AM26: 0.97227177 | AN26: 0.99898843 | AO26: 1.019466 | AP26: 0.94169939 | AQ26: 0.97874574 | AR26: 0.98118237 | AS26: 1.0267884 | AT26: 1.0013623 | AU26: 0.99061683 | AV26: 0.99036152 | AW26: 0.96321276 | AX26: 0.96796031 | AY26: 0.95518526 | AZ26: 0.98800122 | BA26: 0.98087277 | BB26: 1.0115628 | BC26: 1.0085241 | BD26: 0.88021406 | BE26: 0.99400352 | BF26: 1.0045692 | BG26: 3245.187 | BH26: 0 | BI26: 0 | BJ26: 266760.47 | BK26: 127663.03 | BL26: 402711.1 | BM26: 606108.89 | BN26: 880086.52 | BO26: 636955.6 | BP26: 551061.81 | BQ26: 664820.7 | BR26: 540551.58 | BS26: 734421.86 | BT26: 522149.16 | BU26: 636581.01 | BV26: 728887.31 | BW26: 976573.97 | BX26: 1186900.1 | BY26: 936927.97 | BZ26: 424047.22 | CA26: 92533.948 | CB26: 41199.705 | CC26: 3105.2068 | CD26: 0 | CE26: 0 | CF26: 0 | CG26: 0 | CH26: 126.60978 | CI26: 36791.656 | CJ26: 53441.636 | CK26: 7169.1447 | CL26: 1857.2962 | CM26: 2384.4652 | CN26: 2235.1782 | CO26: 22.55748 | CP26: 7002.3227 | CQ26: 67490.096 | CR26: 0 | CS26: 9123.7312 | CT26: 191489.03 | CU26: 322517.51 | CV26: 571.6656 | CW26: 63799.098 | CX26: 31271.446 | CY26: 0 | CZ26: 0 | DX26: 1230.933 | DY26: 0 | DZ26: 0 | EA26: 5829.703 | EB26: 5185.1446 | EC26: 8100.2906 | ED26: 19741.486 | EE26: 31800.225 | EF26: 46839.381 | EG26: 83624.974 | EH26: 107025.03 | EI26: 61948.076 | EJ26: 109816.93 | EK26: 85570.147 | EL26: 79304.28 | EM26: 129516.91 | EN26: 186632.13 | EO26: 242492.26 | EP26: 163949.27 | EQ26: 50316.315 | ER26: 9360.9979 | ES26: 5866.9433 | ET26: 966.62395 | EU26: 0 | EV26: 0 | EW26: 0 | EX26: 0 | EY26: 126.60978 | EZ26: 36791.656 | FA26: 53441.636 | FB26: 7169.1447 | FC26: 1857.2962 | FD26: 2384.4652 | FE26: 2235.1782 | FF26: 22.55748 | FG26: 7002.3227 | FH26: 28337.047 | FI26: 0 | FJ26: 9123.7312 | FK26: 57335.681 | FL26: 321317.5 | FM26: 571.6656 | FN26: 57199.098 | FO26: 217.48596 | FP26: 0 | FQ26: 0
A27: 1E2014 | B27: 1E | C27: 2014 | D27: 80693.222 | E27: 1303.446 | F27: 0 | G27: 0 | H27: 0 | I27: 0 | J27: 0.8784409 | K27: 0 | L27: 0 | M27: =IF(OR(Beazley_data[[#This Row],[total_RC]]<0.6,Beazley_data[[#This Row],[total_RC]]>2),1,Beazley_data[[#This Row],[total_RC]]) -> 0.8784409 | P27: =Beazley_data[[#This Row],[key]] -> 1E2014 | Q27: =Beazley_data[[#This Row],[WEP]] -> 80693.222 | R27: =IFERROR(INDEX($AJ$4:$CZ$182,MATCH($B27,$AI$4:$AI$182,0),MATCH($C27&"WEP",$AJ$1:$FQ$1,0)),0) -> 80695.202 | S27: =IFERROR((R27-Q27)/R27,"no values") -> 2.4536973e-05 | U27: =Beazley_data[[#This Row],[Acq_costs]] -> 1303.446 | V27: =IFERROR(INDEX($AJ$4:$FQ$182,MATCH($B27,$AI$4:$AI$182,0),MATCH($C27&"Acquisition Cost",$AJ$1:$FQ$1,0)),0) -> 1304.0375 | W27: =IFERROR((V27-U27)/V27,"no values") -> 0.00045363329 | Y27: =Beazley_data[[#This Row],[total_RC]] -> 0.8784409 | Z27: =IFERROR(INDEX($AJ$4:$FQ$182,MATCH($B27,$AI$4:$AI$182,0),MATCH($C27&"RC",$AJ$1:$FQ$1,0)),0) -> 0.87844352 | AA27: =IFERROR((Z27-Y27)/Z27,"no values") -> 2.9821292e-06 | AD27: =Beazley_data[[#This Row],[Cat_incurred]]+Beazley_data[[#This Row],[incurred_exc_cat]] -> 0 | AE27: =IFERROR(INDEX($AJ$4:$FQ$182,MATCH($B27,$AI$4:$AI$182,0),MATCH($C27&"Total Incurred (Cat)",$AJ$1:$FQ$1,0)),0)+IFERROR(INDEX($AJ$4:$FQ$182,MATCH($B27,$AI$4:$AI$182,0),MATCH($C27&"Total Incurred (Non Cat)",$AJ$1:$FQ$1,0)),0) -> 0 | AF27: =IFERROR((AE27-AD27)/AE27,"no values") -> no values | AI27: CB | AJ27: 0 | AK27: 0 | AL27: 0 | AM27: 0 | AN27: 0 | AO27: 0 | AP27: 0 | AQ27: 0 | AR27: 0 | AS27: 0 | AT27: 0 | AU27: 1.0201422 | AV27: 1.0042026 | AW27: 1.0087117 | AX27: 0.99785541 | AY27: 1.0041553 | AZ27: 0.99477504 | BA27: 1.0139501 | BB27: 1.0540202 | BC27: 1.1246931 | BD27: 1.1508185 | BE27: 1.2181055 | BF27: 1.0558089 | BG27: 0 | BH27: 0 | BI27: 0 | BJ27: 0 | BK27: 0 | BL27: 0 | BM27: 0 | BN27: 0 | BO27: 0 | BP27: 0 | BQ27: 0 | BR27: 9496687.3 | BS27: 8589596.6 | BT27: 9824319.4 | BU27: 9191383.6 | BV27: 11739994 | BW27: 10597520 | BX27: 12471276 | BY27: 10901437 | BZ27: 368148.89 | CA27: 425149.79 | CB27: 4004419.5 | CC27: 26611441 | CD27: 0 | CE27: 0 | CF27: 0 | CG27: 0 | CH27: 0 | CI27: 0 | CJ27: 0 | CK27: 0 | CL27: 0 | CM27: 0 | CN27: 0 | CO27: 5843456.1 | CP27: 4898624.6 | CQ27: 7116569.5 | CR27: 4597139.8 | CS27: 16116640 | CT27: 10677213 | CU27: 12336653 | CV27: 9813523 | CW27: 42089.018 | CX27: 0 | CY27: 0 | CZ27: 105 | DX27: 0 | DY27: 0 | DZ27: 0 | EA27: 0 | EB27: 0 | EC27: 0 | ED27: 0 | EE27: 0 | EF27: 0 | EG27: 0 | EH27: 0 | EI27: 1609721.5 | EJ27: 1688719.2 | EK27: 1471242.4 | EL27: 1513128.7 | EM27: 1928132.8 | EN27: 2128165 | EO27: 2989633.9 | EP27: 2642377.6 | EQ27: 73207.732 | ER27: 93623.035 | ES27: 1477818.9 | ET27: 4398269.4 | EU27: 0 | EV27: 0 | EW27: 0 | EX27: 0 | EY27: 0 | EZ27: 0 | FA27: 0 | FB27: 0 | FC27: 0 | FD27: 0 | FE27: 0 | FF27: 5334703 | FG27: 4594850.9 | FH27: 6784190.4 | FI27: 3816454.9 | FJ27: 7521077.4 | FK27: 9114830.7 | FL27: 8816443.3 | FM27: 6033886.7 | FN27: 22660.433 | FO27: 0 | FP27: 0 | FQ27: 0
... A40: 1T2023 | B40: 1T | C40: 2023 | D40: 0.0471 | E40: 0.012909796 | F40: 0 | G40: 0 | H40: 0 | I40: 0 | J40: 1.15 | K40: 0 | L40: 0 | M40: =IF(OR(Beazley_data[[#This Row],[total_RC]]<0.6,Beazley_data[[#This Row],[total_RC]]>2),1,Beazley_data[[#This Row],[total_RC]]) -> 1.15 | P40: =Beazley_data[[#This Row],[key]] -> 1T2023 | Q40: =Beazley_data[[#This Row],[WEP]] -> 0.0471 | R40: =IFERROR(INDEX($AJ$4:$CZ$182,MATCH($B40,$AI$4:$AI$182,0),MATCH($C40&"WEP",$AJ$1:$FQ$1,0)),0) -> 0 | S40: =IFERROR((R40-Q40)/R40,"no values") -> no values | U40: =Beazley_data[[#This Row],[Acq_costs]] -> 0.012909796 | V40: =IFERROR(INDEX($AJ$4:$FQ$182,MATCH($B40,$AI$4:$AI$182,0),MATCH($C40&"Acquisition Cost",$AJ$1:$FQ$1,0)),0) -> 0 | W40: =IFERROR((V40-U40)/V40,"no values") -> no values | Y40: =Beazley_data[[#This Row],[total_RC]] -> 1.15 | Z40: =IFERROR(INDEX($AJ$4:$FQ$182,MATCH($B40,$AI$4:$AI$182,0),MATCH($C40&"RC",$AJ$1:$FQ$1,0)),0) -> 0 | AA40: =IFERROR((Z40-Y40)/Z40,"no values") -> no values | AD40: =Beazley_data[[#This Row],[Cat_incurred]]+Beazley_data[[#This Row],[incurred_exc_cat]] -> 0 | AE40: =IFERROR(INDEX($AJ$4:$FQ$182,MATCH($B40,$AI$4:$AI$182,0),MATCH($C40&"Total Incurred (Cat)",$AJ$1:$FQ$1,0)),0)+IFERROR(INDEX($AJ$4:$FQ$182,MATCH($B40,$AI$4:$AI$182,0),MATCH($C40&"Total Incurred (Non Cat)",$AJ$1:$FQ$1,0)),0) -> 0 | AF40: =IFERROR((AE40-AD40)/AE40,"no values") -> no values | AI40: D8 | AJ40: 0 | AK40: 0 | AL40: 0 | AM40: 0 | AN40: 0 | AO40: 0 | AP40: 0 | AQ40: 0 | AR40: 0 | AS40: 0 | AT40: 0 | AU40: 0 | AV40: 0 | AW40: 0 | AX40: 0 | AY40: 0 | AZ40: 0 | BA40: 0 | BB40: 0.99853776 | BC40: 0.11273781 | BD40: 1.0355741 | BE40: 1.0202486 | BF40: 1 | BG40: 0 | BH40: 0 | BI40: 0 | BJ40: 0 | BK40: 0 | BL40: 0 | BM40: 0 | BN40: 0 | BO40: 0 | BP40: 0 | BQ40: 0 | BR40: 0 | BS40: 0 | BT40: 0 | BU40: 0 | BV40: 0 | BW40: 0 | BX40: 0 | BY40: 39542998 | BZ40: 36782548 | CA40: 40421517 | CB40: 60181504 | CC40: 59303550 | CD40: 0 | CE40: 0 | CF40: 0 | CG40: 0 | CH40: 0 | CI40: 0 | CJ40: 0 | CK40: 0 | CL40: 0 | CM40: 0 | CN40: 0 | CO40: 0 | CP40: 0 | CQ40: 0 | CR40: 0 | CS40: 0 | CT40: 0 | CU40: 0 | CV40: 15040009 | CW40: 7273058 | CX40: 1821470.1 | CY40: 183480 | CZ40: 0 | DX40: 0 | DY40: 0 | DZ40: 0 | EA40: 0 | EB40: 0 | EC40: 0 | ED40: 0 | EE40: 0 | EF40: 0 | EG40: 0 | EH40: 0 | EI40: 0 | EJ40: 0 | EK40: 0 | EL40: 0 | EM40: 0 | EN40: 0 | EO40: 0 | EP40: 8595870.5 | EQ40: 7838334.7 | ER40: 9721532.2 | ES40: 14855079 | ET40: 16169652 | EU40: 0 | EV40: 0 | EW40: 0 | EX40: 0 | EY40: 0 | EZ40: 0 | FA40: 0 | FB40: 0 | FC40: 0 | FD40: 0 | FE40: 0 | FF40: 0 | FG40: 0 | FH40: 0 | FI40: 0 | FJ40: 0 | FK40: 0 | FL40: 0 | FM40: 13300652 | FN40: 3644837 | FO40: 1323408.1 | FP40: 110597.1 | FQ40: 0
